Workbook

Sheet ÍNDICE
A1: ÍNDICE — CLIQUE NO NOME PARA ABRIR A ABA [MODELO EM BRANCO — pronto para uma semana nova]
A3: ABAS DE TRABALHO
A4: =HYPERLINK("#'Entrada de Dados'!A1","Entrada de Dados") | B4: onde você digita pedido e entrega
A5: =HYPERLINK("#'RESUMO'!A1","RESUMO") | B5: o resultado final, calculado sozinho
A6: =HYPERLINK("#'BALANÇO FINANCEIRO'!A1","BALANÇO FINANCEIRO") | B6: custos reais da semana e saldo (positivo ou negativo)
A7: =HYPERLINK("#'DIFERENÇA'!A1","DIFERENÇA") | B7: quanto faltou entregar, produto por produto
A8: =HYPERLINK("#'MAPA DE MONTAGEM'!A1","MAPA DE MONTAGEM") | B8: separação da carga por rota — segunda e terça
A9: =HYPERLINK("#'MAPA DE PRODUÇÃO'!A1","MAPA DE PRODUÇÃO") | B9: quem planta o quê, por mês
A10: =HYPERLINK("#'MOTIVO'!A1","MOTIVO") | B10: lista de motivos de devolução
A12: COMO USAR — PASSO A PASSO DA SEMANA
A13: 1. Pedido da prefeitura chega
A14: Aba "Entrada de Dados", bloco de cima (ESCOLAS): digite a quantidade de cada produto, na linha da escola e coluna do produto.
A15: 2. Divisão entre produtores + pedido a eles
A16: Decisão da cooperativa (fora da planilha). Depois, aba "Entrada de Dados", bloco do meio (PEDIDO PRODUTORES): digite quanto foi pedido a cada produtor. A partir daqui, a ficha de cada produtor (clique no nome) já mostra o Pedido e a Entrega (vêm sozinhos da Entrada de Dados) — dá pra imprimir e entregar antes da entrega chegar, como referência de quanto ele deve trazer. É a mesma ficha que depois vira o romaneio: quando ele chegar, digite a quantidade em ENTREGA PRODUTORES (passo 3 abaixo) e, se o galpão rejeitar algo, a Devolução direto na ficha do produtor — sem criar outro documento.
A17: 3. Recebimento e rejeição no galpão
A18: Aba "Entrada de Dados", bloco de baixo (ENTREGA PRODUTORES): digite quanto cada produtor trouxe. Depois abra a ficha do produtor (clique no nome) e digite a Devolução, se o galpão rejeitar algo.
A20: 4. Complemento, se faltar produto — aba "COMPLEMENTOS": bloco B (Recebimento no galpão) uma linha por entrega, gera o pagamento. Bloco C (Entrega às escolas): escolha o Nº do recebimento, produtor/produto vêm sozinhos. Só 15 linhas aparecem por bloco — clique no "+" à esquerda da grade pra abrir mais. Pra imprimir um comprovante de complemento, use o seletor no topo da própria aba (Tipo + Nº) — o documento muda sozinho, sem mexer nos dados.
A21: 5. Montagem e carregamento
A22: Aba "MAPA DE MONTAGEM": as quantidades de cada rota aparecem sozinhas. Preencha só Peso Embarcado, Veículo e Motorista no rodapé de cada rota, na hora de carregar. Imprima a rota pra levar no caminhão.
A23: 6. Entrega e assinatura na escola
A24: Imprima a ficha da escola em 4 cópias antes de sair — é o romaneio. A merendeira/diretora confere, anota o que recebeu de próprio punho no papel, e assina.
... A42: ESCOLAS
A43: CÓDIGO | B43: ESCOLA (clique para abrir) | C43: BAIRRO
A44: ='E M ABELARDO DE LAMARE'!B5 | B44: =HYPERLINK("#'E M ABELARDO DE LAMARE'!A1",'E M ABELARDO DE LAMARE'!B2) | C44: ='E M ABELARDO DE LAMARE'!B3
A45: ='E M BATAILLARD'!B5 | B45: =HYPERLINK("#'E M BATAILLARD'!A1",'E M BATAILLARD'!B2) | C45: ='E M BATAILLARD'!B3
A46: ='E M LEONARDO BOFF'!B5 | B46: =HYPERLINK("#'E M LEONARDO BOFF'!A1",'E M LEONARDO BOFF'!B2) | C46: ='E M LEONARDO BOFF'!B3
A47: ='E M CLEMENTE FERNANDES'!B5 | B47: =HYPERLINK("#'E M CLEMENTE FERNANDES'!A1",'E M CLEMENTE FERNANDES'!B2) | C47: ='E M CLEMENTE FERNANDES'!B3
A48: ='E M DOM PEDRO DE ALCÂNTARA'!B5 | B48: =HYPERLINK("#'E M DOM PEDRO DE ALCÂNTARA'!A1",'E M DOM PEDRO DE ALCÂNTARA'!B2) | C48: ='E M DOM PEDRO DE ALCÂNTARA'!B3
A49: ='E M DUQUE DE CAXIAS'!B5 | B49: =HYPERLINK("#'E M DUQUE DE CAXIAS'!A1",'E M DUQUE DE CAXIAS'!B2) | C49: ='E M DUQUE DE CAXIAS'!B3
A50: ='E M LUIZ CARLOS SOARES'!B5 | B50: =HYPERLINK("#'E M LUIZ CARLOS SOARES'!A1",'E M LUIZ CARLOS SOARES'!B2) | C50: ='E M LUIZ CARLOS SOARES'!B3
A51: ='ESCOLA MUNICIPAL GENERAL HEITOR'!B5 | B51: =HYPERLINK("#'ESCOLA MUNICIPAL GENERAL HEITOR'!A1",'ESCOLA MUNICIPAL GENERAL HEITOR'!B2) | C51: ='ESCOLA MUNICIPAL GENERAL HEITOR'!B3
A52: ='E M JOÃO KOPKE'!B5 | B52: =HYPERLINK("#'E M JOÃO KOPKE'!A1",'E M JOÃO KOPKE'!B2) | C52: ='E M JOÃO KOPKE'!B3
A53: ='ESCOLA MUNICIPAL ODETTE FONSECA'!B5 | B53: =HYPERLINK("#'ESCOLA MUNICIPAL ODETTE FONSECA'!A1",'ESCOLA MUNICIPAL ODETTE FONSECA'!B2) | C53: ='ESCOLA MUNICIPAL ODETTE FONSECA'!B3
A54: ='E M GOVERNADOR MARCELLO ALENCAR'!B5 | B54: =HYPERLINK("#'E M GOVERNADOR MARCELLO ALENCAR'!A1",'E M GOVERNADOR MARCELLO ALENCAR'!B2) | C54: ='E M GOVERNADOR MARCELLO ALENCAR'!B3
A55: ='E M PROF JOAQUIM DEISTER'!B5 | B55: =HYPERLINK("#'E M PROF JOAQUIM DEISTER'!A1",'E M PROF JOAQUIM DEISTER'!B2) | C55: ='E M PROF JOAQUIM DEISTER'!B3
A56: ='E M ROBERT KENNEDY'!B5 | B56: =HYPERLINK("#'E M ROBERT KENNEDY'!A1",'E M ROBERT KENNEDY'!B2) | C56: ='E M ROBERT KENNEDY'!B3
A57: ='E M ROTARY'!B5 | B57: =HYPERLINK("#'E M ROTARY'!A1",'E M ROTARY'!B2) | C57: ='E M ROTARY'!B3
A58: ='E M ROSALINA NICOLAY'!B5 | B58: =HYPERLINK("#'E M ROSALINA NICOLAY'!A1",'E M ROSALINA NICOLAY'!B2) | C58: ='E M ROSALINA NICOLAY'!B3
A59: ='E M DE EDUCAÇÃO ESPECIAL SANTOS'!B5 | B59: =HYPERLINK("#'E M DE EDUCAÇÃO ESPECIAL SANTOS'!A1",'E M DE EDUCAÇÃO ESPECIAL SANTOS'!B2) | C59: ='E M DE EDUCAÇÃO ESPECIAL SANTOS'!B3
A60: ='E M SOROPTIMISTA'!B5 | B60: =HYPERLINK("#'E M SOROPTIMISTA'!A1",'E M SOROPTIMISTA'!B2) | C60: ='E M SOROPTIMISTA'!B3
A61: ='LICEU MUN PREFEITO CORDOLINO AM'!B5 | B61: =HYPERLINK("#'LICEU MUN PREFEITO CORDOLINO AM'!A1",'LICEU MUN PREFEITO CORDOLINO AM'!B2) | C61: ='LICEU MUN PREFEITO CORDOLINO AM'!B3
A62: ='E M ANTÔNIO LEITE GARCIA'!B5 | B62: =HYPERLINK("#'E M ANTÔNIO LEITE GARCIA'!A1",'E M ANTÔNIO LEITE GARCIA'!B2) | C62: ='E M ANTÔNIO LEITE GARCIA'!B3
A63: ='ESCOLA MUNICIPAL JORGE AMADO'!B5 | B63: =HYPERLINK("#'ESCOLA MUNICIPAL JORGE AMADO'!A1",'ESCOLA MUNICIPAL JORGE AMADO'!B2) | C63: ='ESCOLA MUNICIPAL JORGE AMADO'!B3
A64: ='ESCOLA MUNICIPAL LÚCIA DE ALMEI'!B5 | B64: =HYPERLINK("#'ESCOLA MUNICIPAL LÚCIA DE ALMEI'!A1",'ESCOLA MUNICIPAL LÚCIA DE ALMEI'!B2) | C64: ='ESCOLA MUNICIPAL LÚCIA DE ALMEI'!B3
A65: ='E M MAGDALENA TAGLIAFERRO'!B5 | B65: =HYPERLINK("#'E M MAGDALENA TAGLIAFERRO'!A1",'E M MAGDALENA TAGLIAFERRO'!B2) | C65: ='E M MAGDALENA TAGLIAFERRO'!B3
A66: ='ESCOLA MUNICIPAL MAJOR JÚLIO FR'!B5 | B66: =HYPERLINK("#'ESCOLA MUNICIPAL MAJOR JÚLIO FR'!A1",'ESCOLA MUNICIPAL MAJOR JÚLIO FR'!B2) | C66: ='ESCOLA MUNICIPAL MAJOR JÚLIO FR'!B3
A67: ='E M MARIETA GONÇALVES'!B5 | B67: =HYPERLINK("#'E M MARIETA GONÇALVES'!A1",'E M MARIETA GONÇALVES'!B2) | C67: ='E M MARIETA GONÇALVES'!B3
A68: ='ESCOLA MUNICIPAL ODETTE YOUNG M'!B5 | B68: =HYPERLINK("#'ESCOLA MUNICIPAL ODETTE YOUNG M'!A1",'ESCOLA MUNICIPAL ODETTE YOUNG M'!B2) | C68: ='ESCOLA MUNICIPAL ODETTE YOUNG M'!B3
A69: ='E M FÁBRICA DO SABER'!B5 | B69: =HYPERLINK("#'E M FÁBRICA DO SABER'!A1",'E M FÁBRICA DO SABER'!B2) | C69: ='E M FÁBRICA DO SABER'!B3
A70: ='ESCOLA MUNICIPAL PROFESSOR PAUL'!B5 | B70: =HYPERLINK("#'ESCOLA MUNICIPAL PROFESSOR PAUL'!A1",'ESCOLA MUNICIPAL PROFESSOR PAUL'!B2) | C70: ='ESCOLA MUNICIPAL PROFESSOR PAUL'!B3
A71: ='E M ROSEMIRA DE OLIVEIRA CAVALC'!B5 | B71: =HYPERLINK("#'E M ROSEMIRA DE OLIVEIRA CAVALC'!A1",'E M ROSEMIRA DE OLIVEIRA CAVALC'!B2) | C71: ='E M ROSEMIRA DE OLIVEIRA CAVALC'!B3
A72: ='E M AMÉLIA ANTUNES RABELLO'!B5 | B72: =HYPERLINK("#'E M AMÉLIA ANTUNES RABELLO'!A1",'E M AMÉLIA ANTUNES RABELLO'!B2) | C72: ='E M AMÉLIA ANTUNES RABELLO'!B3
A73: ='ESCOLA MUNICIPAL AUGUSTO PUGNAL'!B5 | B73: =HYPERLINK("#'ESCOLA MUNICIPAL AUGUSTO PUGNAL'!A1",'ESCOLA MUNICIPAL AUGUSTO PUGNAL'!B2) | C73: ='ESCOLA MUNICIPAL AUGUSTO PUGNAL'!B3
A74: ='ESCOLA MUNICIPAL CELINA SCHECHN'!B5 | B74: =HYPERLINK("#'ESCOLA MUNICIPAL CELINA SCHECHN'!A1",'ESCOLA MUNICIPAL CELINA SCHECHN'!B2) | C74: ='ESCOLA MUNICIPAL CELINA SCHECHN'!B3
A75: ='E M DARCY CORREA DA VEIGA'!B5 | B75: =HYPERLINK("#'E M DARCY CORREA DA VEIGA'!A1",'E M DARCY CORREA DA VEIGA'!B2) | C75: ='E M DARCY CORREA DA VEIGA'!B3
A76: ='E M DR PAULA BUARQUE'!B5 | B76: =HYPERLINK("#'E M DR PAULA BUARQUE'!A1",'E M DR PAULA BUARQUE'!B2) | C76: ='E M DR PAULA BUARQUE'!B3
A77: ='E M DR THEODORO MACHADO'!B5 | B77: =HYPERLINK("#'E M DR THEODORO MACHADO'!A1",'E M DR THEODORO MACHADO'!B2) | C77: ='E M DR THEODORO MACHADO'!B3
A78: ='E M ARNALDO DYCKERHOFF'!B5 | B78: =HYPERLINK("#'E M ARNALDO DYCKERHOFF'!A1",'E M ARNALDO DYCKERHOFF'!B2) | C78: ='E M ARNALDO DYCKERHOFF'!B3
A79: ='E M CARLOS CANEDO'!B5 | B79: =HYPERLINK("#'E M CARLOS CANEDO'!A1",'E M CARLOS CANEDO'!B2) | C79: ='E M CARLOS CANEDO'!B3
A80: ='E M DR BARROS FRANCO'!B5 | B80: =HYPERLINK("#'E M DR BARROS FRANCO'!A1",'E M DR BARROS FRANCO'!B2) | C80: ='E M DR BARROS FRANCO'!B3
A81: ='E M MAJOR THEÓFILO DE CARVALHO'!B5 | B81: =HYPERLINK("#'E M MAJOR THEÓFILO DE CARVALHO'!A1",'E M MAJOR THEÓFILO DE CARVALHO'!B2) | C81: ='E M MAJOR THEÓFILO DE CARVALHO'!B3
A82: ='E M TAQUARIL'!B5 | B82: =HYPERLINK("#'E M TAQUARIL'!A1",'E M TAQUARIL'!B2) | C82: ='E M TAQUARIL'!B3
A83: ='E M BEATRIZ ZALESKI'!B5 | B83: =HYPERLINK("#'E M BEATRIZ ZALESKI'!A1",'E M BEATRIZ ZALESKI'!B2) | C83: ='E M BEATRIZ ZALESKI'!B3
A84: ='E M ANTÔNIO JOSÉ DE LIMA'!B5 | B84: =HYPERLINK("#'E M ANTÔNIO JOSÉ DE LIMA'!A1",'E M ANTÔNIO JOSÉ DE LIMA'!B2) | C84: ='E M ANTÔNIO JOSÉ DE LIMA'!B3
A85: ='E M FELIX WAN ERVEN DE BARROS'!B5 | B85: =HYPERLINK("#'E M FELIX WAN ERVEN DE BARROS'!A1",'E M FELIX WAN ERVEN DE BARROS'!B2) | C85: ='E M FELIX WAN ERVEN DE BARROS'!B3
A86: ='ESCOLA MUNICIPAL HILDEBRANDO DE'!B5 | B86: =HYPERLINK("#'ESCOLA MUNICIPAL HILDEBRANDO DE'!A1",'ESCOLA MUNICIPAL HILDEBRANDO DE'!B2) | C86: ='ESCOLA MUNICIPAL HILDEBRANDO DE'!B3
A87: ='E M OSWALDO DA COSTA FRIAS'!B5 | B87: =HYPERLINK("#'E M OSWALDO DA COSTA FRIAS'!A1",'E M OSWALDO DA COSTA FRIAS'!B2) | C87: ='E M OSWALDO DA COSTA FRIAS'!B3
A88: ='E MZDA CARMEM NUNES MARTINS'!B5 | B88: =HYPERLINK("#'E MZDA CARMEM NUNES MARTINS'!A1",'E MZDA CARMEM NUNES MARTINS'!B2) | C88: ='E MZDA CARMEM NUNES MARTINS'!B3
A89: ='E MZDA AVELINO DE CARVALHO'!B5 | B89: =HYPERLINK("#'E MZDA AVELINO DE CARVALHO'!A1",'E MZDA AVELINO DE CARVALHO'!B2) | C89: ='E MZDA AVELINO DE CARVALHO'!B3
A90: ='E M GERALDO VENTURA DIAS'!B5 | B90: =HYPERLINK("#'E M GERALDO VENTURA DIAS'!A1",'E M GERALDO VENTURA DIAS'!B2) | C90: ='E M GERALDO VENTURA DIAS'!B3
A91: ='E M SALVADOR KLING'!B5 | B91: =HYPERLINK("#'E M SALVADOR KLING'!A1",'E M SALVADOR KLING'!B2) | C91: ='E M SALVADOR KLING'!B3
A92: ='E M PREFEITO JAMIL SABRÁ'!B5 | B92: =HYPERLINK("#'E M PREFEITO JAMIL SABRÁ'!A1",'E M PREFEITO JAMIL SABRÁ'!B2) | C92: ='E M PREFEITO JAMIL SABRÁ'!B3
A93: ='LICEU MUNICIPAL CARLOS CHAGAS F'!B5 | B93: =HYPERLINK("#'LICEU MUNICIPAL CARLOS CHAGAS F'!A1",'LICEU MUNICIPAL CARLOS CHAGAS F'!B2) | C93: ='LICEU MUNICIPAL CARLOS CHAGAS F'!B3
A94: ='ESCOLA MUNICIPAL ANA MOHAMMAD'!B5 | B94: =HYPERLINK("#'ESCOLA MUNICIPAL ANA MOHAMMAD'!A1",'ESCOLA MUNICIPAL ANA MOHAMMAD'!B2) | C94: ='ESCOLA MUNICIPAL ANA MOHAMMAD'!B3
A95: ='ESCOLA MUNICIPAL ALTO INDEPENDÊ'!B5 | B95: =HYPERLINK("#'ESCOLA MUNICIPAL ALTO INDEPENDÊ'!A1",'ESCOLA MUNICIPAL ALTO INDEPENDÊ'!B2) | C95: ='ESCOLA MUNICIPAL ALTO INDEPENDÊ'!B3
A96: ='E M ALMIRANTE TAMANDARÉ'!B5 | B96: =HYPERLINK("#'E M ALMIRANTE TAMANDARÉ'!A1",'E M ALMIRANTE TAMANDARÉ'!B2) | C96: ='E M ALMIRANTE TAMANDARÉ'!B3
A97: ='ESCOLA MUNICIPALIZADA FREI ANIC'!B5 | B97: =HYPERLINK("#'ESCOLA MUNICIPALIZADA FREI ANIC'!A1",'ESCOLA MUNICIPALIZADA FREI ANIC'!B2) | C97: ='ESCOLA MUNICIPALIZADA FREI ANIC'!B3
A98: ='E M PEDRO AMADO'!B5 | B98: =HYPERLINK("#'E M PEDRO AMADO'!A1",'E M PEDRO AMADO'!B2) | C98: ='E M PEDRO AMADO'!B3
A99: ='E M PROFª MARIA DA GLÓRIA QUEIR'!B5 | B99: =HYPERLINK("#'E M PROFª MARIA DA GLÓRIA QUEIR'!A1",'E M PROFª MARIA DA GLÓRIA QUEIR'!B2) | C99: ='E M PROFª MARIA DA GLÓRIA QUEIR'!B3
A100: ='E M SEBASTIÃO LACERDA'!B5 | B100: =HYPERLINK("#'E M SEBASTIÃO LACERDA'!A1",'E M SEBASTIÃO LACERDA'!B2) | C100: ='E M SEBASTIÃO LACERDA'!B3
A101: ='E M PROFESSOR FLÁVIO MACIEL'!B5 | B101: =HYPERLINK("#'E M PROFESSOR FLÁVIO MACIEL'!A1",'E M PROFESSOR FLÁVIO MACIEL'!B2) | C101: ='E M PROFESSOR FLÁVIO MACIEL'!B3
A102: ='ESCOLA MUNICIPAL PAULO SALDANHA'!B5 | B102: =HYPERLINK("#'ESCOLA MUNICIPAL PAULO SALDANHA'!A1",'ESCOLA MUNICIPAL PAULO SALDANHA'!B2) | C102: ='ESCOLA MUNICIPAL PAULO SALDANHA'!B3
A103: ='ESCOLA MUNICIPAL PROFESSOR JOSE'!B5 | B103: =HYPERLINK("#'ESCOLA MUNICIPAL PROFESSOR JOSE'!A1",'ESCOLA MUNICIPAL PROFESSOR JOSE'!B2) | C103: ='ESCOLA MUNICIPAL PROFESSOR JOSE'!B3
A104: ='E M MONSENHOR CIRILLO CALAON'!B5 | B104: =HYPERLINK("#'E M MONSENHOR CIRILLO CALAON'!A1",'E M MONSENHOR CIRILLO CALAON'!B2) | C104: ='E M MONSENHOR CIRILLO CALAON'!B3
A105: ='E M AMÉRICO FERNANDES RIBEIRO'!B5 | B105: =HYPERLINK("#'E M AMÉRICO FERNANDES RIBEIRO'!A1",'E M AMÉRICO FERNANDES RIBEIRO'!B2) | C105: ='E M AMÉRICO FERNANDES RIBEIRO'!B3
A106: ='E M PROFª JANDIRA PEIXOTO BORDI'!B5 | B106: =HYPERLINK("#'E M PROFª JANDIRA PEIXOTO BORDI'!A1",'E M PROFª JANDIRA PEIXOTO BORDI'!B2) | C106: ='E M PROFª JANDIRA PEIXOTO BORDI'!B3
A107: ='E M MONSENHOR JOÃO DE DEUS RODR'!B5 | B107: =HYPERLINK("#'E M MONSENHOR JOÃO DE DEUS RODR'!A1",'E M MONSENHOR JOÃO DE DEUS RODR'!B2) | C107: ='E M MONSENHOR JOÃO DE DEUS RODR'!B3
A108: ='E M DOM MANOEL PEDRO DA CUNHA C'!B5 | B108: =HYPERLINK("#'E M DOM MANOEL PEDRO DA CUNHA C'!A1",'E M DOM MANOEL PEDRO DA CUNHA C'!B2) | C108: ='E M DOM MANOEL PEDRO DA CUNHA C'!B3
A109: ='E M JOHANN NOEL'!B5 | B109: =HYPERLINK("#'E M JOHANN NOEL'!A1",'E M JOHANN NOEL'!B2) | C109: ='E M JOHANN NOEL'!B3
A110: ='E MZDA SANTA TEREZINHA'!B5 | B110: =HYPERLINK("#'E MZDA SANTA TEREZINHA'!A1",'E MZDA SANTA TEREZINHA'!B2) | C110: ='E MZDA SANTA TEREZINHA'!B3
A111: ='E M PAPA JOÃO PAULO II'!B5 | B111: =HYPERLINK("#'E M PAPA JOÃO PAULO II'!A1",'E M PAPA JOÃO PAULO II'!B2) | C111: ='E M PAPA JOÃO PAULO II'!B3
A112: ='E M STEFAN ZWEIG'!B5 | B112: =HYPERLINK("#'E M STEFAN ZWEIG'!A1",'E M STEFAN ZWEIG'!B2) | C112: ='E M STEFAN ZWEIG'!B3
A113: ='ESCOLA MUNICIPAL SENADOR MARIO '!B5 | B113: =HYPERLINK("#'ESCOLA MUNICIPAL SENADOR MARIO '!A1",'ESCOLA MUNICIPAL SENADOR MARIO '!B2) | C113: ='ESCOLA MUNICIPAL SENADOR MARIO '!B3
A114: ='E M DR RUBENS DE CASTRO BOMTEMP'!B5 | B114: =HYPERLINK("#'E M DR RUBENS DE CASTRO BOMTEMP'!A1",'E M DR RUBENS DE CASTRO BOMTEMP'!B2) | C114: ='E M DR RUBENS DE CASTRO BOMTEMP'!B3
A115: ='E M PAULO FREIRE'!B5 | B115: =HYPERLINK("#'E M PAULO FREIRE'!A1",'E M PAULO FREIRE'!B2) | C115: ='E M PAULO FREIRE'!B3
A116: ='E M PROFª MARIA CAMPOS DA SILVA'!B5 | B116: =HYPERLINK("#'E M PROFª MARIA CAMPOS DA SILVA'!A1",'E M PROFª MARIA CAMPOS DA SILVA'!B2) | C116: ='E M PROFª MARIA CAMPOS DA SILVA'!B3
A117: ='E M HERCÍLIA HENRIQUES MORET'!B5 | B117: =HYPERLINK("#'E M HERCÍLIA HENRIQUES MORET'!A1",'E M HERCÍLIA HENRIQUES MORET'!B2) | C117: ='E M HERCÍLIA HENRIQUES MORET'!B3
A118: ='ESCOLA MUNICIPALIZADA MOYSÉS FU'!B5 | B118: =HYPERLINK("#'ESCOLA MUNICIPALIZADA MOYSÉS FU'!A1",'ESCOLA MUNICIPALIZADA MOYSÉS FU'!B2) | C118: ='ESCOLA MUNICIPALIZADA MOYSÉS FU'!B3
A119: ='CIEP BRIZOLÃO 474 MAESTRO GUERR'!B5 | B119: =HYPERLINK("#'CIEP BRIZOLÃO 474 MAESTRO GUERR'!A1",'CIEP BRIZOLÃO 474 MAESTRO GUERR'!B2) | C119: ='CIEP BRIZOLÃO 474 MAESTRO GUERR'!B3
A120: ='CENTRO DE ENSINO PROF DARCY RIB'!B5 | B120: =HYPERLINK("#'CENTRO DE ENSINO PROF DARCY RIB'!A1",'CENTRO DE ENSINO PROF DARCY RIB'!B2) | C120: ='CENTRO DE ENSINO PROF DARCY RIB'!B3
...

Sheet Entrada de Dados
A1: ENTRADA DE DADOS
A2: PREÇO (R$/kg) | C2: 15.57 | D2: 7.7 | E2: 16.94 | F2: 14.62 | G2: 12.05 | H2: 11.59 | I2: 9.87 | J2: 13.67 | K2: 10.2 | L2: 25.1 | M2: 8.56 | N2: 14.6 | O2: 19.11 | P2: 11.22 | Q2: 16.63 | R2: 65.68 | S2: 15.45 | T2: 10.24 | U2: 13.55
A4: PEDIDO DAS ESCOLAS (kg)
A5: CÓDIGO | B5: ESCOLA | C5: Abacate | D5: Abobrinha | E5: Agrião | F5: Alface lisa | G5: Banana prata | H5: Batata inglesa | I5: Beterraba | J5: Brócolis | K5: Cenoura | L5: Cheiro verde | M5: Chuchu | N5: Couve manteiga | O5: Couve-flor | P5: Espinafre | Q5: Maçã gala | R5: Mel | S5: Ovos (dz) | T5: Repolho | U5: Tangerina ponkan | V5: Aba real (ref.)
A6: ='E M ABELARDO DE LAMARE'!B5 | B6: =HYPERLINK("#'E M ABELARDO DE LAMARE'!A1",'E M ABELARDO DE LAMARE'!B2) | V6: E M ABELARDO DE LAMARE
A7: ='E M BATAILLARD'!B5 | B7: =HYPERLINK("#'E M BATAILLARD'!A1",'E M BATAILLARD'!B2) | V7: E M BATAILLARD
A8: ='E M LEONARDO BOFF'!B5 | B8: =HYPERLINK("#'E M LEONARDO BOFF'!A1",'E M LEONARDO BOFF'!B2) | V8: E M LEONARDO BOFF
A9: ='E M CLEMENTE FERNANDES'!B5 | B9: =HYPERLINK("#'E M CLEMENTE FERNANDES'!A1",'E M CLEMENTE FERNANDES'!B2) | V9: E M CLEMENTE FERNANDES
A10: ='E M DOM PEDRO DE ALCÂNTARA'!B5 | B10: =HYPERLINK("#'E M DOM PEDRO DE ALCÂNTARA'!A1",'E M DOM PEDRO DE ALCÂNTARA'!B2) | V10: E M DOM PEDRO DE ALCÂNTARA
A11: ='E M DUQUE DE CAXIAS'!B5 | B11: =HYPERLINK("#'E M DUQUE DE CAXIAS'!A1",'E M DUQUE DE CAXIAS'!B2) | V11: E M DUQUE DE CAXIAS
A12: ='E M LUIZ CARLOS SOARES'!B5 | B12: =HYPERLINK("#'E M LUIZ CARLOS SOARES'!A1",'E M LUIZ CARLOS SOARES'!B2) | V12: E M LUIZ CARLOS SOARES
A13: ='ESCOLA MUNICIPAL GENERAL HEITOR'!B5 | B13: =HYPERLINK("#'ESCOLA MUNICIPAL GENERAL HEITOR'!A1",'ESCOLA MUNICIPAL GENERAL HEITOR'!B2) | V13: ESCOLA MUNICIPAL GENERAL HEITOR
A14: ='E M JOÃO KOPKE'!B5 | B14: =HYPERLINK("#'E M JOÃO KOPKE'!A1",'E M JOÃO KOPKE'!B2) | V14: E M JOÃO KOPKE
A15: ='ESCOLA MUNICIPAL ODETTE FONSECA'!B5 | B15: =HYPERLINK("#'ESCOLA MUNICIPAL ODETTE FONSECA'!A1",'ESCOLA MUNICIPAL ODETTE FONSECA'!B2) | V15: ESCOLA MUNICIPAL ODETTE FONSECA
A16: ='E M GOVERNADOR MARCELLO ALENCAR'!B5 | B16: =HYPERLINK("#'E M GOVERNADOR MARCELLO ALENCAR'!A1",'E M GOVERNADOR MARCELLO ALENCAR'!B2) | V16: E M GOVERNADOR MARCELLO ALENCAR
A17: ='E M PROF JOAQUIM DEISTER'!B5 | B17: =HYPERLINK("#'E M PROF JOAQUIM DEISTER'!A1",'E M PROF JOAQUIM DEISTER'!B2) | V17: E M PROF JOAQUIM DEISTER
A18: ='E M ROBERT KENNEDY'!B5 | B18: =HYPERLINK("#'E M ROBERT KENNEDY'!A1",'E M ROBERT KENNEDY'!B2) | V18: E M ROBERT KENNEDY
A19: ='E M ROTARY'!B5 | B19: =HYPERLINK("#'E M ROTARY'!A1",'E M ROTARY'!B2) | V19: E M ROTARY
A20: ='E M ROSALINA NICOLAY'!B5 | B20: =HYPERLINK("#'E M ROSALINA NICOLAY'!A1",'E M ROSALINA NICOLAY'!B2) | V20: E M ROSALINA NICOLAY
A21: ='E M DE EDUCAÇÃO ESPECIAL SANTOS'!B5 | B21: =HYPERLINK("#'E M DE EDUCAÇÃO ESPECIAL SANTOS'!A1",'E M DE EDUCAÇÃO ESPECIAL SANTOS'!B2) | V21: E M DE EDUCAÇÃO ESPECIAL SANTOS
A22: ='E M SOROPTIMISTA'!B5 | B22: =HYPERLINK("#'E M SOROPTIMISTA'!A1",'E M SOROPTIMISTA'!B2) | V22: E M SOROPTIMISTA
A23: ='LICEU MUN PREFEITO CORDOLINO AM'!B5 | B23: =HYPERLINK("#'LICEU MUN PREFEITO CORDOLINO AM'!A1",'LICEU MUN PREFEITO CORDOLINO AM'!B2) | V23: LICEU MUN PREFEITO CORDOLINO AM
A24: ='E M ANTÔNIO LEITE GARCIA'!B5 | B24: =HYPERLINK("#'E M ANTÔNIO LEITE GARCIA'!A1",'E M ANTÔNIO LEITE GARCIA'!B2) | V24: E M ANTÔNIO LEITE GARCIA
A25: ='ESCOLA MUNICIPAL JORGE AMADO'!B5 | B25: =HYPERLINK("#'ESCOLA MUNICIPAL JORGE AMADO'!A1",'ESCOLA MUNICIPAL JORGE AMADO'!B2) | V25: ESCOLA MUNICIPAL JORGE AMADO
A26: ='ESCOLA MUNICIPAL LÚCIA DE ALMEI'!B5 | B26: =HYPERLINK("#'ESCOLA MUNICIPAL LÚCIA DE ALMEI'!A1",'ESCOLA MUNICIPAL LÚCIA DE ALMEI'!B2) | V26: ESCOLA MUNICIPAL LÚCIA DE ALMEI
A27: ='E M MAGDALENA TAGLIAFERRO'!B5 | B27: =HYPERLINK("#'E M MAGDALENA TAGLIAFERRO'!A1",'E M MAGDALENA TAGLIAFERRO'!B2) | V27: E M MAGDALENA TAGLIAFERRO
A28: ='ESCOLA MUNICIPAL MAJOR JÚLIO FR'!B5 | B28: =HYPERLINK("#'ESCOLA MUNICIPAL MAJOR JÚLIO FR'!A1",'ESCOLA MUNICIPAL MAJOR JÚLIO FR'!B2) | V28: ESCOLA MUNICIPAL MAJOR JÚLIO FR
A29: ='E M MARIETA GONÇALVES'!B5 | B29: =HYPERLINK("#'E M MARIETA GONÇALVES'!A1",'E M MARIETA GONÇALVES'!B2) | V29: E M MARIETA GONÇALVES
A30: ='ESCOLA MUNICIPAL ODETTE YOUNG M'!B5 | B30: =HYPERLINK("#'ESCOLA MUNICIPAL ODETTE YOUNG M'!A1",'ESCOLA MUNICIPAL ODETTE YOUNG M'!B2) | V30: ESCOLA MUNICIPAL ODETTE YOUNG M
A31: ='E M FÁBRICA DO SABER'!B5 | B31: =HYPERLINK("#'E M FÁBRICA DO SABER'!A1",'E M FÁBRICA DO SABER'!B2) | V31: E M FÁBRICA DO SABER
A32: ='ESCOLA MUNICIPAL PROFESSOR PAUL'!B5 | B32: =HYPERLINK("#'ESCOLA MUNICIPAL PROFESSOR PAUL'!A1",'ESCOLA MUNICIPAL PROFESSOR PAUL'!B2) | V32: ESCOLA MUNICIPAL PROFESSOR PAUL
A33: ='E M ROSEMIRA DE OLIVEIRA CAVALC'!B5 | B33: =HYPERLINK("#'E M ROSEMIRA DE OLIVEIRA CAVALC'!A1",'E M ROSEMIRA DE OLIVEIRA CAVALC'!B2) | V33: E M ROSEMIRA DE OLIVEIRA CAVALC
A34: ='E M AMÉLIA ANTUNES RABELLO'!B5 | B34: =HYPERLINK("#'E M AMÉLIA ANTUNES RABELLO'!A1",'E M AMÉLIA ANTUNES RABELLO'!B2) | V34: E M AMÉLIA ANTUNES RABELLO
A35: ='ESCOLA MUNICIPAL AUGUSTO PUGNAL'!B5 | B35: =HYPERLINK("#'ESCOLA MUNICIPAL AUGUSTO PUGNAL'!A1",'ESCOLA MUNICIPAL AUGUSTO PUGNAL'!B2) | V35: ESCOLA MUNICIPAL AUGUSTO PUGNAL
A36: ='ESCOLA MUNICIPAL CELINA SCHECHN'!B5 | B36: =HYPERLINK("#'ESCOLA MUNICIPAL CELINA SCHECHN'!A1",'ESCOLA MUNICIPAL CELINA SCHECHN'!B2) | V36: ESCOLA MUNICIPAL CELINA SCHECHN
A37: ='E M DARCY CORREA DA VEIGA'!B5 | B37: =HYPERLINK("#'E M DARCY CORREA DA VEIGA'!A1",'E M DARCY CORREA DA VEIGA'!B2) | V37: E M DARCY CORREA DA VEIGA
A38: ='E M DR PAULA BUARQUE'!B5 | B38: =HYPERLINK("#'E M DR PAULA BUARQUE'!A1",'E M DR PAULA BUARQUE'!B2) | V38: E M DR PAULA BUARQUE
A39: ='E M DR THEODORO MACHADO'!B5 | B39: =HYPERLINK("#'E M DR THEODORO MACHADO'!A1",'E M DR THEODORO MACHADO'!B2) | V39: E M DR THEODORO MACHADO
A40: ='E M ARNALDO DYCKERHOFF'!B5 | B40: =HYPERLINK("#'E M ARNALDO DYCKERHOFF'!A1",'E M ARNALDO DYCKERHOFF'!B2) | V40: E M ARNALDO DYCKERHOFF
A41: ='E M CARLOS CANEDO'!B5 | B41: =HYPERLINK("#'E M CARLOS CANEDO'!A1",'E M CARLOS CANEDO'!B2) | V41: E M CARLOS CANEDO
A42: ='E M DR BARROS FRANCO'!B5 | B42: =HYPERLINK("#'E M DR BARROS FRANCO'!A1",'E M DR BARROS FRANCO'!B2) | V42: E M DR BARROS FRANCO
A43: ='E M MAJOR THEÓFILO DE CARVALHO'!B5 | B43: =HYPERLINK("#'E M MAJOR THEÓFILO DE CARVALHO'!A1",'E M MAJOR THEÓFILO DE CARVALHO'!B2) | V43: E M MAJOR THEÓFILO DE CARVALHO
A44: ='E M TAQUARIL'!B5 | B44: =HYPERLINK("#'E M TAQUARIL'!A1",'E M TAQUARIL'!B2) | V44: E M TAQUARIL
A45: ='E M BEATRIZ ZALESKI'!B5 | B45: =HYPERLINK("#'E M BEATRIZ ZALESKI'!A1",'E M BEATRIZ ZALESKI'!B2) | V45: E M BEATRIZ ZALESKI
A46: ='E M ANTÔNIO JOSÉ DE LIMA'!B5 | B46: =HYPERLINK("#'E M ANTÔNIO JOSÉ DE LIMA'!A1",'E M ANTÔNIO JOSÉ DE LIMA'!B2) | V46: E M ANTÔNIO JOSÉ DE LIMA
A47: ='E M FELIX WAN ERVEN DE BARROS'!B5 | B47: =HYPERLINK("#'E M FELIX WAN ERVEN DE BARROS'!A1",'E M FELIX WAN ERVEN DE BARROS'!B2) | V47: E M FELIX WAN ERVEN DE BARROS
A48: ='ESCOLA MUNICIPAL HILDEBRANDO DE'!B5 | B48: =HYPERLINK("#'ESCOLA MUNICIPAL HILDEBRANDO DE'!A1",'ESCOLA MUNICIPAL HILDEBRANDO DE'!B2) | V48: ESCOLA MUNICIPAL HILDEBRANDO DE
A49: ='E M OSWALDO DA COSTA FRIAS'!B5 | B49: =HYPERLINK("#'E M OSWALDO DA COSTA FRIAS'!A1",'E M OSWALDO DA COSTA FRIAS'!B2) | V49: E M OSWALDO DA COSTA FRIAS
A50: ='E MZDA CARMEM NUNES MARTINS'!B5 | B50: =HYPERLINK("#'E MZDA CARMEM NUNES MARTINS'!A1",'E MZDA CARMEM NUNES MARTINS'!B2) | V50: E MZDA CARMEM NUNES MARTINS
A51: ='E MZDA AVELINO DE CARVALHO'!B5 | B51: =HYPERLINK("#'E MZDA AVELINO DE CARVALHO'!A1",'E MZDA AVELINO DE CARVALHO'!B2) | V51: E MZDA AVELINO DE CARVALHO
A52: ='E M GERALDO VENTURA DIAS'!B5 | B52: =HYPERLINK("#'E M GERALDO VENTURA DIAS'!A1",'E M GERALDO VENTURA DIAS'!B2) | V52: E M GERALDO VENTURA DIAS
A53: ='E M SALVADOR KLING'!B5 | B53: =HYPERLINK("#'E M SALVADOR KLING'!A1",'E M SALVADOR KLING'!B2) | V53: E M SALVADOR KLING
A54: ='E M PREFEITO JAMIL SABRÁ'!B5 | B54: =HYPERLINK("#'E M PREFEITO JAMIL SABRÁ'!A1",'E M PREFEITO JAMIL SABRÁ'!B2) | V54: E M PREFEITO JAMIL SABRÁ
A55: ='LICEU MUNICIPAL CARLOS CHAGAS F'!B5 | B55: =HYPERLINK("#'LICEU MUNICIPAL CARLOS CHAGAS F'!A1",'LICEU MUNICIPAL CARLOS CHAGAS F'!B2) | V55: LICEU MUNICIPAL CARLOS CHAGAS F
A56: ='ESCOLA MUNICIPAL ANA MOHAMMAD'!B5 | B56: =HYPERLINK("#'ESCOLA MUNICIPAL ANA MOHAMMAD'!A1",'ESCOLA MUNICIPAL ANA MOHAMMAD'!B2) | V56: ESCOLA MUNICIPAL ANA MOHAMMAD
A57: ='ESCOLA MUNICIPAL ALTO INDEPENDÊ'!B5 | B57: =HYPERLINK("#'ESCOLA MUNICIPAL ALTO INDEPENDÊ'!A1",'ESCOLA MUNICIPAL ALTO INDEPENDÊ'!B2) | V57: ESCOLA MUNICIPAL ALTO INDEPENDÊ
A58: ='E M ALMIRANTE TAMANDARÉ'!B5 | B58: =HYPERLINK("#'E M ALMIRANTE TAMANDARÉ'!A1",'E M ALMIRANTE TAMANDARÉ'!B2) | V58: E M ALMIRANTE TAMANDARÉ
A59: ='ESCOLA MUNICIPALIZADA FREI ANIC'!B5 | B59: =HYPERLINK("#'ESCOLA MUNICIPALIZADA FREI ANIC'!A1",'ESCOLA MUNICIPALIZADA FREI ANIC'!B2) | V59: ESCOLA MUNICIPALIZADA FREI ANIC
A60: ='E M PEDRO AMADO'!B5 | B60: =HYPERLINK("#'E M PEDRO AMADO'!A1",'E M PEDRO AMADO'!B2) | V60: E M PEDRO AMADO
A61: ='E M PROFª MARIA DA GLÓRIA QUEIR'!B5 | B61: =HYPERLINK("#'E M PROFª MARIA DA GLÓRIA QUEIR'!A1",'E M PROFª MARIA DA GLÓRIA QUEIR'!B2) | V61: E M PROFª MARIA DA GLÓRIA QUEIR
A62: ='E M SEBASTIÃO LACERDA'!B5 | B62: =HYPERLINK("#'E M SEBASTIÃO LACERDA'!A1",'E M SEBASTIÃO LACERDA'!B2) | V62: E M SEBASTIÃO LACERDA
A63: ='E M PROFESSOR FLÁVIO MACIEL'!B5 | B63: =HYPERLINK("#'E M PROFESSOR FLÁVIO MACIEL'!A1",'E M PROFESSOR FLÁVIO MACIEL'!B2) | V63: E M PROFESSOR FLÁVIO MACIEL
A64: ='ESCOLA MUNICIPAL PAULO SALDANHA'!B5 | B64: =HYPERLINK("#'ESCOLA MUNICIPAL PAULO SALDANHA'!A1",'ESCOLA MUNICIPAL PAULO SALDANHA'!B2) | V64: ESCOLA MUNICIPAL PAULO SALDANHA
A65: ='ESCOLA MUNICIPAL PROFESSOR JOSE'!B5 | B65: =HYPERLINK("#'ESCOLA MUNICIPAL PROFESSOR JOSE'!A1",'ESCOLA MUNICIPAL PROFESSOR JOSE'!B2) | V65: ESCOLA MUNICIPAL PROFESSOR JOSE
A66: ='E M MONSENHOR CIRILLO CALAON'!B5 | B66: =HYPERLINK("#'E M MONSENHOR CIRILLO CALAON'!A1",'E M MONSENHOR CIRILLO CALAON'!B2) | V66: E M MONSENHOR CIRILLO CALAON
A67: ='E M AMÉRICO FERNANDES RIBEIRO'!B5 | B67: =HYPERLINK("#'E M AMÉRICO FERNANDES RIBEIRO'!A1",'E M AMÉRICO FERNANDES RIBEIRO'!B2) | V67: E M AMÉRICO FERNANDES RIBEIRO
A68: ='E M PROFª JANDIRA PEIXOTO BORDI'!B5 | B68: =HYPERLINK("#'E M PROFª JANDIRA PEIXOTO BORDI'!A1",'E M PROFª JANDIRA PEIXOTO BORDI'!B2) | V68: E M PROFª JANDIRA PEIXOTO BORDI
A69: ='E M MONSENHOR JOÃO DE DEUS RODR'!B5 | B69: =HYPERLINK("#'E M MONSENHOR JOÃO DE DEUS RODR'!A1",'E M MONSENHOR JOÃO DE DEUS RODR'!B2) | V69: E M MONSENHOR JOÃO DE DEUS RODR
A70: ='E M DOM MANOEL PEDRO DA CUNHA C'!B5 | B70: =HYPERLINK("#'E M DOM MANOEL PEDRO DA CUNHA C'!A1",'E M DOM MANOEL PEDRO DA CUNHA C'!B2) | V70: E M DOM MANOEL PEDRO DA CUNHA C
A71: ='E M JOHANN NOEL'!B5 | B71: =HYPERLINK("#'E M JOHANN NOEL'!A1",'E M JOHANN NOEL'!B2) | V71: E M JOHANN NOEL
A72: ='E MZDA SANTA TEREZINHA'!B5 | B72: =HYPERLINK("#'E MZDA SANTA TEREZINHA'!A1",'E MZDA SANTA TEREZINHA'!B2) | V72: E MZDA SANTA TEREZINHA
A73: ='E M PAPA JOÃO PAULO II'!B5 | B73: =HYPERLINK("#'E M PAPA JOÃO PAULO II'!A1",'E M PAPA JOÃO PAULO II'!B2) | V73: E M PAPA JOÃO PAULO II
A74: ='E M STEFAN ZWEIG'!B5 | B74: =HYPERLINK("#'E M STEFAN ZWEIG'!A1",'E M STEFAN ZWEIG'!B2) | V74: E M STEFAN ZWEIG
A75: ='ESCOLA MUNICIPAL SENADOR MARIO '!B5 | B75: =HYPERLINK("#'ESCOLA MUNICIPAL SENADOR MARIO '!A1",'ESCOLA MUNICIPAL SENADOR MARIO '!B2) | V75: ESCOLA MUNICIPAL SENADOR MARIO
A76: ='E M DR RUBENS DE CASTRO BOMTEMP'!B5 | B76: =HYPERLINK("#'E M DR RUBENS DE CASTRO BOMTEMP'!A1",'E M DR RUBENS DE CASTRO BOMTEMP'!B2) | V76: E M DR RUBENS DE CASTRO BOMTEMP
A77: ='E M PAULO FREIRE'!B5 | B77: =HYPERLINK("#'E M PAULO FREIRE'!A1",'E M PAULO FREIRE'!B2) | V77: E M PAULO FREIRE
A78: ='E M PROFª MARIA CAMPOS DA SILVA'!B5 | B78: =HYPERLINK("#'E M PROFª MARIA CAMPOS DA SILVA'!A1",'E M PROFª MARIA CAMPOS DA SILVA'!B2) | V78: E M PROFª MARIA CAMPOS DA SILVA
A79: ='E M HERCÍLIA HENRIQUES MORET'!B5 | B79: =HYPERLINK("#'E M HERCÍLIA HENRIQUES MORET'!A1",'E M HERCÍLIA HENRIQUES MORET'!B2) | V79: E M HERCÍLIA HENRIQUES MORET
A80: ='ESCOLA MUNICIPALIZADA MOYSÉS FU'!B5 | B80: =HYPERLINK("#'ESCOLA MUNICIPALIZADA MOYSÉS FU'!A1",'ESCOLA MUNICIPALIZADA MOYSÉS FU'!B2) | V80: ESCOLA MUNICIPALIZADA MOYSÉS FU
A81: ='CIEP BRIZOLÃO 474 MAESTRO GUERR'!B5 | B81: =HYPERLINK("#'CIEP BRIZOLÃO 474 MAESTRO GUERR'!A1",'CIEP BRIZOLÃO 474 MAESTRO GUERR'!B2) | V81: CIEP BRIZOLÃO 474 MAESTRO GUERR
A82: ='CENTRO DE ENSINO PROF DARCY RIB'!B5 | B82: =HYPERLINK("#'CENTRO DE ENSINO PROF DARCY RIB'!A1",'CENTRO DE ENSINO PROF DARCY RIB'!B2) | V82: CENTRO DE ENSINO PROF DARCY RIB
A83: ='CASA DA EDUCAÇÃO VISCONDE DE MA'!B5 | B83: =HYPERLINK("#'CASA DA EDUCAÇÃO VISCONDE DE MA'!A1",'CASA DA EDUCAÇÃO VISCONDE DE MA'!B2) | V83: CASA DA EDUCAÇÃO VISCONDE DE MA
A84: ='CENTRO DE REFERÊNCIA EM EDUCAÇÃ'!B5 | B84: =HYPERLINK("#'CENTRO DE REFERÊNCIA EM EDUCAÇÃ'!A1",'CENTRO DE REFERÊNCIA EM EDUCAÇÃ'!B2) | V84: CENTRO DE REFERÊNCIA EM EDUCAÇÃ
A85: ='E M PROF NILTON COSTA PEREIRA D'!B5 | B85: =HYPERLINK("#'E M PROF NILTON COSTA PEREIRA D'!A1",'E M PROF NILTON COSTA PEREIRA D'!B2) | V85: E M PROF NILTON COSTA PEREIRA D
A86: ='COLÉGIO GUNNAR VINGREN DE PETRÓ'!B5 | B86: =HYPERLINK("#'COLÉGIO GUNNAR VINGREN DE PETRÓ'!A1",'COLÉGIO GUNNAR VINGREN DE PETRÓ'!B2) | V86: COLÉGIO GUNNAR VINGREN DE PETRÓ
A87: ='CENTRO DE REFERÊNCIA EM EDUC 2'!B5 | B87: =HYPERLINK("#'CENTRO DE REFERÊNCIA EM EDUC 2'!A1",'CENTRO DE REFERÊNCIA EM EDUC 2'!B2) | V87: CENTRO DE REFERÊNCIA EM EDUC 2
A88: ='ESCOLA SANTA LUIZA DE MARILLAC'!B5 | B88: =HYPERLINK("#'ESCOLA SANTA LUIZA DE MARILLAC'!A1",'ESCOLA SANTA LUIZA DE MARILLAC'!B2) | V88: ESCOLA SANTA LUIZA DE MARILLAC
A89: ='CENTRO EDUCACIONAL COMUNIDADE S'!B5 | B89: =HYPERLINK("#'CENTRO EDUCACIONAL COMUNIDADE S'!A1",'CENTRO EDUCACIONAL COMUNIDADE S'!B2) | V89: CENTRO EDUCACIONAL COMUNIDADE S
A90: ='EDUCANDÁRIO TERRA SANTA'!B5 | B90: =HYPERLINK("#'EDUCANDÁRIO TERRA SANTA'!A1",'EDUCANDÁRIO TERRA SANTA'!B2) | V90: EDUCANDÁRIO TERRA SANTA
A91: ='ESCOLA GERMANO VALENTE'!B5 | B91: =HYPERLINK("#'ESCOLA GERMANO VALENTE'!A1",'ESCOLA GERMANO VALENTE'!B2) | V91: ESCOLA GERMANO VALENTE
A92: ='ESCOLA DAS COMUNIDADES SANTO AN'!B5 | B92: =HYPERLINK("#'ESCOLA DAS COMUNIDADES SANTO AN'!A1",'ESCOLA DAS COMUNIDADES SANTO AN'!B2) | V92: ESCOLA DAS COMUNIDADES SANTO AN
A93: ='ESCOLA DOMÉSTICA NOSSA SENHORA '!B5 | B93: =HYPERLINK("#'ESCOLA DOMÉSTICA NOSSA SENHORA '!A1",'ESCOLA DOMÉSTICA NOSSA SENHORA '!B2) | V93: ESCOLA DOMÉSTICA NOSSA SENHORA
A94: ='ESCOLA PAROQUIAL NOSSA SENHO 3'!B5 | B94: =HYPERLINK("#'ESCOLA PAROQUIAL NOSSA SENHO 3'!A1",'ESCOLA PAROQUIAL NOSSA SENHO 3'!B2) | V94: ESCOLA PAROQUIAL NOSSA SENHO 3
A95: ='ESCOLA MONSENHOR GENTIL'!B5 | B95: =HYPERLINK("#'ESCOLA MONSENHOR GENTIL'!A1",'ESCOLA MONSENHOR GENTIL'!B2) | V95: ESCOLA MONSENHOR GENTIL
A96: ='ESCOLA PAROQUIAL BOM JESUS'!B5 | B96: =HYPERLINK("#'ESCOLA PAROQUIAL BOM JESUS'!A1",'ESCOLA PAROQUIAL BOM JESUS'!B2) | V96: ESCOLA PAROQUIAL BOM JESUS
A97: ='ESCOLA PAROQUIAL CARLOS DEMIÁ'!B5 | B97: =HYPERLINK("#'ESCOLA PAROQUIAL CARLOS DEMIÁ'!A1",'ESCOLA PAROQUIAL CARLOS DEMIÁ'!B2) | V97: ESCOLA PAROQUIAL CARLOS DEMIÁ
A98: ='ESCOLA PAROQUIAL NOSSA SENHO 2'!B5 | B98: =HYPERLINK("#'ESCOLA PAROQUIAL NOSSA SENHO 2'!A1",'ESCOLA PAROQUIAL NOSSA SENHO 2'!B2) | V98: ESCOLA PAROQUIAL NOSSA SENHO 2
A99: ='ESCOLA PAROQUIAL NOSSA SENHORA '!B5 | B99: =HYPERLINK("#'ESCOLA PAROQUIAL NOSSA SENHORA '!A1",'ESCOLA PAROQUIAL NOSSA SENHORA '!B2) | V99: ESCOLA PAROQUIAL NOSSA SENHORA
A100: ='ESCOLA PAROQUIAL SÃO PEDRO DE A'!B5 | B100: =HYPERLINK("#'ESCOLA PAROQUIAL SÃO PEDRO DE A'!A1",'ESCOLA PAROQUIAL SÃO PEDRO DE A'!B2) | V100: ESCOLA PAROQUIAL SÃO PEDRO DE A
A101: ='ESCOLA SANTA MARIA GORETTI'!B5 | B101: =HYPERLINK("#'ESCOLA SANTA MARIA GORETTI'!A1",'ESCOLA SANTA MARIA GORETTI'!B2) | V101: ESCOLA SANTA MARIA GORETTI
...

Sheet RESUMO
A1: RESUMO GERAL | H1: =HYPERLINK("#'ÍNDICE'!A1","◄ Voltar ao Índice")
A3: 🏫 ESCOLAS — PEDIDO × DEVOLUÇÃO × VALOR A COBRAR DA PREFEITURA
A4: PRODUTO | B4: PEDIDO (kg) | C4: REJEITADO NA ESCOLA (kg) | D4: ACEITO (kg) | E4: VALOR (R$/kg) | F4: VALOR A COBRAR (R$)
A5: ='Entrada de Dados'!C5 | B5: ='Entrada de Dados'!C197 | C5: ='E M ROTARY'!D9+'E M DE EDUCAÇÃO ESPECIAL SANTOS'!D9+'LICEU MUN PREFEITO CORDOLINO AM'!D9+'E M PREFEITO JAMIL SABRÁ'!D9+'LICEU MUNICIPAL CARLOS CHAGAS F'!D9+'E M PAULO FREIRE'!D9+'E M PROFª MARIA CAMPOS DA SILVA'!D9+'CASA DA EDUCAÇÃO VISCONDE DE MA'!D9+'CENTRO DE REFERÊNCIA EM EDUCAÇÃ'!D9+'ESCOLA SANTA LUIZA DE MARILLAC'!D9+'ESCOLA DOMÉSTICA NOSSA SENHORA '!D9+'ESCOLA MONSENHOR GENTIL'!D9+'ESCOLA PAROQUIAL NOSSA SENHORA '!D9+'ESCOLA PAROQUIAL SÃO PEDRO DE A'!D9+'CEI TERRA SANTA'!D9+'CEI PRIMEIRA INFÂNCIA'!D9+'CEI PROFª PATRÍCIA FERREIRA E S'!D9+'CEI DRA ZILDA ARNS NEUMANN'!D9+'CENTRO DE EDUCAÇÃO INFANTIL PRO'!D9+'CEI MONSENHOR PAULO ELIAS DAHER'!D9+'COLÉGIO GUNNAR VINGREN DE PETRÓ'!D9+'EDUCANDÁRIO TERRA SANTA'!D9+'CEI LIONS CLUBE DE PETRÓPOLIS'!D9+'ESCOLA PAROQUIAL NOSSA SENHO 2'!D9+'CENTRO DE EDUCAÇÃO INFANTIL IRM'!D9+'E M LUIZ CARLOS SOARES'!D9+'ESCOLA GERMANO VALENTE'!D9+'ESCOLA PAROQUIAL NOSSA SENHO 3'!D9+'CEI JORGE ROLANDO DA SILVA'!D9+'E M CLEMENTE FERNANDES'!D9+'E M GERALDO VENTURA DIAS'!D9+'ESCOLA DAS COMUNIDADES SANTO AN'!D9+'CEI PROFª ROSANGELA DA SILVA LE'!D9+'CEI DEISE ELOY GOMES'!D9+'CEI PROFª SONIA REGINA SCUDESE '!D9+'CEI TIA ALICE'!D9+'E M BATAILLARD'!D9+'E M SOROPTIMISTA'!D9+'E M SALVADOR KLING'!D9+'ESCOLA MUNICIPALIZADA FREI ANIC'!D9+'ESCOLA SÃO JUDAS TADEU'!D9+'CEI PEDRAS BRANCAS'!D9+'CEI MARIA THEREZA KLING DO VALL'!D9+'CEI DONA ESPERANZA DE BOURBON D'!D9+'CEI GIUSEPPE-NEVA VOLONTERIO'!D9+'CENTRO DE EDUCAÇÃO INFANTIL SÃO'!D9+'E M LEONARDO BOFF'!D9+'ESCOLA MUNICIPAL GENERAL HEITOR'!D9+'E M JOHANN NOEL'!D9+'ESCOLA SANTA MARIA GORETTI'!D9+'ESCOLA SANTA RITA DE CASSIA'!D9+'ESCOLA SÃO JOÃO BATISTA'!D9+'CEI CASA DA SOLIDARIEDADE DE NO'!D9+'CEI A SEMENTEIRA'!D9+'CEI VILA SAO JOSE'!D9+'E M DR RUBENS DE CASTRO BOMTEMP'!D9+'CEI FREI LEÃO'!D9+'CEI SÃO JOÃO BATISTA'!D9+'CEI JURACI PINTO DO AMARAL DE C'!D9+'E M PEDRO AMADO'!D9+'E M ABELARDO DE LAMARE'!D9+'ESCOLA MUNICIPAL SENADOR MARIO '!D9+'ESCOLA PAROQUIAL SÃO PIO X'!D9+'CEI SÃO CHARBEL'!D9+'E M ROSALINA NICOLAY'!D9+'CEI INÊS BELARMINO DE SOUZA'!D9+'E M PROFª MARIA DA GLÓRIA QUEIR'!D9+'CENTRO EDUCACIONAL COMUNIDADE S'!D9+'CEI ROMANO CANAVESE'!D9+'CEI CÉLIA LÔBO PAULO'!D9+'CEI PROFª DORA KILLER'!D9+'CEI ALTO INDEPENDÊNCIA'!D9+'ESCOLA MUNICIPAL ALTO INDEPENDÊ'!D9+'E M PAPA JOÃO PAULO II'!D9+'CEI ANDRÉ REBOUÇAS'!D9+'CEI PROFª HERMÍNIA MATHEUS'!D9+'ESCOLA MUNICIPAL MAJOR JÚLIO FR'!D9+'E M ALMIRANTE TAMANDARÉ'!D9+'ESCOLA PAROQUIAL CARLOS DEMIÁ'!D9+'CENTRO PAROQUIAL DE EDUCAÇÃO IN'!D9+'CEI IRMÃ SILVANA'!D9+'CEI OLÍVIA MACHADO DA COSTA NOG'!D9+'E M GOVERNADOR MARCELLO ALENCAR'!D9+'E M PROFESSOR FLÁVIO MACIEL'!D9+'E M PROFª JANDIRA PEIXOTO BORDI'!D9+'E M STEFAN ZWEIG'!D9+'ESCOLA PAROQUIAL BOM JESUS'!D9+'CEI MARLI SOARES FERREIRA NETTO'!D9+'CENTRO DE EDUCAÇÃO INFANTIL CHI'!D9+'CEI VILA IPANEMA'!D9+'E M ROBERT KENNEDY'!D9+'ESCOLA MUNICIPAL ANA MOHAMMAD'!D9+'ESCOLA SÃO CRISTÓVÃO'!D9+'CEI DÉA LÚCIA CORDEIRO'!D9+'CEI SAGRADA FAMÍLIA'!D9+'CEI SÃO JOSÉ DAS OBLATAS DE NAZ'!D9+'ESCOLA MUNICIPAL JORGE AMADO'!D9+'E M FÁBRICA DO SABER'!D9+'CIEP BRIZOLÃO 474 MAESTRO GUERR'!D9+'CENTRO DE ENSINO PROF DARCY RIB'!D9+'CEI ANDRÉ VANZAN'!D9+'CENTRO DE EDUCAÇÃO INFANTIL CAR'!D9+'CEI BOA VISTA'!D9+'ASSOCIAÇÃO DA CRECHE SÃO FRANCI'!D9+'ESCOLA MUNICIPAL PAULO SALDANHA'!D9+'ESCOLA MUNICIPAL LÚCIA DE ALMEI'!D9+'E M DOM MANOEL PEDRO DA CUNHA C'!D9+'ESCOLA SÃO GERALDO'!D9+'CEI LULU MONTEIRO DE CASTRO'!D9+'CEI CARANGOLA'!D9+'ASSOCIAÇÃO RECREAR'!D9+'CENTRO DE EDUCAÇÃO INFANTIL CAS'!D9+'E M ROSEMIRA DE OLIVEIRA CAVALC'!D9+'E MZDA CARMEM NUNES MARTINS'!D9+'CEI SÃO JOSÉ DO ITAMARATI'!D9+'E M DUQUE DE CAXIAS'!D9+'CENTRO DE EDUCAÇÃO INFANTIL 2'!D9+'E M ANTÔNIO LEITE GARCIA'!D9+'ESCOLA PAROQUIAL DA ALCOBAÇA'!D9+'CENTRO DE EDUCAÇÃO INFANTIL LOT'!D9+'ESCOLA PAROQUIAL DO LOTEAMENTO '!D9+'E M PROF JOAQUIM DEISTER'!D9+'E M MARIETA GONÇALVES'!D9+'ESCOLA MUNICIPAL ODETTE YOUNG M'!D9+'ESCOLA MUNICIPAL PROFESSOR JOSE'!D9+'E M HERCÍLIA HENRIQUES MORET'!D9+'COLEGIO VICENTINO PADRE CORRÊA'!D9+'CEI PROFª MARLUCE DE SOUZA PEST'!D9+'CEI IRINEU MARINHO'!D9+'CEI DAGMAR ROLANDO DE OLIVEIRA'!D9+'CEI NOSSA SENHORA DA GLÓRIA'!D9+'E M PROF NILTON COSTA PEREIRA D'!D9+'CENTRO DE EDUCAÇÃO INFANTIL SÉR'!D9+'CEI SANTO ANTÔNIO AGOSTINHO'!D9+'CEI OSWALDO CRUZ'!D9+'E M MAGDALENA TAGLIAFERRO'!D9+'ESCOLA SÃO JOSÉ DO CAETITU'!D9+'CRECHE-ESCOLA CASTELO SÃO MANOE'!D9+'CEI THEREZINHA DE JESUS LIMA'!D9+'ESCOLA MUNICIPAL PROFESSOR PAUL'!D9+'COLÉGIO ANGLICANO DE ARARAS'!D9+'ESCOLA PAROQUIAL SANTA BERNADET'!D9+'CEI VISTA ALEGRE'!D9+'CEI DENISE BESSA DE OLIVA MAYA'!D9+'CEI VIDEIRINHA'!D9+'E M AMÉRICO FERNANDES RIBEIRO'!D9+'ESCOLA MUNICIPAL AUGUSTO PUGNAL'!D9+'ESCOLA MUNICIPAL CELINA SCHECHN'!D9+'E M DARCY CORREA DA VEIGA'!D9+'E M DR PAULA BUARQUE'!D9+'LICEU SÃO JOSÉ DE ITAIPAVA'!D9+'CEI LUIZ MARCHIORI'!D9+'CENTRO DE EDUCAÇÃO INFANTIL AUG'!D9+'CEI PROFª ADRIANA CONSTÂNCIO TR'!D9+'E M AMÉLIA ANTUNES RABELLO'!D9+'CEI PREFEITO SÉRGIO FADEL'!D9+'E M DR THEODORO MACHADO'!D9+'ESCOLA SANTO ANTÔNIO'!D9+'E M TAQUARIL'!D9+'E M MONSENHOR JOÃO DE DEUS RODR'!D9+'CENTRO DE REFERÊNCIA EM EDUC 2'!D9+'CEI PROFª GRAÇA COSTA'!D9+'CEI VILA LEOPOLDINA'!D9+'CEI NILO PEÇANHA'!D9+'E MZDA SANTA TEREZINHA'!D9+'CEI CRIANÇA SANTA EDWIGES'!D9+'E M ARNALDO DYCKERHOFF'!D9+'E M CARLOS CANEDO'!D9+'E M BEATRIZ ZALESKI'!D9+'E M ANTÔNIO JOSÉ DE LIMA'!D9+'E M FELIX WAN ERVEN DE BARROS'!D9+'ESCOLA MUNICIPAL HILDEBRANDO DE'!D9+'E M OSWALDO DA COSTA FRIAS'!D9+'E MZDA AVELINO DE CARVALHO'!D9+'ESCOLA MUNICIPALIZADA MOYSÉS FU'!D9+'CEI ANGELA MARIA DA CONCEIÇÃO S'!D9+'CEI JOSÉ GONÇALVES DA MOTTA'!D9+'E M DR BARROS FRANCO'!D9+'E M MAJOR THEÓFILO DE CARVALHO'!D9+'E M JOÃO KOPKE'!D9+'CEI ASSOCIAÇÃO BENEFICENTE FAZE'!D9+'ESCOLA SAO FRANCISCO DE ASSIS'!D9+'CEI SÃO FRANCISCO ASSIS'!D9+'CEI ALDEIA DA CRIANCA'!D9+'ESCOLA MUNICIPAL ODETTE FONSECA'!D9+'CEI ANA CAROLINA TELLES'!D9+'E M SEBASTIÃO LACERDA'!D9+'E M DOM PEDRO DE ALCÂNTARA'!D9+'ESCOLA NOSSA SENHORA DE FÁTIMA'!D9+'ESCOLA PAROQUIAL SÃO FRANCISCO '!D9+'E M MONSENHOR CIRILLO CALAON'!D9 | D5: ='E M ABELARDO DE LAMARE'!M9+'E M BATAILLARD'!M9+'E M LEONARDO BOFF'!M9+'E M CLEMENTE FERNANDES'!M9+'E M DOM PEDRO DE ALCÂNTARA'!M9+'E M DUQUE DE CAXIAS'!M9+'E M LUIZ CARLOS SOARES'!M9+'ESCOLA MUNICIPAL GENERAL HEITOR'!M9+'E M JOÃO KOPKE'!M9+'ESCOLA MUNICIPAL ODETTE FONSECA'!M9+'E M GOVERNADOR MARCELLO ALENCAR'!M9+'E M PROF JOAQUIM DEISTER'!M9+'E M ROBERT KENNEDY'!M9+'E M ROTARY'!M9+'E M ROSALINA NICOLAY'!M9+'E M DE EDUCAÇÃO ESPECIAL SANTOS'!M9+'E M SOROPTIMISTA'!M9+'LICEU MUN PREFEITO CORDOLINO AM'!M9+'E M ANTÔNIO LEITE GARCIA'!M9+'ESCOLA MUNICIPAL JORGE AMADO'!M9+'ESCOLA MUNICIPAL LÚCIA DE ALMEI'!M9+'E M MAGDALENA TAGLIAFERRO'!M9+'ESCOLA MUNICIPAL MAJOR JÚLIO FR'!M9+'E M MARIETA GONÇALVES'!M9+'ESCOLA MUNICIPAL ODETTE YOUNG M'!M9+'E M FÁBRICA DO SABER'!M9+'ESCOLA MUNICIPAL PROFESSOR PAUL'!M9+'E M ROSEMIRA DE OLIVEIRA CAVALC'!M9+'E M AMÉLIA ANTUNES RABELLO'!M9+'ESCOLA MUNICIPAL AUGUSTO PUGNAL'!M9+'ESCOLA MUNICIPAL CELINA SCHECHN'!M9+'E M DARCY CORREA DA VEIGA'!M9+'E M DR PAULA BUARQUE'!M9+'E M DR THEODORO MACHADO'!M9+'E M ARNALDO DYCKERHOFF'!M9+'E M CARLOS CANEDO'!M9+'E M DR BARROS FRANCO'!M9+'E M MAJOR THEÓFILO DE CARVALHO'!M9+'E M TAQUARIL'!M9+'E M BEATRIZ ZALESKI'!M9+'E M ANTÔNIO JOSÉ DE LIMA'!M9+'E M FELIX WAN ERVEN DE BARROS'!M9+'ESCOLA MUNICIPAL HILDEBRANDO DE'!M9+'E M OSWALDO DA COSTA FRIAS'!M9+'E MZDA CARMEM NUNES MARTINS'!M9+'E MZDA AVELINO DE CARVALHO'!M9+'E M GERALDO VENTURA DIAS'!M9+'E M SALVADOR KLING'!M9+'E M PREFEITO JAMIL SABRÁ'!M9+'LICEU MUNICIPAL CARLOS CHAGAS F'!M9+'ESCOLA MUNICIPAL ANA MOHAMMAD'!M9+'ESCOLA MUNICIPAL ALTO INDEPENDÊ'!M9+'E M ALMIRANTE TAMANDARÉ'!M9+'ESCOLA MUNICIPALIZADA FREI ANIC'!M9+'E M PEDRO AMADO'!M9+'E M PROFª MARIA DA GLÓRIA QUEIR'!M9+'E M SEBASTIÃO LACERDA'!M9+'E M PROFESSOR FLÁVIO MACIEL'!M9+'ESCOLA MUNICIPAL PAULO SALDANHA'!M9+'ESCOLA MUNICIPAL PROFESSOR JOSE'!M9+'E M MONSENHOR CIRILLO CALAON'!M9+'E M AMÉRICO FERNANDES RIBEIRO'!M9+'E M PROFª JANDIRA PEIXOTO BORDI'!M9+'E M MONSENHOR JOÃO DE DEUS RODR'!M9+'E M DOM MANOEL PEDRO DA CUNHA C'!M9+'E M JOHANN NOEL'!M9+'E MZDA SANTA TEREZINHA'!M9+'E M PAPA JOÃO PAULO II'!M9+'E M STEFAN ZWEIG'!M9+'ESCOLA MUNICIPAL SENADOR MARIO '!M9+'E M DR RUBENS DE CASTRO BOMTEMP'!M9+'E M PAULO FREIRE'!M9+'E M PROFª MARIA CAMPOS DA SILVA'!M9+'E M HERCÍLIA HENRIQUES MORET'!M9+'ESCOLA MUNICIPALIZADA MOYSÉS FU'!M9+'CIEP BRIZOLÃO 474 MAESTRO GUERR'!M9+'CENTRO DE ENSINO PROF DARCY RIB'!M9+'CASA DA EDUCAÇÃO VISCONDE DE MA'!M9+'CENTRO DE REFERÊNCIA EM EDUCAÇÃ'!M9+'E M PROF NILTON COSTA PEREIRA D'!M9+'COLÉGIO GUNNAR VINGREN DE PETRÓ'!M9+'CENTRO DE REFERÊNCIA EM EDUC 2'!M9+'ESCOLA SANTA LUIZA DE MARILLAC'!M9+'CENTRO EDUCACIONAL COMUNIDADE S'!M9+'EDUCANDÁRIO TERRA SANTA'!M9+'ESCOLA GERMANO VALENTE'!M9+'ESCOLA DAS COMUNIDADES SANTO AN'!M9+'ESCOLA DOMÉSTICA NOSSA SENHORA '!M9+'ESCOLA PAROQUIAL NOSSA SENHO 3'!M9+'ESCOLA MONSENHOR GENTIL'!M9+'ESCOLA PAROQUIAL BOM JESUS'!M9+'ESCOLA PAROQUIAL CARLOS DEMIÁ'!M9+'ESCOLA PAROQUIAL NOSSA SENHO 2'!M9+'ESCOLA PAROQUIAL NOSSA SENHORA '!M9+'ESCOLA PAROQUIAL SÃO PEDRO DE A'!M9+'ESCOLA SANTA MARIA GORETTI'!M9+'ESCOLA SANTA RITA DE CASSIA'!M9+'ESCOLA SÃO CRISTÓVÃO'!M9+'ESCOLA PAROQUIAL SÃO FRANCISCO '!M9+'ESCOLA SAO FRANCISCO DE ASSIS'!M9+'ESCOLA SÃO JOÃO BATISTA'!M9+'ESCOLA SÃO JUDAS TADEU'!M9+'ESCOLA PAROQUIAL SÃO PIO X'!M9+'COLÉGIO ANGLICANO DE ARARAS'!M9+'COLEGIO VICENTINO PADRE CORRÊA'!M9+'ESCOLA NOSSA SENHORA DE FÁTIMA'!M9+'ESCOLA PAROQUIAL DA ALCOBAÇA'!M9+'ESCOLA PAROQUIAL DO LOTEAMENTO '!M9+'ESCOLA PAROQUIAL SANTA BERNADET'!M9+'ESCOLA SÃO GERALDO'!M9+'ESCOLA SANTO ANTÔNIO'!M9+'LICEU SÃO JOSÉ DE ITAIPAVA'!M9+'ESCOLA SÃO JOSÉ DO CAETITU'!M9+'CEI ASSOCIAÇÃO BENEFICENTE FAZE'!M9+'CEI CASA DA SOLIDARIEDADE DE NO'!M9+'CEI LULU MONTEIRO DE CASTRO'!M9+'CEI SÃO JOÃO BATISTA'!M9+'CEI SÃO FRANCISCO ASSIS'!M9+'CEI A SEMENTEIRA'!M9+'CEI FREI LEÃO'!M9+'CEI ROMANO CANAVESE'!M9+'CEI ANDRÉ VANZAN'!M9+'CEI CRIANÇA SANTA EDWIGES'!M9+'CENTRO DE EDUCAÇÃO INFANTIL IRM'!M9+'CEI PEDRAS BRANCAS'!M9+'CEI INÊS BELARMINO DE SOUZA'!M9+'CEI PROFª ROSANGELA DA SILVA LE'!M9+'CEI VILA SAO JOSE'!M9+'CEI MARIA THEREZA KLING DO VALL'!M9+'CEI DEISE ELOY GOMES'!M9+'CENTRO PAROQUIAL DE EDUCAÇÃO IN'!M9+'CEI VISTA ALEGRE'!M9+'CEI ALDEIA DA CRIANCA'!M9+'CEI DÉA LÚCIA CORDEIRO'!M9+'CENTRO DE EDUCAÇÃO INFANTIL CAR'!M9+'CEI IRMÃ SILVANA'!M9+'CEI MARLI SOARES FERREIRA NETTO'!M9+'CEI PROFª SONIA REGINA SCUDESE '!M9+'CEI DONA ESPERANZA DE BOURBON D'!M9+'CEI PREFEITO SÉRGIO FADEL'!M9+'CEI ANDRÉ REBOUÇAS'!M9+'CENTRO DE EDUCAÇÃO INFANTIL CHI'!M9+'CEI TIA ALICE'!M9+'CEI TERRA SANTA'!M9+'CEI JORGE ROLANDO DA SILVA'!M9+'CEI CARANGOLA'!M9+'CEI CÉLIA LÔBO PAULO'!M9+'CEI LIONS CLUBE DE PETRÓPOLIS'!M9+'CEI PROFª GRAÇA COSTA'!M9+'CEI ANGELA MARIA DA CONCEIÇÃO S'!M9+'CEI LUIZ MARCHIORI'!M9+'CEI PROFª MARLUCE DE SOUZA PEST'!M9+'CEI OLÍVIA MACHADO DA COSTA NOG'!M9+'CEI VILA IPANEMA'!M9+'CEI VILA LEOPOLDINA'!M9+'CENTRO DE EDUCAÇÃO INFANTIL CAS'!M9+'CEI PRIMEIRA INFÂNCIA'!M9+'CEI PROFª DORA KILLER'!M9+'CEI PROFª PATRÍCIA FERREIRA E S'!M9+'CEI DRA ZILDA ARNS NEUMANN'!M9+'CEI DENISE BESSA DE OLIVA MAYA'!M9+'CEI GIUSEPPE-NEVA VOLONTERIO'!M9+'CENTRO DE EDUCAÇÃO INFANTIL LOT'!M9+'CEI IRINEU MARINHO'!M9+'CEI OSWALDO CRUZ'!M9+'CEI ANA CAROLINA TELLES'!M9+'CEI JOSÉ GONÇALVES DA MOTTA'!M9+'CEI SAGRADA FAMÍLIA'!M9+'CEI PROFª HERMÍNIA MATHEUS'!M9+'CENTRO DE EDUCAÇÃO INFANTIL PRO'!M9+'CEI MONSENHOR PAULO ELIAS DAHER'!M9+'CEI DAGMAR ROLANDO DE OLIVEIRA'!M9+'CENTRO DE EDUCAÇÃO INFANTIL 2'!M9+'CEI BOA VISTA'!M9+'CEI NILO PEÇANHA'!M9+'CENTRO DE EDUCAÇÃO INFANTIL AUG'!M9+'CEI THEREZINHA DE JESUS LIMA'!M9+'CEI VIDEIRINHA'!M9+'CEI PROFª ADRIANA CONSTÂNCIO TR'!M9+'CENTRO DE EDUCAÇÃO INFANTIL SÉR'!M9+'CEI JURACI PINTO DO AMARAL DE C'!M9+'CEI NOSSA SENHORA DA GLÓRIA'!M9+'CEI ALTO INDEPENDÊNCIA'!M9+'CEI SÃO JOSÉ DAS OBLATAS DE NAZ'!M9+'CEI SANTO ANTÔNIO AGOSTINHO'!M9+'CEI SÃO CHARBEL'!M9+'ASSOCIAÇÃO DA CRECHE SÃO FRANCI'!M9+'CEI SÃO JOSÉ DO ITAMARATI'!M9+'ASSOCIAÇÃO RECREAR'!M9+'CRECHE-ESCOLA CASTELO SÃO MANOE'!M9+'CENTRO DE EDUCAÇÃO INFANTIL SÃO'!M9 | E5: ='Entrada de Dados'!C2 | F5: =D5*E5
A6: ='Entrada de Dados'!D5 | B6: ='Entrada de Dados'!D197 | C6: ='E M ROTARY'!D10+'E M DE EDUCAÇÃO ESPECIAL SANTOS'!D10+'LICEU MUN PREFEITO CORDOLINO AM'!D10+'E M PREFEITO JAMIL SABRÁ'!D10+'LICEU MUNICIPAL CARLOS CHAGAS F'!D10+'E M PAULO FREIRE'!D10+'E M PROFª MARIA CAMPOS DA SILVA'!D10+'CASA DA EDUCAÇÃO VISCONDE DE MA'!D10+'CENTRO DE REFERÊNCIA EM EDUCAÇÃ'!D10+'ESCOLA SANTA LUIZA DE MARILLAC'!D10+'ESCOLA DOMÉSTICA NOSSA SENHORA '!D10+'ESCOLA MONSENHOR GENTIL'!D10+'ESCOLA PAROQUIAL NOSSA SENHORA '!D10+'ESCOLA PAROQUIAL SÃO PEDRO DE A'!D10+'CEI TERRA SANTA'!D10+'CEI PRIMEIRA INFÂNCIA'!D10+'CEI PROFª PATRÍCIA FERREIRA E S'!D10+'CEI DRA ZILDA ARNS NEUMANN'!D10+'CENTRO DE EDUCAÇÃO INFANTIL PRO'!D10+'CEI MONSENHOR PAULO ELIAS DAHER'!D10+'COLÉGIO GUNNAR VINGREN DE PETRÓ'!D10+'EDUCANDÁRIO TERRA SANTA'!D10+'CEI LIONS CLUBE DE PETRÓPOLIS'!D10+'ESCOLA PAROQUIAL NOSSA SENHO 2'!D10+'CENTRO DE EDUCAÇÃO INFANTIL IRM'!D10+'E M LUIZ CARLOS SOARES'!D10+'ESCOLA GERMANO VALENTE'!D10+'ESCOLA PAROQUIAL NOSSA SENHO 3'!D10+'CEI JORGE ROLANDO DA SILVA'!D10+'E M CLEMENTE FERNANDES'!D10+'E M GERALDO VENTURA DIAS'!D10+'ESCOLA DAS COMUNIDADES SANTO AN'!D10+'CEI PROFª ROSANGELA DA SILVA LE'!D10+'CEI DEISE ELOY GOMES'!D10+'CEI PROFª SONIA REGINA SCUDESE '!D10+'CEI TIA ALICE'!D10+'E M BATAILLARD'!D10+'E M SOROPTIMISTA'!D10+'E M SALVADOR KLING'!D10+'ESCOLA MUNICIPALIZADA FREI ANIC'!D10+'ESCOLA SÃO JUDAS TADEU'!D10+'CEI PEDRAS BRANCAS'!D10+'CEI MARIA THEREZA KLING DO VALL'!D10+'CEI DONA ESPERANZA DE BOURBON D'!D10+'CEI GIUSEPPE-NEVA VOLONTERIO'!D10+'CENTRO DE EDUCAÇÃO INFANTIL SÃO'!D10+'E M LEONARDO BOFF'!D10+'ESCOLA MUNICIPAL GENERAL HEITOR'!D10+'E M JOHANN NOEL'!D10+'ESCOLA SANTA MARIA GORETTI'!D10+'ESCOLA SANTA RITA DE CASSIA'!D10+'ESCOLA SÃO JOÃO BATISTA'!D10+'CEI CASA DA SOLIDARIEDADE DE NO'!D10+'CEI A SEMENTEIRA'!D10+'CEI VILA SAO JOSE'!D10+'E M DR RUBENS DE CASTRO BOMTEMP'!D10+'CEI FREI LEÃO'!D10+'CEI SÃO JOÃO BATISTA'!D10+'CEI JURACI PINTO DO AMARAL DE C'!D10+'E M PEDRO AMADO'!D10+'E M ABELARDO DE LAMARE'!D10+'ESCOLA MUNICIPAL SENADOR MARIO '!D10+'ESCOLA PAROQUIAL SÃO PIO X'!D10+'CEI SÃO CHARBEL'!D10+'E M ROSALINA NICOLAY'!D10+'CEI INÊS BELARMINO DE SOUZA'!D10+'E M PROFª MARIA DA GLÓRIA QUEIR'!D10+'CENTRO EDUCACIONAL COMUNIDADE S'!D10+'CEI ROMANO CANAVESE'!D10+'CEI CÉLIA LÔBO PAULO'!D10+'CEI PROFª DORA KILLER'!D10+'CEI ALTO INDEPENDÊNCIA'!D10+'ESCOLA MUNICIPAL ALTO INDEPENDÊ'!D10+'E M PAPA JOÃO PAULO II'!D10+'CEI ANDRÉ REBOUÇAS'!D10+'CEI PROFª HERMÍNIA MATHEUS'!D10+'ESCOLA MUNICIPAL MAJOR JÚLIO FR'!D10+'E M ALMIRANTE TAMANDARÉ'!D10+'ESCOLA PAROQUIAL CARLOS DEMIÁ'!D10+'CENTRO PAROQUIAL DE EDUCAÇÃO IN'!D10+'CEI IRMÃ SILVANA'!D10+'CEI OLÍVIA MACHADO DA COSTA NOG'!D10+'E M GOVERNADOR MARCELLO ALENCAR'!D10+'E M PROFESSOR FLÁVIO MACIEL'!D10+'E M PROFª JANDIRA PEIXOTO BORDI'!D10+'E M STEFAN ZWEIG'!D10+'ESCOLA PAROQUIAL BOM JESUS'!D10+'CEI MARLI SOARES FERREIRA NETTO'!D10+'CENTRO DE EDUCAÇÃO INFANTIL CHI'!D10+'CEI VILA IPANEMA'!D10+'E M ROBERT KENNEDY'!D10+'ESCOLA MUNICIPAL ANA MOHAMMAD'!D10+'ESCOLA SÃO CRISTÓVÃO'!D10+'CEI DÉA LÚCIA CORDEIRO'!D10+'CEI SAGRADA FAMÍLIA'!D10+'CEI SÃO JOSÉ DAS OBLATAS DE NAZ'!D10+'ESCOLA MUNICIPAL JORGE AMADO'!D10+'E M FÁBRICA DO SABER'!D10+'CIEP BRIZOLÃO 474 MAESTRO GUERR'!D10+'CENTRO DE ENSINO PROF DARCY RIB'!D10+'CEI ANDRÉ VANZAN'!D10+'CENTRO DE EDUCAÇÃO INFANTIL CAR'!D10+'CEI BOA VISTA'!D10+'ASSOCIAÇÃO DA CRECHE SÃO FRANCI'!D10+'ESCOLA MUNICIPAL PAULO SALDANHA'!D10+'ESCOLA MUNICIPAL LÚCIA DE ALMEI'!D10+'E M DOM MANOEL PEDRO DA CUNHA C'!D10+'ESCOLA SÃO GERALDO'!D10+'CEI LULU MONTEIRO DE CASTRO'!D10+'CEI CARANGOLA'!D10+'ASSOCIAÇÃO RECREAR'!D10+'CENTRO DE EDUCAÇÃO INFANTIL CAS'!D10+'E M ROSEMIRA DE OLIVEIRA CAVALC'!D10+'E MZDA CARMEM NUNES MARTINS'!D10+'CEI SÃO JOSÉ DO ITAMARATI'!D10+'E M DUQUE DE CAXIAS'!D10+'CENTRO DE EDUCAÇÃO INFANTIL 2'!D10+'E M ANTÔNIO LEITE GARCIA'!D10+'ESCOLA PAROQUIAL DA ALCOBAÇA'!D10+'CENTRO DE EDUCAÇÃO INFANTIL LOT'!D10+'ESCOLA PAROQUIAL DO LOTEAMENTO '!D10+'E M PROF JOAQUIM DEISTER'!D10+'E M MARIETA GONÇALVES'!D10+'ESCOLA MUNICIPAL ODETTE YOUNG M'!D10+'ESCOLA MUNICIPAL PROFESSOR JOSE'!D10+'E M HERCÍLIA HENRIQUES MORET'!D10+'COLEGIO VICENTINO PADRE CORRÊA'!D10+'CEI PROFª MARLUCE DE SOUZA PEST'!D10+'CEI IRINEU MARINHO'!D10+'CEI DAGMAR ROLANDO DE OLIVEIRA'!D10+'CEI NOSSA SENHORA DA GLÓRIA'!D10+'E M PROF NILTON COSTA PEREIRA D'!D10+'CENTRO DE EDUCAÇÃO INFANTIL SÉR'!D10+'CEI SANTO ANTÔNIO AGOSTINHO'!D10+'CEI OSWALDO CRUZ'!D10+'E M MAGDALENA TAGLIAFERRO'!D10+'ESCOLA SÃO JOSÉ DO CAETITU'!D10+'CRECHE-ESCOLA CASTELO SÃO MANOE'!D10+'CEI THEREZINHA DE JESUS LIMA'!D10+'ESCOLA MUNICIPAL PROFESSOR PAUL'!D10+'COLÉGIO ANGLICANO DE ARARAS'!D10+'ESCOLA PAROQUIAL SANTA BERNADET'!D10+'CEI VISTA ALEGRE'!D10+'CEI DENISE BESSA DE OLIVA MAYA'!D10+'CEI VIDEIRINHA'!D10+'E M AMÉRICO FERNANDES RIBEIRO'!D10+'ESCOLA MUNICIPAL AUGUSTO PUGNAL'!D10+'ESCOLA MUNICIPAL CELINA SCHECHN'!D10+'E M DARCY CORREA DA VEIGA'!D10+'E M DR PAULA BUARQUE'!D10+'LICEU SÃO JOSÉ DE ITAIPAVA'!D10+'CEI LUIZ MARCHIORI'!D10+'CENTRO DE EDUCAÇÃO INFANTIL AUG'!D10+'CEI PROFª ADRIANA CONSTÂNCIO TR'!D10+'E M AMÉLIA ANTUNES RABELLO'!D10+'CEI PREFEITO SÉRGIO FADEL'!D10+'E M DR THEODORO MACHADO'!D10+'ESCOLA SANTO ANTÔNIO'!D10+'E M TAQUARIL'!D10+'E M MONSENHOR JOÃO DE DEUS RODR'!D10+'CENTRO DE REFERÊNCIA EM EDUC 2'!D10+'CEI PROFª GRAÇA COSTA'!D10+'CEI VILA LEOPOLDINA'!D10+'CEI NILO PEÇANHA'!D10+'E MZDA SANTA TEREZINHA'!D10+'CEI CRIANÇA SANTA EDWIGES'!D10+'E M ARNALDO DYCKERHOFF'!D10+'E M CARLOS CANEDO'!D10+'E M BEATRIZ ZALESKI'!D10+'E M ANTÔNIO JOSÉ DE LIMA'!D10+'E M FELIX WAN ERVEN DE BARROS'!D10+'ESCOLA MUNICIPAL HILDEBRANDO DE'!D10+'E M OSWALDO DA COSTA FRIAS'!D10+'E MZDA AVELINO DE CARVALHO'!D10+'ESCOLA MUNICIPALIZADA MOYSÉS FU'!D10+'CEI ANGELA MARIA DA CONCEIÇÃO S'!D10+'CEI JOSÉ GONÇALVES DA MOTTA'!D10+'E M DR BARROS FRANCO'!D10+'E M MAJOR THEÓFILO DE CARVALHO'!D10+'E M JOÃO KOPKE'!D10+'CEI ASSOCIAÇÃO BENEFICENTE FAZE'!D10+'ESCOLA SAO FRANCISCO DE ASSIS'!D10+'CEI SÃO FRANCISCO ASSIS'!D10+'CEI ALDEIA DA CRIANCA'!D10+'ESCOLA MUNICIPAL ODETTE FONSECA'!D10+'CEI ANA CAROLINA TELLES'!D10+'E M SEBASTIÃO LACERDA'!D10+'E M DOM PEDRO DE ALCÂNTARA'!D10+'ESCOLA NOSSA SENHORA DE FÁTIMA'!D10+'ESCOLA PAROQUIAL SÃO FRANCISCO '!D10+'E M MONSENHOR CIRILLO CALAON'!D10 | D6: ='E M ABELARDO DE LAMARE'!M10+'E M BATAILLARD'!M10+'E M LEONARDO BOFF'!M10+'E M CLEMENTE FERNANDES'!M10+'E M DOM PEDRO DE ALCÂNTARA'!M10+'E M DUQUE DE CAXIAS'!M10+'E M LUIZ CARLOS SOARES'!M10+'ESCOLA MUNICIPAL GENERAL HEITOR'!M10+'E M JOÃO KOPKE'!M10+'ESCOLA MUNICIPAL ODETTE FONSECA'!M10+'E M GOVERNADOR MARCELLO ALENCAR'!M10+'E M PROF JOAQUIM DEISTER'!M10+'E M ROBERT KENNEDY'!M10+'E M ROTARY'!M10+'E M ROSALINA NICOLAY'!M10+'E M DE EDUCAÇÃO ESPECIAL SANTOS'!M10+'E M SOROPTIMISTA'!M10+'LICEU MUN PREFEITO CORDOLINO AM'!M10+'E M ANTÔNIO LEITE GARCIA'!M10+'ESCOLA MUNICIPAL JORGE AMADO'!M10+'ESCOLA MUNICIPAL LÚCIA DE ALMEI'!M10+'E M MAGDALENA TAGLIAFERRO'!M10+'ESCOLA MUNICIPAL MAJOR JÚLIO FR'!M10+'E M MARIETA GONÇALVES'!M10+'ESCOLA MUNICIPAL ODETTE YOUNG M'!M10+'E M FÁBRICA DO SABER'!M10+'ESCOLA MUNICIPAL PROFESSOR PAUL'!M10+'E M ROSEMIRA DE OLIVEIRA CAVALC'!M10+'E M AMÉLIA ANTUNES RABELLO'!M10+'ESCOLA MUNICIPAL AUGUSTO PUGNAL'!M10+'ESCOLA MUNICIPAL CELINA SCHECHN'!M10+'E M DARCY CORREA DA VEIGA'!M10+'E M DR PAULA BUARQUE'!M10+'E M DR THEODORO MACHADO'!M10+'E M ARNALDO DYCKERHOFF'!M10+'E M CARLOS CANEDO'!M10+'E M DR BARROS FRANCO'!M10+'E M MAJOR THEÓFILO DE CARVALHO'!M10+'E M TAQUARIL'!M10+'E M BEATRIZ ZALESKI'!M10+'E M ANTÔNIO JOSÉ DE LIMA'!M10+'E M FELIX WAN ERVEN DE BARROS'!M10+'ESCOLA MUNICIPAL HILDEBRANDO DE'!M10+'E M OSWALDO DA COSTA FRIAS'!M10+'E MZDA CARMEM NUNES MARTINS'!M10+'E MZDA AVELINO DE CARVALHO'!M10+'E M GERALDO VENTURA DIAS'!M10+'E M SALVADOR KLING'!M10+'E M PREFEITO JAMIL SABRÁ'!M10+'LICEU MUNICIPAL CARLOS CHAGAS F'!M10+'ESCOLA MUNICIPAL ANA MOHAMMAD'!M10+'ESCOLA MUNICIPAL ALTO INDEPENDÊ'!M10+'E M ALMIRANTE TAMANDARÉ'!M10+'ESCOLA MUNICIPALIZADA FREI ANIC'!M10+'E M PEDRO AMADO'!M10+'E M PROFª MARIA DA GLÓRIA QUEIR'!M10+'E M SEBASTIÃO LACERDA'!M10+'E M PROFESSOR FLÁVIO MACIEL'!M10+'ESCOLA MUNICIPAL PAULO SALDANHA'!M10+'ESCOLA MUNICIPAL PROFESSOR JOSE'!M10+'E M MONSENHOR CIRILLO CALAON'!M10+'E M AMÉRICO FERNANDES RIBEIRO'!M10+'E M PROFª JANDIRA PEIXOTO BORDI'!M10+'E M MONSENHOR JOÃO DE DEUS RODR'!M10+'E M DOM MANOEL PEDRO DA CUNHA C'!M10+'E M JOHANN NOEL'!M10+'E MZDA SANTA TEREZINHA'!M10+'E M PAPA JOÃO PAULO II'!M10+'E M STEFAN ZWEIG'!M10+'ESCOLA MUNICIPAL SENADOR MARIO '!M10+'E M DR RUBENS DE CASTRO BOMTEMP'!M10+'E M PAULO FREIRE'!M10+'E M PROFª MARIA CAMPOS DA SILVA'!M10+'E M HERCÍLIA HENRIQUES MORET'!M10+'ESCOLA MUNICIPALIZADA MOYSÉS FU'!M10+'CIEP BRIZOLÃO 474 MAESTRO GUERR'!M10+'CENTRO DE ENSINO PROF DARCY RIB'!M10+'CASA DA EDUCAÇÃO VISCONDE DE MA'!M10+'CENTRO DE REFERÊNCIA EM EDUCAÇÃ'!M10+'E M PROF NILTON COSTA PEREIRA D'!M10+'COLÉGIO GUNNAR VINGREN DE PETRÓ'!M10+'CENTRO DE REFERÊNCIA EM EDUC 2'!M10+'ESCOLA SANTA LUIZA DE MARILLAC'!M10+'CENTRO EDUCACIONAL COMUNIDADE S'!M10+'EDUCANDÁRIO TERRA SANTA'!M10+'ESCOLA GERMANO VALENTE'!M10+'ESCOLA DAS COMUNIDADES SANTO AN'!M10+'ESCOLA DOMÉSTICA NOSSA SENHORA '!M10+'ESCOLA PAROQUIAL NOSSA SENHO 3'!M10+'ESCOLA MONSENHOR GENTIL'!M10+'ESCOLA PAROQUIAL BOM JESUS'!M10+'ESCOLA PAROQUIAL CARLOS DEMIÁ'!M10+'ESCOLA PAROQUIAL NOSSA SENHO 2'!M10+'ESCOLA PAROQUIAL NOSSA SENHORA '!M10+'ESCOLA PAROQUIAL SÃO PEDRO DE A'!M10+'ESCOLA SANTA MARIA GORETTI'!M10+'ESCOLA SANTA RITA DE CASSIA'!M10+'ESCOLA SÃO CRISTÓVÃO'!M10+'ESCOLA PAROQUIAL SÃO FRANCISCO '!M10+'ESCOLA SAO FRANCISCO DE ASSIS'!M10+'ESCOLA SÃO JOÃO BATISTA'!M10+'ESCOLA SÃO JUDAS TADEU'!M10+'ESCOLA PAROQUIAL SÃO PIO X'!M10+'COLÉGIO ANGLICANO DE ARARAS'!M10+'COLEGIO VICENTINO PADRE CORRÊA'!M10+'ESCOLA NOSSA SENHORA DE FÁTIMA'!M10+'ESCOLA PAROQUIAL DA ALCOBAÇA'!M10+'ESCOLA PAROQUIAL DO LOTEAMENTO '!M10+'ESCOLA PAROQUIAL SANTA BERNADET'!M10+'ESCOLA SÃO GERALDO'!M10+'ESCOLA SANTO ANTÔNIO'!M10+'LICEU SÃO JOSÉ DE ITAIPAVA'!M10+'ESCOLA SÃO JOSÉ DO CAETITU'!M10+'CEI ASSOCIAÇÃO BENEFICENTE FAZE'!M10+'CEI CASA DA SOLIDARIEDADE DE NO'!M10+'CEI LULU MONTEIRO DE CASTRO'!M10+'CEI SÃO JOÃO BATISTA'!M10+'CEI SÃO FRANCISCO ASSIS'!M10+'CEI A SEMENTEIRA'!M10+'CEI FREI LEÃO'!M10+'CEI ROMANO CANAVESE'!M10+'CEI ANDRÉ VANZAN'!M10+'CEI CRIANÇA SANTA EDWIGES'!M10+'CENTRO DE EDUCAÇÃO INFANTIL IRM'!M10+'CEI PEDRAS BRANCAS'!M10+'CEI INÊS BELARMINO DE SOUZA'!M10+'CEI PROFª ROSANGELA DA SILVA LE'!M10+'CEI VILA SAO JOSE'!M10+'CEI MARIA THEREZA KLING DO VALL'!M10+'CEI DEISE ELOY GOMES'!M10+'CENTRO PAROQUIAL DE EDUCAÇÃO IN'!M10+'CEI VISTA ALEGRE'!M10+'CEI ALDEIA DA CRIANCA'!M10+'CEI DÉA LÚCIA CORDEIRO'!M10+'CENTRO DE EDUCAÇÃO INFANTIL CAR'!M10+'CEI IRMÃ SILVANA'!M10+'CEI MARLI SOARES FERREIRA NETTO'!M10+'CEI PROFª SONIA REGINA SCUDESE '!M10+'CEI DONA ESPERANZA DE BOURBON D'!M10+'CEI PREFEITO SÉRGIO FADEL'!M10+'CEI ANDRÉ REBOUÇAS'!M10+'CENTRO DE EDUCAÇÃO INFANTIL CHI'!M10+'CEI TIA ALICE'!M10+'CEI TERRA SANTA'!M10+'CEI JORGE ROLANDO DA SILVA'!M10+'CEI CARANGOLA'!M10+'CEI CÉLIA LÔBO PAULO'!M10+'CEI LIONS CLUBE DE PETRÓPOLIS'!M10+'CEI PROFª GRAÇA COSTA'!M10+'CEI ANGELA MARIA DA CONCEIÇÃO S'!M10+'CEI LUIZ MARCHIORI'!M10+'CEI PROFª MARLUCE DE SOUZA PEST'!M10+'CEI OLÍVIA MACHADO DA COSTA NOG'!M10+'CEI VILA IPANEMA'!M10+'CEI VILA LEOPOLDINA'!M10+'CENTRO DE EDUCAÇÃO INFANTIL CAS'!M10+'CEI PRIMEIRA INFÂNCIA'!M10+'CEI PROFª DORA KILLER'!M10+'CEI PROFª PATRÍCIA FERREIRA E S'!M10+'CEI DRA ZILDA ARNS NEUMANN'!M10+'CEI DENISE BESSA DE OLIVA MAYA'!M10+'CEI GIUSEPPE-NEVA VOLONTERIO'!M10+'CENTRO DE EDUCAÇÃO INFANTIL LOT'!M10+'CEI IRINEU MARINHO'!M10+'CEI OSWALDO CRUZ'!M10+'CEI ANA CAROLINA TELLES'!M10+'CEI JOSÉ GONÇALVES DA MOTTA'!M10+'CEI SAGRADA FAMÍLIA'!M10+'CEI PROFª HERMÍNIA MATHEUS'!M10+'CENTRO DE EDUCAÇÃO INFANTIL PRO'!M10+'CEI MONSENHOR PAULO ELIAS DAHER'!M10+'CEI DAGMAR ROLANDO DE OLIVEIRA'!M10+'CENTRO DE EDUCAÇÃO INFANTIL 2'!M10+'CEI BOA VISTA'!M10+'CEI NILO PEÇANHA'!M10+'CENTRO DE EDUCAÇÃO INFANTIL AUG'!M10+'CEI THEREZINHA DE JESUS LIMA'!M10+'CEI VIDEIRINHA'!M10+'CEI PROFª ADRIANA CONSTÂNCIO TR'!M10+'CENTRO DE EDUCAÇÃO INFANTIL SÉR'!M10+'CEI JURACI PINTO DO AMARAL DE C'!M10+'CEI NOSSA SENHORA DA GLÓRIA'!M10+'CEI ALTO INDEPENDÊNCIA'!M10+'CEI SÃO JOSÉ DAS OBLATAS DE NAZ'!M10+'CEI SANTO ANTÔNIO AGOSTINHO'!M10+'CEI SÃO CHARBEL'!M10+'ASSOCIAÇÃO DA CRECHE SÃO FRANCI'!M10+'CEI SÃO JOSÉ DO ITAMARATI'!M10+'ASSOCIAÇÃO RECREAR'!M10+'CRECHE-ESCOLA CASTELO SÃO MANOE'!M10+'CENTRO DE EDUCAÇÃO INFANTIL SÃO'!M10 | E6: ='Entrada de Dados'!D2 | F6: =D6*E6
A7: ='Entrada de Dados'!E5 | B7: ='Entrada de Dados'!E197 | C7: ='E M ROTARY'!D11+'E M DE EDUCAÇÃO ESPECIAL SANTOS'!D11+'LICEU MUN PREFEITO CORDOLINO AM'!D11+'E M PREFEITO JAMIL SABRÁ'!D11+'LICEU MUNICIPAL CARLOS CHAGAS F'!D11+'E M PAULO FREIRE'!D11+'E M PROFª MARIA CAMPOS DA SILVA'!D11+'CASA DA EDUCAÇÃO VISCONDE DE MA'!D11+'CENTRO DE REFERÊNCIA EM EDUCAÇÃ'!D11+'ESCOLA SANTA LUIZA DE MARILLAC'!D11+'ESCOLA DOMÉSTICA NOSSA SENHORA '!D11+'ESCOLA MONSENHOR GENTIL'!D11+'ESCOLA PAROQUIAL NOSSA SENHORA '!D11+'ESCOLA PAROQUIAL SÃO PEDRO DE A'!D11+'CEI TERRA SANTA'!D11+'CEI PRIMEIRA INFÂNCIA'!D11+'CEI PROFª PATRÍCIA FERREIRA E S'!D11+'CEI DRA ZILDA ARNS NEUMANN'!D11+'CENTRO DE EDUCAÇÃO INFANTIL PRO'!D11+'CEI MONSENHOR PAULO ELIAS DAHER'!D11+'COLÉGIO GUNNAR VINGREN DE PETRÓ'!D11+'EDUCANDÁRIO TERRA SANTA'!D11+'CEI LIONS CLUBE DE PETRÓPOLIS'!D11+'ESCOLA PAROQUIAL NOSSA SENHO 2'!D11+'CENTRO DE EDUCAÇÃO INFANTIL IRM'!D11+'E M LUIZ CARLOS SOARES'!D11+'ESCOLA GERMANO VALENTE'!D11+'ESCOLA PAROQUIAL NOSSA SENHO 3'!D11+'CEI JORGE ROLANDO DA SILVA'!D11+'E M CLEMENTE FERNANDES'!D11+'E M GERALDO VENTURA DIAS'!D11+'ESCOLA DAS COMUNIDADES SANTO AN'!D11+'CEI PROFª ROSANGELA DA SILVA LE'!D11+'CEI DEISE ELOY GOMES'!D11+'CEI PROFª SONIA REGINA SCUDESE '!D11+'CEI TIA ALICE'!D11+'E M BATAILLARD'!D11+'E M SOROPTIMISTA'!D11+'E M SALVADOR KLING'!D11+'ESCOLA MUNICIPALIZADA FREI ANIC'!D11+'ESCOLA SÃO JUDAS TADEU'!D11+'CEI PEDRAS BRANCAS'!D11+'CEI MARIA THEREZA KLING DO VALL'!D11+'CEI DONA ESPERANZA DE BOURBON D'!D11+'CEI GIUSEPPE-NEVA VOLONTERIO'!D11+'CENTRO DE EDUCAÇÃO INFANTIL SÃO'!D11+'E M LEONARDO BOFF'!D11+'ESCOLA MUNICIPAL GENERAL HEITOR'!D11+'E M JOHANN NOEL'!D11+'ESCOLA SANTA MARIA GORETTI'!D11+'ESCOLA SANTA RITA DE CASSIA'!D11+'ESCOLA SÃO JOÃO BATISTA'!D11+'CEI CASA DA SOLIDARIEDADE DE NO'!D11+'CEI A SEMENTEIRA'!D11+'CEI VILA SAO JOSE'!D11+'E M DR RUBENS DE CASTRO BOMTEMP'!D11+'CEI FREI LEÃO'!D11+'CEI SÃO JOÃO BATISTA'!D11+'CEI JURACI PINTO DO AMARAL DE C'!D11+'E M PEDRO AMADO'!D11+'E M ABELARDO DE LAMARE'!D11+'ESCOLA MUNICIPAL SENADOR MARIO '!D11+'ESCOLA PAROQUIAL SÃO PIO X'!D11+'CEI SÃO CHARBEL'!D11+'E M ROSALINA NICOLAY'!D11+'CEI INÊS BELARMINO DE SOUZA'!D11+'E M PROFª MARIA DA GLÓRIA QUEIR'!D11+'CENTRO EDUCACIONAL COMUNIDADE S'!D11+'CEI ROMANO CANAVESE'!D11+'CEI CÉLIA LÔBO PAULO'!D11+'CEI PROFª DORA KILLER'!D11+'CEI ALTO INDEPENDÊNCIA'!D11+'ESCOLA MUNICIPAL ALTO INDEPENDÊ'!D11+'E M PAPA JOÃO PAULO II'!D11+'CEI ANDRÉ REBOUÇAS'!D11+'CEI PROFª HERMÍNIA MATHEUS'!D11+'ESCOLA MUNICIPAL MAJOR JÚLIO FR'!D11+'E M ALMIRANTE TAMANDARÉ'!D11+'ESCOLA PAROQUIAL CARLOS DEMIÁ'!D11+'CENTRO PAROQUIAL DE EDUCAÇÃO IN'!D11+'CEI IRMÃ SILVANA'!D11+'CEI OLÍVIA MACHADO DA COSTA NOG'!D11+'E M GOVERNADOR MARCELLO ALENCAR'!D11+'E M PROFESSOR FLÁVIO MACIEL'!D11+'E M PROFª JANDIRA PEIXOTO BORDI'!D11+'E M STEFAN ZWEIG'!D11+'ESCOLA PAROQUIAL BOM JESUS'!D11+'CEI MARLI SOARES FERREIRA NETTO'!D11+'CENTRO DE EDUCAÇÃO INFANTIL CHI'!D11+'CEI VILA IPANEMA'!D11+'E M ROBERT KENNEDY'!D11+'ESCOLA MUNICIPAL ANA MOHAMMAD'!D11+'ESCOLA SÃO CRISTÓVÃO'!D11+'CEI DÉA LÚCIA CORDEIRO'!D11+'CEI SAGRADA FAMÍLIA'!D11+'CEI SÃO JOSÉ DAS OBLATAS DE NAZ'!D11+'ESCOLA MUNICIPAL JORGE AMADO'!D11+'E M FÁBRICA DO SABER'!D11+'CIEP BRIZOLÃO 474 MAESTRO GUERR'!D11+'CENTRO DE ENSINO PROF DARCY RIB'!D11+'CEI ANDRÉ VANZAN'!D11+'CENTRO DE EDUCAÇÃO INFANTIL CAR'!D11+'CEI BOA VISTA'!D11+'ASSOCIAÇÃO DA CRECHE SÃO FRANCI'!D11+'ESCOLA MUNICIPAL PAULO SALDANHA'!D11+'ESCOLA MUNICIPAL LÚCIA DE ALMEI'!D11+'E M DOM MANOEL PEDRO DA CUNHA C'!D11+'ESCOLA SÃO GERALDO'!D11+'CEI LULU MONTEIRO DE CASTRO'!D11+'CEI CARANGOLA'!D11+'ASSOCIAÇÃO RECREAR'!D11+'CENTRO DE EDUCAÇÃO INFANTIL CAS'!D11+'E M ROSEMIRA DE OLIVEIRA CAVALC'!D11+'E MZDA CARMEM NUNES MARTINS'!D11+'CEI SÃO JOSÉ DO ITAMARATI'!D11+'E M DUQUE DE CAXIAS'!D11+'CENTRO DE EDUCAÇÃO INFANTIL 2'!D11+'E M ANTÔNIO LEITE GARCIA'!D11+'ESCOLA PAROQUIAL DA ALCOBAÇA'!D11+'CENTRO DE EDUCAÇÃO INFANTIL LOT'!D11+'ESCOLA PAROQUIAL DO LOTEAMENTO '!D11+'E M PROF JOAQUIM DEISTER'!D11+'E M MARIETA GONÇALVES'!D11+'ESCOLA MUNICIPAL ODETTE YOUNG M'!D11+'ESCOLA MUNICIPAL PROFESSOR JOSE'!D11+'E M HERCÍLIA HENRIQUES MORET'!D11+'COLEGIO VICENTINO PADRE CORRÊA'!D11+'CEI PROFª MARLUCE DE SOUZA PEST'!D11+'CEI IRINEU MARINHO'!D11+'CEI DAGMAR ROLANDO DE OLIVEIRA'!D11+'CEI NOSSA SENHORA DA GLÓRIA'!D11+'E M PROF NILTON COSTA PEREIRA D'!D11+'CENTRO DE EDUCAÇÃO INFANTIL SÉR'!D11+'CEI SANTO ANTÔNIO AGOSTINHO'!D11+'CEI OSWALDO CRUZ'!D11+'E M MAGDALENA TAGLIAFERRO'!D11+'ESCOLA SÃO JOSÉ DO CAETITU'!D11+'CRECHE-ESCOLA CASTELO SÃO MANOE'!D11+'CEI THEREZINHA DE JESUS LIMA'!D11+'ESCOLA MUNICIPAL PROFESSOR PAUL'!D11+'COLÉGIO ANGLICANO DE ARARAS'!D11+'ESCOLA PAROQUIAL SANTA BERNADET'!D11+'CEI VISTA ALEGRE'!D11+'CEI DENISE BESSA DE OLIVA MAYA'!D11+'CEI VIDEIRINHA'!D11+'E M AMÉRICO FERNANDES RIBEIRO'!D11+'ESCOLA MUNICIPAL AUGUSTO PUGNAL'!D11+'ESCOLA MUNICIPAL CELINA SCHECHN'!D11+'E M DARCY CORREA DA VEIGA'!D11+'E M DR PAULA BUARQUE'!D11+'LICEU SÃO JOSÉ DE ITAIPAVA'!D11+'CEI LUIZ MARCHIORI'!D11+'CENTRO DE EDUCAÇÃO INFANTIL AUG'!D11+'CEI PROFª ADRIANA CONSTÂNCIO TR'!D11+'E M AMÉLIA ANTUNES RABELLO'!D11+'CEI PREFEITO SÉRGIO FADEL'!D11+'E M DR THEODORO MACHADO'!D11+'ESCOLA SANTO ANTÔNIO'!D11+'E M TAQUARIL'!D11+'E M MONSENHOR JOÃO DE DEUS RODR'!D11+'CENTRO DE REFERÊNCIA EM EDUC 2'!D11+'CEI PROFª GRAÇA COSTA'!D11+'CEI VILA LEOPOLDINA'!D11+'CEI NILO PEÇANHA'!D11+'E MZDA SANTA TEREZINHA'!D11+'CEI CRIANÇA SANTA EDWIGES'!D11+'E M ARNALDO DYCKERHOFF'!D11+'E M CARLOS CANEDO'!D11+'E M BEATRIZ ZALESKI'!D11+'E M ANTÔNIO JOSÉ DE LIMA'!D11+'E M FELIX WAN ERVEN DE BARROS'!D11+'ESCOLA MUNICIPAL HILDEBRANDO DE'!D11+'E M OSWALDO DA COSTA FRIAS'!D11+'E MZDA AVELINO DE CARVALHO'!D11+'ESCOLA MUNICIPALIZADA MOYSÉS FU'!D11+'CEI ANGELA MARIA DA CONCEIÇÃO S'!D11+'CEI JOSÉ GONÇALVES DA MOTTA'!D11+'E M DR BARROS FRANCO'!D11+'E M MAJOR THEÓFILO DE CARVALHO'!D11+'E M JOÃO KOPKE'!D11+'CEI ASSOCIAÇÃO BENEFICENTE FAZE'!D11+'ESCOLA SAO FRANCISCO DE ASSIS'!D11+'CEI SÃO FRANCISCO ASSIS'!D11+'CEI ALDEIA DA CRIANCA'!D11+'ESCOLA MUNICIPAL ODETTE FONSECA'!D11+'CEI ANA CAROLINA TELLES'!D11+'E M SEBASTIÃO LACERDA'!D11+'E M DOM PEDRO DE ALCÂNTARA'!D11+'ESCOLA NOSSA SENHORA DE FÁTIMA'!D11+'ESCOLA PAROQUIAL SÃO FRANCISCO '!D11+'E M MONSENHOR CIRILLO CALAON'!D11 | D7: ='E M ABELARDO DE LAMARE'!M11+'E M BATAILLARD'!M11+'E M LEONARDO BOFF'!M11+'E M CLEMENTE FERNANDES'!M11+'E M DOM PEDRO DE ALCÂNTARA'!M11+'E M DUQUE DE CAXIAS'!M11+'E M LUIZ CARLOS SOARES'!M11+'ESCOLA MUNICIPAL GENERAL HEITOR'!M11+'E M JOÃO KOPKE'!M11+'ESCOLA MUNICIPAL ODETTE FONSECA'!M11+'E M GOVERNADOR MARCELLO ALENCAR'!M11+'E M PROF JOAQUIM DEISTER'!M11+'E M ROBERT KENNEDY'!M11+'E M ROTARY'!M11+'E M ROSALINA NICOLAY'!M11+'E M DE EDUCAÇÃO ESPECIAL SANTOS'!M11+'E M SOROPTIMISTA'!M11+'LICEU MUN PREFEITO CORDOLINO AM'!M11+'E M ANTÔNIO LEITE GARCIA'!M11+'ESCOLA MUNICIPAL JORGE AMADO'!M11+'ESCOLA MUNICIPAL LÚCIA DE ALMEI'!M11+'E M MAGDALENA TAGLIAFERRO'!M11+'ESCOLA MUNICIPAL MAJOR JÚLIO FR'!M11+'E M MARIETA GONÇALVES'!M11+'ESCOLA MUNICIPAL ODETTE YOUNG M'!M11+'E M FÁBRICA DO SABER'!M11+'ESCOLA MUNICIPAL PROFESSOR PAUL'!M11+'E M ROSEMIRA DE OLIVEIRA CAVALC'!M11+'E M AMÉLIA ANTUNES RABELLO'!M11+'ESCOLA MUNICIPAL AUGUSTO PUGNAL'!M11+'ESCOLA MUNICIPAL CELINA SCHECHN'!M11+'E M DARCY CORREA DA VEIGA'!M11+'E M DR PAULA BUARQUE'!M11+'E M DR THEODORO MACHADO'!M11+'E M ARNALDO DYCKERHOFF'!M11+'E M CARLOS CANEDO'!M11+'E M DR BARROS FRANCO'!M11+'E M MAJOR THEÓFILO DE CARVALHO'!M11+'E M TAQUARIL'!M11+'E M BEATRIZ ZALESKI'!M11+'E M ANTÔNIO JOSÉ DE LIMA'!M11+'E M FELIX WAN ERVEN DE BARROS'!M11+'ESCOLA MUNICIPAL HILDEBRANDO DE'!M11+'E M OSWALDO DA COSTA FRIAS'!M11+'E MZDA CARMEM NUNES MARTINS'!M11+'E MZDA AVELINO DE CARVALHO'!M11+'E M GERALDO VENTURA DIAS'!M11+'E M SALVADOR KLING'!M11+'E M PREFEITO JAMIL SABRÁ'!M11+'LICEU MUNICIPAL CARLOS CHAGAS F'!M11+'ESCOLA MUNICIPAL ANA MOHAMMAD'!M11+'ESCOLA MUNICIPAL ALTO INDEPENDÊ'!M11+'E M ALMIRANTE TAMANDARÉ'!M11+'ESCOLA MUNICIPALIZADA FREI ANIC'!M11+'E M PEDRO AMADO'!M11+'E M PROFª MARIA DA GLÓRIA QUEIR'!M11+'E M SEBASTIÃO LACERDA'!M11+'E M PROFESSOR FLÁVIO MACIEL'!M11+'ESCOLA MUNICIPAL PAULO SALDANHA'!M11+'ESCOLA MUNICIPAL PROFESSOR JOSE'!M11+'E M MONSENHOR CIRILLO CALAON'!M11+'E M AMÉRICO FERNANDES RIBEIRO'!M11+'E M PROFª JANDIRA PEIXOTO BORDI'!M11+'E M MONSENHOR JOÃO DE DEUS RODR'!M11+'E M DOM MANOEL PEDRO DA CUNHA C'!M11+'E M JOHANN NOEL'!M11+'E MZDA SANTA TEREZINHA'!M11+'E M PAPA JOÃO PAULO II'!M11+'E M STEFAN ZWEIG'!M11+'ESCOLA MUNICIPAL SENADOR MARIO '!M11+'E M DR RUBENS DE CASTRO BOMTEMP'!M11+'E M PAULO FREIRE'!M11+'E M PROFª MARIA CAMPOS DA SILVA'!M11+'E M HERCÍLIA HENRIQUES MORET'!M11+'ESCOLA MUNICIPALIZADA MOYSÉS FU'!M11+'CIEP BRIZOLÃO 474 MAESTRO GUERR'!M11+'CENTRO DE ENSINO PROF DARCY RIB'!M11+'CASA DA EDUCAÇÃO VISCONDE DE MA'!M11+'CENTRO DE REFERÊNCIA EM EDUCAÇÃ'!M11+'E M PROF NILTON COSTA PEREIRA D'!M11+'COLÉGIO GUNNAR VINGREN DE PETRÓ'!M11+'CENTRO DE REFERÊNCIA EM EDUC 2'!M11+'ESCOLA SANTA LUIZA DE MARILLAC'!M11+'CENTRO EDUCACIONAL COMUNIDADE S'!M11+'EDUCANDÁRIO TERRA SANTA'!M11+'ESCOLA GERMANO VALENTE'!M11+'ESCOLA DAS COMUNIDADES SANTO AN'!M11+'ESCOLA DOMÉSTICA NOSSA SENHORA '!M11+'ESCOLA PAROQUIAL NOSSA SENHO 3'!M11+'ESCOLA MONSENHOR GENTIL'!M11+'ESCOLA PAROQUIAL BOM JESUS'!M11+'ESCOLA PAROQUIAL CARLOS DEMIÁ'!M11+'ESCOLA PAROQUIAL NOSSA SENHO 2'!M11+'ESCOLA PAROQUIAL NOSSA SENHORA '!M11+'ESCOLA PAROQUIAL SÃO PEDRO DE A'!M11+'ESCOLA SANTA MARIA GORETTI'!M11+'ESCOLA SANTA RITA DE CASSIA'!M11+'ESCOLA SÃO CRISTÓVÃO'!M11+'ESCOLA PAROQUIAL SÃO FRANCISCO '!M11+'ESCOLA SAO FRANCISCO DE ASSIS'!M11+'ESCOLA SÃO JOÃO BATISTA'!M11+'ESCOLA SÃO JUDAS TADEU'!M11+'ESCOLA PAROQUIAL SÃO PIO X'!M11+'COLÉGIO ANGLICANO DE ARARAS'!M11+'COLEGIO VICENTINO PADRE CORRÊA'!M11+'ESCOLA NOSSA SENHORA DE FÁTIMA'!M11+'ESCOLA PAROQUIAL DA ALCOBAÇA'!M11+'ESCOLA PAROQUIAL DO LOTEAMENTO '!M11+'ESCOLA PAROQUIAL SANTA BERNADET'!M11+'ESCOLA SÃO GERALDO'!M11+'ESCOLA SANTO ANTÔNIO'!M11+'LICEU SÃO JOSÉ DE ITAIPAVA'!M11+'ESCOLA SÃO JOSÉ DO CAETITU'!M11+'CEI ASSOCIAÇÃO BENEFICENTE FAZE'!M11+'CEI CASA DA SOLIDARIEDADE DE NO'!M11+'CEI LULU MONTEIRO DE CASTRO'!M11+'CEI SÃO JOÃO BATISTA'!M11+'CEI SÃO FRANCISCO ASSIS'!M11+'CEI A SEMENTEIRA'!M11+'CEI FREI LEÃO'!M11+'CEI ROMANO CANAVESE'!M11+'CEI ANDRÉ VANZAN'!M11+'CEI CRIANÇA SANTA EDWIGES'!M11+'CENTRO DE EDUCAÇÃO INFANTIL IRM'!M11+'CEI PEDRAS BRANCAS'!M11+'CEI INÊS BELARMINO DE SOUZA'!M11+'CEI PROFª ROSANGELA DA SILVA LE'!M11+'CEI VILA SAO JOSE'!M11+'CEI MARIA THEREZA KLING DO VALL'!M11+'CEI DEISE ELOY GOMES'!M11+'CENTRO PAROQUIAL DE EDUCAÇÃO IN'!M11+'CEI VISTA ALEGRE'!M11+'CEI ALDEIA DA CRIANCA'!M11+'CEI DÉA LÚCIA CORDEIRO'!M11+'CENTRO DE EDUCAÇÃO INFANTIL CAR'!M11+'CEI IRMÃ SILVANA'!M11+'CEI MARLI SOARES FERREIRA NETTO'!M11+'CEI PROFª SONIA REGINA SCUDESE '!M11+'CEI DONA ESPERANZA DE BOURBON D'!M11+'CEI PREFEITO SÉRGIO FADEL'!M11+'CEI ANDRÉ REBOUÇAS'!M11+'CENTRO DE EDUCAÇÃO INFANTIL CHI'!M11+'CEI TIA ALICE'!M11+'CEI TERRA SANTA'!M11+'CEI JORGE ROLANDO DA SILVA'!M11+'CEI CARANGOLA'!M11+'CEI CÉLIA LÔBO PAULO'!M11+'CEI LIONS CLUBE DE PETRÓPOLIS'!M11+'CEI PROFª GRAÇA COSTA'!M11+'CEI ANGELA MARIA DA CONCEIÇÃO S'!M11+'CEI LUIZ MARCHIORI'!M11+'CEI PROFª MARLUCE DE SOUZA PEST'!M11+'CEI OLÍVIA MACHADO DA COSTA NOG'!M11+'CEI VILA IPANEMA'!M11+'CEI VILA LEOPOLDINA'!M11+'CENTRO DE EDUCAÇÃO INFANTIL CAS'!M11+'CEI PRIMEIRA INFÂNCIA'!M11+'CEI PROFª DORA KILLER'!M11+'CEI PROFª PATRÍCIA FERREIRA E S'!M11+'CEI DRA ZILDA ARNS NEUMANN'!M11+'CEI DENISE BESSA DE OLIVA MAYA'!M11+'CEI GIUSEPPE-NEVA VOLONTERIO'!M11+'CENTRO DE EDUCAÇÃO INFANTIL LOT'!M11+'CEI IRINEU MARINHO'!M11+'CEI OSWALDO CRUZ'!M11+'CEI ANA CAROLINA TELLES'!M11+'CEI JOSÉ GONÇALVES DA MOTTA'!M11+'CEI SAGRADA FAMÍLIA'!M11+'CEI PROFª HERMÍNIA MATHEUS'!M11+'CENTRO DE EDUCAÇÃO INFANTIL PRO'!M11+'CEI MONSENHOR PAULO ELIAS DAHER'!M11+'CEI DAGMAR ROLANDO DE OLIVEIRA'!M11+'CENTRO DE EDUCAÇÃO INFANTIL 2'!M11+'CEI BOA VISTA'!M11+'CEI NILO PEÇANHA'!M11+'CENTRO DE EDUCAÇÃO INFANTIL AUG'!M11+'CEI THEREZINHA DE JESUS LIMA'!M11+'CEI VIDEIRINHA'!M11+'CEI PROFª ADRIANA CONSTÂNCIO TR'!M11+'CENTRO DE EDUCAÇÃO INFANTIL SÉR'!M11+'CEI JURACI PINTO DO AMARAL DE C'!M11+'CEI NOSSA SENHORA DA GLÓRIA'!M11+'CEI ALTO INDEPENDÊNCIA'!M11+'CEI SÃO JOSÉ DAS OBLATAS DE NAZ'!M11+'CEI SANTO ANTÔNIO AGOSTINHO'!M11+'CEI SÃO CHARBEL'!M11+'ASSOCIAÇÃO DA CRECHE SÃO FRANCI'!M11+'CEI SÃO JOSÉ DO ITAMARATI'!M11+'ASSOCIAÇÃO RECREAR'!M11+'CRECHE-ESCOLA CASTELO SÃO MANOE'!M11+'CENTRO DE EDUCAÇÃO INFANTIL SÃO'!M11 | E7: ='Entrada de Dados'!E2 | F7: =D7*E7
A8: ='Entrada de Dados'!F5 | B8: ='Entrada de Dados'!F197 | C8: ='E M ROTARY'!D12+'E M DE EDUCAÇÃO ESPECIAL SANTOS'!D12+'LICEU MUN PREFEITO CORDOLINO AM'!D12+'E M PREFEITO JAMIL SABRÁ'!D12+'LICEU MUNICIPAL CARLOS CHAGAS F'!D12+'E M PAULO FREIRE'!D12+'E M PROFª MARIA CAMPOS DA SILVA'!D12+'CASA DA EDUCAÇÃO VISCONDE DE MA'!D12+'CENTRO DE REFERÊNCIA EM EDUCAÇÃ'!D12+'ESCOLA SANTA LUIZA DE MARILLAC'!D12+'ESCOLA DOMÉSTICA NOSSA SENHORA '!D12+'ESCOLA MONSENHOR GENTIL'!D12+'ESCOLA PAROQUIAL NOSSA SENHORA '!D12+'ESCOLA PAROQUIAL SÃO PEDRO DE A'!D12+'CEI TERRA SANTA'!D12+'CEI PRIMEIRA INFÂNCIA'!D12+'CEI PROFª PATRÍCIA FERREIRA E S'!D12+'CEI DRA ZILDA ARNS NEUMANN'!D12+'CENTRO DE EDUCAÇÃO INFANTIL PRO'!D12+'CEI MONSENHOR PAULO ELIAS DAHER'!D12+'COLÉGIO GUNNAR VINGREN DE PETRÓ'!D12+'EDUCANDÁRIO TERRA SANTA'!D12+'CEI LIONS CLUBE DE PETRÓPOLIS'!D12+'ESCOLA PAROQUIAL NOSSA SENHO 2'!D12+'CENTRO DE EDUCAÇÃO INFANTIL IRM'!D12+'E M LUIZ CARLOS SOARES'!D12+'ESCOLA GERMANO VALENTE'!D12+'ESCOLA PAROQUIAL NOSSA SENHO 3'!D12+'CEI JORGE ROLANDO DA SILVA'!D12+'E M CLEMENTE FERNANDES'!D12+'E M GERALDO VENTURA DIAS'!D12+'ESCOLA DAS COMUNIDADES SANTO AN'!D12+'CEI PROFª ROSANGELA DA SILVA LE'!D12+'CEI DEISE ELOY GOMES'!D12+'CEI PROFª SONIA REGINA SCUDESE '!D12+'CEI TIA ALICE'!D12+'E M BATAILLARD'!D12+'E M SOROPTIMISTA'!D12+'E M SALVADOR KLING'!D12+'ESCOLA MUNICIPALIZADA FREI ANIC'!D12+'ESCOLA SÃO JUDAS TADEU'!D12+'CEI PEDRAS BRANCAS'!D12+'CEI MARIA THEREZA KLING DO VALL'!D12+'CEI DONA ESPERANZA DE BOURBON D'!D12+'CEI GIUSEPPE-NEVA VOLONTERIO'!D12+'CENTRO DE EDUCAÇÃO INFANTIL SÃO'!D12+'E M LEONARDO BOFF'!D12+'ESCOLA MUNICIPAL GENERAL HEITOR'!D12+'E M JOHANN NOEL'!D12+'ESCOLA SANTA MARIA GORETTI'!D12+'ESCOLA SANTA RITA DE CASSIA'!D12+'ESCOLA SÃO JOÃO BATISTA'!D12+'CEI CASA DA SOLIDARIEDADE DE NO'!D12+'CEI A SEMENTEIRA'!D12+'CEI VILA SAO JOSE'!D12+'E M DR RUBENS DE CASTRO BOMTEMP'!D12+'CEI FREI LEÃO'!D12+'CEI SÃO JOÃO BATISTA'!D12+'CEI JURACI PINTO DO AMARAL DE C'!D12+'E M PEDRO AMADO'!D12+'E M ABELARDO DE LAMARE'!D12+'ESCOLA MUNICIPAL SENADOR MARIO '!D12+'ESCOLA PAROQUIAL SÃO PIO X'!D12+'CEI SÃO CHARBEL'!D12+'E M ROSALINA NICOLAY'!D12+'CEI INÊS BELARMINO DE SOUZA'!D12+'E M PROFª MARIA DA GLÓRIA QUEIR'!D12+'CENTRO EDUCACIONAL COMUNIDADE S'!D12+'CEI ROMANO CANAVESE'!D12+'CEI CÉLIA LÔBO PAULO'!D12+'CEI PROFª DORA KILLER'!D12+'CEI ALTO INDEPENDÊNCIA'!D12+'ESCOLA MUNICIPAL ALTO INDEPENDÊ'!D12+'E M PAPA JOÃO PAULO II'!D12+'CEI ANDRÉ REBOUÇAS'!D12+'CEI PROFª HERMÍNIA MATHEUS'!D12+'ESCOLA MUNICIPAL MAJOR JÚLIO FR'!D12+'E M ALMIRANTE TAMANDARÉ'!D12+'ESCOLA PAROQUIAL CARLOS DEMIÁ'!D12+'CENTRO PAROQUIAL DE EDUCAÇÃO IN'!D12+'CEI IRMÃ SILVANA'!D12+'CEI OLÍVIA MACHADO DA COSTA NOG'!D12+'E M GOVERNADOR MARCELLO ALENCAR'!D12+'E M PROFESSOR FLÁVIO MACIEL'!D12+'E M PROFª JANDIRA PEIXOTO BORDI'!D12+'E M STEFAN ZWEIG'!D12+'ESCOLA PAROQUIAL BOM JESUS'!D12+'CEI MARLI SOARES FERREIRA NETTO'!D12+'CENTRO DE EDUCAÇÃO INFANTIL CHI'!D12+'CEI VILA IPANEMA'!D12+'E M ROBERT KENNEDY'!D12+'ESCOLA MUNICIPAL ANA MOHAMMAD'!D12+'ESCOLA SÃO CRISTÓVÃO'!D12+'CEI DÉA LÚCIA CORDEIRO'!D12+'CEI SAGRADA FAMÍLIA'!D12+'CEI SÃO JOSÉ DAS OBLATAS DE NAZ'!D12+'ESCOLA MUNICIPAL JORGE AMADO'!D12+'E M FÁBRICA DO SABER'!D12+'CIEP BRIZOLÃO 474 MAESTRO GUERR'!D12+'CENTRO DE ENSINO PROF DARCY RIB'!D12+'CEI ANDRÉ VANZAN'!D12+'CENTRO DE EDUCAÇÃO INFANTIL CAR'!D12+'CEI BOA VISTA'!D12+'ASSOCIAÇÃO DA CRECHE SÃO FRANCI'!D12+'ESCOLA MUNICIPAL PAULO SALDANHA'!D12+'ESCOLA MUNICIPAL LÚCIA DE ALMEI'!D12+'E M DOM MANOEL PEDRO DA CUNHA C'!D12+'ESCOLA SÃO GERALDO'!D12+'CEI LULU MONTEIRO DE CASTRO'!D12+'CEI CARANGOLA'!D12+'ASSOCIAÇÃO RECREAR'!D12+'CENTRO DE EDUCAÇÃO INFANTIL CAS'!D12+'E M ROSEMIRA DE OLIVEIRA CAVALC'!D12+'E MZDA CARMEM NUNES MARTINS'!D12+'CEI SÃO JOSÉ DO ITAMARATI'!D12+'E M DUQUE DE CAXIAS'!D12+'CENTRO DE EDUCAÇÃO INFANTIL 2'!D12+'E M ANTÔNIO LEITE GARCIA'!D12+'ESCOLA PAROQUIAL DA ALCOBAÇA'!D12+'CENTRO DE EDUCAÇÃO INFANTIL LOT'!D12+'ESCOLA PAROQUIAL DO LOTEAMENTO '!D12+'E M PROF JOAQUIM DEISTER'!D12+'E M MARIETA GONÇALVES'!D12+'ESCOLA MUNICIPAL ODETTE YOUNG M'!D12+'ESCOLA MUNICIPAL PROFESSOR JOSE'!D12+'E M HERCÍLIA HENRIQUES MORET'!D12+'COLEGIO VICENTINO PADRE CORRÊA'!D12+'CEI PROFª MARLUCE DE SOUZA PEST'!D12+'CEI IRINEU MARINHO'!D12+'CEI DAGMAR ROLANDO DE OLIVEIRA'!D12+'CEI NOSSA SENHORA DA GLÓRIA'!D12+'E M PROF NILTON COSTA PEREIRA D'!D12+'CENTRO DE EDUCAÇÃO INFANTIL SÉR'!D12+'CEI SANTO ANTÔNIO AGOSTINHO'!D12+'CEI OSWALDO CRUZ'!D12+'E M MAGDALENA TAGLIAFERRO'!D12+'ESCOLA SÃO JOSÉ DO CAETITU'!D12+'CRECHE-ESCOLA CASTELO SÃO MANOE'!D12+'CEI THEREZINHA DE JESUS LIMA'!D12+'ESCOLA MUNICIPAL PROFESSOR PAUL'!D12+'COLÉGIO ANGLICANO DE ARARAS'!D12+'ESCOLA PAROQUIAL SANTA BERNADET'!D12+'CEI VISTA ALEGRE'!D12+'CEI DENISE BESSA DE OLIVA MAYA'!D12+'CEI VIDEIRINHA'!D12+'E M AMÉRICO FERNANDES RIBEIRO'!D12+'ESCOLA MUNICIPAL AUGUSTO PUGNAL'!D12+'ESCOLA MUNICIPAL CELINA SCHECHN'!D12+'E M DARCY CORREA DA VEIGA'!D12+'E M DR PAULA BUARQUE'!D12+'LICEU SÃO JOSÉ DE ITAIPAVA'!D12+'CEI LUIZ MARCHIORI'!D12+'CENTRO DE EDUCAÇÃO INFANTIL AUG'!D12+'CEI PROFª ADRIANA CONSTÂNCIO TR'!D12+'E M AMÉLIA ANTUNES RABELLO'!D12+'CEI PREFEITO SÉRGIO FADEL'!D12+'E M DR THEODORO MACHADO'!D12+'ESCOLA SANTO ANTÔNIO'!D12+'E M TAQUARIL'!D12+'E M MONSENHOR JOÃO DE DEUS RODR'!D12+'CENTRO DE REFERÊNCIA EM EDUC 2'!D12+'CEI PROFª GRAÇA COSTA'!D12+'CEI VILA LEOPOLDINA'!D12+'CEI NILO PEÇANHA'!D12+'E MZDA SANTA TEREZINHA'!D12+'CEI CRIANÇA SANTA EDWIGES'!D12+'E M ARNALDO DYCKERHOFF'!D12+'E M CARLOS CANEDO'!D12+'E M BEATRIZ ZALESKI'!D12+'E M ANTÔNIO JOSÉ DE LIMA'!D12+'E M FELIX WAN ERVEN DE BARROS'!D12+'ESCOLA MUNICIPAL HILDEBRANDO DE'!D12+'E M OSWALDO DA COSTA FRIAS'!D12+'E MZDA AVELINO DE CARVALHO'!D12+'ESCOLA MUNICIPALIZADA MOYSÉS FU'!D12+'CEI ANGELA MARIA DA CONCEIÇÃO S'!D12+'CEI JOSÉ GONÇALVES DA MOTTA'!D12+'E M DR BARROS FRANCO'!D12+'E M MAJOR THEÓFILO DE CARVALHO'!D12+'E M JOÃO KOPKE'!D12+'CEI ASSOCIAÇÃO BENEFICENTE FAZE'!D12+'ESCOLA SAO FRANCISCO DE ASSIS'!D12+'CEI SÃO FRANCISCO ASSIS'!D12+'CEI ALDEIA DA CRIANCA'!D12+'ESCOLA MUNICIPAL ODETTE FONSECA'!D12+'CEI ANA CAROLINA TELLES'!D12+'E M SEBASTIÃO LACERDA'!D12+'E M DOM PEDRO DE ALCÂNTARA'!D12+'ESCOLA NOSSA SENHORA DE FÁTIMA'!D12+'ESCOLA PAROQUIAL SÃO FRANCISCO '!D12+'E M MONSENHOR CIRILLO CALAON'!D12 | D8: ='E M ABELARDO DE LAMARE'!M12+'E M BATAILLARD'!M12+'E M LEONARDO BOFF'!M12+'E M CLEMENTE FERNANDES'!M12+'E M DOM PEDRO DE ALCÂNTARA'!M12+'E M DUQUE DE CAXIAS'!M12+'E M LUIZ CARLOS SOARES'!M12+'ESCOLA MUNICIPAL GENERAL HEITOR'!M12+'E M JOÃO KOPKE'!M12+'ESCOLA MUNICIPAL ODETTE FONSECA'!M12+'E M GOVERNADOR MARCELLO ALENCAR'!M12+'E M PROF JOAQUIM DEISTER'!M12+'E M ROBERT KENNEDY'!M12+'E M ROTARY'!M12+'E M ROSALINA NICOLAY'!M12+'E M DE EDUCAÇÃO ESPECIAL SANTOS'!M12+'E M SOROPTIMISTA'!M12+'LICEU MUN PREFEITO CORDOLINO AM'!M12+'E M ANTÔNIO LEITE GARCIA'!M12+'ESCOLA MUNICIPAL JORGE AMADO'!M12+'ESCOLA MUNICIPAL LÚCIA DE ALMEI'!M12+'E M MAGDALENA TAGLIAFERRO'!M12+'ESCOLA MUNICIPAL MAJOR JÚLIO FR'!M12+'E M MARIETA GONÇALVES'!M12+'ESCOLA MUNICIPAL ODETTE YOUNG M'!M12+'E M FÁBRICA DO SABER'!M12+'ESCOLA MUNICIPAL PROFESSOR PAUL'!M12+'E M ROSEMIRA DE OLIVEIRA CAVALC'!M12+'E M AMÉLIA ANTUNES RABELLO'!M12+'ESCOLA MUNICIPAL AUGUSTO PUGNAL'!M12+'ESCOLA MUNICIPAL CELINA SCHECHN'!M12+'E M DARCY CORREA DA VEIGA'!M12+'E M DR PAULA BUARQUE'!M12+'E M DR THEODORO MACHADO'!M12+'E M ARNALDO DYCKERHOFF'!M12+'E M CARLOS CANEDO'!M12+'E M DR BARROS FRANCO'!M12+'E M MAJOR THEÓFILO DE CARVALHO'!M12+'E M TAQUARIL'!M12+'E M BEATRIZ ZALESKI'!M12+'E M ANTÔNIO JOSÉ DE LIMA'!M12+'E M FELIX WAN ERVEN DE BARROS'!M12+'ESCOLA MUNICIPAL HILDEBRANDO DE'!M12+'E M OSWALDO DA COSTA FRIAS'!M12+'E MZDA CARMEM NUNES MARTINS'!M12+'E MZDA AVELINO DE CARVALHO'!M12+'E M GERALDO VENTURA DIAS'!M12+'E M SALVADOR KLING'!M12+'E M PREFEITO JAMIL SABRÁ'!M12+'LICEU MUNICIPAL CARLOS CHAGAS F'!M12+'ESCOLA MUNICIPAL ANA MOHAMMAD'!M12+'ESCOLA MUNICIPAL ALTO INDEPENDÊ'!M12+'E M ALMIRANTE TAMANDARÉ'!M12+'ESCOLA MUNICIPALIZADA FREI ANIC'!M12+'E M PEDRO AMADO'!M12+'E M PROFª MARIA DA GLÓRIA QUEIR'!M12+'E M SEBASTIÃO LACERDA'!M12+'E M PROFESSOR FLÁVIO MACIEL'!M12+'ESCOLA MUNICIPAL PAULO SALDANHA'!M12+'ESCOLA MUNICIPAL PROFESSOR JOSE'!M12+'E M MONSENHOR CIRILLO CALAON'!M12+'E M AMÉRICO FERNANDES RIBEIRO'!M12+'E M PROFª JANDIRA PEIXOTO BORDI'!M12+'E M MONSENHOR JOÃO DE DEUS RODR'!M12+'E M DOM MANOEL PEDRO DA CUNHA C'!M12+'E M JOHANN NOEL'!M12+'E MZDA SANTA TEREZINHA'!M12+'E M PAPA JOÃO PAULO II'!M12+'E M STEFAN ZWEIG'!M12+'ESCOLA MUNICIPAL SENADOR MARIO '!M12+'E M DR RUBENS DE CASTRO BOMTEMP'!M12+'E M PAULO FREIRE'!M12+'E M PROFª MARIA CAMPOS DA SILVA'!M12+'E M HERCÍLIA HENRIQUES MORET'!M12+'ESCOLA MUNICIPALIZADA MOYSÉS FU'!M12+'CIEP BRIZOLÃO 474 MAESTRO GUERR'!M12+'CENTRO DE ENSINO PROF DARCY RIB'!M12+'CASA DA EDUCAÇÃO VISCONDE DE MA'!M12+'CENTRO DE REFERÊNCIA EM EDUCAÇÃ'!M12+'E M PROF NILTON COSTA PEREIRA D'!M12+'COLÉGIO GUNNAR VINGREN DE PETRÓ'!M12+'CENTRO DE REFERÊNCIA EM EDUC 2'!M12+'ESCOLA SANTA LUIZA DE MARILLAC'!M12+'CENTRO EDUCACIONAL COMUNIDADE S'!M12+'EDUCANDÁRIO TERRA SANTA'!M12+'ESCOLA GERMANO VALENTE'!M12+'ESCOLA DAS COMUNIDADES SANTO AN'!M12+'ESCOLA DOMÉSTICA NOSSA SENHORA '!M12+'ESCOLA PAROQUIAL NOSSA SENHO 3'!M12+'ESCOLA MONSENHOR GENTIL'!M12+'ESCOLA PAROQUIAL BOM JESUS'!M12+'ESCOLA PAROQUIAL CARLOS DEMIÁ'!M12+'ESCOLA PAROQUIAL NOSSA SENHO 2'!M12+'ESCOLA PAROQUIAL NOSSA SENHORA '!M12+'ESCOLA PAROQUIAL SÃO PEDRO DE A'!M12+'ESCOLA SANTA MARIA GORETTI'!M12+'ESCOLA SANTA RITA DE CASSIA'!M12+'ESCOLA SÃO CRISTÓVÃO'!M12+'ESCOLA PAROQUIAL SÃO FRANCISCO '!M12+'ESCOLA SAO FRANCISCO DE ASSIS'!M12+'ESCOLA SÃO JOÃO BATISTA'!M12+'ESCOLA SÃO JUDAS TADEU'!M12+'ESCOLA PAROQUIAL SÃO PIO X'!M12+'COLÉGIO ANGLICANO DE ARARAS'!M12+'COLEGIO VICENTINO PADRE CORRÊA'!M12+'ESCOLA NOSSA SENHORA DE FÁTIMA'!M12+'ESCOLA PAROQUIAL DA ALCOBAÇA'!M12+'ESCOLA PAROQUIAL DO LOTEAMENTO '!M12+'ESCOLA PAROQUIAL SANTA BERNADET'!M12+'ESCOLA SÃO GERALDO'!M12+'ESCOLA SANTO ANTÔNIO'!M12+'LICEU SÃO JOSÉ DE ITAIPAVA'!M12+'ESCOLA SÃO JOSÉ DO CAETITU'!M12+'CEI ASSOCIAÇÃO BENEFICENTE FAZE'!M12+'CEI CASA DA SOLIDARIEDADE DE NO'!M12+'CEI LULU MONTEIRO DE CASTRO'!M12+'CEI SÃO JOÃO BATISTA'!M12+'CEI SÃO FRANCISCO ASSIS'!M12+'CEI A SEMENTEIRA'!M12+'CEI FREI LEÃO'!M12+'CEI ROMANO CANAVESE'!M12+'CEI ANDRÉ VANZAN'!M12+'CEI CRIANÇA SANTA EDWIGES'!M12+'CENTRO DE EDUCAÇÃO INFANTIL IRM'!M12+'CEI PEDRAS BRANCAS'!M12+'CEI INÊS BELARMINO DE SOUZA'!M12+'CEI PROFª ROSANGELA DA SILVA LE'!M12+'CEI VILA SAO JOSE'!M12+'CEI MARIA THEREZA KLING DO VALL'!M12+'CEI DEISE ELOY GOMES'!M12+'CENTRO PAROQUIAL DE EDUCAÇÃO IN'!M12+'CEI VISTA ALEGRE'!M12+'CEI ALDEIA DA CRIANCA'!M12+'CEI DÉA LÚCIA CORDEIRO'!M12+'CENTRO DE EDUCAÇÃO INFANTIL CAR'!M12+'CEI IRMÃ SILVANA'!M12+'CEI MARLI SOARES FERREIRA NETTO'!M12+'CEI PROFª SONIA REGINA SCUDESE '!M12+'CEI DONA ESPERANZA DE BOURBON D'!M12+'CEI PREFEITO SÉRGIO FADEL'!M12+'CEI ANDRÉ REBOUÇAS'!M12+'CENTRO DE EDUCAÇÃO INFANTIL CHI'!M12+'CEI TIA ALICE'!M12+'CEI TERRA SANTA'!M12+'CEI JORGE ROLANDO DA SILVA'!M12+'CEI CARANGOLA'!M12+'CEI CÉLIA LÔBO PAULO'!M12+'CEI LIONS CLUBE DE PETRÓPOLIS'!M12+'CEI PROFª GRAÇA COSTA'!M12+'CEI ANGELA MARIA DA CONCEIÇÃO S'!M12+'CEI LUIZ MARCHIORI'!M12+'CEI PROFª MARLUCE DE SOUZA PEST'!M12+'CEI OLÍVIA MACHADO DA COSTA NOG'!M12+'CEI VILA IPANEMA'!M12+'CEI VILA LEOPOLDINA'!M12+'CENTRO DE EDUCAÇÃO INFANTIL CAS'!M12+'CEI PRIMEIRA INFÂNCIA'!M12+'CEI PROFª DORA KILLER'!M12+'CEI PROFª PATRÍCIA FERREIRA E S'!M12+'CEI DRA ZILDA ARNS NEUMANN'!M12+'CEI DENISE BESSA DE OLIVA MAYA'!M12+'CEI GIUSEPPE-NEVA VOLONTERIO'!M12+'CENTRO DE EDUCAÇÃO INFANTIL LOT'!M12+'CEI IRINEU MARINHO'!M12+'CEI OSWALDO CRUZ'!M12+'CEI ANA CAROLINA TELLES'!M12+'CEI JOSÉ GONÇALVES DA MOTTA'!M12+'CEI SAGRADA FAMÍLIA'!M12+'CEI PROFª HERMÍNIA MATHEUS'!M12+'CENTRO DE EDUCAÇÃO INFANTIL PRO'!M12+'CEI MONSENHOR PAULO ELIAS DAHER'!M12+'CEI DAGMAR ROLANDO DE OLIVEIRA'!M12+'CENTRO DE EDUCAÇÃO INFANTIL 2'!M12+'CEI BOA VISTA'!M12+'CEI NILO PEÇANHA'!M12+'CENTRO DE EDUCAÇÃO INFANTIL AUG'!M12+'CEI THEREZINHA DE JESUS LIMA'!M12+'CEI VIDEIRINHA'!M12+'CEI PROFª ADRIANA CONSTÂNCIO TR'!M12+'CENTRO DE EDUCAÇÃO INFANTIL SÉR'!M12+'CEI JURACI PINTO DO AMARAL DE C'!M12+'CEI NOSSA SENHORA DA GLÓRIA'!M12+'CEI ALTO INDEPENDÊNCIA'!M12+'CEI SÃO JOSÉ DAS OBLATAS DE NAZ'!M12+'CEI SANTO ANTÔNIO AGOSTINHO'!M12+'CEI SÃO CHARBEL'!M12+'ASSOCIAÇÃO DA CRECHE SÃO FRANCI'!M12+'CEI SÃO JOSÉ DO ITAMARATI'!M12+'ASSOCIAÇÃO RECREAR'!M12+'CRECHE-ESCOLA CASTELO SÃO MANOE'!M12+'CENTRO DE EDUCAÇÃO INFANTIL SÃO'!M12 | E8: ='Entrada de Dados'!F2 | F8: =D8*E8
A9: ='Entrada de Dados'!G5 | B9: ='Entrada de Dados'!G197 | C9: ='E M ROTARY'!D13+'E M DE EDUCAÇÃO ESPECIAL SANTOS'!D13+'LICEU MUN PREFEITO CORDOLINO AM'!D13+'E M PREFEITO JAMIL SABRÁ'!D13+'LICEU MUNICIPAL CARLOS CHAGAS F'!D13+'E M PAULO FREIRE'!D13+'E M PROFª MARIA CAMPOS DA SILVA'!D13+'CASA DA EDUCAÇÃO VISCONDE DE MA'!D13+'CENTRO DE REFERÊNCIA EM EDUCAÇÃ'!D13+'ESCOLA SANTA LUIZA DE MARILLAC'!D13+'ESCOLA DOMÉSTICA NOSSA SENHORA '!D13+'ESCOLA MONSENHOR GENTIL'!D13+'ESCOLA PAROQUIAL NOSSA SENHORA '!D13+'ESCOLA PAROQUIAL SÃO PEDRO DE A'!D13+'CEI TERRA SANTA'!D13+'CEI PRIMEIRA INFÂNCIA'!D13+'CEI PROFª PATRÍCIA FERREIRA E S'!D13+'CEI DRA ZILDA ARNS NEUMANN'!D13+'CENTRO DE EDUCAÇÃO INFANTIL PRO'!D13+'CEI MONSENHOR PAULO ELIAS DAHER'!D13+'COLÉGIO GUNNAR VINGREN DE PETRÓ'!D13+'EDUCANDÁRIO TERRA SANTA'!D13+'CEI LIONS CLUBE DE PETRÓPOLIS'!D13+'ESCOLA PAROQUIAL NOSSA SENHO 2'!D13+'CENTRO DE EDUCAÇÃO INFANTIL IRM'!D13+'E M LUIZ CARLOS SOARES'!D13+'ESCOLA GERMANO VALENTE'!D13+'ESCOLA PAROQUIAL NOSSA SENHO 3'!D13+'CEI JORGE ROLANDO DA SILVA'!D13+'E M CLEMENTE FERNANDES'!D13+'E M GERALDO VENTURA DIAS'!D13+'ESCOLA DAS COMUNIDADES SANTO AN'!D13+'CEI PROFª ROSANGELA DA SILVA LE'!D13+'CEI DEISE ELOY GOMES'!D13+'CEI PROFª SONIA REGINA SCUDESE '!D13+'CEI TIA ALICE'!D13+'E M BATAILLARD'!D13+'E M SOROPTIMISTA'!D13+'E M SALVADOR KLING'!D13+'ESCOLA MUNICIPALIZADA FREI ANIC'!D13+'ESCOLA SÃO JUDAS TADEU'!D13+'CEI PEDRAS BRANCAS'!D13+'CEI MARIA THEREZA KLING DO VALL'!D13+'CEI DONA ESPERANZA DE BOURBON D'!D13+'CEI GIUSEPPE-NEVA VOLONTERIO'!D13+'CENTRO DE EDUCAÇÃO INFANTIL SÃO'!D13+'E M LEONARDO BOFF'!D13+'ESCOLA MUNICIPAL GENERAL HEITOR'!D13+'E M JOHANN NOEL'!D13+'ESCOLA SANTA MARIA GORETTI'!D13+'ESCOLA SANTA RITA DE CASSIA'!D13+'ESCOLA SÃO JOÃO BATISTA'!D13+'CEI CASA DA SOLIDARIEDADE DE NO'!D13+'CEI A SEMENTEIRA'!D13+'CEI VILA SAO JOSE'!D13+'E M DR RUBENS DE CASTRO BOMTEMP'!D13+'CEI FREI LEÃO'!D13+'CEI SÃO JOÃO BATISTA'!D13+'CEI JURACI PINTO DO AMARAL DE C'!D13+'E M PEDRO AMADO'!D13+'E M ABELARDO DE LAMARE'!D13+'ESCOLA MUNICIPAL SENADOR MARIO '!D13+'ESCOLA PAROQUIAL SÃO PIO X'!D13+'CEI SÃO CHARBEL'!D13+'E M ROSALINA NICOLAY'!D13+'CEI INÊS BELARMINO DE SOUZA'!D13+'E M PROFª MARIA DA GLÓRIA QUEIR'!D13+'CENTRO EDUCACIONAL COMUNIDADE S'!D13+'CEI ROMANO CANAVESE'!D13+'CEI CÉLIA LÔBO PAULO'!D13+'CEI PROFª DORA KILLER'!D13+'CEI ALTO INDEPENDÊNCIA'!D13+'ESCOLA MUNICIPAL ALTO INDEPENDÊ'!D13+'E M PAPA JOÃO PAULO II'!D13+'CEI ANDRÉ REBOUÇAS'!D13+'CEI PROFª HERMÍNIA MATHEUS'!D13+'ESCOLA MUNICIPAL MAJOR JÚLIO FR'!D13+'E M ALMIRANTE TAMANDARÉ'!D13+'ESCOLA PAROQUIAL CARLOS DEMIÁ'!D13+'CENTRO PAROQUIAL DE EDUCAÇÃO IN'!D13+'CEI IRMÃ SILVANA'!D13+'CEI OLÍVIA MACHADO DA COSTA NOG'!D13+'E M GOVERNADOR MARCELLO ALENCAR'!D13+'E M PROFESSOR FLÁVIO MACIEL'!D13+'E M PROFª JANDIRA PEIXOTO BORDI'!D13+'E M STEFAN ZWEIG'!D13+'ESCOLA PAROQUIAL BOM JESUS'!D13+'CEI MARLI SOARES FERREIRA NETTO'!D13+'CENTRO DE EDUCAÇÃO INFANTIL CHI'!D13+'CEI VILA IPANEMA'!D13+'E M ROBERT KENNEDY'!D13+'ESCOLA MUNICIPAL ANA MOHAMMAD'!D13+'ESCOLA SÃO CRISTÓVÃO'!D13+'CEI DÉA LÚCIA CORDEIRO'!D13+'CEI SAGRADA FAMÍLIA'!D13+'CEI SÃO JOSÉ DAS OBLATAS DE NAZ'!D13+'ESCOLA MUNICIPAL JORGE AMADO'!D13+'E M FÁBRICA DO SABER'!D13+'CIEP BRIZOLÃO 474 MAESTRO GUERR'!D13+'CENTRO DE ENSINO PROF DARCY RIB'!D13+'CEI ANDRÉ VANZAN'!D13+'CENTRO DE EDUCAÇÃO INFANTIL CAR'!D13+'CEI BOA VISTA'!D13+'ASSOCIAÇÃO DA CRECHE SÃO FRANCI'!D13+'ESCOLA MUNICIPAL PAULO SALDANHA'!D13+'ESCOLA MUNICIPAL LÚCIA DE ALMEI'!D13+'E M DOM MANOEL PEDRO DA CUNHA C'!D13+'ESCOLA SÃO GERALDO'!D13+'CEI LULU MONTEIRO DE CASTRO'!D13+'CEI CARANGOLA'!D13+'ASSOCIAÇÃO RECREAR'!D13+'CENTRO DE EDUCAÇÃO INFANTIL CAS'!D13+'E M ROSEMIRA DE OLIVEIRA CAVALC'!D13+'E MZDA CARMEM NUNES MARTINS'!D13+'CEI SÃO JOSÉ DO ITAMARATI'!D13+'E M DUQUE DE CAXIAS'!D13+'CENTRO DE EDUCAÇÃO INFANTIL 2'!D13+'E M ANTÔNIO LEITE GARCIA'!D13+'ESCOLA PAROQUIAL DA ALCOBAÇA'!D13+'CENTRO DE EDUCAÇÃO INFANTIL LOT'!D13+'ESCOLA PAROQUIAL DO LOTEAMENTO '!D13+'E M PROF JOAQUIM DEISTER'!D13+'E M MARIETA GONÇALVES'!D13+'ESCOLA MUNICIPAL ODETTE YOUNG M'!D13+'ESCOLA MUNICIPAL PROFESSOR JOSE'!D13+'E M HERCÍLIA HENRIQUES MORET'!D13+'COLEGIO VICENTINO PADRE CORRÊA'!D13+'CEI PROFª MARLUCE DE SOUZA PEST'!D13+'CEI IRINEU MARINHO'!D13+'CEI DAGMAR ROLANDO DE OLIVEIRA'!D13+'CEI NOSSA SENHORA DA GLÓRIA'!D13+'E M PROF NILTON COSTA PEREIRA D'!D13+'CENTRO DE EDUCAÇÃO INFANTIL SÉR'!D13+'CEI SANTO ANTÔNIO AGOSTINHO'!D13+'CEI OSWALDO CRUZ'!D13+'E M MAGDALENA TAGLIAFERRO'!D13+'ESCOLA SÃO JOSÉ DO CAETITU'!D13+'CRECHE-ESCOLA CASTELO SÃO MANOE'!D13+'CEI THEREZINHA DE JESUS LIMA'!D13+'ESCOLA MUNICIPAL PROFESSOR PAUL'!D13+'COLÉGIO ANGLICANO DE ARARAS'!D13+'ESCOLA PAROQUIAL SANTA BERNADET'!D13+'CEI VISTA ALEGRE'!D13+'CEI DENISE BESSA DE OLIVA MAYA'!D13+'CEI VIDEIRINHA'!D13+'E M AMÉRICO FERNANDES RIBEIRO'!D13+'ESCOLA MUNICIPAL AUGUSTO PUGNAL'!D13+'ESCOLA MUNICIPAL CELINA SCHECHN'!D13+'E M DARCY CORREA DA VEIGA'!D13+'E M DR PAULA BUARQUE'!D13+'LICEU SÃO JOSÉ DE ITAIPAVA'!D13+'CEI LUIZ MARCHIORI'!D13+'CENTRO DE EDUCAÇÃO INFANTIL AUG'!D13+'CEI PROFª ADRIANA CONSTÂNCIO TR'!D13+'E M AMÉLIA ANTUNES RABELLO'!D13+'CEI PREFEITO SÉRGIO FADEL'!D13+'E M DR THEODORO MACHADO'!D13+'ESCOLA SANTO ANTÔNIO'!D13+'E M TAQUARIL'!D13+'E M MONSENHOR JOÃO DE DEUS RODR'!D13+'CENTRO DE REFERÊNCIA EM EDUC 2'!D13+'CEI PROFª GRAÇA COSTA'!D13+'CEI VILA LEOPOLDINA'!D13+'CEI NILO PEÇANHA'!D13+'E MZDA SANTA TEREZINHA'!D13+'CEI CRIANÇA SANTA EDWIGES'!D13+'E M ARNALDO DYCKERHOFF'!D13+'E M CARLOS CANEDO'!D13+'E M BEATRIZ ZALESKI'!D13+'E M ANTÔNIO JOSÉ DE LIMA'!D13+'E M FELIX WAN ERVEN DE BARROS'!D13+'ESCOLA MUNICIPAL HILDEBRANDO DE'!D13+'E M OSWALDO DA COSTA FRIAS'!D13+'E MZDA AVELINO DE CARVALHO'!D13+'ESCOLA MUNICIPALIZADA MOYSÉS FU'!D13+'CEI ANGELA MARIA DA CONCEIÇÃO S'!D13+'CEI JOSÉ GONÇALVES DA MOTTA'!D13+'E M DR BARROS FRANCO'!D13+'E M MAJOR THEÓFILO DE CARVALHO'!D13+'E M JOÃO KOPKE'!D13+'CEI ASSOCIAÇÃO BENEFICENTE FAZE'!D13+'ESCOLA SAO FRANCISCO DE ASSIS'!D13+'CEI SÃO FRANCISCO ASSIS'!D13+'CEI ALDEIA DA CRIANCA'!D13+'ESCOLA MUNICIPAL ODETTE FONSECA'!D13+'CEI ANA CAROLINA TELLES'!D13+'E M SEBASTIÃO LACERDA'!D13+'E M DOM PEDRO DE ALCÂNTARA'!D13+'ESCOLA NOSSA SENHORA DE FÁTIMA'!D13+'ESCOLA PAROQUIAL SÃO FRANCISCO '!D13+'E M MONSENHOR CIRILLO CALAON'!D13 | D9: ='E M ABELARDO DE LAMARE'!M13+'E M BATAILLARD'!M13+'E M LEONARDO BOFF'!M13+'E M CLEMENTE FERNANDES'!M13+'E M DOM PEDRO DE ALCÂNTARA'!M13+'E M DUQUE DE CAXIAS'!M13+'E M LUIZ CARLOS SOARES'!M13+'ESCOLA MUNICIPAL GENERAL HEITOR'!M13+'E M JOÃO KOPKE'!M13+'ESCOLA MUNICIPAL ODETTE FONSECA'!M13+'E M GOVERNADOR MARCELLO ALENCAR'!M13+'E M PROF JOAQUIM DEISTER'!M13+'E M ROBERT KENNEDY'!M13+'E M ROTARY'!M13+'E M ROSALINA NICOLAY'!M13+'E M DE EDUCAÇÃO ESPECIAL SANTOS'!M13+'E M SOROPTIMISTA'!M13+'LICEU MUN PREFEITO CORDOLINO AM'!M13+'E M ANTÔNIO LEITE GARCIA'!M13+'ESCOLA MUNICIPAL JORGE AMADO'!M13+'ESCOLA MUNICIPAL LÚCIA DE ALMEI'!M13+'E M MAGDALENA TAGLIAFERRO'!M13+'ESCOLA MUNICIPAL MAJOR JÚLIO FR'!M13+'E M MARIETA GONÇALVES'!M13+'ESCOLA MUNICIPAL ODETTE YOUNG M'!M13+'E M FÁBRICA DO SABER'!M13+'ESCOLA MUNICIPAL PROFESSOR PAUL'!M13+'E M ROSEMIRA DE OLIVEIRA CAVALC'!M13+'E M AMÉLIA ANTUNES RABELLO'!M13+'ESCOLA MUNICIPAL AUGUSTO PUGNAL'!M13+'ESCOLA MUNICIPAL CELINA SCHECHN'!M13+'E M DARCY CORREA DA VEIGA'!M13+'E M DR PAULA BUARQUE'!M13+'E M DR THEODORO MACHADO'!M13+'E M ARNALDO DYCKERHOFF'!M13+'E M CARLOS CANEDO'!M13+'E M DR BARROS FRANCO'!M13+'E M MAJOR THEÓFILO DE CARVALHO'!M13+'E M TAQUARIL'!M13+'E M BEATRIZ ZALESKI'!M13+'E M ANTÔNIO JOSÉ DE LIMA'!M13+'E M FELIX WAN ERVEN DE BARROS'!M13+'ESCOLA MUNICIPAL HILDEBRANDO DE'!M13+'E M OSWALDO DA COSTA FRIAS'!M13+'E MZDA CARMEM NUNES MARTINS'!M13+'E MZDA AVELINO DE CARVALHO'!M13+'E M GERALDO VENTURA DIAS'!M13+'E M SALVADOR KLING'!M13+'E M PREFEITO JAMIL SABRÁ'!M13+'LICEU MUNICIPAL CARLOS CHAGAS F'!M13+'ESCOLA MUNICIPAL ANA MOHAMMAD'!M13+'ESCOLA MUNICIPAL ALTO INDEPENDÊ'!M13+'E M ALMIRANTE TAMANDARÉ'!M13+'ESCOLA MUNICIPALIZADA FREI ANIC'!M13+'E M PEDRO AMADO'!M13+'E M PROFª MARIA DA GLÓRIA QUEIR'!M13+'E M SEBASTIÃO LACERDA'!M13+'E M PROFESSOR FLÁVIO MACIEL'!M13+'ESCOLA MUNICIPAL PAULO SALDANHA'!M13+'ESCOLA MUNICIPAL PROFESSOR JOSE'!M13+'E M MONSENHOR CIRILLO CALAON'!M13+'E M AMÉRICO FERNANDES RIBEIRO'!M13+'E M PROFª JANDIRA PEIXOTO BORDI'!M13+'E M MONSENHOR JOÃO DE DEUS RODR'!M13+'E M DOM MANOEL PEDRO DA CUNHA C'!M13+'E M JOHANN NOEL'!M13+'E MZDA SANTA TEREZINHA'!M13+'E M PAPA JOÃO PAULO II'!M13+'E M STEFAN ZWEIG'!M13+'ESCOLA MUNICIPAL SENADOR MARIO '!M13+'E M DR RUBENS DE CASTRO BOMTEMP'!M13+'E M PAULO FREIRE'!M13+'E M PROFª MARIA CAMPOS DA SILVA'!M13+'E M HERCÍLIA HENRIQUES MORET'!M13+'ESCOLA MUNICIPALIZADA MOYSÉS FU'!M13+'CIEP BRIZOLÃO 474 MAESTRO GUERR'!M13+'CENTRO DE ENSINO PROF DARCY RIB'!M13+'CASA DA EDUCAÇÃO VISCONDE DE MA'!M13+'CENTRO DE REFERÊNCIA EM EDUCAÇÃ'!M13+'E M PROF NILTON COSTA PEREIRA D'!M13+'COLÉGIO GUNNAR VINGREN DE PETRÓ'!M13+'CENTRO DE REFERÊNCIA EM EDUC 2'!M13+'ESCOLA SANTA LUIZA DE MARILLAC'!M13+'CENTRO EDUCACIONAL COMUNIDADE S'!M13+'EDUCANDÁRIO TERRA SANTA'!M13+'ESCOLA GERMANO VALENTE'!M13+'ESCOLA DAS COMUNIDADES SANTO AN'!M13+'ESCOLA DOMÉSTICA NOSSA SENHORA '!M13+'ESCOLA PAROQUIAL NOSSA SENHO 3'!M13+'ESCOLA MONSENHOR GENTIL'!M13+'ESCOLA PAROQUIAL BOM JESUS'!M13+'ESCOLA PAROQUIAL CARLOS DEMIÁ'!M13+'ESCOLA PAROQUIAL NOSSA SENHO 2'!M13+'ESCOLA PAROQUIAL NOSSA SENHORA '!M13+'ESCOLA PAROQUIAL SÃO PEDRO DE A'!M13+'ESCOLA SANTA MARIA GORETTI'!M13+'ESCOLA SANTA RITA DE CASSIA'!M13+'ESCOLA SÃO CRISTÓVÃO'!M13+'ESCOLA PAROQUIAL SÃO FRANCISCO '!M13+'ESCOLA SAO FRANCISCO DE ASSIS'!M13+'ESCOLA SÃO JOÃO BATISTA'!M13+'ESCOLA SÃO JUDAS TADEU'!M13+'ESCOLA PAROQUIAL SÃO PIO X'!M13+'COLÉGIO ANGLICANO DE ARARAS'!M13+'COLEGIO VICENTINO PADRE CORRÊA'!M13+'ESCOLA NOSSA SENHORA DE FÁTIMA'!M13+'ESCOLA PAROQUIAL DA ALCOBAÇA'!M13+'ESCOLA PAROQUIAL DO LOTEAMENTO '!M13+'ESCOLA PAROQUIAL SANTA BERNADET'!M13+'ESCOLA SÃO GERALDO'!M13+'ESCOLA SANTO ANTÔNIO'!M13+'LICEU SÃO JOSÉ DE ITAIPAVA'!M13+'ESCOLA SÃO JOSÉ DO CAETITU'!M13+'CEI ASSOCIAÇÃO BENEFICENTE FAZE'!M13+'CEI CASA DA SOLIDARIEDADE DE NO'!M13+'CEI LULU MONTEIRO DE CASTRO'!M13+'CEI SÃO JOÃO BATISTA'!M13+'CEI SÃO FRANCISCO ASSIS'!M13+'CEI A SEMENTEIRA'!M13+'CEI FREI LEÃO'!M13+'CEI ROMANO CANAVESE'!M13+'CEI ANDRÉ VANZAN'!M13+'CEI CRIANÇA SANTA EDWIGES'!M13+'CENTRO DE EDUCAÇÃO INFANTIL IRM'!M13+'CEI PEDRAS BRANCAS'!M13+'CEI INÊS BELARMINO DE SOUZA'!M13+'CEI PROFª ROSANGELA DA SILVA LE'!M13+'CEI VILA SAO JOSE'!M13+'CEI MARIA THEREZA KLING DO VALL'!M13+'CEI DEISE ELOY GOMES'!M13+'CENTRO PAROQUIAL DE EDUCAÇÃO IN'!M13+'CEI VISTA ALEGRE'!M13+'CEI ALDEIA DA CRIANCA'!M13+'CEI DÉA LÚCIA CORDEIRO'!M13+'CENTRO DE EDUCAÇÃO INFANTIL CAR'!M13+'CEI IRMÃ SILVANA'!M13+'CEI MARLI SOARES FERREIRA NETTO'!M13+'CEI PROFª SONIA REGINA SCUDESE '!M13+'CEI DONA ESPERANZA DE BOURBON D'!M13+'CEI PREFEITO SÉRGIO FADEL'!M13+'CEI ANDRÉ REBOUÇAS'!M13+'CENTRO DE EDUCAÇÃO INFANTIL CHI'!M13+'CEI TIA ALICE'!M13+'CEI TERRA SANTA'!M13+'CEI JORGE ROLANDO DA SILVA'!M13+'CEI CARANGOLA'!M13+'CEI CÉLIA LÔBO PAULO'!M13+'CEI LIONS CLUBE DE PETRÓPOLIS'!M13+'CEI PROFª GRAÇA COSTA'!M13+'CEI ANGELA MARIA DA CONCEIÇÃO S'!M13+'CEI LUIZ MARCHIORI'!M13+'CEI PROFª MARLUCE DE SOUZA PEST'!M13+'CEI OLÍVIA MACHADO DA COSTA NOG'!M13+'CEI VILA IPANEMA'!M13+'CEI VILA LEOPOLDINA'!M13+'CENTRO DE EDUCAÇÃO INFANTIL CAS'!M13+'CEI PRIMEIRA INFÂNCIA'!M13+'CEI PROFª DORA KILLER'!M13+'CEI PROFª PATRÍCIA FERREIRA E S'!M13+'CEI DRA ZILDA ARNS NEUMANN'!M13+'CEI DENISE BESSA DE OLIVA MAYA'!M13+'CEI GIUSEPPE-NEVA VOLONTERIO'!M13+'CENTRO DE EDUCAÇÃO INFANTIL LOT'!M13+'CEI IRINEU MARINHO'!M13+'CEI OSWALDO CRUZ'!M13+'CEI ANA CAROLINA TELLES'!M13+'CEI JOSÉ GONÇALVES DA MOTTA'!M13+'CEI SAGRADA FAMÍLIA'!M13+'CEI PROFª HERMÍNIA MATHEUS'!M13+'CENTRO DE EDUCAÇÃO INFANTIL PRO'!M13+'CEI MONSENHOR PAULO ELIAS DAHER'!M13+'CEI DAGMAR ROLANDO DE OLIVEIRA'!M13+'CENTRO DE EDUCAÇÃO INFANTIL 2'!M13+'CEI BOA VISTA'!M13+'CEI NILO PEÇANHA'!M13+'CENTRO DE EDUCAÇÃO INFANTIL AUG'!M13+'CEI THEREZINHA DE JESUS LIMA'!M13+'CEI VIDEIRINHA'!M13+'CEI PROFª ADRIANA CONSTÂNCIO TR'!M13+'CENTRO DE EDUCAÇÃO INFANTIL SÉR'!M13+'CEI JURACI PINTO DO AMARAL DE C'!M13+'CEI NOSSA SENHORA DA GLÓRIA'!M13+'CEI ALTO INDEPENDÊNCIA'!M13+'CEI SÃO JOSÉ DAS OBLATAS DE NAZ'!M13+'CEI SANTO ANTÔNIO AGOSTINHO'!M13+'CEI SÃO CHARBEL'!M13+'ASSOCIAÇÃO DA CRECHE SÃO FRANCI'!M13+'CEI SÃO JOSÉ DO ITAMARATI'!M13+'ASSOCIAÇÃO RECREAR'!M13+'CRECHE-ESCOLA CASTELO SÃO MANOE'!M13+'CENTRO DE EDUCAÇÃO INFANTIL SÃO'!M13 | E9: ='Entrada de Dados'!G2 | F9: =D9*E9
A10: ='Entrada de Dados'!H5 | B10: ='Entrada de Dados'!H197 | C10: ='E M ROTARY'!D14+'E M DE EDUCAÇÃO ESPECIAL SANTOS'!D14+'LICEU MUN PREFEITO CORDOLINO AM'!D14+'E M PREFEITO JAMIL SABRÁ'!D14+'LICEU MUNICIPAL CARLOS CHAGAS F'!D14+'E M PAULO FREIRE'!D14+'E M PROFª MARIA CAMPOS DA SILVA'!D14+'CASA DA EDUCAÇÃO VISCONDE DE MA'!D14+'CENTRO DE REFERÊNCIA EM EDUCAÇÃ'!D14+'ESCOLA SANTA LUIZA DE MARILLAC'!D14+'ESCOLA DOMÉSTICA NOSSA SENHORA '!D14+'ESCOLA MONSENHOR GENTIL'!D14+'ESCOLA PAROQUIAL NOSSA SENHORA '!D14+'ESCOLA PAROQUIAL SÃO PEDRO DE A'!D14+'CEI TERRA SANTA'!D14+'CEI PRIMEIRA INFÂNCIA'!D14+'CEI PROFª PATRÍCIA FERREIRA E S'!D14+'CEI DRA ZILDA ARNS NEUMANN'!D14+'CENTRO DE EDUCAÇÃO INFANTIL PRO'!D14+'CEI MONSENHOR PAULO ELIAS DAHER'!D14+'COLÉGIO GUNNAR VINGREN DE PETRÓ'!D14+'EDUCANDÁRIO TERRA SANTA'!D14+'CEI LIONS CLUBE DE PETRÓPOLIS'!D14+'ESCOLA PAROQUIAL NOSSA SENHO 2'!D14+'CENTRO DE EDUCAÇÃO INFANTIL IRM'!D14+'E M LUIZ CARLOS SOARES'!D14+'ESCOLA GERMANO VALENTE'!D14+'ESCOLA PAROQUIAL NOSSA SENHO 3'!D14+'CEI JORGE ROLANDO DA SILVA'!D14+'E M CLEMENTE FERNANDES'!D14+'E M GERALDO VENTURA DIAS'!D14+'ESCOLA DAS COMUNIDADES SANTO AN'!D14+'CEI PROFª ROSANGELA DA SILVA LE'!D14+'CEI DEISE ELOY GOMES'!D14+'CEI PROFª SONIA REGINA SCUDESE '!D14+'CEI TIA ALICE'!D14+'E M BATAILLARD'!D14+'E M SOROPTIMISTA'!D14+'E M SALVADOR KLING'!D14+'ESCOLA MUNICIPALIZADA FREI ANIC'!D14+'ESCOLA SÃO JUDAS TADEU'!D14+'CEI PEDRAS BRANCAS'!D14+'CEI MARIA THEREZA KLING DO VALL'!D14+'CEI DONA ESPERANZA DE BOURBON D'!D14+'CEI GIUSEPPE-NEVA VOLONTERIO'!D14+'CENTRO DE EDUCAÇÃO INFANTIL SÃO'!D14+'E M LEONARDO BOFF'!D14+'ESCOLA MUNICIPAL GENERAL HEITOR'!D14+'E M JOHANN NOEL'!D14+'ESCOLA SANTA MARIA GORETTI'!D14+'ESCOLA SANTA RITA DE CASSIA'!D14+'ESCOLA SÃO JOÃO BATISTA'!D14+'CEI CASA DA SOLIDARIEDADE DE NO'!D14+'CEI A SEMENTEIRA'!D14+'CEI VILA SAO JOSE'!D14+'E M DR RUBENS DE CASTRO BOMTEMP'!D14+'CEI FREI LEÃO'!D14+'CEI SÃO JOÃO BATISTA'!D14+'CEI JURACI PINTO DO AMARAL DE C'!D14+'E M PEDRO AMADO'!D14+'E M ABELARDO DE LAMARE'!D14+'ESCOLA MUNICIPAL SENADOR MARIO '!D14+'ESCOLA PAROQUIAL SÃO PIO X'!D14+'CEI SÃO CHARBEL'!D14+'E M ROSALINA NICOLAY'!D14+'CEI INÊS BELARMINO DE SOUZA'!D14+'E M PROFª MARIA DA GLÓRIA QUEIR'!D14+'CENTRO EDUCACIONAL COMUNIDADE S'!D14+'CEI ROMANO CANAVESE'!D14+'CEI CÉLIA LÔBO PAULO'!D14+'CEI PROFª DORA KILLER'!D14+'CEI ALTO INDEPENDÊNCIA'!D14+'ESCOLA MUNICIPAL ALTO INDEPENDÊ'!D14+'E M PAPA JOÃO PAULO II'!D14+'CEI ANDRÉ REBOUÇAS'!D14+'CEI PROFª HERMÍNIA MATHEUS'!D14+'ESCOLA MUNICIPAL MAJOR JÚLIO FR'!D14+'E M ALMIRANTE TAMANDARÉ'!D14+'ESCOLA PAROQUIAL CARLOS DEMIÁ'!D14+'CENTRO PAROQUIAL DE EDUCAÇÃO IN'!D14+'CEI IRMÃ SILVANA'!D14+'CEI OLÍVIA MACHADO DA COSTA NOG'!D14+'E M GOVERNADOR MARCELLO ALENCAR'!D14+'E M PROFESSOR FLÁVIO MACIEL'!D14+'E M PROFª JANDIRA PEIXOTO BORDI'!D14+'E M STEFAN ZWEIG'!D14+'ESCOLA PAROQUIAL BOM JESUS'!D14+'CEI MARLI SOARES FERREIRA NETTO'!D14+'CENTRO DE EDUCAÇÃO INFANTIL CHI'!D14+'CEI VILA IPANEMA'!D14+'E M ROBERT KENNEDY'!D14+'ESCOLA MUNICIPAL ANA MOHAMMAD'!D14+'ESCOLA SÃO CRISTÓVÃO'!D14+'CEI DÉA LÚCIA CORDEIRO'!D14+'CEI SAGRADA FAMÍLIA'!D14+'CEI SÃO JOSÉ DAS OBLATAS DE NAZ'!D14+'ESCOLA MUNICIPAL JORGE AMADO'!D14+'E M FÁBRICA DO SABER'!D14+'CIEP BRIZOLÃO 474 MAESTRO GUERR'!D14+'CENTRO DE ENSINO PROF DARCY RIB'!D14+'CEI ANDRÉ VANZAN'!D14+'CENTRO DE EDUCAÇÃO INFANTIL CAR'!D14+'CEI BOA VISTA'!D14+'ASSOCIAÇÃO DA CRECHE SÃO FRANCI'!D14+'ESCOLA MUNICIPAL PAULO SALDANHA'!D14+'ESCOLA MUNICIPAL LÚCIA DE ALMEI'!D14+'E M DOM MANOEL PEDRO DA CUNHA C'!D14+'ESCOLA SÃO GERALDO'!D14+'CEI LULU MONTEIRO DE CASTRO'!D14+'CEI CARANGOLA'!D14+'ASSOCIAÇÃO RECREAR'!D14+'CENTRO DE EDUCAÇÃO INFANTIL CAS'!D14+'E M ROSEMIRA DE OLIVEIRA CAVALC'!D14+'E MZDA CARMEM NUNES MARTINS'!D14+'CEI SÃO JOSÉ DO ITAMARATI'!D14+'E M DUQUE DE CAXIAS'!D14+'CENTRO DE EDUCAÇÃO INFANTIL 2'!D14+'E M ANTÔNIO LEITE GARCIA'!D14+'ESCOLA PAROQUIAL DA ALCOBAÇA'!D14+'CENTRO DE EDUCAÇÃO INFANTIL LOT'!D14+'ESCOLA PAROQUIAL DO LOTEAMENTO '!D14+'E M PROF JOAQUIM DEISTER'!D14+'E M MARIETA GONÇALVES'!D14+'ESCOLA MUNICIPAL ODETTE YOUNG M'!D14+'ESCOLA MUNICIPAL PROFESSOR JOSE'!D14+'E M HERCÍLIA HENRIQUES MORET'!D14+'COLEGIO VICENTINO PADRE CORRÊA'!D14+'CEI PROFª MARLUCE DE SOUZA PEST'!D14+'CEI IRINEU MARINHO'!D14+'CEI DAGMAR ROLANDO DE OLIVEIRA'!D14+'CEI NOSSA SENHORA DA GLÓRIA'!D14+'E M PROF NILTON COSTA PEREIRA D'!D14+'CENTRO DE EDUCAÇÃO INFANTIL SÉR'!D14+'CEI SANTO ANTÔNIO AGOSTINHO'!D14+'CEI OSWALDO CRUZ'!D14+'E M MAGDALENA TAGLIAFERRO'!D14+'ESCOLA SÃO JOSÉ DO CAETITU'!D14+'CRECHE-ESCOLA CASTELO SÃO MANOE'!D14+'CEI THEREZINHA DE JESUS LIMA'!D14+'ESCOLA MUNICIPAL PROFESSOR PAUL'!D14+'COLÉGIO ANGLICANO DE ARARAS'!D14+'ESCOLA PAROQUIAL SANTA BERNADET'!D14+'CEI VISTA ALEGRE'!D14+'CEI DENISE BESSA DE OLIVA MAYA'!D14+'CEI VIDEIRINHA'!D14+'E M AMÉRICO FERNANDES RIBEIRO'!D14+'ESCOLA MUNICIPAL AUGUSTO PUGNAL'!D14+'ESCOLA MUNICIPAL CELINA SCHECHN'!D14+'E M DARCY CORREA DA VEIGA'!D14+'E M DR PAULA BUARQUE'!D14+'LICEU SÃO JOSÉ DE ITAIPAVA'!D14+'CEI LUIZ MARCHIORI'!D14+'CENTRO DE EDUCAÇÃO INFANTIL AUG'!D14+'CEI PROFª ADRIANA CONSTÂNCIO TR'!D14+'E M AMÉLIA ANTUNES RABELLO'!D14+'CEI PREFEITO SÉRGIO FADEL'!D14+'E M DR THEODORO MACHADO'!D14+'ESCOLA SANTO ANTÔNIO'!D14+'E M TAQUARIL'!D14+'E M MONSENHOR JOÃO DE DEUS RODR'!D14+'CENTRO DE REFERÊNCIA EM EDUC 2'!D14+'CEI PROFª GRAÇA COSTA'!D14+'CEI VILA LEOPOLDINA'!D14+'CEI NILO PEÇANHA'!D14+'E MZDA SANTA TEREZINHA'!D14+'CEI CRIANÇA SANTA EDWIGES'!D14+'E M ARNALDO DYCKERHOFF'!D14+'E M CARLOS CANEDO'!D14+'E M BEATRIZ ZALESKI'!D14+'E M ANTÔNIO JOSÉ DE LIMA'!D14+'E M FELIX WAN ERVEN DE BARROS'!D14+'ESCOLA MUNICIPAL HILDEBRANDO DE'!D14+'E M OSWALDO DA COSTA FRIAS'!D14+'E MZDA AVELINO DE CARVALHO'!D14+'ESCOLA MUNICIPALIZADA MOYSÉS FU'!D14+'CEI ANGELA MARIA DA CONCEIÇÃO S'!D14+'CEI JOSÉ GONÇALVES DA MOTTA'!D14+'E M DR BARROS FRANCO'!D14+'E M MAJOR THEÓFILO DE CARVALHO'!D14+'E M JOÃO KOPKE'!D14+'CEI ASSOCIAÇÃO BENEFICENTE FAZE'!D14+'ESCOLA SAO FRANCISCO DE ASSIS'!D14+'CEI SÃO FRANCISCO ASSIS'!D14+'CEI ALDEIA DA CRIANCA'!D14+'ESCOLA MUNICIPAL ODETTE FONSECA'!D14+'CEI ANA CAROLINA TELLES'!D14+'E M SEBASTIÃO LACERDA'!D14+'E M DOM PEDRO DE ALCÂNTARA'!D14+'ESCOLA NOSSA SENHORA DE FÁTIMA'!D14+'ESCOLA PAROQUIAL SÃO FRANCISCO '!D14+'E M MONSENHOR CIRILLO CALAON'!D14 | D10: ='E M ABELARDO DE LAMARE'!M14+'E M BATAILLARD'!M14+'E M LEONARDO BOFF'!M14+'E M CLEMENTE FERNANDES'!M14+'E M DOM PEDRO DE ALCÂNTARA'!M14+'E M DUQUE DE CAXIAS'!M14+'E M LUIZ CARLOS SOARES'!M14+'ESCOLA MUNICIPAL GENERAL HEITOR'!M14+'E M JOÃO KOPKE'!M14+'ESCOLA MUNICIPAL ODETTE FONSECA'!M14+'E M GOVERNADOR MARCELLO ALENCAR'!M14+'E M PROF JOAQUIM DEISTER'!M14+'E M ROBERT KENNEDY'!M14+'E M ROTARY'!M14+'E M ROSALINA NICOLAY'!M14+'E M DE EDUCAÇÃO ESPECIAL SANTOS'!M14+'E M SOROPTIMISTA'!M14+'LICEU MUN PREFEITO CORDOLINO AM'!M14+'E M ANTÔNIO LEITE GARCIA'!M14+'ESCOLA MUNICIPAL JORGE AMADO'!M14+'ESCOLA MUNICIPAL LÚCIA DE ALMEI'!M14+'E M MAGDALENA TAGLIAFERRO'!M14+'ESCOLA MUNICIPAL MAJOR JÚLIO FR'!M14+'E M MARIETA GONÇALVES'!M14+'ESCOLA MUNICIPAL ODETTE YOUNG M'!M14+'E M FÁBRICA DO SABER'!M14+'ESCOLA MUNICIPAL PROFESSOR PAUL'!M14+'E M ROSEMIRA DE OLIVEIRA CAVALC'!M14+'E M AMÉLIA ANTUNES RABELLO'!M14+'ESCOLA MUNICIPAL AUGUSTO PUGNAL'!M14+'ESCOLA MUNICIPAL CELINA SCHECHN'!M14+'E M DARCY CORREA DA VEIGA'!M14+'E M DR PAULA BUARQUE'!M14+'E M DR THEODORO MACHADO'!M14+'E M ARNALDO DYCKERHOFF'!M14+'E M CARLOS CANEDO'!M14+'E M DR BARROS FRANCO'!M14+'E M MAJOR THEÓFILO DE CARVALHO'!M14+'E M TAQUARIL'!M14+'E M BEATRIZ ZALESKI'!M14+'E M ANTÔNIO JOSÉ DE LIMA'!M14+'E M FELIX WAN ERVEN DE BARROS'!M14+'ESCOLA MUNICIPAL HILDEBRANDO DE'!M14+'E M OSWALDO DA COSTA FRIAS'!M14+'E MZDA CARMEM NUNES MARTINS'!M14+'E MZDA AVELINO DE CARVALHO'!M14+'E M GERALDO VENTURA DIAS'!M14+'E M SALVADOR KLING'!M14+'E M PREFEITO JAMIL SABRÁ'!M14+'LICEU MUNICIPAL CARLOS CHAGAS F'!M14+'ESCOLA MUNICIPAL ANA MOHAMMAD'!M14+'ESCOLA MUNICIPAL ALTO INDEPENDÊ'!M14+'E M ALMIRANTE TAMANDARÉ'!M14+'ESCOLA MUNICIPALIZADA FREI ANIC'!M14+'E M PEDRO AMADO'!M14+'E M PROFª MARIA DA GLÓRIA QUEIR'!M14+'E M SEBASTIÃO LACERDA'!M14+'E M PROFESSOR FLÁVIO MACIEL'!M14+'ESCOLA MUNICIPAL PAULO SALDANHA'!M14+'ESCOLA MUNICIPAL PROFESSOR JOSE'!M14+'E M MONSENHOR CIRILLO CALAON'!M14+'E M AMÉRICO FERNANDES RIBEIRO'!M14+'E M PROFª JANDIRA PEIXOTO BORDI'!M14+'E M MONSENHOR JOÃO DE DEUS RODR'!M14+'E M DOM MANOEL PEDRO DA CUNHA C'!M14+'E M JOHANN NOEL'!M14+'E MZDA SANTA TEREZINHA'!M14+'E M PAPA JOÃO PAULO II'!M14+'E M STEFAN ZWEIG'!M14+'ESCOLA MUNICIPAL SENADOR MARIO '!M14+'E M DR RUBENS DE CASTRO BOMTEMP'!M14+'E M PAULO FREIRE'!M14+'E M PROFª MARIA CAMPOS DA SILVA'!M14+'E M HERCÍLIA HENRIQUES MORET'!M14+'ESCOLA MUNICIPALIZADA MOYSÉS FU'!M14+'CIEP BRIZOLÃO 474 MAESTRO GUERR'!M14+'CENTRO DE ENSINO PROF DARCY RIB'!M14+'CASA DA EDUCAÇÃO VISCONDE DE MA'!M14+'CENTRO DE REFERÊNCIA EM EDUCAÇÃ'!M14+'E M PROF NILTON COSTA PEREIRA D'!M14+'COLÉGIO GUNNAR VINGREN DE PETRÓ'!M14+'CENTRO DE REFERÊNCIA EM EDUC 2'!M14+'ESCOLA SANTA LUIZA DE MARILLAC'!M14+'CENTRO EDUCACIONAL COMUNIDADE S'!M14+'EDUCANDÁRIO TERRA SANTA'!M14+'ESCOLA GERMANO VALENTE'!M14+'ESCOLA DAS COMUNIDADES SANTO AN'!M14+'ESCOLA DOMÉSTICA NOSSA SENHORA '!M14+'ESCOLA PAROQUIAL NOSSA SENHO 3'!M14+'ESCOLA MONSENHOR GENTIL'!M14+'ESCOLA PAROQUIAL BOM JESUS'!M14+'ESCOLA PAROQUIAL CARLOS DEMIÁ'!M14+'ESCOLA PAROQUIAL NOSSA SENHO 2'!M14+'ESCOLA PAROQUIAL NOSSA SENHORA '!M14+'ESCOLA PAROQUIAL SÃO PEDRO DE A'!M14+'ESCOLA SANTA MARIA GORETTI'!M14+'ESCOLA SANTA RITA DE CASSIA'!M14+'ESCOLA SÃO CRISTÓVÃO'!M14+'ESCOLA PAROQUIAL SÃO FRANCISCO '!M14+'ESCOLA SAO FRANCISCO DE ASSIS'!M14+'ESCOLA SÃO JOÃO BATISTA'!M14+'ESCOLA SÃO JUDAS TADEU'!M14+'ESCOLA PAROQUIAL SÃO PIO X'!M14+'COLÉGIO ANGLICANO DE ARARAS'!M14+'COLEGIO VICENTINO PADRE CORRÊA'!M14+'ESCOLA NOSSA SENHORA DE FÁTIMA'!M14+'ESCOLA PAROQUIAL DA ALCOBAÇA'!M14+'ESCOLA PAROQUIAL DO LOTEAMENTO '!M14+'ESCOLA PAROQUIAL SANTA BERNADET'!M14+'ESCOLA SÃO GERALDO'!M14+'ESCOLA SANTO ANTÔNIO'!M14+'LICEU SÃO JOSÉ DE ITAIPAVA'!M14+'ESCOLA SÃO JOSÉ DO CAETITU'!M14+'CEI ASSOCIAÇÃO BENEFICENTE FAZE'!M14+'CEI CASA DA SOLIDARIEDADE DE NO'!M14+'CEI LULU MONTEIRO DE CASTRO'!M14+'CEI SÃO JOÃO BATISTA'!M14+'CEI SÃO FRANCISCO ASSIS'!M14+'CEI A SEMENTEIRA'!M14+'CEI FREI LEÃO'!M14+'CEI ROMANO CANAVESE'!M14+'CEI ANDRÉ VANZAN'!M14+'CEI CRIANÇA SANTA EDWIGES'!M14+'CENTRO DE EDUCAÇÃO INFANTIL IRM'!M14+'CEI PEDRAS BRANCAS'!M14+'CEI INÊS BELARMINO DE SOUZA'!M14+'CEI PROFª ROSANGELA DA SILVA LE'!M14+'CEI VILA SAO JOSE'!M14+'CEI MARIA THEREZA KLING DO VALL'!M14+'CEI DEISE ELOY GOMES'!M14+'CENTRO PAROQUIAL DE EDUCAÇÃO IN'!M14+'CEI VISTA ALEGRE'!M14+'CEI ALDEIA DA CRIANCA'!M14+'CEI DÉA LÚCIA CORDEIRO'!M14+'CENTRO DE EDUCAÇÃO INFANTIL CAR'!M14+'CEI IRMÃ SILVANA'!M14+'CEI MARLI SOARES FERREIRA NETTO'!M14+'CEI PROFª SONIA REGINA SCUDESE '!M14+'CEI DONA ESPERANZA DE BOURBON D'!M14+'CEI PREFEITO SÉRGIO FADEL'!M14+'CEI ANDRÉ REBOUÇAS'!M14+'CENTRO DE EDUCAÇÃO INFANTIL CHI'!M14+'CEI TIA ALICE'!M14+'CEI TERRA SANTA'!M14+'CEI JORGE ROLANDO DA SILVA'!M14+'CEI CARANGOLA'!M14+'CEI CÉLIA LÔBO PAULO'!M14+'CEI LIONS CLUBE DE PETRÓPOLIS'!M14+'CEI PROFª GRAÇA COSTA'!M14+'CEI ANGELA MARIA DA CONCEIÇÃO S'!M14+'CEI LUIZ MARCHIORI'!M14+'CEI PROFª MARLUCE DE SOUZA PEST'!M14+'CEI OLÍVIA MACHADO DA COSTA NOG'!M14+'CEI VILA IPANEMA'!M14+'CEI VILA LEOPOLDINA'!M14+'CENTRO DE EDUCAÇÃO INFANTIL CAS'!M14+'CEI PRIMEIRA INFÂNCIA'!M14+'CEI PROFª DORA KILLER'!M14+'CEI PROFª PATRÍCIA FERREIRA E S'!M14+'CEI DRA ZILDA ARNS NEUMANN'!M14+'CEI DENISE BESSA DE OLIVA MAYA'!M14+'CEI GIUSEPPE-NEVA VOLONTERIO'!M14+'CENTRO DE EDUCAÇÃO INFANTIL LOT'!M14+'CEI IRINEU MARINHO'!M14+'CEI OSWALDO CRUZ'!M14+'CEI ANA CAROLINA TELLES'!M14+'CEI JOSÉ GONÇALVES DA MOTTA'!M14+'CEI SAGRADA FAMÍLIA'!M14+'CEI PROFª HERMÍNIA MATHEUS'!M14+'CENTRO DE EDUCAÇÃO INFANTIL PRO'!M14+'CEI MONSENHOR PAULO ELIAS DAHER'!M14+'CEI DAGMAR ROLANDO DE OLIVEIRA'!M14+'CENTRO DE EDUCAÇÃO INFANTIL 2'!M14+'CEI BOA VISTA'!M14+'CEI NILO PEÇANHA'!M14+'CENTRO DE EDUCAÇÃO INFANTIL AUG'!M14+'CEI THEREZINHA DE JESUS LIMA'!M14+'CEI VIDEIRINHA'!M14+'CEI PROFª ADRIANA CONSTÂNCIO TR'!M14+'CENTRO DE EDUCAÇÃO INFANTIL SÉR'!M14+'CEI JURACI PINTO DO AMARAL DE C'!M14+'CEI NOSSA SENHORA DA GLÓRIA'!M14+'CEI ALTO INDEPENDÊNCIA'!M14+'CEI SÃO JOSÉ DAS OBLATAS DE NAZ'!M14+'CEI SANTO ANTÔNIO AGOSTINHO'!M14+'CEI SÃO CHARBEL'!M14+'ASSOCIAÇÃO DA CRECHE SÃO FRANCI'!M14+'CEI SÃO JOSÉ DO ITAMARATI'!M14+'ASSOCIAÇÃO RECREAR'!M14+'CRECHE-ESCOLA CASTELO SÃO MANOE'!M14+'CENTRO DE EDUCAÇÃO INFANTIL SÃO'!M14 | E10: ='Entrada de Dados'!H2 | F10: =D10*E10
A11: ='Entrada de Dados'!I5 | B11: ='Entrada de Dados'!I197 | C11: ='E M ROTARY'!D15+'E M DE EDUCAÇÃO ESPECIAL SANTOS'!D15+'LICEU MUN PREFEITO CORDOLINO AM'!D15+'E M PREFEITO JAMIL SABRÁ'!D15+'LICEU MUNICIPAL CARLOS CHAGAS F'!D15+'E M PAULO FREIRE'!D15+'E M PROFª MARIA CAMPOS DA SILVA'!D15+'CASA DA EDUCAÇÃO VISCONDE DE MA'!D15+'CENTRO DE REFERÊNCIA EM EDUCAÇÃ'!D15+'ESCOLA SANTA LUIZA DE MARILLAC'!D15+'ESCOLA DOMÉSTICA NOSSA SENHORA '!D15+'ESCOLA MONSENHOR GENTIL'!D15+'ESCOLA PAROQUIAL NOSSA SENHORA '!D15+'ESCOLA PAROQUIAL SÃO PEDRO DE A'!D15+'CEI TERRA SANTA'!D15+'CEI PRIMEIRA INFÂNCIA'!D15+'CEI PROFª PATRÍCIA FERREIRA E S'!D15+'CEI DRA ZILDA ARNS NEUMANN'!D15+'CENTRO DE EDUCAÇÃO INFANTIL PRO'!D15+'CEI MONSENHOR PAULO ELIAS DAHER'!D15+'COLÉGIO GUNNAR VINGREN DE PETRÓ'!D15+'EDUCANDÁRIO TERRA SANTA'!D15+'CEI LIONS CLUBE DE PETRÓPOLIS'!D15+'ESCOLA PAROQUIAL NOSSA SENHO 2'!D15+'CENTRO DE EDUCAÇÃO INFANTIL IRM'!D15+'E M LUIZ CARLOS SOARES'!D15+'ESCOLA GERMANO VALENTE'!D15+'ESCOLA PAROQUIAL NOSSA SENHO 3'!D15+'CEI JORGE ROLANDO DA SILVA'!D15+'E M CLEMENTE FERNANDES'!D15+'E M GERALDO VENTURA DIAS'!D15+'ESCOLA DAS COMUNIDADES SANTO AN'!D15+'CEI PROFª ROSANGELA DA SILVA LE'!D15+'CEI DEISE ELOY GOMES'!D15+'CEI PROFª SONIA REGINA SCUDESE '!D15+'CEI TIA ALICE'!D15+'E M BATAILLARD'!D15+'E M SOROPTIMISTA'!D15+'E M SALVADOR KLING'!D15+'ESCOLA MUNICIPALIZADA FREI ANIC'!D15+'ESCOLA SÃO JUDAS TADEU'!D15+'CEI PEDRAS BRANCAS'!D15+'CEI MARIA THEREZA KLING DO VALL'!D15+'CEI DONA ESPERANZA DE BOURBON D'!D15+'CEI GIUSEPPE-NEVA VOLONTERIO'!D15+'CENTRO DE EDUCAÇÃO INFANTIL SÃO'!D15+'E M LEONARDO BOFF'!D15+'ESCOLA MUNICIPAL GENERAL HEITOR'!D15+'E M JOHANN NOEL'!D15+'ESCOLA SANTA MARIA GORETTI'!D15+'ESCOLA SANTA RITA DE CASSIA'!D15+'ESCOLA SÃO JOÃO BATISTA'!D15+'CEI CASA DA SOLIDARIEDADE DE NO'!D15+'CEI A SEMENTEIRA'!D15+'CEI VILA SAO JOSE'!D15+'E M DR RUBENS DE CASTRO BOMTEMP'!D15+'CEI FREI LEÃO'!D15+'CEI SÃO JOÃO BATISTA'!D15+'CEI JURACI PINTO DO AMARAL DE C'!D15+'E M PEDRO AMADO'!D15+'E M ABELARDO DE LAMARE'!D15+'ESCOLA MUNICIPAL SENADOR MARIO '!D15+'ESCOLA PAROQUIAL SÃO PIO X'!D15+'CEI SÃO CHARBEL'!D15+'E M ROSALINA NICOLAY'!D15+'CEI INÊS BELARMINO DE SOUZA'!D15+'E M PROFª MARIA DA GLÓRIA QUEIR'!D15+'CENTRO EDUCACIONAL COMUNIDADE S'!D15+'CEI ROMANO CANAVESE'!D15+'CEI CÉLIA LÔBO PAULO'!D15+'CEI PROFª DORA KILLER'!D15+'CEI ALTO INDEPENDÊNCIA'!D15+'ESCOLA MUNICIPAL ALTO INDEPENDÊ'!D15+'E M PAPA JOÃO PAULO II'!D15+'CEI ANDRÉ REBOUÇAS'!D15+'CEI PROFª HERMÍNIA MATHEUS'!D15+'ESCOLA MUNICIPAL MAJOR JÚLIO FR'!D15+'E M ALMIRANTE TAMANDARÉ'!D15+'ESCOLA PAROQUIAL CARLOS DEMIÁ'!D15+'CENTRO PAROQUIAL DE EDUCAÇÃO IN'!D15+'CEI IRMÃ SILVANA'!D15+'CEI OLÍVIA MACHADO DA COSTA NOG'!D15+'E M GOVERNADOR MARCELLO ALENCAR'!D15+'E M PROFESSOR FLÁVIO MACIEL'!D15+'E M PROFª JANDIRA PEIXOTO BORDI'!D15+'E M STEFAN ZWEIG'!D15+'ESCOLA PAROQUIAL BOM JESUS'!D15+'CEI MARLI SOARES FERREIRA NETTO'!D15+'CENTRO DE EDUCAÇÃO INFANTIL CHI'!D15+'CEI VILA IPANEMA'!D15+'E M ROBERT KENNEDY'!D15+'ESCOLA MUNICIPAL ANA MOHAMMAD'!D15+'ESCOLA SÃO CRISTÓVÃO'!D15+'CEI DÉA LÚCIA CORDEIRO'!D15+'CEI SAGRADA FAMÍLIA'!D15+'CEI SÃO JOSÉ DAS OBLATAS DE NAZ'!D15+'ESCOLA MUNICIPAL JORGE AMADO'!D15+'E M FÁBRICA DO SABER'!D15+'CIEP BRIZOLÃO 474 MAESTRO GUERR'!D15+'CENTRO DE ENSINO PROF DARCY RIB'!D15+'CEI ANDRÉ VANZAN'!D15+'CENTRO DE EDUCAÇÃO INFANTIL CAR'!D15+'CEI BOA VISTA'!D15+'ASSOCIAÇÃO DA CRECHE SÃO FRANCI'!D15+'ESCOLA MUNICIPAL PAULO SALDANHA'!D15+'ESCOLA MUNICIPAL LÚCIA DE ALMEI'!D15+'E M DOM MANOEL PEDRO DA CUNHA C'!D15+'ESCOLA SÃO GERALDO'!D15+'CEI LULU MONTEIRO DE CASTRO'!D15+'CEI CARANGOLA'!D15+'ASSOCIAÇÃO RECREAR'!D15+'CENTRO DE EDUCAÇÃO INFANTIL CAS'!D15+'E M ROSEMIRA DE OLIVEIRA CAVALC'!D15+'E MZDA CARMEM NUNES MARTINS'!D15+'CEI SÃO JOSÉ DO ITAMARATI'!D15+'E M DUQUE DE CAXIAS'!D15+'CENTRO DE EDUCAÇÃO INFANTIL 2'!D15+'E M ANTÔNIO LEITE GARCIA'!D15+'ESCOLA PAROQUIAL DA ALCOBAÇA'!D15+'CENTRO DE EDUCAÇÃO INFANTIL LOT'!D15+'ESCOLA PAROQUIAL DO LOTEAMENTO '!D15+'E M PROF JOAQUIM DEISTER'!D15+'E M MARIETA GONÇALVES'!D15+'ESCOLA MUNICIPAL ODETTE YOUNG M'!D15+'ESCOLA MUNICIPAL PROFESSOR JOSE'!D15+'E M HERCÍLIA HENRIQUES MORET'!D15+'COLEGIO VICENTINO PADRE CORRÊA'!D15+'CEI PROFª MARLUCE DE SOUZA PEST'!D15+'CEI IRINEU MARINHO'!D15+'CEI DAGMAR ROLANDO DE OLIVEIRA'!D15+'CEI NOSSA SENHORA DA GLÓRIA'!D15+'E M PROF NILTON COSTA PEREIRA D'!D15+'CENTRO DE EDUCAÇÃO INFANTIL SÉR'!D15+'CEI SANTO ANTÔNIO AGOSTINHO'!D15+'CEI OSWALDO CRUZ'!D15+'E M MAGDALENA TAGLIAFERRO'!D15+'ESCOLA SÃO JOSÉ DO CAETITU'!D15+'CRECHE-ESCOLA CASTELO SÃO MANOE'!D15+'CEI THEREZINHA DE JESUS LIMA'!D15+'ESCOLA MUNICIPAL PROFESSOR PAUL'!D15+'COLÉGIO ANGLICANO DE ARARAS'!D15+'ESCOLA PAROQUIAL SANTA BERNADET'!D15+'CEI VISTA ALEGRE'!D15+'CEI DENISE BESSA DE OLIVA MAYA'!D15+'CEI VIDEIRINHA'!D15+'E M AMÉRICO FERNANDES RIBEIRO'!D15+'ESCOLA MUNICIPAL AUGUSTO PUGNAL'!D15+'ESCOLA MUNICIPAL CELINA SCHECHN'!D15+'E M DARCY CORREA DA VEIGA'!D15+'E M DR PAULA BUARQUE'!D15+'LICEU SÃO JOSÉ DE ITAIPAVA'!D15+'CEI LUIZ MARCHIORI'!D15+'CENTRO DE EDUCAÇÃO INFANTIL AUG'!D15+'CEI PROFª ADRIANA CONSTÂNCIO TR'!D15+'E M AMÉLIA ANTUNES RABELLO'!D15+'CEI PREFEITO SÉRGIO FADEL'!D15+'E M DR THEODORO MACHADO'!D15+'ESCOLA SANTO ANTÔNIO'!D15+'E M TAQUARIL'!D15+'E M MONSENHOR JOÃO DE DEUS RODR'!D15+'CENTRO DE REFERÊNCIA EM EDUC 2'!D15+'CEI PROFª GRAÇA COSTA'!D15+'CEI VILA LEOPOLDINA'!D15+'CEI NILO PEÇANHA'!D15+'E MZDA SANTA TEREZINHA'!D15+'CEI CRIANÇA SANTA EDWIGES'!D15+'E M ARNALDO DYCKERHOFF'!D15+'E M CARLOS CANEDO'!D15+'E M BEATRIZ ZALESKI'!D15+'E M ANTÔNIO JOSÉ DE LIMA'!D15+'E M FELIX WAN ERVEN DE BARROS'!D15+'ESCOLA MUNICIPAL HILDEBRANDO DE'!D15+'E M OSWALDO DA COSTA FRIAS'!D15+'E MZDA AVELINO DE CARVALHO'!D15+'ESCOLA MUNICIPALIZADA MOYSÉS FU'!D15+'CEI ANGELA MARIA DA CONCEIÇÃO S'!D15+'CEI JOSÉ GONÇALVES DA MOTTA'!D15+'E M DR BARROS FRANCO'!D15+'E M MAJOR THEÓFILO DE CARVALHO'!D15+'E M JOÃO KOPKE'!D15+'CEI ASSOCIAÇÃO BENEFICENTE FAZE'!D15+'ESCOLA SAO FRANCISCO DE ASSIS'!D15+'CEI SÃO FRANCISCO ASSIS'!D15+'CEI ALDEIA DA CRIANCA'!D15+'ESCOLA MUNICIPAL ODETTE FONSECA'!D15+'CEI ANA CAROLINA TELLES'!D15+'E M SEBASTIÃO LACERDA'!D15+'E M DOM PEDRO DE ALCÂNTARA'!D15+'ESCOLA NOSSA SENHORA DE FÁTIMA'!D15+'ESCOLA PAROQUIAL SÃO FRANCISCO '!D15+'E M MONSENHOR CIRILLO CALAON'!D15 | D11: ='E M ABELARDO DE LAMARE'!M15+'E M BATAILLARD'!M15+'E M LEONARDO BOFF'!M15+'E M CLEMENTE FERNANDES'!M15+'E M DOM PEDRO DE ALCÂNTARA'!M15+'E M DUQUE DE CAXIAS'!M15+'E M LUIZ CARLOS SOARES'!M15+'ESCOLA MUNICIPAL GENERAL HEITOR'!M15+'E M JOÃO KOPKE'!M15+'ESCOLA MUNICIPAL ODETTE FONSECA'!M15+'E M GOVERNADOR MARCELLO ALENCAR'!M15+'E M PROF JOAQUIM DEISTER'!M15+'E M ROBERT KENNEDY'!M15+'E M ROTARY'!M15+'E M ROSALINA NICOLAY'!M15+'E M DE EDUCAÇÃO ESPECIAL SANTOS'!M15+'E M SOROPTIMISTA'!M15+'LICEU MUN PREFEITO CORDOLINO AM'!M15+'E M ANTÔNIO LEITE GARCIA'!M15+'ESCOLA MUNICIPAL JORGE AMADO'!M15+'ESCOLA MUNICIPAL LÚCIA DE ALMEI'!M15+'E M MAGDALENA TAGLIAFERRO'!M15+'ESCOLA MUNICIPAL MAJOR JÚLIO FR'!M15+'E M MARIETA GONÇALVES'!M15+'ESCOLA MUNICIPAL ODETTE YOUNG M'!M15+'E M FÁBRICA DO SABER'!M15+'ESCOLA MUNICIPAL PROFESSOR PAUL'!M15+'E M ROSEMIRA DE OLIVEIRA CAVALC'!M15+'E M AMÉLIA ANTUNES RABELLO'!M15+'ESCOLA MUNICIPAL AUGUSTO PUGNAL'!M15+'ESCOLA MUNICIPAL CELINA SCHECHN'!M15+'E M DARCY CORREA DA VEIGA'!M15+'E M DR PAULA BUARQUE'!M15+'E M DR THEODORO MACHADO'!M15+'E M ARNALDO DYCKERHOFF'!M15+'E M CARLOS CANEDO'!M15+'E M DR BARROS FRANCO'!M15+'E M MAJOR THEÓFILO DE CARVALHO'!M15+'E M TAQUARIL'!M15+'E M BEATRIZ ZALESKI'!M15+'E M ANTÔNIO JOSÉ DE LIMA'!M15+'E M FELIX WAN ERVEN DE BARROS'!M15+'ESCOLA MUNICIPAL HILDEBRANDO DE'!M15+'E M OSWALDO DA COSTA FRIAS'!M15+'E MZDA CARMEM NUNES MARTINS'!M15+'E MZDA AVELINO DE CARVALHO'!M15+'E M GERALDO VENTURA DIAS'!M15+'E M SALVADOR KLING'!M15+'E M PREFEITO JAMIL SABRÁ'!M15+'LICEU MUNICIPAL CARLOS CHAGAS F'!M15+'ESCOLA MUNICIPAL ANA MOHAMMAD'!M15+'ESCOLA MUNICIPAL ALTO INDEPENDÊ'!M15+'E M ALMIRANTE TAMANDARÉ'!M15+'ESCOLA MUNICIPALIZADA FREI ANIC'!M15+'E M PEDRO AMADO'!M15+'E M PROFª MARIA DA GLÓRIA QUEIR'!M15+'E M SEBASTIÃO LACERDA'!M15+'E M PROFESSOR FLÁVIO MACIEL'!M15+'ESCOLA MUNICIPAL PAULO SALDANHA'!M15+'ESCOLA MUNICIPAL PROFESSOR JOSE'!M15+'E M MONSENHOR CIRILLO CALAON'!M15+'E M AMÉRICO FERNANDES RIBEIRO'!M15+'E M PROFª JANDIRA PEIXOTO BORDI'!M15+'E M MONSENHOR JOÃO DE DEUS RODR'!M15+'E M DOM MANOEL PEDRO DA CUNHA C'!M15+'E M JOHANN NOEL'!M15+'E MZDA SANTA TEREZINHA'!M15+'E M PAPA JOÃO PAULO II'!M15+'E M STEFAN ZWEIG'!M15+'ESCOLA MUNICIPAL SENADOR MARIO '!M15+'E M DR RUBENS DE CASTRO BOMTEMP'!M15+'E M PAULO FREIRE'!M15+'E M PROFª MARIA CAMPOS DA SILVA'!M15+'E M HERCÍLIA HENRIQUES MORET'!M15+'ESCOLA MUNICIPALIZADA MOYSÉS FU'!M15+'CIEP BRIZOLÃO 474 MAESTRO GUERR'!M15+'CENTRO DE ENSINO PROF DARCY RIB'!M15+'CASA DA EDUCAÇÃO VISCONDE DE MA'!M15+'CENTRO DE REFERÊNCIA EM EDUCAÇÃ'!M15+'E M PROF NILTON COSTA PEREIRA D'!M15+'COLÉGIO GUNNAR VINGREN DE PETRÓ'!M15+'CENTRO DE REFERÊNCIA EM EDUC 2'!M15+'ESCOLA SANTA LUIZA DE MARILLAC'!M15+'CENTRO EDUCACIONAL COMUNIDADE S'!M15+'EDUCANDÁRIO TERRA SANTA'!M15+'ESCOLA GERMANO VALENTE'!M15+'ESCOLA DAS COMUNIDADES SANTO AN'!M15+'ESCOLA DOMÉSTICA NOSSA SENHORA '!M15+'ESCOLA PAROQUIAL NOSSA SENHO 3'!M15+'ESCOLA MONSENHOR GENTIL'!M15+'ESCOLA PAROQUIAL BOM JESUS'!M15+'ESCOLA PAROQUIAL CARLOS DEMIÁ'!M15+'ESCOLA PAROQUIAL NOSSA SENHO 2'!M15+'ESCOLA PAROQUIAL NOSSA SENHORA '!M15+'ESCOLA PAROQUIAL SÃO PEDRO DE A'!M15+'ESCOLA SANTA MARIA GORETTI'!M15+'ESCOLA SANTA RITA DE CASSIA'!M15+'ESCOLA SÃO CRISTÓVÃO'!M15+'ESCOLA PAROQUIAL SÃO FRANCISCO '!M15+'ESCOLA SAO FRANCISCO DE ASSIS'!M15+'ESCOLA SÃO JOÃO BATISTA'!M15+'ESCOLA SÃO JUDAS TADEU'!M15+'ESCOLA PAROQUIAL SÃO PIO X'!M15+'COLÉGIO ANGLICANO DE ARARAS'!M15+'COLEGIO VICENTINO PADRE CORRÊA'!M15+'ESCOLA NOSSA SENHORA DE FÁTIMA'!M15+'ESCOLA PAROQUIAL DA ALCOBAÇA'!M15+'ESCOLA PAROQUIAL DO LOTEAMENTO '!M15+'ESCOLA PAROQUIAL SANTA BERNADET'!M15+'ESCOLA SÃO GERALDO'!M15+'ESCOLA SANTO ANTÔNIO'!M15+'LICEU SÃO JOSÉ DE ITAIPAVA'!M15+'ESCOLA SÃO JOSÉ DO CAETITU'!M15+'CEI ASSOCIAÇÃO BENEFICENTE FAZE'!M15+'CEI CASA DA SOLIDARIEDADE DE NO'!M15+'CEI LULU MONTEIRO DE CASTRO'!M15+'CEI SÃO JOÃO BATISTA'!M15+'CEI SÃO FRANCISCO ASSIS'!M15+'CEI A SEMENTEIRA'!M15+'CEI FREI LEÃO'!M15+'CEI ROMANO CANAVESE'!M15+'CEI ANDRÉ VANZAN'!M15+'CEI CRIANÇA SANTA EDWIGES'!M15+'CENTRO DE EDUCAÇÃO INFANTIL IRM'!M15+'CEI PEDRAS BRANCAS'!M15+'CEI INÊS BELARMINO DE SOUZA'!M15+'CEI PROFª ROSANGELA DA SILVA LE'!M15+'CEI VILA SAO JOSE'!M15+'CEI MARIA THEREZA KLING DO VALL'!M15+'CEI DEISE ELOY GOMES'!M15+'CENTRO PAROQUIAL DE EDUCAÇÃO IN'!M15+'CEI VISTA ALEGRE'!M15+'CEI ALDEIA DA CRIANCA'!M15+'CEI DÉA LÚCIA CORDEIRO'!M15+'CENTRO DE EDUCAÇÃO INFANTIL CAR'!M15+'CEI IRMÃ SILVANA'!M15+'CEI MARLI SOARES FERREIRA NETTO'!M15+'CEI PROFª SONIA REGINA SCUDESE '!M15+'CEI DONA ESPERANZA DE BOURBON D'!M15+'CEI PREFEITO SÉRGIO FADEL'!M15+'CEI ANDRÉ REBOUÇAS'!M15+'CENTRO DE EDUCAÇÃO INFANTIL CHI'!M15+'CEI TIA ALICE'!M15+'CEI TERRA SANTA'!M15+'CEI JORGE ROLANDO DA SILVA'!M15+'CEI CARANGOLA'!M15+'CEI CÉLIA LÔBO PAULO'!M15+'CEI LIONS CLUBE DE PETRÓPOLIS'!M15+'CEI PROFª GRAÇA COSTA'!M15+'CEI ANGELA MARIA DA CONCEIÇÃO S'!M15+'CEI LUIZ MARCHIORI'!M15+'CEI PROFª MARLUCE DE SOUZA PEST'!M15+'CEI OLÍVIA MACHADO DA COSTA NOG'!M15+'CEI VILA IPANEMA'!M15+'CEI VILA LEOPOLDINA'!M15+'CENTRO DE EDUCAÇÃO INFANTIL CAS'!M15+'CEI PRIMEIRA INFÂNCIA'!M15+'CEI PROFª DORA KILLER'!M15+'CEI PROFª PATRÍCIA FERREIRA E S'!M15+'CEI DRA ZILDA ARNS NEUMANN'!M15+'CEI DENISE BESSA DE OLIVA MAYA'!M15+'CEI GIUSEPPE-NEVA VOLONTERIO'!M15+'CENTRO DE EDUCAÇÃO INFANTIL LOT'!M15+'CEI IRINEU MARINHO'!M15+'CEI OSWALDO CRUZ'!M15+'CEI ANA CAROLINA TELLES'!M15+'CEI JOSÉ GONÇALVES DA MOTTA'!M15+'CEI SAGRADA FAMÍLIA'!M15+'CEI PROFª HERMÍNIA MATHEUS'!M15+'CENTRO DE EDUCAÇÃO INFANTIL PRO'!M15+'CEI MONSENHOR PAULO ELIAS DAHER'!M15+'CEI DAGMAR ROLANDO DE OLIVEIRA'!M15+'CENTRO DE EDUCAÇÃO INFANTIL 2'!M15+'CEI BOA VISTA'!M15+'CEI NILO PEÇANHA'!M15+'CENTRO DE EDUCAÇÃO INFANTIL AUG'!M15+'CEI THEREZINHA DE JESUS LIMA'!M15+'CEI VIDEIRINHA'!M15+'CEI PROFª ADRIANA CONSTÂNCIO TR'!M15+'CENTRO DE EDUCAÇÃO INFANTIL SÉR'!M15+'CEI JURACI PINTO DO AMARAL DE C'!M15+'CEI NOSSA SENHORA DA GLÓRIA'!M15+'CEI ALTO INDEPENDÊNCIA'!M15+'CEI SÃO JOSÉ DAS OBLATAS DE NAZ'!M15+'CEI SANTO ANTÔNIO AGOSTINHO'!M15+'CEI SÃO CHARBEL'!M15+'ASSOCIAÇÃO DA CRECHE SÃO FRANCI'!M15+'CEI SÃO JOSÉ DO ITAMARATI'!M15+'ASSOCIAÇÃO RECREAR'!M15+'CRECHE-ESCOLA CASTELO SÃO MANOE'!M15+'CENTRO DE EDUCAÇÃO INFANTIL SÃO'!M15 | E11: ='Entrada de Dados'!I2 | F11: =D11*E11
A12: ='Entrada de Dados'!J5 | B12: ='Entrada de Dados'!J197 | C12: ='E M ROTARY'!D16+'E M DE EDUCAÇÃO ESPECIAL SANTOS'!D16+'LICEU MUN PREFEITO CORDOLINO AM'!D16+'E M PREFEITO JAMIL SABRÁ'!D16+'LICEU MUNICIPAL CARLOS CHAGAS F'!D16+'E M PAULO FREIRE'!D16+'E M PROFª MARIA CAMPOS DA SILVA'!D16+'CASA DA EDUCAÇÃO VISCONDE DE MA'!D16+'CENTRO DE REFERÊNCIA EM EDUCAÇÃ'!D16+'ESCOLA SANTA LUIZA DE MARILLAC'!D16+'ESCOLA DOMÉSTICA NOSSA SENHORA '!D16+'ESCOLA MONSENHOR GENTIL'!D16+'ESCOLA PAROQUIAL NOSSA SENHORA '!D16+'ESCOLA PAROQUIAL SÃO PEDRO DE A'!D16+'CEI TERRA SANTA'!D16+'CEI PRIMEIRA INFÂNCIA'!D16+'CEI PROFª PATRÍCIA FERREIRA E S'!D16+'CEI DRA ZILDA ARNS NEUMANN'!D16+'CENTRO DE EDUCAÇÃO INFANTIL PRO'!D16+'CEI MONSENHOR PAULO ELIAS DAHER'!D16+'COLÉGIO GUNNAR VINGREN DE PETRÓ'!D16+'EDUCANDÁRIO TERRA SANTA'!D16+'CEI LIONS CLUBE DE PETRÓPOLIS'!D16+'ESCOLA PAROQUIAL NOSSA SENHO 2'!D16+'CENTRO DE EDUCAÇÃO INFANTIL IRM'!D16+'E M LUIZ CARLOS SOARES'!D16+'ESCOLA GERMANO VALENTE'!D16+'ESCOLA PAROQUIAL NOSSA SENHO 3'!D16+'CEI JORGE ROLANDO DA SILVA'!D16+'E M CLEMENTE FERNANDES'!D16+'E M GERALDO VENTURA DIAS'!D16+'ESCOLA DAS COMUNIDADES SANTO AN'!D16+'CEI PROFª ROSANGELA DA SILVA LE'!D16+'CEI DEISE ELOY GOMES'!D16+'CEI PROFª SONIA REGINA SCUDESE '!D16+'CEI TIA ALICE'!D16+'E M BATAILLARD'!D16+'E M SOROPTIMISTA'!D16+'E M SALVADOR KLING'!D16+'ESCOLA MUNICIPALIZADA FREI ANIC'!D16+'ESCOLA SÃO JUDAS TADEU'!D16+'CEI PEDRAS BRANCAS'!D16+'CEI MARIA THEREZA KLING DO VALL'!D16+'CEI DONA ESPERANZA DE BOURBON D'!D16+'CEI GIUSEPPE-NEVA VOLONTERIO'!D16+'CENTRO DE EDUCAÇÃO INFANTIL SÃO'!D16+'E M LEONARDO BOFF'!D16+'ESCOLA MUNICIPAL GENERAL HEITOR'!D16+'E M JOHANN NOEL'!D16+'ESCOLA SANTA MARIA GORETTI'!D16+'ESCOLA SANTA RITA DE CASSIA'!D16+'ESCOLA SÃO JOÃO BATISTA'!D16+'CEI CASA DA SOLIDARIEDADE DE NO'!D16+'CEI A SEMENTEIRA'!D16+'CEI VILA SAO JOSE'!D16+'E M DR RUBENS DE CASTRO BOMTEMP'!D16+'CEI FREI LEÃO'!D16+'CEI SÃO JOÃO BATISTA'!D16+'CEI JURACI PINTO DO AMARAL DE C'!D16+'E M PEDRO AMADO'!D16+'E M ABELARDO DE LAMARE'!D16+'ESCOLA MUNICIPAL SENADOR MARIO '!D16+'ESCOLA PAROQUIAL SÃO PIO X'!D16+'CEI SÃO CHARBEL'!D16+'E M ROSALINA NICOLAY'!D16+'CEI INÊS BELARMINO DE SOUZA'!D16+'E M PROFª MARIA DA GLÓRIA QUEIR'!D16+'CENTRO EDUCACIONAL COMUNIDADE S'!D16+'CEI ROMANO CANAVESE'!D16+'CEI CÉLIA LÔBO PAULO'!D16+'CEI PROFª DORA KILLER'!D16+'CEI ALTO INDEPENDÊNCIA'!D16+'ESCOLA MUNICIPAL ALTO INDEPENDÊ'!D16+'E M PAPA JOÃO PAULO II'!D16+'CEI ANDRÉ REBOUÇAS'!D16+'CEI PROFª HERMÍNIA MATHEUS'!D16+'ESCOLA MUNICIPAL MAJOR JÚLIO FR'!D16+'E M ALMIRANTE TAMANDARÉ'!D16+'ESCOLA PAROQUIAL CARLOS DEMIÁ'!D16+'CENTRO PAROQUIAL DE EDUCAÇÃO IN'!D16+'CEI IRMÃ SILVANA'!D16+'CEI OLÍVIA MACHADO DA COSTA NOG'!D16+'E M GOVERNADOR MARCELLO ALENCAR'!D16+'E M PROFESSOR FLÁVIO MACIEL'!D16+'E M PROFª JANDIRA PEIXOTO BORDI'!D16+'E M STEFAN ZWEIG'!D16+'ESCOLA PAROQUIAL BOM JESUS'!D16+'CEI MARLI SOARES FERREIRA NETTO'!D16+'CENTRO DE EDUCAÇÃO INFANTIL CHI'!D16+'CEI VILA IPANEMA'!D16+'E M ROBERT KENNEDY'!D16+'ESCOLA MUNICIPAL ANA MOHAMMAD'!D16+'ESCOLA SÃO CRISTÓVÃO'!D16+'CEI DÉA LÚCIA CORDEIRO'!D16+'CEI SAGRADA FAMÍLIA'!D16+'CEI SÃO JOSÉ DAS OBLATAS DE NAZ'!D16+'ESCOLA MUNICIPAL JORGE AMADO'!D16+'E M FÁBRICA DO SABER'!D16+'CIEP BRIZOLÃO 474 MAESTRO GUERR'!D16+'CENTRO DE ENSINO PROF DARCY RIB'!D16+'CEI ANDRÉ VANZAN'!D16+'CENTRO DE EDUCAÇÃO INFANTIL CAR'!D16+'CEI BOA VISTA'!D16+'ASSOCIAÇÃO DA CRECHE SÃO FRANCI'!D16+'ESCOLA MUNICIPAL PAULO SALDANHA'!D16+'ESCOLA MUNICIPAL LÚCIA DE ALMEI'!D16+'E M DOM MANOEL PEDRO DA CUNHA C'!D16+'ESCOLA SÃO GERALDO'!D16+'CEI LULU MONTEIRO DE CASTRO'!D16+'CEI CARANGOLA'!D16+'ASSOCIAÇÃO RECREAR'!D16+'CENTRO DE EDUCAÇÃO INFANTIL CAS'!D16+'E M ROSEMIRA DE OLIVEIRA CAVALC'!D16+'E MZDA CARMEM NUNES MARTINS'!D16+'CEI SÃO JOSÉ DO ITAMARATI'!D16+'E M DUQUE DE CAXIAS'!D16+'CENTRO DE EDUCAÇÃO INFANTIL 2'!D16+'E M ANTÔNIO LEITE GARCIA'!D16+'ESCOLA PAROQUIAL DA ALCOBAÇA'!D16+'CENTRO DE EDUCAÇÃO INFANTIL LOT'!D16+'ESCOLA PAROQUIAL DO LOTEAMENTO '!D16+'E M PROF JOAQUIM DEISTER'!D16+'E M MARIETA GONÇALVES'!D16+'ESCOLA MUNICIPAL ODETTE YOUNG M'!D16+'ESCOLA MUNICIPAL PROFESSOR JOSE'!D16+'E M HERCÍLIA HENRIQUES MORET'!D16+'COLEGIO VICENTINO PADRE CORRÊA'!D16+'CEI PROFª MARLUCE DE SOUZA PEST'!D16+'CEI IRINEU MARINHO'!D16+'CEI DAGMAR ROLANDO DE OLIVEIRA'!D16+'CEI NOSSA SENHORA DA GLÓRIA'!D16+'E M PROF NILTON COSTA PEREIRA D'!D16+'CENTRO DE EDUCAÇÃO INFANTIL SÉR'!D16+'CEI SANTO ANTÔNIO AGOSTINHO'!D16+'CEI OSWALDO CRUZ'!D16+'E M MAGDALENA TAGLIAFERRO'!D16+'ESCOLA SÃO JOSÉ DO CAETITU'!D16+'CRECHE-ESCOLA CASTELO SÃO MANOE'!D16+'CEI THEREZINHA DE JESUS LIMA'!D16+'ESCOLA MUNICIPAL PROFESSOR PAUL'!D16+'COLÉGIO ANGLICANO DE ARARAS'!D16+'ESCOLA PAROQUIAL SANTA BERNADET'!D16+'CEI VISTA ALEGRE'!D16+'CEI DENISE BESSA DE OLIVA MAYA'!D16+'CEI VIDEIRINHA'!D16+'E M AMÉRICO FERNANDES RIBEIRO'!D16+'ESCOLA MUNICIPAL AUGUSTO PUGNAL'!D16+'ESCOLA MUNICIPAL CELINA SCHECHN'!D16+'E M DARCY CORREA DA VEIGA'!D16+'E M DR PAULA BUARQUE'!D16+'LICEU SÃO JOSÉ DE ITAIPAVA'!D16+'CEI LUIZ MARCHIORI'!D16+'CENTRO DE EDUCAÇÃO INFANTIL AUG'!D16+'CEI PROFª ADRIANA CONSTÂNCIO TR'!D16+'E M AMÉLIA ANTUNES RABELLO'!D16+'CEI PREFEITO SÉRGIO FADEL'!D16+'E M DR THEODORO MACHADO'!D16+'ESCOLA SANTO ANTÔNIO'!D16+'E M TAQUARIL'!D16+'E M MONSENHOR JOÃO DE DEUS RODR'!D16+'CENTRO DE REFERÊNCIA EM EDUC 2'!D16+'CEI PROFª GRAÇA COSTA'!D16+'CEI VILA LEOPOLDINA'!D16+'CEI NILO PEÇANHA'!D16+'E MZDA SANTA TEREZINHA'!D16+'CEI CRIANÇA SANTA EDWIGES'!D16+'E M ARNALDO DYCKERHOFF'!D16+'E M CARLOS CANEDO'!D16+'E M BEATRIZ ZALESKI'!D16+'E M ANTÔNIO JOSÉ DE LIMA'!D16+'E M FELIX WAN ERVEN DE BARROS'!D16+'ESCOLA MUNICIPAL HILDEBRANDO DE'!D16+'E M OSWALDO DA COSTA FRIAS'!D16+'E MZDA AVELINO DE CARVALHO'!D16+'ESCOLA MUNICIPALIZADA MOYSÉS FU'!D16+'CEI ANGELA MARIA DA CONCEIÇÃO S'!D16+'CEI JOSÉ GONÇALVES DA MOTTA'!D16+'E M DR BARROS FRANCO'!D16+'E M MAJOR THEÓFILO DE CARVALHO'!D16+'E M JOÃO KOPKE'!D16+'CEI ASSOCIAÇÃO BENEFICENTE FAZE'!D16+'ESCOLA SAO FRANCISCO DE ASSIS'!D16+'CEI SÃO FRANCISCO ASSIS'!D16+'CEI ALDEIA DA CRIANCA'!D16+'ESCOLA MUNICIPAL ODETTE FONSECA'!D16+'CEI ANA CAROLINA TELLES'!D16+'E M SEBASTIÃO LACERDA'!D16+'E M DOM PEDRO DE ALCÂNTARA'!D16+'ESCOLA NOSSA SENHORA DE FÁTIMA'!D16+'ESCOLA PAROQUIAL SÃO FRANCISCO '!D16+'E M MONSENHOR CIRILLO CALAON'!D16 | D12: ='E M ABELARDO DE LAMARE'!M16+'E M BATAILLARD'!M16+'E M LEONARDO BOFF'!M16+'E M CLEMENTE FERNANDES'!M16+'E M DOM PEDRO DE ALCÂNTARA'!M16+'E M DUQUE DE CAXIAS'!M16+'E M LUIZ CARLOS SOARES'!M16+'ESCOLA MUNICIPAL GENERAL HEITOR'!M16+'E M JOÃO KOPKE'!M16+'ESCOLA MUNICIPAL ODETTE FONSECA'!M16+'E M GOVERNADOR MARCELLO ALENCAR'!M16+'E M PROF JOAQUIM DEISTER'!M16+'E M ROBERT KENNEDY'!M16+'E M ROTARY'!M16+'E M ROSALINA NICOLAY'!M16+'E M DE EDUCAÇÃO ESPECIAL SANTOS'!M16+'E M SOROPTIMISTA'!M16+'LICEU MUN PREFEITO CORDOLINO AM'!M16+'E M ANTÔNIO LEITE GARCIA'!M16+'ESCOLA MUNICIPAL JORGE AMADO'!M16+'ESCOLA MUNICIPAL LÚCIA DE ALMEI'!M16+'E M MAGDALENA TAGLIAFERRO'!M16+'ESCOLA MUNICIPAL MAJOR JÚLIO FR'!M16+'E M MARIETA GONÇALVES'!M16+'ESCOLA MUNICIPAL ODETTE YOUNG M'!M16+'E M FÁBRICA DO SABER'!M16+'ESCOLA MUNICIPAL PROFESSOR PAUL'!M16+'E M ROSEMIRA DE OLIVEIRA CAVALC'!M16+'E M AMÉLIA ANTUNES RABELLO'!M16+'ESCOLA MUNICIPAL AUGUSTO PUGNAL'!M16+'ESCOLA MUNICIPAL CELINA SCHECHN'!M16+'E M DARCY CORREA DA VEIGA'!M16+'E M DR PAULA BUARQUE'!M16+'E M DR THEODORO MACHADO'!M16+'E M ARNALDO DYCKERHOFF'!M16+'E M CARLOS CANEDO'!M16+'E M DR BARROS FRANCO'!M16+'E M MAJOR THEÓFILO DE CARVALHO'!M16+'E M TAQUARIL'!M16+'E M BEATRIZ ZALESKI'!M16+'E M ANTÔNIO JOSÉ DE LIMA'!M16+'E M FELIX WAN ERVEN DE BARROS'!M16+'ESCOLA MUNICIPAL HILDEBRANDO DE'!M16+'E M OSWALDO DA COSTA FRIAS'!M16+'E MZDA CARMEM NUNES MARTINS'!M16+'E MZDA AVELINO DE CARVALHO'!M16+'E M GERALDO VENTURA DIAS'!M16+'E M SALVADOR KLING'!M16+'E M PREFEITO JAMIL SABRÁ'!M16+'LICEU MUNICIPAL CARLOS CHAGAS F'!M16+'ESCOLA MUNICIPAL ANA MOHAMMAD'!M16+'ESCOLA MUNICIPAL ALTO INDEPENDÊ'!M16+'E M ALMIRANTE TAMANDARÉ'!M16+'ESCOLA MUNICIPALIZADA FREI ANIC'!M16+'E M PEDRO AMADO'!M16+'E M PROFª MARIA DA GLÓRIA QUEIR'!M16+'E M SEBASTIÃO LACERDA'!M16+'E M PROFESSOR FLÁVIO MACIEL'!M16+'ESCOLA MUNICIPAL PAULO SALDANHA'!M16+'ESCOLA MUNICIPAL PROFESSOR JOSE'!M16+'E M MONSENHOR CIRILLO CALAON'!M16+'E M AMÉRICO FERNANDES RIBEIRO'!M16+'E M PROFª JANDIRA PEIXOTO BORDI'!M16+'E M MONSENHOR JOÃO DE DEUS RODR'!M16+'E M DOM MANOEL PEDRO DA CUNHA C'!M16+'E M JOHANN NOEL'!M16+'E MZDA SANTA TEREZINHA'!M16+'E M PAPA JOÃO PAULO II'!M16+'E M STEFAN ZWEIG'!M16+'ESCOLA MUNICIPAL SENADOR MARIO '!M16+'E M DR RUBENS DE CASTRO BOMTEMP'!M16+'E M PAULO FREIRE'!M16+'E M PROFª MARIA CAMPOS DA SILVA'!M16+'E M HERCÍLIA HENRIQUES MORET'!M16+'ESCOLA MUNICIPALIZADA MOYSÉS FU'!M16+'CIEP BRIZOLÃO 474 MAESTRO GUERR'!M16+'CENTRO DE ENSINO PROF DARCY RIB'!M16+'CASA DA EDUCAÇÃO VISCONDE DE MA'!M16+'CENTRO DE REFERÊNCIA EM EDUCAÇÃ'!M16+'E M PROF NILTON COSTA PEREIRA D'!M16+'COLÉGIO GUNNAR VINGREN DE PETRÓ'!M16+'CENTRO DE REFERÊNCIA EM EDUC 2'!M16+'ESCOLA SANTA LUIZA DE MARILLAC'!M16+'CENTRO EDUCACIONAL COMUNIDADE S'!M16+'EDUCANDÁRIO TERRA SANTA'!M16+'ESCOLA GERMANO VALENTE'!M16+'ESCOLA DAS COMUNIDADES SANTO AN'!M16+'ESCOLA DOMÉSTICA NOSSA SENHORA '!M16+'ESCOLA PAROQUIAL NOSSA SENHO 3'!M16+'ESCOLA MONSENHOR GENTIL'!M16+'ESCOLA PAROQUIAL BOM JESUS'!M16+'ESCOLA PAROQUIAL CARLOS DEMIÁ'!M16+'ESCOLA PAROQUIAL NOSSA SENHO 2'!M16+'ESCOLA PAROQUIAL NOSSA SENHORA '!M16+'ESCOLA PAROQUIAL SÃO PEDRO DE A'!M16+'ESCOLA SANTA MARIA GORETTI'!M16+'ESCOLA SANTA RITA DE CASSIA'!M16+'ESCOLA SÃO CRISTÓVÃO'!M16+'ESCOLA PAROQUIAL SÃO FRANCISCO '!M16+'ESCOLA SAO FRANCISCO DE ASSIS'!M16+'ESCOLA SÃO JOÃO BATISTA'!M16+'ESCOLA SÃO JUDAS TADEU'!M16+'ESCOLA PAROQUIAL SÃO PIO X'!M16+'COLÉGIO ANGLICANO DE ARARAS'!M16+'COLEGIO VICENTINO PADRE CORRÊA'!M16+'ESCOLA NOSSA SENHORA DE FÁTIMA'!M16+'ESCOLA PAROQUIAL DA ALCOBAÇA'!M16+'ESCOLA PAROQUIAL DO LOTEAMENTO '!M16+'ESCOLA PAROQUIAL SANTA BERNADET'!M16+'ESCOLA SÃO GERALDO'!M16+'ESCOLA SANTO ANTÔNIO'!M16+'LICEU SÃO JOSÉ DE ITAIPAVA'!M16+'ESCOLA SÃO JOSÉ DO CAETITU'!M16+'CEI ASSOCIAÇÃO BENEFICENTE FAZE'!M16+'CEI CASA DA SOLIDARIEDADE DE NO'!M16+'CEI LULU MONTEIRO DE CASTRO'!M16+'CEI SÃO JOÃO BATISTA'!M16+'CEI SÃO FRANCISCO ASSIS'!M16+'CEI A SEMENTEIRA'!M16+'CEI FREI LEÃO'!M16+'CEI ROMANO CANAVESE'!M16+'CEI ANDRÉ VANZAN'!M16+'CEI CRIANÇA SANTA EDWIGES'!M16+'CENTRO DE EDUCAÇÃO INFANTIL IRM'!M16+'CEI PEDRAS BRANCAS'!M16+'CEI INÊS BELARMINO DE SOUZA'!M16+'CEI PROFª ROSANGELA DA SILVA LE'!M16+'CEI VILA SAO JOSE'!M16+'CEI MARIA THEREZA KLING DO VALL'!M16+'CEI DEISE ELOY GOMES'!M16+'CENTRO PAROQUIAL DE EDUCAÇÃO IN'!M16+'CEI VISTA ALEGRE'!M16+'CEI ALDEIA DA CRIANCA'!M16+'CEI DÉA LÚCIA CORDEIRO'!M16+'CENTRO DE EDUCAÇÃO INFANTIL CAR'!M16+'CEI IRMÃ SILVANA'!M16+'CEI MARLI SOARES FERREIRA NETTO'!M16+'CEI PROFª SONIA REGINA SCUDESE '!M16+'CEI DONA ESPERANZA DE BOURBON D'!M16+'CEI PREFEITO SÉRGIO FADEL'!M16+'CEI ANDRÉ REBOUÇAS'!M16+'CENTRO DE EDUCAÇÃO INFANTIL CHI'!M16+'CEI TIA ALICE'!M16+'CEI TERRA SANTA'!M16+'CEI JORGE ROLANDO DA SILVA'!M16+'CEI CARANGOLA'!M16+'CEI CÉLIA LÔBO PAULO'!M16+'CEI LIONS CLUBE DE PETRÓPOLIS'!M16+'CEI PROFª GRAÇA COSTA'!M16+'CEI ANGELA MARIA DA CONCEIÇÃO S'!M16+'CEI LUIZ MARCHIORI'!M16+'CEI PROFª MARLUCE DE SOUZA PEST'!M16+'CEI OLÍVIA MACHADO DA COSTA NOG'!M16+'CEI VILA IPANEMA'!M16+'CEI VILA LEOPOLDINA'!M16+'CENTRO DE EDUCAÇÃO INFANTIL CAS'!M16+'CEI PRIMEIRA INFÂNCIA'!M16+'CEI PROFª DORA KILLER'!M16+'CEI PROFª PATRÍCIA FERREIRA E S'!M16+'CEI DRA ZILDA ARNS NEUMANN'!M16+'CEI DENISE BESSA DE OLIVA MAYA'!M16+'CEI GIUSEPPE-NEVA VOLONTERIO'!M16+'CENTRO DE EDUCAÇÃO INFANTIL LOT'!M16+'CEI IRINEU MARINHO'!M16+'CEI OSWALDO CRUZ'!M16+'CEI ANA CAROLINA TELLES'!M16+'CEI JOSÉ GONÇALVES DA MOTTA'!M16+'CEI SAGRADA FAMÍLIA'!M16+'CEI PROFª HERMÍNIA MATHEUS'!M16+'CENTRO DE EDUCAÇÃO INFANTIL PRO'!M16+'CEI MONSENHOR PAULO ELIAS DAHER'!M16+'CEI DAGMAR ROLANDO DE OLIVEIRA'!M16+'CENTRO DE EDUCAÇÃO INFANTIL 2'!M16+'CEI BOA VISTA'!M16+'CEI NILO PEÇANHA'!M16+'CENTRO DE EDUCAÇÃO INFANTIL AUG'!M16+'CEI THEREZINHA DE JESUS LIMA'!M16+'CEI VIDEIRINHA'!M16+'CEI PROFª ADRIANA CONSTÂNCIO TR'!M16+'CENTRO DE EDUCAÇÃO INFANTIL SÉR'!M16+'CEI JURACI PINTO DO AMARAL DE C'!M16+'CEI NOSSA SENHORA DA GLÓRIA'!M16+'CEI ALTO INDEPENDÊNCIA'!M16+'CEI SÃO JOSÉ DAS OBLATAS DE NAZ'!M16+'CEI SANTO ANTÔNIO AGOSTINHO'!M16+'CEI SÃO CHARBEL'!M16+'ASSOCIAÇÃO DA CRECHE SÃO FRANCI'!M16+'CEI SÃO JOSÉ DO ITAMARATI'!M16+'ASSOCIAÇÃO RECREAR'!M16+'CRECHE-ESCOLA CASTELO SÃO MANOE'!M16+'CENTRO DE EDUCAÇÃO INFANTIL SÃO'!M16 | E12: ='Entrada de Dados'!J2 | F12: =D12*E12
A13: ='Entrada de Dados'!K5 | B13: ='Entrada de Dados'!K197 | C13: ='E M ROTARY'!D17+'E M DE EDUCAÇÃO ESPECIAL SANTOS'!D17+'LICEU MUN PREFEITO CORDOLINO AM'!D17+'E M PREFEITO JAMIL SABRÁ'!D17+'LICEU MUNICIPAL CARLOS CHAGAS F'!D17+'E M PAULO FREIRE'!D17+'E M PROFª MARIA CAMPOS DA SILVA'!D17+'CASA DA EDUCAÇÃO VISCONDE DE MA'!D17+'CENTRO DE REFERÊNCIA EM EDUCAÇÃ'!D17+'ESCOLA SANTA LUIZA DE MARILLAC'!D17+'ESCOLA DOMÉSTICA NOSSA SENHORA '!D17+'ESCOLA MONSENHOR GENTIL'!D17+'ESCOLA PAROQUIAL NOSSA SENHORA '!D17+'ESCOLA PAROQUIAL SÃO PEDRO DE A'!D17+'CEI TERRA SANTA'!D17+'CEI PRIMEIRA INFÂNCIA'!D17+'CEI PROFª PATRÍCIA FERREIRA E S'!D17+'CEI DRA ZILDA ARNS NEUMANN'!D17+'CENTRO DE EDUCAÇÃO INFANTIL PRO'!D17+'CEI MONSENHOR PAULO ELIAS DAHER'!D17+'COLÉGIO GUNNAR VINGREN DE PETRÓ'!D17+'EDUCANDÁRIO TERRA SANTA'!D17+'CEI LIONS CLUBE DE PETRÓPOLIS'!D17+'ESCOLA PAROQUIAL NOSSA SENHO 2'!D17+'CENTRO DE EDUCAÇÃO INFANTIL IRM'!D17+'E M LUIZ CARLOS SOARES'!D17+'ESCOLA GERMANO VALENTE'!D17+'ESCOLA PAROQUIAL NOSSA SENHO 3'!D17+'CEI JORGE ROLANDO DA SILVA'!D17+'E M CLEMENTE FERNANDES'!D17+'E M GERALDO VENTURA DIAS'!D17+'ESCOLA DAS COMUNIDADES SANTO AN'!D17+'CEI PROFª ROSANGELA DA SILVA LE'!D17+'CEI DEISE ELOY GOMES'!D17+'CEI PROFª SONIA REGINA SCUDESE '!D17+'CEI TIA ALICE'!D17+'E M BATAILLARD'!D17+'E M SOROPTIMISTA'!D17+'E M SALVADOR KLING'!D17+'ESCOLA MUNICIPALIZADA FREI ANIC'!D17+'ESCOLA SÃO JUDAS TADEU'!D17+'CEI PEDRAS BRANCAS'!D17+'CEI MARIA THEREZA KLING DO VALL'!D17+'CEI DONA ESPERANZA DE BOURBON D'!D17+'CEI GIUSEPPE-NEVA VOLONTERIO'!D17+'CENTRO DE EDUCAÇÃO INFANTIL SÃO'!D17+'E M LEONARDO BOFF'!D17+'ESCOLA MUNICIPAL GENERAL HEITOR'!D17+'E M JOHANN NOEL'!D17+'ESCOLA SANTA MARIA GORETTI'!D17+'ESCOLA SANTA RITA DE CASSIA'!D17+'ESCOLA SÃO JOÃO BATISTA'!D17+'CEI CASA DA SOLIDARIEDADE DE NO'!D17+'CEI A SEMENTEIRA'!D17+'CEI VILA SAO JOSE'!D17+'E M DR RUBENS DE CASTRO BOMTEMP'!D17+'CEI FREI LEÃO'!D17+'CEI SÃO JOÃO BATISTA'!D17+'CEI JURACI PINTO DO AMARAL DE C'!D17+'E M PEDRO AMADO'!D17+'E M ABELARDO DE LAMARE'!D17+'ESCOLA MUNICIPAL SENADOR MARIO '!D17+'ESCOLA PAROQUIAL SÃO PIO X'!D17+'CEI SÃO CHARBEL'!D17+'E M ROSALINA NICOLAY'!D17+'CEI INÊS BELARMINO DE SOUZA'!D17+'E M PROFª MARIA DA GLÓRIA QUEIR'!D17+'CENTRO EDUCACIONAL COMUNIDADE S'!D17+'CEI ROMANO CANAVESE'!D17+'CEI CÉLIA LÔBO PAULO'!D17+'CEI PROFª DORA KILLER'!D17+'CEI ALTO INDEPENDÊNCIA'!D17+'ESCOLA MUNICIPAL ALTO INDEPENDÊ'!D17+'E M PAPA JOÃO PAULO II'!D17+'CEI ANDRÉ REBOUÇAS'!D17+'CEI PROFª HERMÍNIA MATHEUS'!D17+'ESCOLA MUNICIPAL MAJOR JÚLIO FR'!D17+'E M ALMIRANTE TAMANDARÉ'!D17+'ESCOLA PAROQUIAL CARLOS DEMIÁ'!D17+'CENTRO PAROQUIAL DE EDUCAÇÃO IN'!D17+'CEI IRMÃ SILVANA'!D17+'CEI OLÍVIA MACHADO DA COSTA NOG'!D17+'E M GOVERNADOR MARCELLO ALENCAR'!D17+'E M PROFESSOR FLÁVIO MACIEL'!D17+'E M PROFª JANDIRA PEIXOTO BORDI'!D17+'E M STEFAN ZWEIG'!D17+'ESCOLA PAROQUIAL BOM JESUS'!D17+'CEI MARLI SOARES FERREIRA NETTO'!D17+'CENTRO DE EDUCAÇÃO INFANTIL CHI'!D17+'CEI VILA IPANEMA'!D17+'E M ROBERT KENNEDY'!D17+'ESCOLA MUNICIPAL ANA MOHAMMAD'!D17+'ESCOLA SÃO CRISTÓVÃO'!D17+'CEI DÉA LÚCIA CORDEIRO'!D17+'CEI SAGRADA FAMÍLIA'!D17+'CEI SÃO JOSÉ DAS OBLATAS DE NAZ'!D17+'ESCOLA MUNICIPAL JORGE AMADO'!D17+'E M FÁBRICA DO SABER'!D17+'CIEP BRIZOLÃO 474 MAESTRO GUERR'!D17+'CENTRO DE ENSINO PROF DARCY RIB'!D17+'CEI ANDRÉ VANZAN'!D17+'CENTRO DE EDUCAÇÃO INFANTIL CAR'!D17+'CEI BOA VISTA'!D17+'ASSOCIAÇÃO DA CRECHE SÃO FRANCI'!D17+'ESCOLA MUNICIPAL PAULO SALDANHA'!D17+'ESCOLA MUNICIPAL LÚCIA DE ALMEI'!D17+'E M DOM MANOEL PEDRO DA CUNHA C'!D17+'ESCOLA SÃO GERALDO'!D17+'CEI LULU MONTEIRO DE CASTRO'!D17+'CEI CARANGOLA'!D17+'ASSOCIAÇÃO RECREAR'!D17+'CENTRO DE EDUCAÇÃO INFANTIL CAS'!D17+'E M ROSEMIRA DE OLIVEIRA CAVALC'!D17+'E MZDA CARMEM NUNES MARTINS'!D17+'CEI SÃO JOSÉ DO ITAMARATI'!D17+'E M DUQUE DE CAXIAS'!D17+'CENTRO DE EDUCAÇÃO INFANTIL 2'!D17+'E M ANTÔNIO LEITE GARCIA'!D17+'ESCOLA PAROQUIAL DA ALCOBAÇA'!D17+'CENTRO DE EDUCAÇÃO INFANTIL LOT'!D17+'ESCOLA PAROQUIAL DO LOTEAMENTO '!D17+'E M PROF JOAQUIM DEISTER'!D17+'E M MARIETA GONÇALVES'!D17+'ESCOLA MUNICIPAL ODETTE YOUNG M'!D17+'ESCOLA MUNICIPAL PROFESSOR JOSE'!D17+'E M HERCÍLIA HENRIQUES MORET'!D17+'COLEGIO VICENTINO PADRE CORRÊA'!D17+'CEI PROFª MARLUCE DE SOUZA PEST'!D17+'CEI IRINEU MARINHO'!D17+'CEI DAGMAR ROLANDO DE OLIVEIRA'!D17+'CEI NOSSA SENHORA DA GLÓRIA'!D17+'E M PROF NILTON COSTA PEREIRA D'!D17+'CENTRO DE EDUCAÇÃO INFANTIL SÉR'!D17+'CEI SANTO ANTÔNIO AGOSTINHO'!D17+'CEI OSWALDO CRUZ'!D17+'E M MAGDALENA TAGLIAFERRO'!D17+'ESCOLA SÃO JOSÉ DO CAETITU'!D17+'CRECHE-ESCOLA CASTELO SÃO MANOE'!D17+'CEI THEREZINHA DE JESUS LIMA'!D17+'ESCOLA MUNICIPAL PROFESSOR PAUL'!D17+'COLÉGIO ANGLICANO DE ARARAS'!D17+'ESCOLA PAROQUIAL SANTA BERNADET'!D17+'CEI VISTA ALEGRE'!D17+'CEI DENISE BESSA DE OLIVA MAYA'!D17+'CEI VIDEIRINHA'!D17+'E M AMÉRICO FERNANDES RIBEIRO'!D17+'ESCOLA MUNICIPAL AUGUSTO PUGNAL'!D17+'ESCOLA MUNICIPAL CELINA SCHECHN'!D17+'E M DARCY CORREA DA VEIGA'!D17+'E M DR PAULA BUARQUE'!D17+'LICEU SÃO JOSÉ DE ITAIPAVA'!D17+'CEI LUIZ MARCHIORI'!D17+'CENTRO DE EDUCAÇÃO INFANTIL AUG'!D17+'CEI PROFª ADRIANA CONSTÂNCIO TR'!D17+'E M AMÉLIA ANTUNES RABELLO'!D17+'CEI PREFEITO SÉRGIO FADEL'!D17+'E M DR THEODORO MACHADO'!D17+'ESCOLA SANTO ANTÔNIO'!D17+'E M TAQUARIL'!D17+'E M MONSENHOR JOÃO DE DEUS RODR'!D17+'CENTRO DE REFERÊNCIA EM EDUC 2'!D17+'CEI PROFª GRAÇA COSTA'!D17+'CEI VILA LEOPOLDINA'!D17+'CEI NILO PEÇANHA'!D17+'E MZDA SANTA TEREZINHA'!D17+'CEI CRIANÇA SANTA EDWIGES'!D17+'E M ARNALDO DYCKERHOFF'!D17+'E M CARLOS CANEDO'!D17+'E M BEATRIZ ZALESKI'!D17+'E M ANTÔNIO JOSÉ DE LIMA'!D17+'E M FELIX WAN ERVEN DE BARROS'!D17+'ESCOLA MUNICIPAL HILDEBRANDO DE'!D17+'E M OSWALDO DA COSTA FRIAS'!D17+'E MZDA AVELINO DE CARVALHO'!D17+'ESCOLA MUNICIPALIZADA MOYSÉS FU'!D17+'CEI ANGELA MARIA DA CONCEIÇÃO S'!D17+'CEI JOSÉ GONÇALVES DA MOTTA'!D17+'E M DR BARROS FRANCO'!D17+'E M MAJOR THEÓFILO DE CARVALHO'!D17+'E M JOÃO KOPKE'!D17+'CEI ASSOCIAÇÃO BENEFICENTE FAZE'!D17+'ESCOLA SAO FRANCISCO DE ASSIS'!D17+'CEI SÃO FRANCISCO ASSIS'!D17+'CEI ALDEIA DA CRIANCA'!D17+'ESCOLA MUNICIPAL ODETTE FONSECA'!D17+'CEI ANA CAROLINA TELLES'!D17+'E M SEBASTIÃO LACERDA'!D17+'E M DOM PEDRO DE ALCÂNTARA'!D17+'ESCOLA NOSSA SENHORA DE FÁTIMA'!D17+'ESCOLA PAROQUIAL SÃO FRANCISCO '!D17+'E M MONSENHOR CIRILLO CALAON'!D17 | D13: ='E M ABELARDO DE LAMARE'!M17+'E M BATAILLARD'!M17+'E M LEONARDO BOFF'!M17+'E M CLEMENTE FERNANDES'!M17+'E M DOM PEDRO DE ALCÂNTARA'!M17+'E M DUQUE DE CAXIAS'!M17+'E M LUIZ CARLOS SOARES'!M17+'ESCOLA MUNICIPAL GENERAL HEITOR'!M17+'E M JOÃO KOPKE'!M17+'ESCOLA MUNICIPAL ODETTE FONSECA'!M17+'E M GOVERNADOR MARCELLO ALENCAR'!M17+'E M PROF JOAQUIM DEISTER'!M17+'E M ROBERT KENNEDY'!M17+'E M ROTARY'!M17+'E M ROSALINA NICOLAY'!M17+'E M DE EDUCAÇÃO ESPECIAL SANTOS'!M17+'E M SOROPTIMISTA'!M17+'LICEU MUN PREFEITO CORDOLINO AM'!M17+'E M ANTÔNIO LEITE GARCIA'!M17+'ESCOLA MUNICIPAL JORGE AMADO'!M17+'ESCOLA MUNICIPAL LÚCIA DE ALMEI'!M17+'E M MAGDALENA TAGLIAFERRO'!M17+'ESCOLA MUNICIPAL MAJOR JÚLIO FR'!M17+'E M MARIETA GONÇALVES'!M17+'ESCOLA MUNICIPAL ODETTE YOUNG M'!M17+'E M FÁBRICA DO SABER'!M17+'ESCOLA MUNICIPAL PROFESSOR PAUL'!M17+'E M ROSEMIRA DE OLIVEIRA CAVALC'!M17+'E M AMÉLIA ANTUNES RABELLO'!M17+'ESCOLA MUNICIPAL AUGUSTO PUGNAL'!M17+'ESCOLA MUNICIPAL CELINA SCHECHN'!M17+'E M DARCY CORREA DA VEIGA'!M17+'E M DR PAULA BUARQUE'!M17+'E M DR THEODORO MACHADO'!M17+'E M ARNALDO DYCKERHOFF'!M17+'E M CARLOS CANEDO'!M17+'E M DR BARROS FRANCO'!M17+'E M MAJOR THEÓFILO DE CARVALHO'!M17+'E M TAQUARIL'!M17+'E M BEATRIZ ZALESKI'!M17+'E M ANTÔNIO JOSÉ DE LIMA'!M17+'E M FELIX WAN ERVEN DE BARROS'!M17+'ESCOLA MUNICIPAL HILDEBRANDO DE'!M17+'E M OSWALDO DA COSTA FRIAS'!M17+'E MZDA CARMEM NUNES MARTINS'!M17+'E MZDA AVELINO DE CARVALHO'!M17+'E M GERALDO VENTURA DIAS'!M17+'E M SALVADOR KLING'!M17+'E M PREFEITO JAMIL SABRÁ'!M17+'LICEU MUNICIPAL CARLOS CHAGAS F'!M17+'ESCOLA MUNICIPAL ANA MOHAMMAD'!M17+'ESCOLA MUNICIPAL ALTO INDEPENDÊ'!M17+'E M ALMIRANTE TAMANDARÉ'!M17+'ESCOLA MUNICIPALIZADA FREI ANIC'!M17+'E M PEDRO AMADO'!M17+'E M PROFª MARIA DA GLÓRIA QUEIR'!M17+'E M SEBASTIÃO LACERDA'!M17+'E M PROFESSOR FLÁVIO MACIEL'!M17+'ESCOLA MUNICIPAL PAULO SALDANHA'!M17+'ESCOLA MUNICIPAL PROFESSOR JOSE'!M17+'E M MONSENHOR CIRILLO CALAON'!M17+'E M AMÉRICO FERNANDES RIBEIRO'!M17+'E M PROFª JANDIRA PEIXOTO BORDI'!M17+'E M MONSENHOR JOÃO DE DEUS RODR'!M17+'E M DOM MANOEL PEDRO DA CUNHA C'!M17+'E M JOHANN NOEL'!M17+'E MZDA SANTA TEREZINHA'!M17+'E M PAPA JOÃO PAULO II'!M17+'E M STEFAN ZWEIG'!M17+'ESCOLA MUNICIPAL SENADOR MARIO '!M17+'E M DR RUBENS DE CASTRO BOMTEMP'!M17+'E M PAULO FREIRE'!M17+'E M PROFª MARIA CAMPOS DA SILVA'!M17+'E M HERCÍLIA HENRIQUES MORET'!M17+'ESCOLA MUNICIPALIZADA MOYSÉS FU'!M17+'CIEP BRIZOLÃO 474 MAESTRO GUERR'!M17+'CENTRO DE ENSINO PROF DARCY RIB'!M17+'CASA DA EDUCAÇÃO VISCONDE DE MA'!M17+'CENTRO DE REFERÊNCIA EM EDUCAÇÃ'!M17+'E M PROF NILTON COSTA PEREIRA D'!M17+'COLÉGIO GUNNAR VINGREN DE PETRÓ'!M17+'CENTRO DE REFERÊNCIA EM EDUC 2'!M17+'ESCOLA SANTA LUIZA DE MARILLAC'!M17+'CENTRO EDUCACIONAL COMUNIDADE S'!M17+'EDUCANDÁRIO TERRA SANTA'!M17+'ESCOLA GERMANO VALENTE'!M17+'ESCOLA DAS COMUNIDADES SANTO AN'!M17+'ESCOLA DOMÉSTICA NOSSA SENHORA '!M17+'ESCOLA PAROQUIAL NOSSA SENHO 3'!M17+'ESCOLA MONSENHOR GENTIL'!M17+'ESCOLA PAROQUIAL BOM JESUS'!M17+'ESCOLA PAROQUIAL CARLOS DEMIÁ'!M17+'ESCOLA PAROQUIAL NOSSA SENHO 2'!M17+'ESCOLA PAROQUIAL NOSSA SENHORA '!M17+'ESCOLA PAROQUIAL SÃO PEDRO DE A'!M17+'ESCOLA SANTA MARIA GORETTI'!M17+'ESCOLA SANTA RITA DE CASSIA'!M17+'ESCOLA SÃO CRISTÓVÃO'!M17+'ESCOLA PAROQUIAL SÃO FRANCISCO '!M17+'ESCOLA SAO FRANCISCO DE ASSIS'!M17+'ESCOLA SÃO JOÃO BATISTA'!M17+'ESCOLA SÃO JUDAS TADEU'!M17+'ESCOLA PAROQUIAL SÃO PIO X'!M17+'COLÉGIO ANGLICANO DE ARARAS'!M17+'COLEGIO VICENTINO PADRE CORRÊA'!M17+'ESCOLA NOSSA SENHORA DE FÁTIMA'!M17+'ESCOLA PAROQUIAL DA ALCOBAÇA'!M17+'ESCOLA PAROQUIAL DO LOTEAMENTO '!M17+'ESCOLA PAROQUIAL SANTA BERNADET'!M17+'ESCOLA SÃO GERALDO'!M17+'ESCOLA SANTO ANTÔNIO'!M17+'LICEU SÃO JOSÉ DE ITAIPAVA'!M17+'ESCOLA SÃO JOSÉ DO CAETITU'!M17+'CEI ASSOCIAÇÃO BENEFICENTE FAZE'!M17+'CEI CASA DA SOLIDARIEDADE DE NO'!M17+'CEI LULU MONTEIRO DE CASTRO'!M17+'CEI SÃO JOÃO BATISTA'!M17+'CEI SÃO FRANCISCO ASSIS'!M17+'CEI A SEMENTEIRA'!M17+'CEI FREI LEÃO'!M17+'CEI ROMANO CANAVESE'!M17+'CEI ANDRÉ VANZAN'!M17+'CEI CRIANÇA SANTA EDWIGES'!M17+'CENTRO DE EDUCAÇÃO INFANTIL IRM'!M17+'CEI PEDRAS BRANCAS'!M17+'CEI INÊS BELARMINO DE SOUZA'!M17+'CEI PROFª ROSANGELA DA SILVA LE'!M17+'CEI VILA SAO JOSE'!M17+'CEI MARIA THEREZA KLING DO VALL'!M17+'CEI DEISE ELOY GOMES'!M17+'CENTRO PAROQUIAL DE EDUCAÇÃO IN'!M17+'CEI VISTA ALEGRE'!M17+'CEI ALDEIA DA CRIANCA'!M17+'CEI DÉA LÚCIA CORDEIRO'!M17+'CENTRO DE EDUCAÇÃO INFANTIL CAR'!M17+'CEI IRMÃ SILVANA'!M17+'CEI MARLI SOARES FERREIRA NETTO'!M17+'CEI PROFª SONIA REGINA SCUDESE '!M17+'CEI DONA ESPERANZA DE BOURBON D'!M17+'CEI PREFEITO SÉRGIO FADEL'!M17+'CEI ANDRÉ REBOUÇAS'!M17+'CENTRO DE EDUCAÇÃO INFANTIL CHI'!M17+'CEI TIA ALICE'!M17+'CEI TERRA SANTA'!M17+'CEI JORGE ROLANDO DA SILVA'!M17+'CEI CARANGOLA'!M17+'CEI CÉLIA LÔBO PAULO'!M17+'CEI LIONS CLUBE DE PETRÓPOLIS'!M17+'CEI PROFª GRAÇA COSTA'!M17+'CEI ANGELA MARIA DA CONCEIÇÃO S'!M17+'CEI LUIZ MARCHIORI'!M17+'CEI PROFª MARLUCE DE SOUZA PEST'!M17+'CEI OLÍVIA MACHADO DA COSTA NOG'!M17+'CEI VILA IPANEMA'!M17+'CEI VILA LEOPOLDINA'!M17+'CENTRO DE EDUCAÇÃO INFANTIL CAS'!M17+'CEI PRIMEIRA INFÂNCIA'!M17+'CEI PROFª DORA KILLER'!M17+'CEI PROFª PATRÍCIA FERREIRA E S'!M17+'CEI DRA ZILDA ARNS NEUMANN'!M17+'CEI DENISE BESSA DE OLIVA MAYA'!M17+'CEI GIUSEPPE-NEVA VOLONTERIO'!M17+'CENTRO DE EDUCAÇÃO INFANTIL LOT'!M17+'CEI IRINEU MARINHO'!M17+'CEI OSWALDO CRUZ'!M17+'CEI ANA CAROLINA TELLES'!M17+'CEI JOSÉ GONÇALVES DA MOTTA'!M17+'CEI SAGRADA FAMÍLIA'!M17+'CEI PROFª HERMÍNIA MATHEUS'!M17+'CENTRO DE EDUCAÇÃO INFANTIL PRO'!M17+'CEI MONSENHOR PAULO ELIAS DAHER'!M17+'CEI DAGMAR ROLANDO DE OLIVEIRA'!M17+'CENTRO DE EDUCAÇÃO INFANTIL 2'!M17+'CEI BOA VISTA'!M17+'CEI NILO PEÇANHA'!M17+'CENTRO DE EDUCAÇÃO INFANTIL AUG'!M17+'CEI THEREZINHA DE JESUS LIMA'!M17+'CEI VIDEIRINHA'!M17+'CEI PROFª ADRIANA CONSTÂNCIO TR'!M17+'CENTRO DE EDUCAÇÃO INFANTIL SÉR'!M17+'CEI JURACI PINTO DO AMARAL DE C'!M17+'CEI NOSSA SENHORA DA GLÓRIA'!M17+'CEI ALTO INDEPENDÊNCIA'!M17+'CEI SÃO JOSÉ DAS OBLATAS DE NAZ'!M17+'CEI SANTO ANTÔNIO AGOSTINHO'!M17+'CEI SÃO CHARBEL'!M17+'ASSOCIAÇÃO DA CRECHE SÃO FRANCI'!M17+'CEI SÃO JOSÉ DO ITAMARATI'!M17+'ASSOCIAÇÃO RECREAR'!M17+'CRECHE-ESCOLA CASTELO SÃO MANOE'!M17+'CENTRO DE EDUCAÇÃO INFANTIL SÃO'!M17 | E13: ='Entrada de Dados'!K2 | F13: =D13*E13
A14: ='Entrada de Dados'!L5 | B14: ='Entrada de Dados'!L197 | C14: ='E M ROTARY'!D18+'E M DE EDUCAÇÃO ESPECIAL SANTOS'!D18+'LICEU MUN PREFEITO CORDOLINO AM'!D18+'E M PREFEITO JAMIL SABRÁ'!D18+'LICEU MUNICIPAL CARLOS CHAGAS F'!D18+'E M PAULO FREIRE'!D18+'E M PROFª MARIA CAMPOS DA SILVA'!D18+'CASA DA EDUCAÇÃO VISCONDE DE MA'!D18+'CENTRO DE REFERÊNCIA EM EDUCAÇÃ'!D18+'ESCOLA SANTA LUIZA DE MARILLAC'!D18+'ESCOLA DOMÉSTICA NOSSA SENHORA '!D18+'ESCOLA MONSENHOR GENTIL'!D18+'ESCOLA PAROQUIAL NOSSA SENHORA '!D18+'ESCOLA PAROQUIAL SÃO PEDRO DE A'!D18+'CEI TERRA SANTA'!D18+'CEI PRIMEIRA INFÂNCIA'!D18+'CEI PROFª PATRÍCIA FERREIRA E S'!D18+'CEI DRA ZILDA ARNS NEUMANN'!D18+'CENTRO DE EDUCAÇÃO INFANTIL PRO'!D18+'CEI MONSENHOR PAULO ELIAS DAHER'!D18+'COLÉGIO GUNNAR VINGREN DE PETRÓ'!D18+'EDUCANDÁRIO TERRA SANTA'!D18+'CEI LIONS CLUBE DE PETRÓPOLIS'!D18+'ESCOLA PAROQUIAL NOSSA SENHO 2'!D18+'CENTRO DE EDUCAÇÃO INFANTIL IRM'!D18+'E M LUIZ CARLOS SOARES'!D18+'ESCOLA GERMANO VALENTE'!D18+'ESCOLA PAROQUIAL NOSSA SENHO 3'!D18+'CEI JORGE ROLANDO DA SILVA'!D18+'E M CLEMENTE FERNANDES'!D18+'E M GERALDO VENTURA DIAS'!D18+'ESCOLA DAS COMUNIDADES SANTO AN'!D18+'CEI PROFª ROSANGELA DA SILVA LE'!D18+'CEI DEISE ELOY GOMES'!D18+'CEI PROFª SONIA REGINA SCUDESE '!D18+'CEI TIA ALICE'!D18+'E M BATAILLARD'!D18+'E M SOROPTIMISTA'!D18+'E M SALVADOR KLING'!D18+'ESCOLA MUNICIPALIZADA FREI ANIC'!D18+'ESCOLA SÃO JUDAS TADEU'!D18+'CEI PEDRAS BRANCAS'!D18+'CEI MARIA THEREZA KLING DO VALL'!D18+'CEI DONA ESPERANZA DE BOURBON D'!D18+'CEI GIUSEPPE-NEVA VOLONTERIO'!D18+'CENTRO DE EDUCAÇÃO INFANTIL SÃO'!D18+'E M LEONARDO BOFF'!D18+'ESCOLA MUNICIPAL GENERAL HEITOR'!D18+'E M JOHANN NOEL'!D18+'ESCOLA SANTA MARIA GORETTI'!D18+'ESCOLA SANTA RITA DE CASSIA'!D18+'ESCOLA SÃO JOÃO BATISTA'!D18+'CEI CASA DA SOLIDARIEDADE DE NO'!D18+'CEI A SEMENTEIRA'!D18+'CEI VILA SAO JOSE'!D18+'E M DR RUBENS DE CASTRO BOMTEMP'!D18+'CEI FREI LEÃO'!D18+'CEI SÃO JOÃO BATISTA'!D18+'CEI JURACI PINTO DO AMARAL DE C'!D18+'E M PEDRO AMADO'!D18+'E M ABELARDO DE LAMARE'!D18+'ESCOLA MUNICIPAL SENADOR MARIO '!D18+'ESCOLA PAROQUIAL SÃO PIO X'!D18+'CEI SÃO CHARBEL'!D18+'E M ROSALINA NICOLAY'!D18+'CEI INÊS BELARMINO DE SOUZA'!D18+'E M PROFª MARIA DA GLÓRIA QUEIR'!D18+'CENTRO EDUCACIONAL COMUNIDADE S'!D18+'CEI ROMANO CANAVESE'!D18+'CEI CÉLIA LÔBO PAULO'!D18+'CEI PROFª DORA KILLER'!D18+'CEI ALTO INDEPENDÊNCIA'!D18+'ESCOLA MUNICIPAL ALTO INDEPENDÊ'!D18+'E M PAPA JOÃO PAULO II'!D18+'CEI ANDRÉ REBOUÇAS'!D18+'CEI PROFª HERMÍNIA MATHEUS'!D18+'ESCOLA MUNICIPAL MAJOR JÚLIO FR'!D18+'E M ALMIRANTE TAMANDARÉ'!D18+'ESCOLA PAROQUIAL CARLOS DEMIÁ'!D18+'CENTRO PAROQUIAL DE EDUCAÇÃO IN'!D18+'CEI IRMÃ SILVANA'!D18+'CEI OLÍVIA MACHADO DA COSTA NOG'!D18+'E M GOVERNADOR MARCELLO ALENCAR'!D18+'E M PROFESSOR FLÁVIO MACIEL'!D18+'E M PROFª JANDIRA PEIXOTO BORDI'!D18+'E M STEFAN ZWEIG'!D18+'ESCOLA PAROQUIAL BOM JESUS'!D18+'CEI MARLI SOARES FERREIRA NETTO'!D18+'CENTRO DE EDUCAÇÃO INFANTIL CHI'!D18+'CEI VILA IPANEMA'!D18+'E M ROBERT KENNEDY'!D18+'ESCOLA MUNICIPAL ANA MOHAMMAD'!D18+'ESCOLA SÃO CRISTÓVÃO'!D18+'CEI DÉA LÚCIA CORDEIRO'!D18+'CEI SAGRADA FAMÍLIA'!D18+'CEI SÃO JOSÉ DAS OBLATAS DE NAZ'!D18+'ESCOLA MUNICIPAL JORGE AMADO'!D18+'E M FÁBRICA DO SABER'!D18+'CIEP BRIZOLÃO 474 MAESTRO GUERR'!D18+'CENTRO DE ENSINO PROF DARCY RIB'!D18+'CEI ANDRÉ VANZAN'!D18+'CENTRO DE EDUCAÇÃO INFANTIL CAR'!D18+'CEI BOA VISTA'!D18+'ASSOCIAÇÃO DA CRECHE SÃO FRANCI'!D18+'ESCOLA MUNICIPAL PAULO SALDANHA'!D18+'ESCOLA MUNICIPAL LÚCIA DE ALMEI'!D18+'E M DOM MANOEL PEDRO DA CUNHA C'!D18+'ESCOLA SÃO GERALDO'!D18+'CEI LULU MONTEIRO DE CASTRO'!D18+'CEI CARANGOLA'!D18+'ASSOCIAÇÃO RECREAR'!D18+'CENTRO DE EDUCAÇÃO INFANTIL CAS'!D18+'E M ROSEMIRA DE OLIVEIRA CAVALC'!D18+'E MZDA CARMEM NUNES MARTINS'!D18+'CEI SÃO JOSÉ DO ITAMARATI'!D18+'E M DUQUE DE CAXIAS'!D18+'CENTRO DE EDUCAÇÃO INFANTIL 2'!D18+'E M ANTÔNIO LEITE GARCIA'!D18+'ESCOLA PAROQUIAL DA ALCOBAÇA'!D18+'CENTRO DE EDUCAÇÃO INFANTIL LOT'!D18+'ESCOLA PAROQUIAL DO LOTEAMENTO '!D18+'E M PROF JOAQUIM DEISTER'!D18+'E M MARIETA GONÇALVES'!D18+'ESCOLA MUNICIPAL ODETTE YOUNG M'!D18+'ESCOLA MUNICIPAL PROFESSOR JOSE'!D18+'E M HERCÍLIA HENRIQUES MORET'!D18+'COLEGIO VICENTINO PADRE CORRÊA'!D18+'CEI PROFª MARLUCE DE SOUZA PEST'!D18+'CEI IRINEU MARINHO'!D18+'CEI DAGMAR ROLANDO DE OLIVEIRA'!D18+'CEI NOSSA SENHORA DA GLÓRIA'!D18+'E M PROF NILTON COSTA PEREIRA D'!D18+'CENTRO DE EDUCAÇÃO INFANTIL SÉR'!D18+'CEI SANTO ANTÔNIO AGOSTINHO'!D18+'CEI OSWALDO CRUZ'!D18+'E M MAGDALENA TAGLIAFERRO'!D18+'ESCOLA SÃO JOSÉ DO CAETITU'!D18+'CRECHE-ESCOLA CASTELO SÃO MANOE'!D18+'CEI THEREZINHA DE JESUS LIMA'!D18+'ESCOLA MUNICIPAL PROFESSOR PAUL'!D18+'COLÉGIO ANGLICANO DE ARARAS'!D18+'ESCOLA PAROQUIAL SANTA BERNADET'!D18+'CEI VISTA ALEGRE'!D18+'CEI DENISE BESSA DE OLIVA MAYA'!D18+'CEI VIDEIRINHA'!D18+'E M AMÉRICO FERNANDES RIBEIRO'!D18+'ESCOLA MUNICIPAL AUGUSTO PUGNAL'!D18+'ESCOLA MUNICIPAL CELINA SCHECHN'!D18+'E M DARCY CORREA DA VEIGA'!D18+'E M DR PAULA BUARQUE'!D18+'LICEU SÃO JOSÉ DE ITAIPAVA'!D18+'CEI LUIZ MARCHIORI'!D18+'CENTRO DE EDUCAÇÃO INFANTIL AUG'!D18+'CEI PROFª ADRIANA CONSTÂNCIO TR'!D18+'E M AMÉLIA ANTUNES RABELLO'!D18+'CEI PREFEITO SÉRGIO FADEL'!D18+'E M DR THEODORO MACHADO'!D18+'ESCOLA SANTO ANTÔNIO'!D18+'E M TAQUARIL'!D18+'E M MONSENHOR JOÃO DE DEUS RODR'!D18+'CENTRO DE REFERÊNCIA EM EDUC 2'!D18+'CEI PROFª GRAÇA COSTA'!D18+'CEI VILA LEOPOLDINA'!D18+'CEI NILO PEÇANHA'!D18+'E MZDA SANTA TEREZINHA'!D18+'CEI CRIANÇA SANTA EDWIGES'!D18+'E M ARNALDO DYCKERHOFF'!D18+'E M CARLOS CANEDO'!D18+'E M BEATRIZ ZALESKI'!D18+'E M ANTÔNIO JOSÉ DE LIMA'!D18+'E M FELIX WAN ERVEN DE BARROS'!D18+'ESCOLA MUNICIPAL HILDEBRANDO DE'!D18+'E M OSWALDO DA COSTA FRIAS'!D18+'E MZDA AVELINO DE CARVALHO'!D18+'ESCOLA MUNICIPALIZADA MOYSÉS FU'!D18+'CEI ANGELA MARIA DA CONCEIÇÃO S'!D18+'CEI JOSÉ GONÇALVES DA MOTTA'!D18+'E M DR BARROS FRANCO'!D18+'E M MAJOR THEÓFILO DE CARVALHO'!D18+'E M JOÃO KOPKE'!D18+'CEI ASSOCIAÇÃO BENEFICENTE FAZE'!D18+'ESCOLA SAO FRANCISCO DE ASSIS'!D18+'CEI SÃO FRANCISCO ASSIS'!D18+'CEI ALDEIA DA CRIANCA'!D18+'ESCOLA MUNICIPAL ODETTE FONSECA'!D18+'CEI ANA CAROLINA TELLES'!D18+'E M SEBASTIÃO LACERDA'!D18+'E M DOM PEDRO DE ALCÂNTARA'!D18+'ESCOLA NOSSA SENHORA DE FÁTIMA'!D18+'ESCOLA PAROQUIAL SÃO FRANCISCO '!D18+'E M MONSENHOR CIRILLO CALAON'!D18 | D14: ='E M ABELARDO DE LAMARE'!M18+'E M BATAILLARD'!M18+'E M LEONARDO BOFF'!M18+'E M CLEMENTE FERNANDES'!M18+'E M DOM PEDRO DE ALCÂNTARA'!M18+'E M DUQUE DE CAXIAS'!M18+'E M LUIZ CARLOS SOARES'!M18+'ESCOLA MUNICIPAL GENERAL HEITOR'!M18+'E M JOÃO KOPKE'!M18+'ESCOLA MUNICIPAL ODETTE FONSECA'!M18+'E M GOVERNADOR MARCELLO ALENCAR'!M18+'E M PROF JOAQUIM DEISTER'!M18+'E M ROBERT KENNEDY'!M18+'E M ROTARY'!M18+'E M ROSALINA NICOLAY'!M18+'E M DE EDUCAÇÃO ESPECIAL SANTOS'!M18+'E M SOROPTIMISTA'!M18+'LICEU MUN PREFEITO CORDOLINO AM'!M18+'E M ANTÔNIO LEITE GARCIA'!M18+'ESCOLA MUNICIPAL JORGE AMADO'!M18+'ESCOLA MUNICIPAL LÚCIA DE ALMEI'!M18+'E M MAGDALENA TAGLIAFERRO'!M18+'ESCOLA MUNICIPAL MAJOR JÚLIO FR'!M18+'E M MARIETA GONÇALVES'!M18+'ESCOLA MUNICIPAL ODETTE YOUNG M'!M18+'E M FÁBRICA DO SABER'!M18+'ESCOLA MUNICIPAL PROFESSOR PAUL'!M18+'E M ROSEMIRA DE OLIVEIRA CAVALC'!M18+'E M AMÉLIA ANTUNES RABELLO'!M18+'ESCOLA MUNICIPAL AUGUSTO PUGNAL'!M18+'ESCOLA MUNICIPAL CELINA SCHECHN'!M18+'E M DARCY CORREA DA VEIGA'!M18+'E M DR PAULA BUARQUE'!M18+'E M DR THEODORO MACHADO'!M18+'E M ARNALDO DYCKERHOFF'!M18+'E M CARLOS CANEDO'!M18+'E M DR BARROS FRANCO'!M18+'E M MAJOR THEÓFILO DE CARVALHO'!M18+'E M TAQUARIL'!M18+'E M BEATRIZ ZALESKI'!M18+'E M ANTÔNIO JOSÉ DE LIMA'!M18+'E M FELIX WAN ERVEN DE BARROS'!M18+'ESCOLA MUNICIPAL HILDEBRANDO DE'!M18+'E M OSWALDO DA COSTA FRIAS'!M18+'E MZDA CARMEM NUNES MARTINS'!M18+'E MZDA AVELINO DE CARVALHO'!M18+'E M GERALDO VENTURA DIAS'!M18+'E M SALVADOR KLING'!M18+'E M PREFEITO JAMIL SABRÁ'!M18+'LICEU MUNICIPAL CARLOS CHAGAS F'!M18+'ESCOLA MUNICIPAL ANA MOHAMMAD'!M18+'ESCOLA MUNICIPAL ALTO INDEPENDÊ'!M18+'E M ALMIRANTE TAMANDARÉ'!M18+'ESCOLA MUNICIPALIZADA FREI ANIC'!M18+'E M PEDRO AMADO'!M18+'E M PROFª MARIA DA GLÓRIA QUEIR'!M18+'E M SEBASTIÃO LACERDA'!M18+'E M PROFESSOR FLÁVIO MACIEL'!M18+'ESCOLA MUNICIPAL PAULO SALDANHA'!M18+'ESCOLA MUNICIPAL PROFESSOR JOSE'!M18+'E M MONSENHOR CIRILLO CALAON'!M18+'E M AMÉRICO FERNANDES RIBEIRO'!M18+'E M PROFª JANDIRA PEIXOTO BORDI'!M18+'E M MONSENHOR JOÃO DE DEUS RODR'!M18+'E M DOM MANOEL PEDRO DA CUNHA C'!M18+'E M JOHANN NOEL'!M18+'E MZDA SANTA TEREZINHA'!M18+'E M PAPA JOÃO PAULO II'!M18+'E M STEFAN ZWEIG'!M18+'ESCOLA MUNICIPAL SENADOR MARIO '!M18+'E M DR RUBENS DE CASTRO BOMTEMP'!M18+'E M PAULO FREIRE'!M18+'E M PROFª MARIA CAMPOS DA SILVA'!M18+'E M HERCÍLIA HENRIQUES MORET'!M18+'ESCOLA MUNICIPALIZADA MOYSÉS FU'!M18+'CIEP BRIZOLÃO 474 MAESTRO GUERR'!M18+'CENTRO DE ENSINO PROF DARCY RIB'!M18+'CASA DA EDUCAÇÃO VISCONDE DE MA'!M18+'CENTRO DE REFERÊNCIA EM EDUCAÇÃ'!M18+'E M PROF NILTON COSTA PEREIRA D'!M18+'COLÉGIO GUNNAR VINGREN DE PETRÓ'!M18+'CENTRO DE REFERÊNCIA EM EDUC 2'!M18+'ESCOLA SANTA LUIZA DE MARILLAC'!M18+'CENTRO EDUCACIONAL COMUNIDADE S'!M18+'EDUCANDÁRIO TERRA SANTA'!M18+'ESCOLA GERMANO VALENTE'!M18+'ESCOLA DAS COMUNIDADES SANTO AN'!M18+'ESCOLA DOMÉSTICA NOSSA SENHORA '!M18+'ESCOLA PAROQUIAL NOSSA SENHO 3'!M18+'ESCOLA MONSENHOR GENTIL'!M18+'ESCOLA PAROQUIAL BOM JESUS'!M18+'ESCOLA PAROQUIAL CARLOS DEMIÁ'!M18+'ESCOLA PAROQUIAL NOSSA SENHO 2'!M18+'ESCOLA PAROQUIAL NOSSA SENHORA '!M18+'ESCOLA PAROQUIAL SÃO PEDRO DE A'!M18+'ESCOLA SANTA MARIA GORETTI'!M18+'ESCOLA SANTA RITA DE CASSIA'!M18+'ESCOLA SÃO CRISTÓVÃO'!M18+'ESCOLA PAROQUIAL SÃO FRANCISCO '!M18+'ESCOLA SAO FRANCISCO DE ASSIS'!M18+'ESCOLA SÃO JOÃO BATISTA'!M18+'ESCOLA SÃO JUDAS TADEU'!M18+'ESCOLA PAROQUIAL SÃO PIO X'!M18+'COLÉGIO ANGLICANO DE ARARAS'!M18+'COLEGIO VICENTINO PADRE CORRÊA'!M18+'ESCOLA NOSSA SENHORA DE FÁTIMA'!M18+'ESCOLA PAROQUIAL DA ALCOBAÇA'!M18+'ESCOLA PAROQUIAL DO LOTEAMENTO '!M18+'ESCOLA PAROQUIAL SANTA BERNADET'!M18+'ESCOLA SÃO GERALDO'!M18+'ESCOLA SANTO ANTÔNIO'!M18+'LICEU SÃO JOSÉ DE ITAIPAVA'!M18+'ESCOLA SÃO JOSÉ DO CAETITU'!M18+'CEI ASSOCIAÇÃO BENEFICENTE FAZE'!M18+'CEI CASA DA SOLIDARIEDADE DE NO'!M18+'CEI LULU MONTEIRO DE CASTRO'!M18+'CEI SÃO JOÃO BATISTA'!M18+'CEI SÃO FRANCISCO ASSIS'!M18+'CEI A SEMENTEIRA'!M18+'CEI FREI LEÃO'!M18+'CEI ROMANO CANAVESE'!M18+'CEI ANDRÉ VANZAN'!M18+'CEI CRIANÇA SANTA EDWIGES'!M18+'CENTRO DE EDUCAÇÃO INFANTIL IRM'!M18+'CEI PEDRAS BRANCAS'!M18+'CEI INÊS BELARMINO DE SOUZA'!M18+'CEI PROFª ROSANGELA DA SILVA LE'!M18+'CEI VILA SAO JOSE'!M18+'CEI MARIA THEREZA KLING DO VALL'!M18+'CEI DEISE ELOY GOMES'!M18+'CENTRO PAROQUIAL DE EDUCAÇÃO IN'!M18+'CEI VISTA ALEGRE'!M18+'CEI ALDEIA DA CRIANCA'!M18+'CEI DÉA LÚCIA CORDEIRO'!M18+'CENTRO DE EDUCAÇÃO INFANTIL CAR'!M18+'CEI IRMÃ SILVANA'!M18+'CEI MARLI SOARES FERREIRA NETTO'!M18+'CEI PROFª SONIA REGINA SCUDESE '!M18+'CEI DONA ESPERANZA DE BOURBON D'!M18+'CEI PREFEITO SÉRGIO FADEL'!M18+'CEI ANDRÉ REBOUÇAS'!M18+'CENTRO DE EDUCAÇÃO INFANTIL CHI'!M18+'CEI TIA ALICE'!M18+'CEI TERRA SANTA'!M18+'CEI JORGE ROLANDO DA SILVA'!M18+'CEI CARANGOLA'!M18+'CEI CÉLIA LÔBO PAULO'!M18+'CEI LIONS CLUBE DE PETRÓPOLIS'!M18+'CEI PROFª GRAÇA COSTA'!M18+'CEI ANGELA MARIA DA CONCEIÇÃO S'!M18+'CEI LUIZ MARCHIORI'!M18+'CEI PROFª MARLUCE DE SOUZA PEST'!M18+'CEI OLÍVIA MACHADO DA COSTA NOG'!M18+'CEI VILA IPANEMA'!M18+'CEI VILA LEOPOLDINA'!M18+'CENTRO DE EDUCAÇÃO INFANTIL CAS'!M18+'CEI PRIMEIRA INFÂNCIA'!M18+'CEI PROFª DORA KILLER'!M18+'CEI PROFª PATRÍCIA FERREIRA E S'!M18+'CEI DRA ZILDA ARNS NEUMANN'!M18+'CEI DENISE BESSA DE OLIVA MAYA'!M18+'CEI GIUSEPPE-NEVA VOLONTERIO'!M18+'CENTRO DE EDUCAÇÃO INFANTIL LOT'!M18+'CEI IRINEU MARINHO'!M18+'CEI OSWALDO CRUZ'!M18+'CEI ANA CAROLINA TELLES'!M18+'CEI JOSÉ GONÇALVES DA MOTTA'!M18+'CEI SAGRADA FAMÍLIA'!M18+'CEI PROFª HERMÍNIA MATHEUS'!M18+'CENTRO DE EDUCAÇÃO INFANTIL PRO'!M18+'CEI MONSENHOR PAULO ELIAS DAHER'!M18+'CEI DAGMAR ROLANDO DE OLIVEIRA'!M18+'CENTRO DE EDUCAÇÃO INFANTIL 2'!M18+'CEI BOA VISTA'!M18+'CEI NILO PEÇANHA'!M18+'CENTRO DE EDUCAÇÃO INFANTIL AUG'!M18+'CEI THEREZINHA DE JESUS LIMA'!M18+'CEI VIDEIRINHA'!M18+'CEI PROFª ADRIANA CONSTÂNCIO TR'!M18+'CENTRO DE EDUCAÇÃO INFANTIL SÉR'!M18+'CEI JURACI PINTO DO AMARAL DE C'!M18+'CEI NOSSA SENHORA DA GLÓRIA'!M18+'CEI ALTO INDEPENDÊNCIA'!M18+'CEI SÃO JOSÉ DAS OBLATAS DE NAZ'!M18+'CEI SANTO ANTÔNIO AGOSTINHO'!M18+'CEI SÃO CHARBEL'!M18+'ASSOCIAÇÃO DA CRECHE SÃO FRANCI'!M18+'CEI SÃO JOSÉ DO ITAMARATI'!M18+'ASSOCIAÇÃO RECREAR'!M18+'CRECHE-ESCOLA CASTELO SÃO MANOE'!M18+'CENTRO DE EDUCAÇÃO INFANTIL SÃO'!M18 | E14: ='Entrada de Dados'!L2 | F14: =D14*E14
A15: ='Entrada de Dados'!M5 | B15: ='Entrada de Dados'!M197 | C15: ='E M ROTARY'!D19+'E M DE EDUCAÇÃO ESPECIAL SANTOS'!D19+'LICEU MUN PREFEITO CORDOLINO AM'!D19+'E M PREFEITO JAMIL SABRÁ'!D19+'LICEU MUNICIPAL CARLOS CHAGAS F'!D19+'E M PAULO FREIRE'!D19+'E M PROFª MARIA CAMPOS DA SILVA'!D19+'CASA DA EDUCAÇÃO VISCONDE DE MA'!D19+'CENTRO DE REFERÊNCIA EM EDUCAÇÃ'!D19+'ESCOLA SANTA LUIZA DE MARILLAC'!D19+'ESCOLA DOMÉSTICA NOSSA SENHORA '!D19+'ESCOLA MONSENHOR GENTIL'!D19+'ESCOLA PAROQUIAL NOSSA SENHORA '!D19+'ESCOLA PAROQUIAL SÃO PEDRO DE A'!D19+'CEI TERRA SANTA'!D19+'CEI PRIMEIRA INFÂNCIA'!D19+'CEI PROFª PATRÍCIA FERREIRA E S'!D19+'CEI DRA ZILDA ARNS NEUMANN'!D19+'CENTRO DE EDUCAÇÃO INFANTIL PRO'!D19+'CEI MONSENHOR PAULO ELIAS DAHER'!D19+'COLÉGIO GUNNAR VINGREN DE PETRÓ'!D19+'EDUCANDÁRIO TERRA SANTA'!D19+'CEI LIONS CLUBE DE PETRÓPOLIS'!D19+'ESCOLA PAROQUIAL NOSSA SENHO 2'!D19+'CENTRO DE EDUCAÇÃO INFANTIL IRM'!D19+'E M LUIZ CARLOS SOARES'!D19+'ESCOLA GERMANO VALENTE'!D19+'ESCOLA PAROQUIAL NOSSA SENHO 3'!D19+'CEI JORGE ROLANDO DA SILVA'!D19+'E M CLEMENTE FERNANDES'!D19+'E M GERALDO VENTURA DIAS'!D19+'ESCOLA DAS COMUNIDADES SANTO AN'!D19+'CEI PROFª ROSANGELA DA SILVA LE'!D19+'CEI DEISE ELOY GOMES'!D19+'CEI PROFª SONIA REGINA SCUDESE '!D19+'CEI TIA ALICE'!D19+'E M BATAILLARD'!D19+'E M SOROPTIMISTA'!D19+'E M SALVADOR KLING'!D19+'ESCOLA MUNICIPALIZADA FREI ANIC'!D19+'ESCOLA SÃO JUDAS TADEU'!D19+'CEI PEDRAS BRANCAS'!D19+'CEI MARIA THEREZA KLING DO VALL'!D19+'CEI DONA ESPERANZA DE BOURBON D'!D19+'CEI GIUSEPPE-NEVA VOLONTERIO'!D19+'CENTRO DE EDUCAÇÃO INFANTIL SÃO'!D19+'E M LEONARDO BOFF'!D19+'ESCOLA MUNICIPAL GENERAL HEITOR'!D19+'E M JOHANN NOEL'!D19+'ESCOLA SANTA MARIA GORETTI'!D19+'ESCOLA SANTA RITA DE CASSIA'!D19+'ESCOLA SÃO JOÃO BATISTA'!D19+'CEI CASA DA SOLIDARIEDADE DE NO'!D19+'CEI A SEMENTEIRA'!D19+'CEI VILA SAO JOSE'!D19+'E M DR RUBENS DE CASTRO BOMTEMP'!D19+'CEI FREI LEÃO'!D19+'CEI SÃO JOÃO BATISTA'!D19+'CEI JURACI PINTO DO AMARAL DE C'!D19+'E M PEDRO AMADO'!D19+'E M ABELARDO DE LAMARE'!D19+'ESCOLA MUNICIPAL SENADOR MARIO '!D19+'ESCOLA PAROQUIAL SÃO PIO X'!D19+'CEI SÃO CHARBEL'!D19+'E M ROSALINA NICOLAY'!D19+'CEI INÊS BELARMINO DE SOUZA'!D19+'E M PROFª MARIA DA GLÓRIA QUEIR'!D19+'CENTRO EDUCACIONAL COMUNIDADE S'!D19+'CEI ROMANO CANAVESE'!D19+'CEI CÉLIA LÔBO PAULO'!D19+'CEI PROFª DORA KILLER'!D19+'CEI ALTO INDEPENDÊNCIA'!D19+'ESCOLA MUNICIPAL ALTO INDEPENDÊ'!D19+'E M PAPA JOÃO PAULO II'!D19+'CEI ANDRÉ REBOUÇAS'!D19+'CEI PROFª HERMÍNIA MATHEUS'!D19+'ESCOLA MUNICIPAL MAJOR JÚLIO FR'!D19+'E M ALMIRANTE TAMANDARÉ'!D19+'ESCOLA PAROQUIAL CARLOS DEMIÁ'!D19+'CENTRO PAROQUIAL DE EDUCAÇÃO IN'!D19+'CEI IRMÃ SILVANA'!D19+'CEI OLÍVIA MACHADO DA COSTA NOG'!D19+'E M GOVERNADOR MARCELLO ALENCAR'!D19+'E M PROFESSOR FLÁVIO MACIEL'!D19+'E M PROFª JANDIRA PEIXOTO BORDI'!D19+'E M STEFAN ZWEIG'!D19+'ESCOLA PAROQUIAL BOM JESUS'!D19+'CEI MARLI SOARES FERREIRA NETTO'!D19+'CENTRO DE EDUCAÇÃO INFANTIL CHI'!D19+'CEI VILA IPANEMA'!D19+'E M ROBERT KENNEDY'!D19+'ESCOLA MUNICIPAL ANA MOHAMMAD'!D19+'ESCOLA SÃO CRISTÓVÃO'!D19+'CEI DÉA LÚCIA CORDEIRO'!D19+'CEI SAGRADA FAMÍLIA'!D19+'CEI SÃO JOSÉ DAS OBLATAS DE NAZ'!D19+'ESCOLA MUNICIPAL JORGE AMADO'!D19+'E M FÁBRICA DO SABER'!D19+'CIEP BRIZOLÃO 474 MAESTRO GUERR'!D19+'CENTRO DE ENSINO PROF DARCY RIB'!D19+'CEI ANDRÉ VANZAN'!D19+'CENTRO DE EDUCAÇÃO INFANTIL CAR'!D19+'CEI BOA VISTA'!D19+'ASSOCIAÇÃO DA CRECHE SÃO FRANCI'!D19+'ESCOLA MUNICIPAL PAULO SALDANHA'!D19+'ESCOLA MUNICIPAL LÚCIA DE ALMEI'!D19+'E M DOM MANOEL PEDRO DA CUNHA C'!D19+'ESCOLA SÃO GERALDO'!D19+'CEI LULU MONTEIRO DE CASTRO'!D19+'CEI CARANGOLA'!D19+'ASSOCIAÇÃO RECREAR'!D19+'CENTRO DE EDUCAÇÃO INFANTIL CAS'!D19+'E M ROSEMIRA DE OLIVEIRA CAVALC'!D19+'E MZDA CARMEM NUNES MARTINS'!D19+'CEI SÃO JOSÉ DO ITAMARATI'!D19+'E M DUQUE DE CAXIAS'!D19+'CENTRO DE EDUCAÇÃO INFANTIL 2'!D19+'E M ANTÔNIO LEITE GARCIA'!D19+'ESCOLA PAROQUIAL DA ALCOBAÇA'!D19+'CENTRO DE EDUCAÇÃO INFANTIL LOT'!D19+'ESCOLA PAROQUIAL DO LOTEAMENTO '!D19+'E M PROF JOAQUIM DEISTER'!D19+'E M MARIETA GONÇALVES'!D19+'ESCOLA MUNICIPAL ODETTE YOUNG M'!D19+'ESCOLA MUNICIPAL PROFESSOR JOSE'!D19+'E M HERCÍLIA HENRIQUES MORET'!D19+'COLEGIO VICENTINO PADRE CORRÊA'!D19+'CEI PROFª MARLUCE DE SOUZA PEST'!D19+'CEI IRINEU MARINHO'!D19+'CEI DAGMAR ROLANDO DE OLIVEIRA'!D19+'CEI NOSSA SENHORA DA GLÓRIA'!D19+'E M PROF NILTON COSTA PEREIRA D'!D19+'CENTRO DE EDUCAÇÃO INFANTIL SÉR'!D19+'CEI SANTO ANTÔNIO AGOSTINHO'!D19+'CEI OSWALDO CRUZ'!D19+'E M MAGDALENA TAGLIAFERRO'!D19+'ESCOLA SÃO JOSÉ DO CAETITU'!D19+'CRECHE-ESCOLA CASTELO SÃO MANOE'!D19+'CEI THEREZINHA DE JESUS LIMA'!D19+'ESCOLA MUNICIPAL PROFESSOR PAUL'!D19+'COLÉGIO ANGLICANO DE ARARAS'!D19+'ESCOLA PAROQUIAL SANTA BERNADET'!D19+'CEI VISTA ALEGRE'!D19+'CEI DENISE BESSA DE OLIVA MAYA'!D19+'CEI VIDEIRINHA'!D19+'E M AMÉRICO FERNANDES RIBEIRO'!D19+'ESCOLA MUNICIPAL AUGUSTO PUGNAL'!D19+'ESCOLA MUNICIPAL CELINA SCHECHN'!D19+'E M DARCY CORREA DA VEIGA'!D19+'E M DR PAULA BUARQUE'!D19+'LICEU SÃO JOSÉ DE ITAIPAVA'!D19+'CEI LUIZ MARCHIORI'!D19+'CENTRO DE EDUCAÇÃO INFANTIL AUG'!D19+'CEI PROFª ADRIANA CONSTÂNCIO TR'!D19+'E M AMÉLIA ANTUNES RABELLO'!D19+'CEI PREFEITO SÉRGIO FADEL'!D19+'E M DR THEODORO MACHADO'!D19+'ESCOLA SANTO ANTÔNIO'!D19+'E M TAQUARIL'!D19+'E M MONSENHOR JOÃO DE DEUS RODR'!D19+'CENTRO DE REFERÊNCIA EM EDUC 2'!D19+'CEI PROFª GRAÇA COSTA'!D19+'CEI VILA LEOPOLDINA'!D19+'CEI NILO PEÇANHA'!D19+'E MZDA SANTA TEREZINHA'!D19+'CEI CRIANÇA SANTA EDWIGES'!D19+'E M ARNALDO DYCKERHOFF'!D19+'E M CARLOS CANEDO'!D19+'E M BEATRIZ ZALESKI'!D19+'E M ANTÔNIO JOSÉ DE LIMA'!D19+'E M FELIX WAN ERVEN DE BARROS'!D19+'ESCOLA MUNICIPAL HILDEBRANDO DE'!D19+'E M OSWALDO DA COSTA FRIAS'!D19+'E MZDA AVELINO DE CARVALHO'!D19+'ESCOLA MUNICIPALIZADA MOYSÉS FU'!D19+'CEI ANGELA MARIA DA CONCEIÇÃO S'!D19+'CEI JOSÉ GONÇALVES DA MOTTA'!D19+'E M DR BARROS FRANCO'!D19+'E M MAJOR THEÓFILO DE CARVALHO'!D19+'E M JOÃO KOPKE'!D19+'CEI ASSOCIAÇÃO BENEFICENTE FAZE'!D19+'ESCOLA SAO FRANCISCO DE ASSIS'!D19+'CEI SÃO FRANCISCO ASSIS'!D19+'CEI ALDEIA DA CRIANCA'!D19+'ESCOLA MUNICIPAL ODETTE FONSECA'!D19+'CEI ANA CAROLINA TELLES'!D19+'E M SEBASTIÃO LACERDA'!D19+'E M DOM PEDRO DE ALCÂNTARA'!D19+'ESCOLA NOSSA SENHORA DE FÁTIMA'!D19+'ESCOLA PAROQUIAL SÃO FRANCISCO '!D19+'E M MONSENHOR CIRILLO CALAON'!D19 | D15: ='E M ABELARDO DE LAMARE'!M19+'E M BATAILLARD'!M19+'E M LEONARDO BOFF'!M19+'E M CLEMENTE FERNANDES'!M19+'E M DOM PEDRO DE ALCÂNTARA'!M19+'E M DUQUE DE CAXIAS'!M19+'E M LUIZ CARLOS SOARES'!M19+'ESCOLA MUNICIPAL GENERAL HEITOR'!M19+'E M JOÃO KOPKE'!M19+'ESCOLA MUNICIPAL ODETTE FONSECA'!M19+'E M GOVERNADOR MARCELLO ALENCAR'!M19+'E M PROF JOAQUIM DEISTER'!M19+'E M ROBERT KENNEDY'!M19+'E M ROTARY'!M19+'E M ROSALINA NICOLAY'!M19+'E M DE EDUCAÇÃO ESPECIAL SANTOS'!M19+'E M SOROPTIMISTA'!M19+'LICEU MUN PREFEITO CORDOLINO AM'!M19+'E M ANTÔNIO LEITE GARCIA'!M19+'ESCOLA MUNICIPAL JORGE AMADO'!M19+'ESCOLA MUNICIPAL LÚCIA DE ALMEI'!M19+'E M MAGDALENA TAGLIAFERRO'!M19+'ESCOLA MUNICIPAL MAJOR JÚLIO FR'!M19+'E M MARIETA GONÇALVES'!M19+'ESCOLA MUNICIPAL ODETTE YOUNG M'!M19+'E M FÁBRICA DO SABER'!M19+'ESCOLA MUNICIPAL PROFESSOR PAUL'!M19+'E M ROSEMIRA DE OLIVEIRA CAVALC'!M19+'E M AMÉLIA ANTUNES RABELLO'!M19+'ESCOLA MUNICIPAL AUGUSTO PUGNAL'!M19+'ESCOLA MUNICIPAL CELINA SCHECHN'!M19+'E M DARCY CORREA DA VEIGA'!M19+'E M DR PAULA BUARQUE'!M19+'E M DR THEODORO MACHADO'!M19+'E M ARNALDO DYCKERHOFF'!M19+'E M CARLOS CANEDO'!M19+'E M DR BARROS FRANCO'!M19+'E M MAJOR THEÓFILO DE CARVALHO'!M19+'E M TAQUARIL'!M19+'E M BEATRIZ ZALESKI'!M19+'E M ANTÔNIO JOSÉ DE LIMA'!M19+'E M FELIX WAN ERVEN DE BARROS'!M19+'ESCOLA MUNICIPAL HILDEBRANDO DE'!M19+'E M OSWALDO DA COSTA FRIAS'!M19+'E MZDA CARMEM NUNES MARTINS'!M19+'E MZDA AVELINO DE CARVALHO'!M19+'E M GERALDO VENTURA DIAS'!M19+'E M SALVADOR KLING'!M19+'E M PREFEITO JAMIL SABRÁ'!M19+'LICEU MUNICIPAL CARLOS CHAGAS F'!M19+'ESCOLA MUNICIPAL ANA MOHAMMAD'!M19+'ESCOLA MUNICIPAL ALTO INDEPENDÊ'!M19+'E M ALMIRANTE TAMANDARÉ'!M19+'ESCOLA MUNICIPALIZADA FREI ANIC'!M19+'E M PEDRO AMADO'!M19+'E M PROFª MARIA DA GLÓRIA QUEIR'!M19+'E M SEBASTIÃO LACERDA'!M19+'E M PROFESSOR FLÁVIO MACIEL'!M19+'ESCOLA MUNICIPAL PAULO SALDANHA'!M19+'ESCOLA MUNICIPAL PROFESSOR JOSE'!M19+'E M MONSENHOR CIRILLO CALAON'!M19+'E M AMÉRICO FERNANDES RIBEIRO'!M19+'E M PROFª JANDIRA PEIXOTO BORDI'!M19+'E M MONSENHOR JOÃO DE DEUS RODR'!M19+'E M DOM MANOEL PEDRO DA CUNHA C'!M19+'E M JOHANN NOEL'!M19+'E MZDA SANTA TEREZINHA'!M19+'E M PAPA JOÃO PAULO II'!M19+'E M STEFAN ZWEIG'!M19+'ESCOLA MUNICIPAL SENADOR MARIO '!M19+'E M DR RUBENS DE CASTRO BOMTEMP'!M19+'E M PAULO FREIRE'!M19+'E M PROFª MARIA CAMPOS DA SILVA'!M19+'E M HERCÍLIA HENRIQUES MORET'!M19+'ESCOLA MUNICIPALIZADA MOYSÉS FU'!M19+'CIEP BRIZOLÃO 474 MAESTRO GUERR'!M19+'CENTRO DE ENSINO PROF DARCY RIB'!M19+'CASA DA EDUCAÇÃO VISCONDE DE MA'!M19+'CENTRO DE REFERÊNCIA EM EDUCAÇÃ'!M19+'E M PROF NILTON COSTA PEREIRA D'!M19+'COLÉGIO GUNNAR VINGREN DE PETRÓ'!M19+'CENTRO DE REFERÊNCIA EM EDUC 2'!M19+'ESCOLA SANTA LUIZA DE MARILLAC'!M19+'CENTRO EDUCACIONAL COMUNIDADE S'!M19+'EDUCANDÁRIO TERRA SANTA'!M19+'ESCOLA GERMANO VALENTE'!M19+'ESCOLA DAS COMUNIDADES SANTO AN'!M19+'ESCOLA DOMÉSTICA NOSSA SENHORA '!M19+'ESCOLA PAROQUIAL NOSSA SENHO 3'!M19+'ESCOLA MONSENHOR GENTIL'!M19+'ESCOLA PAROQUIAL BOM JESUS'!M19+'ESCOLA PAROQUIAL CARLOS DEMIÁ'!M19+'ESCOLA PAROQUIAL NOSSA SENHO 2'!M19+'ESCOLA PAROQUIAL NOSSA SENHORA '!M19+'ESCOLA PAROQUIAL SÃO PEDRO DE A'!M19+'ESCOLA SANTA MARIA GORETTI'!M19+'ESCOLA SANTA RITA DE CASSIA'!M19+'ESCOLA SÃO CRISTÓVÃO'!M19+'ESCOLA PAROQUIAL SÃO FRANCISCO '!M19+'ESCOLA SAO FRANCISCO DE ASSIS'!M19+'ESCOLA SÃO JOÃO BATISTA'!M19+'ESCOLA SÃO JUDAS TADEU'!M19+'ESCOLA PAROQUIAL SÃO PIO X'!M19+'COLÉGIO ANGLICANO DE ARARAS'!M19+'COLEGIO VICENTINO PADRE CORRÊA'!M19+'ESCOLA NOSSA SENHORA DE FÁTIMA'!M19+'ESCOLA PAROQUIAL DA ALCOBAÇA'!M19+'ESCOLA PAROQUIAL DO LOTEAMENTO '!M19+'ESCOLA PAROQUIAL SANTA BERNADET'!M19+'ESCOLA SÃO GERALDO'!M19+'ESCOLA SANTO ANTÔNIO'!M19+'LICEU SÃO JOSÉ DE ITAIPAVA'!M19+'ESCOLA SÃO JOSÉ DO CAETITU'!M19+'CEI ASSOCIAÇÃO BENEFICENTE FAZE'!M19+'CEI CASA DA SOLIDARIEDADE DE NO'!M19+'CEI LULU MONTEIRO DE CASTRO'!M19+'CEI SÃO JOÃO BATISTA'!M19+'CEI SÃO FRANCISCO ASSIS'!M19+'CEI A SEMENTEIRA'!M19+'CEI FREI LEÃO'!M19+'CEI ROMANO CANAVESE'!M19+'CEI ANDRÉ VANZAN'!M19+'CEI CRIANÇA SANTA EDWIGES'!M19+'CENTRO DE EDUCAÇÃO INFANTIL IRM'!M19+'CEI PEDRAS BRANCAS'!M19+'CEI INÊS BELARMINO DE SOUZA'!M19+'CEI PROFª ROSANGELA DA SILVA LE'!M19+'CEI VILA SAO JOSE'!M19+'CEI MARIA THEREZA KLING DO VALL'!M19+'CEI DEISE ELOY GOMES'!M19+'CENTRO PAROQUIAL DE EDUCAÇÃO IN'!M19+'CEI VISTA ALEGRE'!M19+'CEI ALDEIA DA CRIANCA'!M19+'CEI DÉA LÚCIA CORDEIRO'!M19+'CENTRO DE EDUCAÇÃO INFANTIL CAR'!M19+'CEI IRMÃ SILVANA'!M19+'CEI MARLI SOARES FERREIRA NETTO'!M19+'CEI PROFª SONIA REGINA SCUDESE '!M19+'CEI DONA ESPERANZA DE BOURBON D'!M19+'CEI PREFEITO SÉRGIO FADEL'!M19+'CEI ANDRÉ REBOUÇAS'!M19+'CENTRO DE EDUCAÇÃO INFANTIL CHI'!M19+'CEI TIA ALICE'!M19+'CEI TERRA SANTA'!M19+'CEI JORGE ROLANDO DA SILVA'!M19+'CEI CARANGOLA'!M19+'CEI CÉLIA LÔBO PAULO'!M19+'CEI LIONS CLUBE DE PETRÓPOLIS'!M19+'CEI PROFª GRAÇA COSTA'!M19+'CEI ANGELA MARIA DA CONCEIÇÃO S'!M19+'CEI LUIZ MARCHIORI'!M19+'CEI PROFª MARLUCE DE SOUZA PEST'!M19+'CEI OLÍVIA MACHADO DA COSTA NOG'!M19+'CEI VILA IPANEMA'!M19+'CEI VILA LEOPOLDINA'!M19+'CENTRO DE EDUCAÇÃO INFANTIL CAS'!M19+'CEI PRIMEIRA INFÂNCIA'!M19+'CEI PROFª DORA KILLER'!M19+'CEI PROFª PATRÍCIA FERREIRA E S'!M19+'CEI DRA ZILDA ARNS NEUMANN'!M19+'CEI DENISE BESSA DE OLIVA MAYA'!M19+'CEI GIUSEPPE-NEVA VOLONTERIO'!M19+'CENTRO DE EDUCAÇÃO INFANTIL LOT'!M19+'CEI IRINEU MARINHO'!M19+'CEI OSWALDO CRUZ'!M19+'CEI ANA CAROLINA TELLES'!M19+'CEI JOSÉ GONÇALVES DA MOTTA'!M19+'CEI SAGRADA FAMÍLIA'!M19+'CEI PROFª HERMÍNIA MATHEUS'!M19+'CENTRO DE EDUCAÇÃO INFANTIL PRO'!M19+'CEI MONSENHOR PAULO ELIAS DAHER'!M19+'CEI DAGMAR ROLANDO DE OLIVEIRA'!M19+'CENTRO DE EDUCAÇÃO INFANTIL 2'!M19+'CEI BOA VISTA'!M19+'CEI NILO PEÇANHA'!M19+'CENTRO DE EDUCAÇÃO INFANTIL AUG'!M19+'CEI THEREZINHA DE JESUS LIMA'!M19+'CEI VIDEIRINHA'!M19+'CEI PROFª ADRIANA CONSTÂNCIO TR'!M19+'CENTRO DE EDUCAÇÃO INFANTIL SÉR'!M19+'CEI JURACI PINTO DO AMARAL DE C'!M19+'CEI NOSSA SENHORA DA GLÓRIA'!M19+'CEI ALTO INDEPENDÊNCIA'!M19+'CEI SÃO JOSÉ DAS OBLATAS DE NAZ'!M19+'CEI SANTO ANTÔNIO AGOSTINHO'!M19+'CEI SÃO CHARBEL'!M19+'ASSOCIAÇÃO DA CRECHE SÃO FRANCI'!M19+'CEI SÃO JOSÉ DO ITAMARATI'!M19+'ASSOCIAÇÃO RECREAR'!M19+'CRECHE-ESCOLA CASTELO SÃO MANOE'!M19+'CENTRO DE EDUCAÇÃO INFANTIL SÃO'!M19 | E15: ='Entrada de Dados'!M2 | F15: =D15*E15
A16: ='Entrada de Dados'!N5 | B16: ='Entrada de Dados'!N197 | C16: ='E M ROTARY'!D20+'E M DE EDUCAÇÃO ESPECIAL SANTOS'!D20+'LICEU MUN PREFEITO CORDOLINO AM'!D20+'E M PREFEITO JAMIL SABRÁ'!D20+'LICEU MUNICIPAL CARLOS CHAGAS F'!D20+'E M PAULO FREIRE'!D20+'E M PROFª MARIA CAMPOS DA SILVA'!D20+'CASA DA EDUCAÇÃO VISCONDE DE MA'!D20+'CENTRO DE REFERÊNCIA EM EDUCAÇÃ'!D20+'ESCOLA SANTA LUIZA DE MARILLAC'!D20+'ESCOLA DOMÉSTICA NOSSA SENHORA '!D20+'ESCOLA MONSENHOR GENTIL'!D20+'ESCOLA PAROQUIAL NOSSA SENHORA '!D20+'ESCOLA PAROQUIAL SÃO PEDRO DE A'!D20+'CEI TERRA SANTA'!D20+'CEI PRIMEIRA INFÂNCIA'!D20+'CEI PROFª PATRÍCIA FERREIRA E S'!D20+'CEI DRA ZILDA ARNS NEUMANN'!D20+'CENTRO DE EDUCAÇÃO INFANTIL PRO'!D20+'CEI MONSENHOR PAULO ELIAS DAHER'!D20+'COLÉGIO GUNNAR VINGREN DE PETRÓ'!D20+'EDUCANDÁRIO TERRA SANTA'!D20+'CEI LIONS CLUBE DE PETRÓPOLIS'!D20+'ESCOLA PAROQUIAL NOSSA SENHO 2'!D20+'CENTRO DE EDUCAÇÃO INFANTIL IRM'!D20+'E M LUIZ CARLOS SOARES'!D20+'ESCOLA GERMANO VALENTE'!D20+'ESCOLA PAROQUIAL NOSSA SENHO 3'!D20+'CEI JORGE ROLANDO DA SILVA'!D20+'E M CLEMENTE FERNANDES'!D20+'E M GERALDO VENTURA DIAS'!D20+'ESCOLA DAS COMUNIDADES SANTO AN'!D20+'CEI PROFª ROSANGELA DA SILVA LE'!D20+'CEI DEISE ELOY GOMES'!D20+'CEI PROFª SONIA REGINA SCUDESE '!D20+'CEI TIA ALICE'!D20+'E M BATAILLARD'!D20+'E M SOROPTIMISTA'!D20+'E M SALVADOR KLING'!D20+'ESCOLA MUNICIPALIZADA FREI ANIC'!D20+'ESCOLA SÃO JUDAS TADEU'!D20+'CEI PEDRAS BRANCAS'!D20+'CEI MARIA THEREZA KLING DO VALL'!D20+'CEI DONA ESPERANZA DE BOURBON D'!D20+'CEI GIUSEPPE-NEVA VOLONTERIO'!D20+'CENTRO DE EDUCAÇÃO INFANTIL SÃO'!D20+'E M LEONARDO BOFF'!D20+'ESCOLA MUNICIPAL GENERAL HEITOR'!D20+'E M JOHANN NOEL'!D20+'ESCOLA SANTA MARIA GORETTI'!D20+'ESCOLA SANTA RITA DE CASSIA'!D20+'ESCOLA SÃO JOÃO BATISTA'!D20+'CEI CASA DA SOLIDARIEDADE DE NO'!D20+'CEI A SEMENTEIRA'!D20+'CEI VILA SAO JOSE'!D20+'E M DR RUBENS DE CASTRO BOMTEMP'!D20+'CEI FREI LEÃO'!D20+'CEI SÃO JOÃO BATISTA'!D20+'CEI JURACI PINTO DO AMARAL DE C'!D20+'E M PEDRO AMADO'!D20+'E M ABELARDO DE LAMARE'!D20+'ESCOLA MUNICIPAL SENADOR MARIO '!D20+'ESCOLA PAROQUIAL SÃO PIO X'!D20+'CEI SÃO CHARBEL'!D20+'E M ROSALINA NICOLAY'!D20+'CEI INÊS BELARMINO DE SOUZA'!D20+'E M PROFª MARIA DA GLÓRIA QUEIR'!D20+'CENTRO EDUCACIONAL COMUNIDADE S'!D20+'CEI ROMANO CANAVESE'!D20+'CEI CÉLIA LÔBO PAULO'!D20+'CEI PROFª DORA KILLER'!D20+'CEI ALTO INDEPENDÊNCIA'!D20+'ESCOLA MUNICIPAL ALTO INDEPENDÊ'!D20+'E M PAPA JOÃO PAULO II'!D20+'CEI ANDRÉ REBOUÇAS'!D20+'CEI PROFª HERMÍNIA MATHEUS'!D20+'ESCOLA MUNICIPAL MAJOR JÚLIO FR'!D20+'E M ALMIRANTE TAMANDARÉ'!D20+'ESCOLA PAROQUIAL CARLOS DEMIÁ'!D20+'CENTRO PAROQUIAL DE EDUCAÇÃO IN'!D20+'CEI IRMÃ SILVANA'!D20+'CEI OLÍVIA MACHADO DA COSTA NOG'!D20+'E M GOVERNADOR MARCELLO ALENCAR'!D20+'E M PROFESSOR FLÁVIO MACIEL'!D20+'E M PROFª JANDIRA PEIXOTO BORDI'!D20+'E M STEFAN ZWEIG'!D20+'ESCOLA PAROQUIAL BOM JESUS'!D20+'CEI MARLI SOARES FERREIRA NETTO'!D20+'CENTRO DE EDUCAÇÃO INFANTIL CHI'!D20+'CEI VILA IPANEMA'!D20+'E M ROBERT KENNEDY'!D20+'ESCOLA MUNICIPAL ANA MOHAMMAD'!D20+'ESCOLA SÃO CRISTÓVÃO'!D20+'CEI DÉA LÚCIA CORDEIRO'!D20+'CEI SAGRADA FAMÍLIA'!D20+'CEI SÃO JOSÉ DAS OBLATAS DE NAZ'!D20+'ESCOLA MUNICIPAL JORGE AMADO'!D20+'E M FÁBRICA DO SABER'!D20+'CIEP BRIZOLÃO 474 MAESTRO GUERR'!D20+'CENTRO DE ENSINO PROF DARCY RIB'!D20+'CEI ANDRÉ VANZAN'!D20+'CENTRO DE EDUCAÇÃO INFANTIL CAR'!D20+'CEI BOA VISTA'!D20+'ASSOCIAÇÃO DA CRECHE SÃO FRANCI'!D20+'ESCOLA MUNICIPAL PAULO SALDANHA'!D20+'ESCOLA MUNICIPAL LÚCIA DE ALMEI'!D20+'E M DOM MANOEL PEDRO DA CUNHA C'!D20+'ESCOLA SÃO GERALDO'!D20+'CEI LULU MONTEIRO DE CASTRO'!D20+'CEI CARANGOLA'!D20+'ASSOCIAÇÃO RECREAR'!D20+'CENTRO DE EDUCAÇÃO INFANTIL CAS'!D20+'E M ROSEMIRA DE OLIVEIRA CAVALC'!D20+'E MZDA CARMEM NUNES MARTINS'!D20+'CEI SÃO JOSÉ DO ITAMARATI'!D20+'E M DUQUE DE CAXIAS'!D20+'CENTRO DE EDUCAÇÃO INFANTIL 2'!D20+'E M ANTÔNIO LEITE GARCIA'!D20+'ESCOLA PAROQUIAL DA ALCOBAÇA'!D20+'CENTRO DE EDUCAÇÃO INFANTIL LOT'!D20+'ESCOLA PAROQUIAL DO LOTEAMENTO '!D20+'E M PROF JOAQUIM DEISTER'!D20+'E M MARIETA GONÇALVES'!D20+'ESCOLA MUNICIPAL ODETTE YOUNG M'!D20+'ESCOLA MUNICIPAL PROFESSOR JOSE'!D20+'E M HERCÍLIA HENRIQUES MORET'!D20+'COLEGIO VICENTINO PADRE CORRÊA'!D20+'CEI PROFª MARLUCE DE SOUZA PEST'!D20+'CEI IRINEU MARINHO'!D20+'CEI DAGMAR ROLANDO DE OLIVEIRA'!D20+'CEI NOSSA SENHORA DA GLÓRIA'!D20+'E M PROF NILTON COSTA PEREIRA D'!D20+'CENTRO DE EDUCAÇÃO INFANTIL SÉR'!D20+'CEI SANTO ANTÔNIO AGOSTINHO'!D20+'CEI OSWALDO CRUZ'!D20+'E M MAGDALENA TAGLIAFERRO'!D20+'ESCOLA SÃO JOSÉ DO CAETITU'!D20+'CRECHE-ESCOLA CASTELO SÃO MANOE'!D20+'CEI THEREZINHA DE JESUS LIMA'!D20+'ESCOLA MUNICIPAL PROFESSOR PAUL'!D20+'COLÉGIO ANGLICANO DE ARARAS'!D20+'ESCOLA PAROQUIAL SANTA BERNADET'!D20+'CEI VISTA ALEGRE'!D20+'CEI DENISE BESSA DE OLIVA MAYA'!D20+'CEI VIDEIRINHA'!D20+'E M AMÉRICO FERNANDES RIBEIRO'!D20+'ESCOLA MUNICIPAL AUGUSTO PUGNAL'!D20+'ESCOLA MUNICIPAL CELINA SCHECHN'!D20+'E M DARCY CORREA DA VEIGA'!D20+'E M DR PAULA BUARQUE'!D20+'LICEU SÃO JOSÉ DE ITAIPAVA'!D20+'CEI LUIZ MARCHIORI'!D20+'CENTRO DE EDUCAÇÃO INFANTIL AUG'!D20+'CEI PROFª ADRIANA CONSTÂNCIO TR'!D20+'E M AMÉLIA ANTUNES RABELLO'!D20+'CEI PREFEITO SÉRGIO FADEL'!D20+'E M DR THEODORO MACHADO'!D20+'ESCOLA SANTO ANTÔNIO'!D20+'E M TAQUARIL'!D20+'E M MONSENHOR JOÃO DE DEUS RODR'!D20+'CENTRO DE REFERÊNCIA EM EDUC 2'!D20+'CEI PROFª GRAÇA COSTA'!D20+'CEI VILA LEOPOLDINA'!D20+'CEI NILO PEÇANHA'!D20+'E MZDA SANTA TEREZINHA'!D20+'CEI CRIANÇA SANTA EDWIGES'!D20+'E M ARNALDO DYCKERHOFF'!D20+'E M CARLOS CANEDO'!D20+'E M BEATRIZ ZALESKI'!D20+'E M ANTÔNIO JOSÉ DE LIMA'!D20+'E M FELIX WAN ERVEN DE BARROS'!D20+'ESCOLA MUNICIPAL HILDEBRANDO DE'!D20+'E M OSWALDO DA COSTA FRIAS'!D20+'E MZDA AVELINO DE CARVALHO'!D20+'ESCOLA MUNICIPALIZADA MOYSÉS FU'!D20+'CEI ANGELA MARIA DA CONCEIÇÃO S'!D20+'CEI JOSÉ GONÇALVES DA MOTTA'!D20+'E M DR BARROS FRANCO'!D20+'E M MAJOR THEÓFILO DE CARVALHO'!D20+'E M JOÃO KOPKE'!D20+'CEI ASSOCIAÇÃO BENEFICENTE FAZE'!D20+'ESCOLA SAO FRANCISCO DE ASSIS'!D20+'CEI SÃO FRANCISCO ASSIS'!D20+'CEI ALDEIA DA CRIANCA'!D20+'ESCOLA MUNICIPAL ODETTE FONSECA'!D20+'CEI ANA CAROLINA TELLES'!D20+'E M SEBASTIÃO LACERDA'!D20+'E M DOM PEDRO DE ALCÂNTARA'!D20+'ESCOLA NOSSA SENHORA DE FÁTIMA'!D20+'ESCOLA PAROQUIAL SÃO FRANCISCO '!D20+'E M MONSENHOR CIRILLO CALAON'!D20 | D16: ='E M ABELARDO DE LAMARE'!M20+'E M BATAILLARD'!M20+'E M LEONARDO BOFF'!M20+'E M CLEMENTE FERNANDES'!M20+'E M DOM PEDRO DE ALCÂNTARA'!M20+'E M DUQUE DE CAXIAS'!M20+'E M LUIZ CARLOS SOARES'!M20+'ESCOLA MUNICIPAL GENERAL HEITOR'!M20+'E M JOÃO KOPKE'!M20+'ESCOLA MUNICIPAL ODETTE FONSECA'!M20+'E M GOVERNADOR MARCELLO ALENCAR'!M20+'E M PROF JOAQUIM DEISTER'!M20+'E M ROBERT KENNEDY'!M20+'E M ROTARY'!M20+'E M ROSALINA NICOLAY'!M20+'E M DE EDUCAÇÃO ESPECIAL SANTOS'!M20+'E M SOROPTIMISTA'!M20+'LICEU MUN PREFEITO CORDOLINO AM'!M20+'E M ANTÔNIO LEITE GARCIA'!M20+'ESCOLA MUNICIPAL JORGE AMADO'!M20+'ESCOLA MUNICIPAL LÚCIA DE ALMEI'!M20+'E M MAGDALENA TAGLIAFERRO'!M20+'ESCOLA MUNICIPAL MAJOR JÚLIO FR'!M20+'E M MARIETA GONÇALVES'!M20+'ESCOLA MUNICIPAL ODETTE YOUNG M'!M20+'E M FÁBRICA DO SABER'!M20+'ESCOLA MUNICIPAL PROFESSOR PAUL'!M20+'E M ROSEMIRA DE OLIVEIRA CAVALC'!M20+'E M AMÉLIA ANTUNES RABELLO'!M20+'ESCOLA MUNICIPAL AUGUSTO PUGNAL'!M20+'ESCOLA MUNICIPAL CELINA SCHECHN'!M20+'E M DARCY CORREA DA VEIGA'!M20+'E M DR PAULA BUARQUE'!M20+'E M DR THEODORO MACHADO'!M20+'E M ARNALDO DYCKERHOFF'!M20+'E M CARLOS CANEDO'!M20+'E M DR BARROS FRANCO'!M20+'E M MAJOR THEÓFILO DE CARVALHO'!M20+'E M TAQUARIL'!M20+'E M BEATRIZ ZALESKI'!M20+'E M ANTÔNIO JOSÉ DE LIMA'!M20+'E M FELIX WAN ERVEN DE BARROS'!M20+'ESCOLA MUNICIPAL HILDEBRANDO DE'!M20+'E M OSWALDO DA COSTA FRIAS'!M20+'E MZDA CARMEM NUNES MARTINS'!M20+'E MZDA AVELINO DE CARVALHO'!M20+'E M GERALDO VENTURA DIAS'!M20+'E M SALVADOR KLING'!M20+'E M PREFEITO JAMIL SABRÁ'!M20+'LICEU MUNICIPAL CARLOS CHAGAS F'!M20+'ESCOLA MUNICIPAL ANA MOHAMMAD'!M20+'ESCOLA MUNICIPAL ALTO INDEPENDÊ'!M20+'E M ALMIRANTE TAMANDARÉ'!M20+'ESCOLA MUNICIPALIZADA FREI ANIC'!M20+'E M PEDRO AMADO'!M20+'E M PROFª MARIA DA GLÓRIA QUEIR'!M20+'E M SEBASTIÃO LACERDA'!M20+'E M PROFESSOR FLÁVIO MACIEL'!M20+'ESCOLA MUNICIPAL PAULO SALDANHA'!M20+'ESCOLA MUNICIPAL PROFESSOR JOSE'!M20+'E M MONSENHOR CIRILLO CALAON'!M20+'E M AMÉRICO FERNANDES RIBEIRO'!M20+'E M PROFª JANDIRA PEIXOTO BORDI'!M20+'E M MONSENHOR JOÃO DE DEUS RODR'!M20+'E M DOM MANOEL PEDRO DA CUNHA C'!M20+'E M JOHANN NOEL'!M20+'E MZDA SANTA TEREZINHA'!M20+'E M PAPA JOÃO PAULO II'!M20+'E M STEFAN ZWEIG'!M20+'ESCOLA MUNICIPAL SENADOR MARIO '!M20+'E M DR RUBENS DE CASTRO BOMTEMP'!M20+'E M PAULO FREIRE'!M20+'E M PROFª MARIA CAMPOS DA SILVA'!M20+'E M HERCÍLIA HENRIQUES MORET'!M20+'ESCOLA MUNICIPALIZADA MOYSÉS FU'!M20+'CIEP BRIZOLÃO 474 MAESTRO GUERR'!M20+'CENTRO DE ENSINO PROF DARCY RIB'!M20+'CASA DA EDUCAÇÃO VISCONDE DE MA'!M20+'CENTRO DE REFERÊNCIA EM EDUCAÇÃ'!M20+'E M PROF NILTON COSTA PEREIRA D'!M20+'COLÉGIO GUNNAR VINGREN DE PETRÓ'!M20+'CENTRO DE REFERÊNCIA EM EDUC 2'!M20+'ESCOLA SANTA LUIZA DE MARILLAC'!M20+'CENTRO EDUCACIONAL COMUNIDADE S'!M20+'EDUCANDÁRIO TERRA SANTA'!M20+'ESCOLA GERMANO VALENTE'!M20+'ESCOLA DAS COMUNIDADES SANTO AN'!M20+'ESCOLA DOMÉSTICA NOSSA SENHORA '!M20+'ESCOLA PAROQUIAL NOSSA SENHO 3'!M20+'ESCOLA MONSENHOR GENTIL'!M20+'ESCOLA PAROQUIAL BOM JESUS'!M20+'ESCOLA PAROQUIAL CARLOS DEMIÁ'!M20+'ESCOLA PAROQUIAL NOSSA SENHO 2'!M20+'ESCOLA PAROQUIAL NOSSA SENHORA '!M20+'ESCOLA PAROQUIAL SÃO PEDRO DE A'!M20+'ESCOLA SANTA MARIA GORETTI'!M20+'ESCOLA SANTA RITA DE CASSIA'!M20+'ESCOLA SÃO CRISTÓVÃO'!M20+'ESCOLA PAROQUIAL SÃO FRANCISCO '!M20+'ESCOLA SAO FRANCISCO DE ASSIS'!M20+'ESCOLA SÃO JOÃO BATISTA'!M20+'ESCOLA SÃO JUDAS TADEU'!M20+'ESCOLA PAROQUIAL SÃO PIO X'!M20+'COLÉGIO ANGLICANO DE ARARAS'!M20+'COLEGIO VICENTINO PADRE CORRÊA'!M20+'ESCOLA NOSSA SENHORA DE FÁTIMA'!M20+'ESCOLA PAROQUIAL DA ALCOBAÇA'!M20+'ESCOLA PAROQUIAL DO LOTEAMENTO '!M20+'ESCOLA PAROQUIAL SANTA BERNADET'!M20+'ESCOLA SÃO GERALDO'!M20+'ESCOLA SANTO ANTÔNIO'!M20+'LICEU SÃO JOSÉ DE ITAIPAVA'!M20+'ESCOLA SÃO JOSÉ DO CAETITU'!M20+'CEI ASSOCIAÇÃO BENEFICENTE FAZE'!M20+'CEI CASA DA SOLIDARIEDADE DE NO'!M20+'CEI LULU MONTEIRO DE CASTRO'!M20+'CEI SÃO JOÃO BATISTA'!M20+'CEI SÃO FRANCISCO ASSIS'!M20+'CEI A SEMENTEIRA'!M20+'CEI FREI LEÃO'!M20+'CEI ROMANO CANAVESE'!M20+'CEI ANDRÉ VANZAN'!M20+'CEI CRIANÇA SANTA EDWIGES'!M20+'CENTRO DE EDUCAÇÃO INFANTIL IRM'!M20+'CEI PEDRAS BRANCAS'!M20+'CEI INÊS BELARMINO DE SOUZA'!M20+'CEI PROFª ROSANGELA DA SILVA LE'!M20+'CEI VILA SAO JOSE'!M20+'CEI MARIA THEREZA KLING DO VALL'!M20+'CEI DEISE ELOY GOMES'!M20+'CENTRO PAROQUIAL DE EDUCAÇÃO IN'!M20+'CEI VISTA ALEGRE'!M20+'CEI ALDEIA DA CRIANCA'!M20+'CEI DÉA LÚCIA CORDEIRO'!M20+'CENTRO DE EDUCAÇÃO INFANTIL CAR'!M20+'CEI IRMÃ SILVANA'!M20+'CEI MARLI SOARES FERREIRA NETTO'!M20+'CEI PROFª SONIA REGINA SCUDESE '!M20+'CEI DONA ESPERANZA DE BOURBON D'!M20+'CEI PREFEITO SÉRGIO FADEL'!M20+'CEI ANDRÉ REBOUÇAS'!M20+'CENTRO DE EDUCAÇÃO INFANTIL CHI'!M20+'CEI TIA ALICE'!M20+'CEI TERRA SANTA'!M20+'CEI JORGE ROLANDO DA SILVA'!M20+'CEI CARANGOLA'!M20+'CEI CÉLIA LÔBO PAULO'!M20+'CEI LIONS CLUBE DE PETRÓPOLIS'!M20+'CEI PROFª GRAÇA COSTA'!M20+'CEI ANGELA MARIA DA CONCEIÇÃO S'!M20+'CEI LUIZ MARCHIORI'!M20+'CEI PROFª MARLUCE DE SOUZA PEST'!M20+'CEI OLÍVIA MACHADO DA COSTA NOG'!M20+'CEI VILA IPANEMA'!M20+'CEI VILA LEOPOLDINA'!M20+'CENTRO DE EDUCAÇÃO INFANTIL CAS'!M20+'CEI PRIMEIRA INFÂNCIA'!M20+'CEI PROFª DORA KILLER'!M20+'CEI PROFª PATRÍCIA FERREIRA E S'!M20+'CEI DRA ZILDA ARNS NEUMANN'!M20+'CEI DENISE BESSA DE OLIVA MAYA'!M20+'CEI GIUSEPPE-NEVA VOLONTERIO'!M20+'CENTRO DE EDUCAÇÃO INFANTIL LOT'!M20+'CEI IRINEU MARINHO'!M20+'CEI OSWALDO CRUZ'!M20+'CEI ANA CAROLINA TELLES'!M20+'CEI JOSÉ GONÇALVES DA MOTTA'!M20+'CEI SAGRADA FAMÍLIA'!M20+'CEI PROFª HERMÍNIA MATHEUS'!M20+'CENTRO DE EDUCAÇÃO INFANTIL PRO'!M20+'CEI MONSENHOR PAULO ELIAS DAHER'!M20+'CEI DAGMAR ROLANDO DE OLIVEIRA'!M20+'CENTRO DE EDUCAÇÃO INFANTIL 2'!M20+'CEI BOA VISTA'!M20+'CEI NILO PEÇANHA'!M20+'CENTRO DE EDUCAÇÃO INFANTIL AUG'!M20+'CEI THEREZINHA DE JESUS LIMA'!M20+'CEI VIDEIRINHA'!M20+'CEI PROFª ADRIANA CONSTÂNCIO TR'!M20+'CENTRO DE EDUCAÇÃO INFANTIL SÉR'!M20+'CEI JURACI PINTO DO AMARAL DE C'!M20+'CEI NOSSA SENHORA DA GLÓRIA'!M20+'CEI ALTO INDEPENDÊNCIA'!M20+'CEI SÃO JOSÉ DAS OBLATAS DE NAZ'!M20+'CEI SANTO ANTÔNIO AGOSTINHO'!M20+'CEI SÃO CHARBEL'!M20+'ASSOCIAÇÃO DA CRECHE SÃO FRANCI'!M20+'CEI SÃO JOSÉ DO ITAMARATI'!M20+'ASSOCIAÇÃO RECREAR'!M20+'CRECHE-ESCOLA CASTELO SÃO MANOE'!M20+'CENTRO DE EDUCAÇÃO INFANTIL SÃO'!M20 | E16: ='Entrada de Dados'!N2 | F16: =D16*E16
A17: ='Entrada de Dados'!O5 | B17: ='Entrada de Dados'!O197 | C17: ='E M ROTARY'!D21+'E M DE EDUCAÇÃO ESPECIAL SANTOS'!D21+'LICEU MUN PREFEITO CORDOLINO AM'!D21+'E M PREFEITO JAMIL SABRÁ'!D21+'LICEU MUNICIPAL CARLOS CHAGAS F'!D21+'E M PAULO FREIRE'!D21+'E M PROFª MARIA CAMPOS DA SILVA'!D21+'CASA DA EDUCAÇÃO VISCONDE DE MA'!D21+'CENTRO DE REFERÊNCIA EM EDUCAÇÃ'!D21+'ESCOLA SANTA LUIZA DE MARILLAC'!D21+'ESCOLA DOMÉSTICA NOSSA SENHORA '!D21+'ESCOLA MONSENHOR GENTIL'!D21+'ESCOLA PAROQUIAL NOSSA SENHORA '!D21+'ESCOLA PAROQUIAL SÃO PEDRO DE A'!D21+'CEI TERRA SANTA'!D21+'CEI PRIMEIRA INFÂNCIA'!D21+'CEI PROFª PATRÍCIA FERREIRA E S'!D21+'CEI DRA ZILDA ARNS NEUMANN'!D21+'CENTRO DE EDUCAÇÃO INFANTIL PRO'!D21+'CEI MONSENHOR PAULO ELIAS DAHER'!D21+'COLÉGIO GUNNAR VINGREN DE PETRÓ'!D21+'EDUCANDÁRIO TERRA SANTA'!D21+'CEI LIONS CLUBE DE PETRÓPOLIS'!D21+'ESCOLA PAROQUIAL NOSSA SENHO 2'!D21+'CENTRO DE EDUCAÇÃO INFANTIL IRM'!D21+'E M LUIZ CARLOS SOARES'!D21+'ESCOLA GERMANO VALENTE'!D21+'ESCOLA PAROQUIAL NOSSA SENHO 3'!D21+'CEI JORGE ROLANDO DA SILVA'!D21+'E M CLEMENTE FERNANDES'!D21+'E M GERALDO VENTURA DIAS'!D21+'ESCOLA DAS COMUNIDADES SANTO AN'!D21+'CEI PROFª ROSANGELA DA SILVA LE'!D21+'CEI DEISE ELOY GOMES'!D21+'CEI PROFª SONIA REGINA SCUDESE '!D21+'CEI TIA ALICE'!D21+'E M BATAILLARD'!D21+'E M SOROPTIMISTA'!D21+'E M SALVADOR KLING'!D21+'ESCOLA MUNICIPALIZADA FREI ANIC'!D21+'ESCOLA SÃO JUDAS TADEU'!D21+'CEI PEDRAS BRANCAS'!D21+'CEI MARIA THEREZA KLING DO VALL'!D21+'CEI DONA ESPERANZA DE BOURBON D'!D21+'CEI GIUSEPPE-NEVA VOLONTERIO'!D21+'CENTRO DE EDUCAÇÃO INFANTIL SÃO'!D21+'E M LEONARDO BOFF'!D21+'ESCOLA MUNICIPAL GENERAL HEITOR'!D21+'E M JOHANN NOEL'!D21+'ESCOLA SANTA MARIA GORETTI'!D21+'ESCOLA SANTA RITA DE CASSIA'!D21+'ESCOLA SÃO JOÃO BATISTA'!D21+'CEI CASA DA SOLIDARIEDADE DE NO'!D21+'CEI A SEMENTEIRA'!D21+'CEI VILA SAO JOSE'!D21+'E M DR RUBENS DE CASTRO BOMTEMP'!D21+'CEI FREI LEÃO'!D21+'CEI SÃO JOÃO BATISTA'!D21+'CEI JURACI PINTO DO AMARAL DE C'!D21+'E M PEDRO AMADO'!D21+'E M ABELARDO DE LAMARE'!D21+'ESCOLA MUNICIPAL SENADOR MARIO '!D21+'ESCOLA PAROQUIAL SÃO PIO X'!D21+'CEI SÃO CHARBEL'!D21+'E M ROSALINA NICOLAY'!D21+'CEI INÊS BELARMINO DE SOUZA'!D21+'E M PROFª MARIA DA GLÓRIA QUEIR'!D21+'CENTRO EDUCACIONAL COMUNIDADE S'!D21+'CEI ROMANO CANAVESE'!D21+'CEI CÉLIA LÔBO PAULO'!D21+'CEI PROFª DORA KILLER'!D21+'CEI ALTO INDEPENDÊNCIA'!D21+'ESCOLA MUNICIPAL ALTO INDEPENDÊ'!D21+'E M PAPA JOÃO PAULO II'!D21+'CEI ANDRÉ REBOUÇAS'!D21+'CEI PROFª HERMÍNIA MATHEUS'!D21+'ESCOLA MUNICIPAL MAJOR JÚLIO FR'!D21+'E M ALMIRANTE TAMANDARÉ'!D21+'ESCOLA PAROQUIAL CARLOS DEMIÁ'!D21+'CENTRO PAROQUIAL DE EDUCAÇÃO IN'!D21+'CEI IRMÃ SILVANA'!D21+'CEI OLÍVIA MACHADO DA COSTA NOG'!D21+'E M GOVERNADOR MARCELLO ALENCAR'!D21+'E M PROFESSOR FLÁVIO MACIEL'!D21+'E M PROFª JANDIRA PEIXOTO BORDI'!D21+'E M STEFAN ZWEIG'!D21+'ESCOLA PAROQUIAL BOM JESUS'!D21+'CEI MARLI SOARES FERREIRA NETTO'!D21+'CENTRO DE EDUCAÇÃO INFANTIL CHI'!D21+'CEI VILA IPANEMA'!D21+'E M ROBERT KENNEDY'!D21+'ESCOLA MUNICIPAL ANA MOHAMMAD'!D21+'ESCOLA SÃO CRISTÓVÃO'!D21+'CEI DÉA LÚCIA CORDEIRO'!D21+'CEI SAGRADA FAMÍLIA'!D21+'CEI SÃO JOSÉ DAS OBLATAS DE NAZ'!D21+'ESCOLA MUNICIPAL JORGE AMADO'!D21+'E M FÁBRICA DO SABER'!D21+'CIEP BRIZOLÃO 474 MAESTRO GUERR'!D21+'CENTRO DE ENSINO PROF DARCY RIB'!D21+'CEI ANDRÉ VANZAN'!D21+'CENTRO DE EDUCAÇÃO INFANTIL CAR'!D21+'CEI BOA VISTA'!D21+'ASSOCIAÇÃO DA CRECHE SÃO FRANCI'!D21+'ESCOLA MUNICIPAL PAULO SALDANHA'!D21+'ESCOLA MUNICIPAL LÚCIA DE ALMEI'!D21+'E M DOM MANOEL PEDRO DA CUNHA C'!D21+'ESCOLA SÃO GERALDO'!D21+'CEI LULU MONTEIRO DE CASTRO'!D21+'CEI CARANGOLA'!D21+'ASSOCIAÇÃO RECREAR'!D21+'CENTRO DE EDUCAÇÃO INFANTIL CAS'!D21+'E M ROSEMIRA DE OLIVEIRA CAVALC'!D21+'E MZDA CARMEM NUNES MARTINS'!D21+'CEI SÃO JOSÉ DO ITAMARATI'!D21+'E M DUQUE DE CAXIAS'!D21+'CENTRO DE EDUCAÇÃO INFANTIL 2'!D21+'E M ANTÔNIO LEITE GARCIA'!D21+'ESCOLA PAROQUIAL DA ALCOBAÇA'!D21+'CENTRO DE EDUCAÇÃO INFANTIL LOT'!D21+'ESCOLA PAROQUIAL DO LOTEAMENTO '!D21+'E M PROF JOAQUIM DEISTER'!D21+'E M MARIETA GONÇALVES'!D21+'ESCOLA MUNICIPAL ODETTE YOUNG M'!D21+'ESCOLA MUNICIPAL PROFESSOR JOSE'!D21+'E M HERCÍLIA HENRIQUES MORET'!D21+'COLEGIO VICENTINO PADRE CORRÊA'!D21+'CEI PROFª MARLUCE DE SOUZA PEST'!D21+'CEI IRINEU MARINHO'!D21+'CEI DAGMAR ROLANDO DE OLIVEIRA'!D21+'CEI NOSSA SENHORA DA GLÓRIA'!D21+'E M PROF NILTON COSTA PEREIRA D'!D21+'CENTRO DE EDUCAÇÃO INFANTIL SÉR'!D21+'CEI SANTO ANTÔNIO AGOSTINHO'!D21+'CEI OSWALDO CRUZ'!D21+'E M MAGDALENA TAGLIAFERRO'!D21+'ESCOLA SÃO JOSÉ DO CAETITU'!D21+'CRECHE-ESCOLA CASTELO SÃO MANOE'!D21+'CEI THEREZINHA DE JESUS LIMA'!D21+'ESCOLA MUNICIPAL PROFESSOR PAUL'!D21+'COLÉGIO ANGLICANO DE ARARAS'!D21+'ESCOLA PAROQUIAL SANTA BERNADET'!D21+'CEI VISTA ALEGRE'!D21+'CEI DENISE BESSA DE OLIVA MAYA'!D21+'CEI VIDEIRINHA'!D21+'E M AMÉRICO FERNANDES RIBEIRO'!D21+'ESCOLA MUNICIPAL AUGUSTO PUGNAL'!D21+'ESCOLA MUNICIPAL CELINA SCHECHN'!D21+'E M DARCY CORREA DA VEIGA'!D21+'E M DR PAULA BUARQUE'!D21+'LICEU SÃO JOSÉ DE ITAIPAVA'!D21+'CEI LUIZ MARCHIORI'!D21+'CENTRO DE EDUCAÇÃO INFANTIL AUG'!D21+'CEI PROFª ADRIANA CONSTÂNCIO TR'!D21+'E M AMÉLIA ANTUNES RABELLO'!D21+'CEI PREFEITO SÉRGIO FADEL'!D21+'E M DR THEODORO MACHADO'!D21+'ESCOLA SANTO ANTÔNIO'!D21+'E M TAQUARIL'!D21+'E M MONSENHOR JOÃO DE DEUS RODR'!D21+'CENTRO DE REFERÊNCIA EM EDUC 2'!D21+'CEI PROFª GRAÇA COSTA'!D21+'CEI VILA LEOPOLDINA'!D21+'CEI NILO PEÇANHA'!D21+'E MZDA SANTA TEREZINHA'!D21+'CEI CRIANÇA SANTA EDWIGES'!D21+'E M ARNALDO DYCKERHOFF'!D21+'E M CARLOS CANEDO'!D21+'E M BEATRIZ ZALESKI'!D21+'E M ANTÔNIO JOSÉ DE LIMA'!D21+'E M FELIX WAN ERVEN DE BARROS'!D21+'ESCOLA MUNICIPAL HILDEBRANDO DE'!D21+'E M OSWALDO DA COSTA FRIAS'!D21+'E MZDA AVELINO DE CARVALHO'!D21+'ESCOLA MUNICIPALIZADA MOYSÉS FU'!D21+'CEI ANGELA MARIA DA CONCEIÇÃO S'!D21+'CEI JOSÉ GONÇALVES DA MOTTA'!D21+'E M DR BARROS FRANCO'!D21+'E M MAJOR THEÓFILO DE CARVALHO'!D21+'E M JOÃO KOPKE'!D21+'CEI ASSOCIAÇÃO BENEFICENTE FAZE'!D21+'ESCOLA SAO FRANCISCO DE ASSIS'!D21+'CEI SÃO FRANCISCO ASSIS'!D21+'CEI ALDEIA DA CRIANCA'!D21+'ESCOLA MUNICIPAL ODETTE FONSECA'!D21+'CEI ANA CAROLINA TELLES'!D21+'E M SEBASTIÃO LACERDA'!D21+'E M DOM PEDRO DE ALCÂNTARA'!D21+'ESCOLA NOSSA SENHORA DE FÁTIMA'!D21+'ESCOLA PAROQUIAL SÃO FRANCISCO '!D21+'E M MONSENHOR CIRILLO CALAON'!D21 | D17: ='E M ABELARDO DE LAMARE'!M21+'E M BATAILLARD'!M21+'E M LEONARDO BOFF'!M21+'E M CLEMENTE FERNANDES'!M21+'E M DOM PEDRO DE ALCÂNTARA'!M21+'E M DUQUE DE CAXIAS'!M21+'E M LUIZ CARLOS SOARES'!M21+'ESCOLA MUNICIPAL GENERAL HEITOR'!M21+'E M JOÃO KOPKE'!M21+'ESCOLA MUNICIPAL ODETTE FONSECA'!M21+'E M GOVERNADOR MARCELLO ALENCAR'!M21+'E M PROF JOAQUIM DEISTER'!M21+'E M ROBERT KENNEDY'!M21+'E M ROTARY'!M21+'E M ROSALINA NICOLAY'!M21+'E M DE EDUCAÇÃO ESPECIAL SANTOS'!M21+'E M SOROPTIMISTA'!M21+'LICEU MUN PREFEITO CORDOLINO AM'!M21+'E M ANTÔNIO LEITE GARCIA'!M21+'ESCOLA MUNICIPAL JORGE AMADO'!M21+'ESCOLA MUNICIPAL LÚCIA DE ALMEI'!M21+'E M MAGDALENA TAGLIAFERRO'!M21+'ESCOLA MUNICIPAL MAJOR JÚLIO FR'!M21+'E M MARIETA GONÇALVES'!M21+'ESCOLA MUNICIPAL ODETTE YOUNG M'!M21+'E M FÁBRICA DO SABER'!M21+'ESCOLA MUNICIPAL PROFESSOR PAUL'!M21+'E M ROSEMIRA DE OLIVEIRA CAVALC'!M21+'E M AMÉLIA ANTUNES RABELLO'!M21+'ESCOLA MUNICIPAL AUGUSTO PUGNAL'!M21+'ESCOLA MUNICIPAL CELINA SCHECHN'!M21+'E M DARCY CORREA DA VEIGA'!M21+'E M DR PAULA BUARQUE'!M21+'E M DR THEODORO MACHADO'!M21+'E M ARNALDO DYCKERHOFF'!M21+'E M CARLOS CANEDO'!M21+'E M DR BARROS FRANCO'!M21+'E M MAJOR THEÓFILO DE CARVALHO'!M21+'E M TAQUARIL'!M21+'E M BEATRIZ ZALESKI'!M21+'E M ANTÔNIO JOSÉ DE LIMA'!M21+'E M FELIX WAN ERVEN DE BARROS'!M21+'ESCOLA MUNICIPAL HILDEBRANDO DE'!M21+'E M OSWALDO DA COSTA FRIAS'!M21+'E MZDA CARMEM NUNES MARTINS'!M21+'E MZDA AVELINO DE CARVALHO'!M21+'E M GERALDO VENTURA DIAS'!M21+'E M SALVADOR KLING'!M21+'E M PREFEITO JAMIL SABRÁ'!M21+'LICEU MUNICIPAL CARLOS CHAGAS F'!M21+'ESCOLA MUNICIPAL ANA MOHAMMAD'!M21+'ESCOLA MUNICIPAL ALTO INDEPENDÊ'!M21+'E M ALMIRANTE TAMANDARÉ'!M21+'ESCOLA MUNICIPALIZADA FREI ANIC'!M21+'E M PEDRO AMADO'!M21+'E M PROFª MARIA DA GLÓRIA QUEIR'!M21+'E M SEBASTIÃO LACERDA'!M21+'E M PROFESSOR FLÁVIO MACIEL'!M21+'ESCOLA MUNICIPAL PAULO SALDANHA'!M21+'ESCOLA MUNICIPAL PROFESSOR JOSE'!M21+'E M MONSENHOR CIRILLO CALAON'!M21+'E M AMÉRICO FERNANDES RIBEIRO'!M21+'E M PROFª JANDIRA PEIXOTO BORDI'!M21+'E M MONSENHOR JOÃO DE DEUS RODR'!M21+'E M DOM MANOEL PEDRO DA CUNHA C'!M21+'E M JOHANN NOEL'!M21+'E MZDA SANTA TEREZINHA'!M21+'E M PAPA JOÃO PAULO II'!M21+'E M STEFAN ZWEIG'!M21+'ESCOLA MUNICIPAL SENADOR MARIO '!M21+'E M DR RUBENS DE CASTRO BOMTEMP'!M21+'E M PAULO FREIRE'!M21+'E M PROFª MARIA CAMPOS DA SILVA'!M21+'E M HERCÍLIA HENRIQUES MORET'!M21+'ESCOLA MUNICIPALIZADA MOYSÉS FU'!M21+'CIEP BRIZOLÃO 474 MAESTRO GUERR'!M21+'CENTRO DE ENSINO PROF DARCY RIB'!M21+'CASA DA EDUCAÇÃO VISCONDE DE MA'!M21+'CENTRO DE REFERÊNCIA EM EDUCAÇÃ'!M21+'E M PROF NILTON COSTA PEREIRA D'!M21+'COLÉGIO GUNNAR VINGREN DE PETRÓ'!M21+'CENTRO DE REFERÊNCIA EM EDUC 2'!M21+'ESCOLA SANTA LUIZA DE MARILLAC'!M21+'CENTRO EDUCACIONAL COMUNIDADE S'!M21+'EDUCANDÁRIO TERRA SANTA'!M21+'ESCOLA GERMANO VALENTE'!M21+'ESCOLA DAS COMUNIDADES SANTO AN'!M21+'ESCOLA DOMÉSTICA NOSSA SENHORA '!M21+'ESCOLA PAROQUIAL NOSSA SENHO 3'!M21+'ESCOLA MONSENHOR GENTIL'!M21+'ESCOLA PAROQUIAL BOM JESUS'!M21+'ESCOLA PAROQUIAL CARLOS DEMIÁ'!M21+'ESCOLA PAROQUIAL NOSSA SENHO 2'!M21+'ESCOLA PAROQUIAL NOSSA SENHORA '!M21+'ESCOLA PAROQUIAL SÃO PEDRO DE A'!M21+'ESCOLA SANTA MARIA GORETTI'!M21+'ESCOLA SANTA RITA DE CASSIA'!M21+'ESCOLA SÃO CRISTÓVÃO'!M21+'ESCOLA PAROQUIAL SÃO FRANCISCO '!M21+'ESCOLA SAO FRANCISCO DE ASSIS'!M21+'ESCOLA SÃO JOÃO BATISTA'!M21+'ESCOLA SÃO JUDAS TADEU'!M21+'ESCOLA PAROQUIAL SÃO PIO X'!M21+'COLÉGIO ANGLICANO DE ARARAS'!M21+'COLEGIO VICENTINO PADRE CORRÊA'!M21+'ESCOLA NOSSA SENHORA DE FÁTIMA'!M21+'ESCOLA PAROQUIAL DA ALCOBAÇA'!M21+'ESCOLA PAROQUIAL DO LOTEAMENTO '!M21+'ESCOLA PAROQUIAL SANTA BERNADET'!M21+'ESCOLA SÃO GERALDO'!M21+'ESCOLA SANTO ANTÔNIO'!M21+'LICEU SÃO JOSÉ DE ITAIPAVA'!M21+'ESCOLA SÃO JOSÉ DO CAETITU'!M21+'CEI ASSOCIAÇÃO BENEFICENTE FAZE'!M21+'CEI CASA DA SOLIDARIEDADE DE NO'!M21+'CEI LULU MONTEIRO DE CASTRO'!M21+'CEI SÃO JOÃO BATISTA'!M21+'CEI SÃO FRANCISCO ASSIS'!M21+'CEI A SEMENTEIRA'!M21+'CEI FREI LEÃO'!M21+'CEI ROMANO CANAVESE'!M21+'CEI ANDRÉ VANZAN'!M21+'CEI CRIANÇA SANTA EDWIGES'!M21+'CENTRO DE EDUCAÇÃO INFANTIL IRM'!M21+'CEI PEDRAS BRANCAS'!M21+'CEI INÊS BELARMINO DE SOUZA'!M21+'CEI PROFª ROSANGELA DA SILVA LE'!M21+'CEI VILA SAO JOSE'!M21+'CEI MARIA THEREZA KLING DO VALL'!M21+'CEI DEISE ELOY GOMES'!M21+'CENTRO PAROQUIAL DE EDUCAÇÃO IN'!M21+'CEI VISTA ALEGRE'!M21+'CEI ALDEIA DA CRIANCA'!M21+'CEI DÉA LÚCIA CORDEIRO'!M21+'CENTRO DE EDUCAÇÃO INFANTIL CAR'!M21+'CEI IRMÃ SILVANA'!M21+'CEI MARLI SOARES FERREIRA NETTO'!M21+'CEI PROFª SONIA REGINA SCUDESE '!M21+'CEI DONA ESPERANZA DE BOURBON D'!M21+'CEI PREFEITO SÉRGIO FADEL'!M21+'CEI ANDRÉ REBOUÇAS'!M21+'CENTRO DE EDUCAÇÃO INFANTIL CHI'!M21+'CEI TIA ALICE'!M21+'CEI TERRA SANTA'!M21+'CEI JORGE ROLANDO DA SILVA'!M21+'CEI CARANGOLA'!M21+'CEI CÉLIA LÔBO PAULO'!M21+'CEI LIONS CLUBE DE PETRÓPOLIS'!M21+'CEI PROFª GRAÇA COSTA'!M21+'CEI ANGELA MARIA DA CONCEIÇÃO S'!M21+'CEI LUIZ MARCHIORI'!M21+'CEI PROFª MARLUCE DE SOUZA PEST'!M21+'CEI OLÍVIA MACHADO DA COSTA NOG'!M21+'CEI VILA IPANEMA'!M21+'CEI VILA LEOPOLDINA'!M21+'CENTRO DE EDUCAÇÃO INFANTIL CAS'!M21+'CEI PRIMEIRA INFÂNCIA'!M21+'CEI PROFª DORA KILLER'!M21+'CEI PROFª PATRÍCIA FERREIRA E S'!M21+'CEI DRA ZILDA ARNS NEUMANN'!M21+'CEI DENISE BESSA DE OLIVA MAYA'!M21+'CEI GIUSEPPE-NEVA VOLONTERIO'!M21+'CENTRO DE EDUCAÇÃO INFANTIL LOT'!M21+'CEI IRINEU MARINHO'!M21+'CEI OSWALDO CRUZ'!M21+'CEI ANA CAROLINA TELLES'!M21+'CEI JOSÉ GONÇALVES DA MOTTA'!M21+'CEI SAGRADA FAMÍLIA'!M21+'CEI PROFª HERMÍNIA MATHEUS'!M21+'CENTRO DE EDUCAÇÃO INFANTIL PRO'!M21+'CEI MONSENHOR PAULO ELIAS DAHER'!M21+'CEI DAGMAR ROLANDO DE OLIVEIRA'!M21+'CENTRO DE EDUCAÇÃO INFANTIL 2'!M21+'CEI BOA VISTA'!M21+'CEI NILO PEÇANHA'!M21+'CENTRO DE EDUCAÇÃO INFANTIL AUG'!M21+'CEI THEREZINHA DE JESUS LIMA'!M21+'CEI VIDEIRINHA'!M21+'CEI PROFª ADRIANA CONSTÂNCIO TR'!M21+'CENTRO DE EDUCAÇÃO INFANTIL SÉR'!M21+'CEI JURACI PINTO DO AMARAL DE C'!M21+'CEI NOSSA SENHORA DA GLÓRIA'!M21+'CEI ALTO INDEPENDÊNCIA'!M21+'CEI SÃO JOSÉ DAS OBLATAS DE NAZ'!M21+'CEI SANTO ANTÔNIO AGOSTINHO'!M21+'CEI SÃO CHARBEL'!M21+'ASSOCIAÇÃO DA CRECHE SÃO FRANCI'!M21+'CEI SÃO JOSÉ DO ITAMARATI'!M21+'ASSOCIAÇÃO RECREAR'!M21+'CRECHE-ESCOLA CASTELO SÃO MANOE'!M21+'CENTRO DE EDUCAÇÃO INFANTIL SÃO'!M21 | E17: ='Entrada de Dados'!O2 | F17: =D17*E17
