Workbook

Sheet ÍNDICE
A1: ÍNDICE — CLIQUE NO NOME PARA ABRIR A ABA
A3: ABAS DE TRABALHO
A4: =HYPERLINK("#'Entrada de Dados'!A1","Entrada de Dados") | B4: onde você digita pedido e entrega
A5: =HYPERLINK("#'RESUMO'!A1","RESUMO") | B5: o resultado final, calculado sozinho
A6: =HYPERLINK("#'BALANÇO FINANCEIRO'!A1","BALANÇO FINANCEIRO") | B6: custos reais da semana e saldo (positivo ou negativo)
A7: =HYPERLINK("#'DIFERENÇA'!A1","DIFERENÇA") | B7: quanto faltou entregar, produto por produto
A8: =HYPERLINK("#'MAPA DE MONTAGEM'!A1","MAPA DE MONTAGEM") | B8: separação da carga por rota — segunda e terça
A9: =HYPERLINK("#'MAPA DE PRODUÇÃO'!A1","MAPA DE PRODUÇÃO") | B9: quem planta o quê, por mês
A10: =HYPERLINK("#'MOTIVO'!A1","MOTIVO") | B10: lista de motivos de devolução
A12: COMO USAR — PASSO A PASSO
A13: 1. Pedido da prefeitura | B13: Entrada de Dados, bloco de cima → digite a quantidade de cada produto, na linha de cada escola.
A14: 2. Decidir quem entrega | B14: Abra o Mapa de Produção → veja quem planta cada produto e quanto planejou naquele mês.
A15: 3. Pedido aos produtores | B15: Entrada de Dados, bloco do meio → digite quanto vai pedir a cada produtor.
A16: 4. Entrega real | B16: Caminhão chegou → Entrada de Dados, bloco de baixo → digite quanto cada produtor realmente trouxe.
A17: 5. Devolução da escola (se houver) | B17: Clique no nome da escola (vira link) → anote a devolução e o motivo.
A18: 6. Devolução do produtor (se houver) | B18: Clique em "Anotar devolução" na linha do produtor → registre lá, com o motivo.
A19: 7. Montagem da carga | B19: Abra o Mapa de Montagem → escolha a rota do dia (S1–S10 segunda, T1–T8 terça) e separe os produtos na ordem da parada.
A20: 8. Resultado | B20: Abra o RESUMO — não precisa digitar nada, já mostra quanto cobrar, quanto pagar, e a margem.
A21: 9. Balanço financeiro | B21: Abra o Balanço Financeiro → digite os custos reais da semana (frete, montagem, etc.) e veja o saldo final.
A23: ESCOLAS
A24: CÓDIGO | B24: ESCOLA (clique para abrir) | C24: BAIRRO
A25: ='E M ABELARDO DE LAMARE'!B5 | B25: =HYPERLINK("#'E M ABELARDO DE LAMARE'!A1",'E M ABELARDO DE LAMARE'!B2) | C25: ='E M ABELARDO DE LAMARE'!B3
A26: ='E M BATAILLARD'!B5 | B26: =HYPERLINK("#'E M BATAILLARD'!A1",'E M BATAILLARD'!B2) | C26: ='E M BATAILLARD'!B3
A27: ='E M LEONARDO BOFF'!B5 | B27: =HYPERLINK("#'E M LEONARDO BOFF'!A1",'E M LEONARDO BOFF'!B2) | C27: ='E M LEONARDO BOFF'!B3
A28: ='E M CLEMENTE FERNANDES'!B5 | B28: =HYPERLINK("#'E M CLEMENTE FERNANDES'!A1",'E M CLEMENTE FERNANDES'!B2) | C28: ='E M CLEMENTE FERNANDES'!B3
A29: ='E M DOM PEDRO DE ALCÂNTARA'!B5 | B29: =HYPERLINK("#'E M DOM PEDRO DE ALCÂNTARA'!A1",'E M DOM PEDRO DE ALCÂNTARA'!B2) | C29: ='E M DOM PEDRO DE ALCÂNTARA'!B3
A30: ='E M DUQUE DE CAXIAS'!B5 | B30: =HYPERLINK("#'E M DUQUE DE CAXIAS'!A1",'E M DUQUE DE CAXIAS'!B2) | C30: ='E M DUQUE DE CAXIAS'!B3
A31: ='E M LUIZ CARLOS SOARES'!B5 | B31: =HYPERLINK("#'E M LUIZ CARLOS SOARES'!A1",'E M LUIZ CARLOS SOARES'!B2) | C31: ='E M LUIZ CARLOS SOARES'!B3
A32: ='ESCOLA MUNICIPAL GENERAL HEITOR'!B5 | B32: =HYPERLINK("#'ESCOLA MUNICIPAL GENERAL HEITOR'!A1",'ESCOLA MUNICIPAL GENERAL HEITOR'!B2) | C32: ='ESCOLA MUNICIPAL GENERAL HEITOR'!B3
A33: ='E M JOÃO KOPKE'!B5 | B33: =HYPERLINK("#'E M JOÃO KOPKE'!A1",'E M JOÃO KOPKE'!B2) | C33: ='E M JOÃO KOPKE'!B3
A34: ='ESCOLA MUNICIPAL ODETTE FONSECA'!B5 | B34: =HYPERLINK("#'ESCOLA MUNICIPAL ODETTE FONSECA'!A1",'ESCOLA MUNICIPAL ODETTE FONSECA'!B2) | C34: ='ESCOLA MUNICIPAL ODETTE FONSECA'!B3
A35: ='E M GOVERNADOR MARCELLO ALENCAR'!B5 | B35: =HYPERLINK("#'E M GOVERNADOR MARCELLO ALENCAR'!A1",'E M GOVERNADOR MARCELLO ALENCAR'!B2) | C35: ='E M GOVERNADOR MARCELLO ALENCAR'!B3
A36: ='E M PROF JOAQUIM DEISTER'!B5 | B36: =HYPERLINK("#'E M PROF JOAQUIM DEISTER'!A1",'E M PROF JOAQUIM DEISTER'!B2) | C36: ='E M PROF JOAQUIM DEISTER'!B3
A37: ='E M ROBERT KENNEDY'!B5 | B37: =HYPERLINK("#'E M ROBERT KENNEDY'!A1",'E M ROBERT KENNEDY'!B2) | C37: ='E M ROBERT KENNEDY'!B3
A38: ='E M ROTARY'!B5 | B38: =HYPERLINK("#'E M ROTARY'!A1",'E M ROTARY'!B2) | C38: ='E M ROTARY'!B3
A39: ='E M ROSALINA NICOLAY'!B5 | B39: =HYPERLINK("#'E M ROSALINA NICOLAY'!A1",'E M ROSALINA NICOLAY'!B2) | C39: ='E M ROSALINA NICOLAY'!B3
A40: ='E M DE EDUCAÇÃO ESPECIAL SANTOS'!B5 | B40: =HYPERLINK("#'E M DE EDUCAÇÃO ESPECIAL SANTOS'!A1",'E M DE EDUCAÇÃO ESPECIAL SANTOS'!B2) | C40: ='E M DE EDUCAÇÃO ESPECIAL SANTOS'!B3
A41: ='E M SOROPTIMISTA'!B5 | B41: =HYPERLINK("#'E M SOROPTIMISTA'!A1",'E M SOROPTIMISTA'!B2) | C41: ='E M SOROPTIMISTA'!B3
A42: ='LICEU MUN PREFEITO CORDOLINO AM'!B5 | B42: =HYPERLINK("#'LICEU MUN PREFEITO CORDOLINO AM'!A1",'LICEU MUN PREFEITO CORDOLINO AM'!B2) | C42: ='LICEU MUN PREFEITO CORDOLINO AM'!B3
A43: ='E M ANTÔNIO LEITE GARCIA'!B5 | B43: =HYPERLINK("#'E M ANTÔNIO LEITE GARCIA'!A1",'E M ANTÔNIO LEITE GARCIA'!B2) | C43: ='E M ANTÔNIO LEITE GARCIA'!B3
A44: ='ESCOLA MUNICIPAL JORGE AMADO'!B5 | B44: =HYPERLINK("#'ESCOLA MUNICIPAL JORGE AMADO'!A1",'ESCOLA MUNICIPAL JORGE AMADO'!B2) | C44: ='ESCOLA MUNICIPAL JORGE AMADO'!B3
A45: ='ESCOLA MUNICIPAL LÚCIA DE ALMEI'!B5 | B45: =HYPERLINK("#'ESCOLA MUNICIPAL LÚCIA DE ALMEI'!A1",'ESCOLA MUNICIPAL LÚCIA DE ALMEI'!B2) | C45: ='ESCOLA MUNICIPAL LÚCIA DE ALMEI'!B3
A46: ='E M MAGDALENA TAGLIAFERRO'!B5 | B46: =HYPERLINK("#'E M MAGDALENA TAGLIAFERRO'!A1",'E M MAGDALENA TAGLIAFERRO'!B2) | C46: ='E M MAGDALENA TAGLIAFERRO'!B3
A47: ='ESCOLA MUNICIPAL MAJOR JÚLIO FR'!B5 | B47: =HYPERLINK("#'ESCOLA MUNICIPAL MAJOR JÚLIO FR'!A1",'ESCOLA MUNICIPAL MAJOR JÚLIO FR'!B2) | C47: ='ESCOLA MUNICIPAL MAJOR JÚLIO FR'!B3
A48: ='E M MARIETA GONÇALVES'!B5 | B48: =HYPERLINK("#'E M MARIETA GONÇALVES'!A1",'E M MARIETA GONÇALVES'!B2) | C48: ='E M MARIETA GONÇALVES'!B3
A49: ='ESCOLA MUNICIPAL ODETTE YOUNG M'!B5 | B49: =HYPERLINK("#'ESCOLA MUNICIPAL ODETTE YOUNG M'!A1",'ESCOLA MUNICIPAL ODETTE YOUNG M'!B2) | C49: ='ESCOLA MUNICIPAL ODETTE YOUNG M'!B3
A50: ='E M FÁBRICA DO SABER'!B5 | B50: =HYPERLINK("#'E M FÁBRICA DO SABER'!A1",'E M FÁBRICA DO SABER'!B2) | C50: ='E M FÁBRICA DO SABER'!B3
A51: ='ESCOLA MUNICIPAL PROFESSOR PAUL'!B5 | B51: =HYPERLINK("#'ESCOLA MUNICIPAL PROFESSOR PAUL'!A1",'ESCOLA MUNICIPAL PROFESSOR PAUL'!B2) | C51: ='ESCOLA MUNICIPAL PROFESSOR PAUL'!B3
A52: ='E M ROSEMIRA DE OLIVEIRA CAVALC'!B5 | B52: =HYPERLINK("#'E M ROSEMIRA DE OLIVEIRA CAVALC'!A1",'E M ROSEMIRA DE OLIVEIRA CAVALC'!B2) | C52: ='E M ROSEMIRA DE OLIVEIRA CAVALC'!B3
A53: ='E M AMÉLIA ANTUNES RABELLO'!B5 | B53: =HYPERLINK("#'E M AMÉLIA ANTUNES RABELLO'!A1",'E M AMÉLIA ANTUNES RABELLO'!B2) | C53: ='E M AMÉLIA ANTUNES RABELLO'!B3
A54: ='ESCOLA MUNICIPAL AUGUSTO PUGNAL'!B5 | B54: =HYPERLINK("#'ESCOLA MUNICIPAL AUGUSTO PUGNAL'!A1",'ESCOLA MUNICIPAL AUGUSTO PUGNAL'!B2) | C54: ='ESCOLA MUNICIPAL AUGUSTO PUGNAL'!B3
A55: ='ESCOLA MUNICIPAL CELINA SCHECHN'!B5 | B55: =HYPERLINK("#'ESCOLA MUNICIPAL CELINA SCHECHN'!A1",'ESCOLA MUNICIPAL CELINA SCHECHN'!B2) | C55: ='ESCOLA MUNICIPAL CELINA SCHECHN'!B3
A56: ='E M DARCY CORREA DA VEIGA'!B5 | B56: =HYPERLINK("#'E M DARCY CORREA DA VEIGA'!A1",'E M DARCY CORREA DA VEIGA'!B2) | C56: ='E M DARCY CORREA DA VEIGA'!B3
A57: ='E M DR PAULA BUARQUE'!B5 | B57: =HYPERLINK("#'E M DR PAULA BUARQUE'!A1",'E M DR PAULA BUARQUE'!B2) | C57: ='E M DR PAULA BUARQUE'!B3
A58: ='E M DR THEODORO MACHADO'!B5 | B58: =HYPERLINK("#'E M DR THEODORO MACHADO'!A1",'E M DR THEODORO MACHADO'!B2) | C58: ='E M DR THEODORO MACHADO'!B3
A59: ='E M ARNALDO DYCKERHOFF'!B5 | B59: =HYPERLINK("#'E M ARNALDO DYCKERHOFF'!A1",'E M ARNALDO DYCKERHOFF'!B2) | C59: ='E M ARNALDO DYCKERHOFF'!B3
A60: ='E M CARLOS CANEDO'!B5 | B60: =HYPERLINK("#'E M CARLOS CANEDO'!A1",'E M CARLOS CANEDO'!B2) | C60: ='E M CARLOS CANEDO'!B3
A61: ='E M DR BARROS FRANCO'!B5 | B61: =HYPERLINK("#'E M DR BARROS FRANCO'!A1",'E M DR BARROS FRANCO'!B2) | C61: ='E M DR BARROS FRANCO'!B3
A62: ='E M MAJOR THEÓFILO DE CARVALHO'!B5 | B62: =HYPERLINK("#'E M MAJOR THEÓFILO DE CARVALHO'!A1",'E M MAJOR THEÓFILO DE CARVALHO'!B2) | C62: ='E M MAJOR THEÓFILO DE CARVALHO'!B3
A63: ='E M TAQUARIL'!B5 | B63: =HYPERLINK("#'E M TAQUARIL'!A1",'E M TAQUARIL'!B2) | C63: ='E M TAQUARIL'!B3
A64: ='E M BEATRIZ ZALESKI'!B5 | B64: =HYPERLINK("#'E M BEATRIZ ZALESKI'!A1",'E M BEATRIZ ZALESKI'!B2) | C64: ='E M BEATRIZ ZALESKI'!B3
A65: ='E M ANTÔNIO JOSÉ DE LIMA'!B5 | B65: =HYPERLINK("#'E M ANTÔNIO JOSÉ DE LIMA'!A1",'E M ANTÔNIO JOSÉ DE LIMA'!B2) | C65: ='E M ANTÔNIO JOSÉ DE LIMA'!B3
A66: ='E M FELIX WAN ERVEN DE BARROS'!B5 | B66: =HYPERLINK("#'E M FELIX WAN ERVEN DE BARROS'!A1",'E M FELIX WAN ERVEN DE BARROS'!B2) | C66: ='E M FELIX WAN ERVEN DE BARROS'!B3
A67: ='ESCOLA MUNICIPAL HILDEBRANDO DE'!B5 | B67: =HYPERLINK("#'ESCOLA MUNICIPAL HILDEBRANDO DE'!A1",'ESCOLA MUNICIPAL HILDEBRANDO DE'!B2) | C67: ='ESCOLA MUNICIPAL HILDEBRANDO DE'!B3
A68: ='E M OSWALDO DA COSTA FRIAS'!B5 | B68: =HYPERLINK("#'E M OSWALDO DA COSTA FRIAS'!A1",'E M OSWALDO DA COSTA FRIAS'!B2) | C68: ='E M OSWALDO DA COSTA FRIAS'!B3
A69: ='E MZDA CARMEM NUNES MARTINS'!B5 | B69: =HYPERLINK("#'E MZDA CARMEM NUNES MARTINS'!A1",'E MZDA CARMEM NUNES MARTINS'!B2) | C69: ='E MZDA CARMEM NUNES MARTINS'!B3
A70: ='E MZDA AVELINO DE CARVALHO'!B5 | B70: =HYPERLINK("#'E MZDA AVELINO DE CARVALHO'!A1",'E MZDA AVELINO DE CARVALHO'!B2) | C70: ='E MZDA AVELINO DE CARVALHO'!B3
A71: ='E M GERALDO VENTURA DIAS'!B5 | B71: =HYPERLINK("#'E M GERALDO VENTURA DIAS'!A1",'E M GERALDO VENTURA DIAS'!B2) | C71: ='E M GERALDO VENTURA DIAS'!B3
A72: ='E M SALVADOR KLING'!B5 | B72: =HYPERLINK("#'E M SALVADOR KLING'!A1",'E M SALVADOR KLING'!B2) | C72: ='E M SALVADOR KLING'!B3
A73: ='E M PREFEITO JAMIL SABRÁ'!B5 | B73: =HYPERLINK("#'E M PREFEITO JAMIL SABRÁ'!A1",'E M PREFEITO JAMIL SABRÁ'!B2) | C73: ='E M PREFEITO JAMIL SABRÁ'!B3
A74: ='LICEU MUNICIPAL CARLOS CHAGAS F'!B5 | B74: =HYPERLINK("#'LICEU MUNICIPAL CARLOS CHAGAS F'!A1",'LICEU MUNICIPAL CARLOS CHAGAS F'!B2) | C74: ='LICEU MUNICIPAL CARLOS CHAGAS F'!B3
A75: ='ESCOLA MUNICIPAL ANA MOHAMMAD'!B5 | B75: =HYPERLINK("#'ESCOLA MUNICIPAL ANA MOHAMMAD'!A1",'ESCOLA MUNICIPAL ANA MOHAMMAD'!B2) | C75: ='ESCOLA MUNICIPAL ANA MOHAMMAD'!B3
A76: ='ESCOLA MUNICIPAL ALTO INDEPENDÊ'!B5 | B76: =HYPERLINK("#'ESCOLA MUNICIPAL ALTO INDEPENDÊ'!A1",'ESCOLA MUNICIPAL ALTO INDEPENDÊ'!B2) | C76: ='ESCOLA MUNICIPAL ALTO INDEPENDÊ'!B3
A77: ='E M ALMIRANTE TAMANDARÉ'!B5 | B77: =HYPERLINK("#'E M ALMIRANTE TAMANDARÉ'!A1",'E M ALMIRANTE TAMANDARÉ'!B2) | C77: ='E M ALMIRANTE TAMANDARÉ'!B3
A78: ='ESCOLA MUNICIPALIZADA FREI ANIC'!B5 | B78: =HYPERLINK("#'ESCOLA MUNICIPALIZADA FREI ANIC'!A1",'ESCOLA MUNICIPALIZADA FREI ANIC'!B2) | C78: ='ESCOLA MUNICIPALIZADA FREI ANIC'!B3
A79: ='E M PEDRO AMADO'!B5 | B79: =HYPERLINK("#'E M PEDRO AMADO'!A1",'E M PEDRO AMADO'!B2) | C79: ='E M PEDRO AMADO'!B3
A80: ='E M PROFª MARIA DA GLÓRIA QUEIR'!B5 | B80: =HYPERLINK("#'E M PROFª MARIA DA GLÓRIA QUEIR'!A1",'E M PROFª MARIA DA GLÓRIA QUEIR'!B2) | C80: ='E M PROFª MARIA DA GLÓRIA QUEIR'!B3
A81: ='E M SEBASTIÃO LACERDA'!B5 | B81: =HYPERLINK("#'E M SEBASTIÃO LACERDA'!A1",'E M SEBASTIÃO LACERDA'!B2) | C81: ='E M SEBASTIÃO LACERDA'!B3
A82: ='E M PROFESSOR FLÁVIO MACIEL'!B5 | B82: =HYPERLINK("#'E M PROFESSOR FLÁVIO MACIEL'!A1",'E M PROFESSOR FLÁVIO MACIEL'!B2) | C82: ='E M PROFESSOR FLÁVIO MACIEL'!B3
A83: ='ESCOLA MUNICIPAL PAULO SALDANHA'!B5 | B83: =HYPERLINK("#'ESCOLA MUNICIPAL PAULO SALDANHA'!A1",'ESCOLA MUNICIPAL PAULO SALDANHA'!B2) | C83: ='ESCOLA MUNICIPAL PAULO SALDANHA'!B3
A84: ='ESCOLA MUNICIPAL PROFESSOR JOSE'!B5 | B84: =HYPERLINK("#'ESCOLA MUNICIPAL PROFESSOR JOSE'!A1",'ESCOLA MUNICIPAL PROFESSOR JOSE'!B2) | C84: ='ESCOLA MUNICIPAL PROFESSOR JOSE'!B3
A85: ='E M MONSENHOR CIRILLO CALAON'!B5 | B85: =HYPERLINK("#'E M MONSENHOR CIRILLO CALAON'!A1",'E M MONSENHOR CIRILLO CALAON'!B2) | C85: ='E M MONSENHOR CIRILLO CALAON'!B3
A86: ='E M AMÉRICO FERNANDES RIBEIRO'!B5 | B86: =HYPERLINK("#'E M AMÉRICO FERNANDES RIBEIRO'!A1",'E M AMÉRICO FERNANDES RIBEIRO'!B2) | C86: ='E M AMÉRICO FERNANDES RIBEIRO'!B3
A87: ='E M PROFª JANDIRA PEIXOTO BORDI'!B5 | B87: =HYPERLINK("#'E M PROFª JANDIRA PEIXOTO BORDI'!A1",'E M PROFª JANDIRA PEIXOTO BORDI'!B2) | C87: ='E M PROFª JANDIRA PEIXOTO BORDI'!B3
A88: ='E M MONSENHOR JOÃO DE DEUS RODR'!B5 | B88: =HYPERLINK("#'E M MONSENHOR JOÃO DE DEUS RODR'!A1",'E M MONSENHOR JOÃO DE DEUS RODR'!B2) | C88: ='E M MONSENHOR JOÃO DE DEUS RODR'!B3
A89: ='E M DOM MANOEL PEDRO DA CUNHA C'!B5 | B89: =HYPERLINK("#'E M DOM MANOEL PEDRO DA CUNHA C'!A1",'E M DOM MANOEL PEDRO DA CUNHA C'!B2) | C89: ='E M DOM MANOEL PEDRO DA CUNHA C'!B3
A90: ='E M JOHANN NOEL'!B5 | B90: =HYPERLINK("#'E M JOHANN NOEL'!A1",'E M JOHANN NOEL'!B2) | C90: ='E M JOHANN NOEL'!B3
A91: ='E MZDA SANTA TEREZINHA'!B5 | B91: =HYPERLINK("#'E MZDA SANTA TEREZINHA'!A1",'E MZDA SANTA TEREZINHA'!B2) | C91: ='E MZDA SANTA TEREZINHA'!B3
A92: ='E M PAPA JOÃO PAULO II'!B5 | B92: =HYPERLINK("#'E M PAPA JOÃO PAULO II'!A1",'E M PAPA JOÃO PAULO II'!B2) | C92: ='E M PAPA JOÃO PAULO II'!B3
A93: ='E M STEFAN ZWEIG'!B5 | B93: =HYPERLINK("#'E M STEFAN ZWEIG'!A1",'E M STEFAN ZWEIG'!B2) | C93: ='E M STEFAN ZWEIG'!B3
A94: ='ESCOLA MUNICIPAL SENADOR MARIO '!B5 | B94: =HYPERLINK("#'ESCOLA MUNICIPAL SENADOR MARIO '!A1",'ESCOLA MUNICIPAL SENADOR MARIO '!B2) | C94: ='ESCOLA MUNICIPAL SENADOR MARIO '!B3
A95: ='E M DR RUBENS DE CASTRO BOMTEMP'!B5 | B95: =HYPERLINK("#'E M DR RUBENS DE CASTRO BOMTEMP'!A1",'E M DR RUBENS DE CASTRO BOMTEMP'!B2) | C95: ='E M DR RUBENS DE CASTRO BOMTEMP'!B3
A96: ='E M PAULO FREIRE'!B5 | B96: =HYPERLINK("#'E M PAULO FREIRE'!A1",'E M PAULO FREIRE'!B2) | C96: ='E M PAULO FREIRE'!B3
A97: ='E M PROFª MARIA CAMPOS DA SILVA'!B5 | B97: =HYPERLINK("#'E M PROFª MARIA CAMPOS DA SILVA'!A1",'E M PROFª MARIA CAMPOS DA SILVA'!B2) | C97: ='E M PROFª MARIA CAMPOS DA SILVA'!B3
A98: ='E M HERCÍLIA HENRIQUES MORET'!B5 | B98: =HYPERLINK("#'E M HERCÍLIA HENRIQUES MORET'!A1",'E M HERCÍLIA HENRIQUES MORET'!B2) | C98: ='E M HERCÍLIA HENRIQUES MORET'!B3
A99: ='ESCOLA MUNICIPALIZADA MOYSÉS FU'!B5 | B99: =HYPERLINK("#'ESCOLA MUNICIPALIZADA MOYSÉS FU'!A1",'ESCOLA MUNICIPALIZADA MOYSÉS FU'!B2) | C99: ='ESCOLA MUNICIPALIZADA MOYSÉS FU'!B3
A100: ='CIEP BRIZOLÃO 474 MAESTRO GUERR'!B5 | B100: =HYPERLINK("#'CIEP BRIZOLÃO 474 MAESTRO GUERR'!A1",'CIEP BRIZOLÃO 474 MAESTRO GUERR'!B2) | C100: ='CIEP BRIZOLÃO 474 MAESTRO GUERR'!B3
A101: ='CENTRO DE ENSINO PROF DARCY RIB'!B5 | B101: =HYPERLINK("#'CENTRO DE ENSINO PROF DARCY RIB'!A1",'CENTRO DE ENSINO PROF DARCY RIB'!B2) | C101: ='CENTRO DE ENSINO PROF DARCY RIB'!B3
A102: ='CASA DA EDUCAÇÃO VISCONDE DE MA'!B5 | B102: =HYPERLINK("#'CASA DA EDUCAÇÃO VISCONDE DE MA'!A1",'CASA DA EDUCAÇÃO VISCONDE DE MA'!B2) | C102: ='CASA DA EDUCAÇÃO VISCONDE DE MA'!B3
A103: ='CENTRO DE REFERÊNCIA EM EDUCAÇÃ'!B5 | B103: =HYPERLINK("#'CENTRO DE REFERÊNCIA EM EDUCAÇÃ'!A1",'CENTRO DE REFERÊNCIA EM EDUCAÇÃ'!B2) | C103: ='CENTRO DE REFERÊNCIA EM EDUCAÇÃ'!B3
...

Sheet Entrada de Dados
A1: ENTRADA DE DADOS
A2: PREÇO (R$/kg) | C2: 15.57 | D2: 7.7 | E2: 16.94 | F2: 14.62 | G2: 12.05 | H2: 11.59 | I2: 9.87 | J2: 13.67 | K2: 10.2 | L2: 25.1 | M2: 8.56 | N2: 14.6 | O2: 19.11 | P2: 11.22 | Q2: 16.63 | R2: 65.68 | S2: 15.45 | T2: 10.24 | U2: 13.55
A4: PEDIDO DAS ESCOLAS (kg)
A5: CÓDIGO | B5: ESCOLA | C5: Abacate | D5: Abobrinha | E5: Agrião | F5: Alface lisa | G5: Banana prata | H5: Batata inglesa | I5: Beterraba | J5: Brócolis | K5: Cenoura | L5: Cheiro verde | M5: Chuchu | N5: Couve manteiga | O5: Couve-flor | P5: Espinafre | Q5: Maçã gala | R5: Mel | S5: Ovos (dz) | T5: Repolho | U5: Tangerina ponkan
A6: ='E M ABELARDO DE LAMARE'!B5 | B6: =HYPERLINK("#'E M ABELARDO DE LAMARE'!A1",'E M ABELARDO DE LAMARE'!B2) | C6: 0 | D6: 0 | E6: 0 | F6: 0 | G6: 0 | H6: 0 | I6: 0 | J6: 0 | K6: 0 | L6: 0 | M6: 0 | N6: 0 | O6: 0 | P6: 0 | Q6: 0 | R6: 0 | S6: 0 | T6: 0 | U6: 0
A7: ='E M BATAILLARD'!B5 | B7: =HYPERLINK("#'E M BATAILLARD'!A1",'E M BATAILLARD'!B2) | C7: 0 | D7: 0 | E7: 0 | F7: 0 | G7: 0 | H7: 0 | I7: 0 | J7: 0 | K7: 0 | L7: 0 | M7: 0 | N7: 0 | O7: 0 | P7: 0 | Q7: 0 | R7: 0 | S7: 0 | T7: 0 | U7: 0
A8: ='E M LEONARDO BOFF'!B5 | B8: =HYPERLINK("#'E M LEONARDO BOFF'!A1",'E M LEONARDO BOFF'!B2) | C8: 0 | D8: 0 | E8: 0 | F8: 0 | G8: 0 | H8: 0 | I8: 0 | J8: 0 | K8: 0 | L8: 0 | M8: 0 | N8: 0 | O8: 0 | P8: 0 | Q8: 0 | R8: 0 | S8: 0 | T8: 0 | U8: 0
A9: ='E M CLEMENTE FERNANDES'!B5 | B9: =HYPERLINK("#'E M CLEMENTE FERNANDES'!A1",'E M CLEMENTE FERNANDES'!B2) | C9: 0 | D9: 0 | E9: 0 | F9: 0 | G9: 0 | H9: 0 | I9: 0 | J9: 0 | K9: 0 | L9: 0 | M9: 0 | N9: 0 | O9: 0 | P9: 0 | Q9: 0 | R9: 0 | S9: 0 | T9: 0 | U9: 0
A10: ='E M DOM PEDRO DE ALCÂNTARA'!B5 | B10: =HYPERLINK("#'E M DOM PEDRO DE ALCÂNTARA'!A1",'E M DOM PEDRO DE ALCÂNTARA'!B2) | C10: 0 | D10: 0 | E10: 0 | F10: 0 | G10: 0 | H10: 0 | I10: 0 | J10: 0 | K10: 0 | L10: 0 | M10: 0 | N10: 0 | O10: 0 | P10: 0 | Q10: 0 | R10: 0 | S10: 0 | T10: 0 | U10: 0
A11: ='E M DUQUE DE CAXIAS'!B5 | B11: =HYPERLINK("#'E M DUQUE DE CAXIAS'!A1",'E M DUQUE DE CAXIAS'!B2) | C11: 0 | D11: 0 | E11: 0 | F11: 0 | G11: 0 | H11: 0 | I11: 0 | J11: 0 | K11: 0 | L11: 0 | M11: 0 | N11: 0 | O11: 0 | P11: 0 | Q11: 0 | R11: 0 | S11: 0 | T11: 0 | U11: 0
A12: ='E M LUIZ CARLOS SOARES'!B5 | B12: =HYPERLINK("#'E M LUIZ CARLOS SOARES'!A1",'E M LUIZ CARLOS SOARES'!B2) | C12: 0 | D12: 0 | E12: 0 | F12: 0 | G12: 0 | H12: 0 | I12: 0 | J12: 0 | K12: 0 | L12: 0 | M12: 0 | N12: 0 | O12: 0 | P12: 0 | Q12: 0 | R12: 0 | S12: 0 | T12: 0 | U12: 0
A13: ='ESCOLA MUNICIPAL GENERAL HEITOR'!B5 | B13: =HYPERLINK("#'ESCOLA MUNICIPAL GENERAL HEITOR'!A1",'ESCOLA MUNICIPAL GENERAL HEITOR'!B2) | C13: 0 | D13: 0 | E13: 0 | F13: 0 | G13: 0 | H13: 0 | I13: 0 | J13: 0 | K13: 0 | L13: 0 | M13: 0 | N13: 0 | O13: 0 | P13: 0 | Q13: 0 | R13: 0 | S13: 0 | T13: 0 | U13: 0
A14: ='E M JOÃO KOPKE'!B5 | B14: =HYPERLINK("#'E M JOÃO KOPKE'!A1",'E M JOÃO KOPKE'!B2) | C14: 0 | D14: 0 | E14: 0 | F14: 0 | G14: 0 | H14: 0 | I14: 0 | J14: 0 | K14: 0 | L14: 0 | M14: 0 | N14: 0 | O14: 0 | P14: 0 | Q14: 0 | R14: 0 | S14: 0 | T14: 0 | U14: 0
A15: ='ESCOLA MUNICIPAL ODETTE FONSECA'!B5 | B15: =HYPERLINK("#'ESCOLA MUNICIPAL ODETTE FONSECA'!A1",'ESCOLA MUNICIPAL ODETTE FONSECA'!B2) | C15: 0 | D15: 0 | E15: 0 | F15: 0 | G15: 0 | H15: 0 | I15: 0 | J15: 0 | K15: 0 | L15: 0 | M15: 0 | N15: 0 | O15: 0 | P15: 0 | Q15: 0 | R15: 0 | S15: 0 | T15: 0 | U15: 0
A16: ='E M GOVERNADOR MARCELLO ALENCAR'!B5 | B16: =HYPERLINK("#'E M GOVERNADOR MARCELLO ALENCAR'!A1",'E M GOVERNADOR MARCELLO ALENCAR'!B2) | C16: 0 | D16: 0 | E16: 0 | F16: 0 | G16: 0 | H16: 0 | I16: 0 | J16: 0 | K16: 0 | L16: 0 | M16: 0 | N16: 0 | O16: 0 | P16: 0 | Q16: 0 | R16: 0 | S16: 0 | T16: 0 | U16: 0
A17: ='E M PROF JOAQUIM DEISTER'!B5 | B17: =HYPERLINK("#'E M PROF JOAQUIM DEISTER'!A1",'E M PROF JOAQUIM DEISTER'!B2) | C17: 0 | D17: 0 | E17: 0 | F17: 0 | G17: 0 | H17: 0 | I17: 0 | J17: 0 | K17: 0 | L17: 0 | M17: 0 | N17: 0 | O17: 0 | P17: 0 | Q17: 0 | R17: 0 | S17: 0 | T17: 0 | U17: 0
A18: ='E M ROBERT KENNEDY'!B5 | B18: =HYPERLINK("#'E M ROBERT KENNEDY'!A1",'E M ROBERT KENNEDY'!B2) | C18: 0 | D18: 0 | E18: 0 | F18: 0 | G18: 0 | H18: 0 | I18: 0 | J18: 0 | K18: 0 | L18: 0 | M18: 0 | N18: 0 | O18: 0 | P18: 0 | Q18: 0 | R18: 0 | S18: 0 | T18: 0 | U18: 0
A19: ='E M ROTARY'!B5 | B19: =HYPERLINK("#'E M ROTARY'!A1",'E M ROTARY'!B2) | C19: 0 | D19: 0 | E19: 0 | F19: 0 | G19: 0 | H19: 0 | I19: 0 | J19: 0 | K19: 0 | L19: 0 | M19: 0 | N19: 0 | O19: 0 | P19: 0 | Q19: 0 | R19: 0 | S19: 0 | T19: 0 | U19: 0
A20: ='E M ROSALINA NICOLAY'!B5 | B20: =HYPERLINK("#'E M ROSALINA NICOLAY'!A1",'E M ROSALINA NICOLAY'!B2) | C20: 0 | D20: 0 | E20: 0 | F20: 0 | G20: 0 | H20: 0 | I20: 0 | J20: 0 | K20: 0 | L20: 0 | M20: 0 | N20: 0 | O20: 0 | P20: 0 | Q20: 0 | R20: 0 | S20: 0 | T20: 0 | U20: 0
A21: ='E M DE EDUCAÇÃO ESPECIAL SANTOS'!B5 | B21: =HYPERLINK("#'E M DE EDUCAÇÃO ESPECIAL SANTOS'!A1",'E M DE EDUCAÇÃO ESPECIAL SANTOS'!B2) | C21: 0 | D21: 0 | E21: 0 | F21: 0 | G21: 0 | H21: 0 | I21: 0 | J21: 0 | K21: 0 | L21: 0 | M21: 0 | N21: 0 | O21: 0 | P21: 0 | Q21: 0 | R21: 0 | S21: 0 | T21: 0 | U21: 0
A22: ='E M SOROPTIMISTA'!B5 | B22: =HYPERLINK("#'E M SOROPTIMISTA'!A1",'E M SOROPTIMISTA'!B2) | C22: 0 | D22: 0 | E22: 0 | F22: 0 | G22: 0 | H22: 0 | I22: 0 | J22: 0 | K22: 0 | L22: 0 | M22: 0 | N22: 0 | O22: 0 | P22: 0 | Q22: 0 | R22: 0 | S22: 0 | T22: 0 | U22: 0
A23: ='LICEU MUN PREFEITO CORDOLINO AM'!B5 | B23: =HYPERLINK("#'LICEU MUN PREFEITO CORDOLINO AM'!A1",'LICEU MUN PREFEITO CORDOLINO AM'!B2) | C23: 0 | D23: 0 | E23: 0 | F23: 0 | G23: 0 | H23: 0 | I23: 0 | J23: 0 | K23: 0 | L23: 0 | M23: 0 | N23: 0 | O23: 0 | P23: 0 | Q23: 0 | R23: 0 | S23: 0 | T23: 0 | U23: 0
A24: ='E M ANTÔNIO LEITE GARCIA'!B5 | B24: =HYPERLINK("#'E M ANTÔNIO LEITE GARCIA'!A1",'E M ANTÔNIO LEITE GARCIA'!B2) | C24: 0 | D24: 0 | E24: 0 | F24: 0 | G24: 0 | H24: 0 | I24: 0 | J24: 0 | K24: 0 | L24: 0 | M24: 0 | N24: 0 | O24: 0 | P24: 0 | Q24: 0 | R24: 0 | S24: 0 | T24: 0 | U24: 0
A25: ='ESCOLA MUNICIPAL JORGE AMADO'!B5 | B25: =HYPERLINK("#'ESCOLA MUNICIPAL JORGE AMADO'!A1",'ESCOLA MUNICIPAL JORGE AMADO'!B2) | C25: 0 | D25: 0 | E25: 0 | F25: 0 | G25: 0 | H25: 0 | I25: 0 | J25: 0 | K25: 0 | L25: 0 | M25: 0 | N25: 0 | O25: 0 | P25: 0 | Q25: 0 | R25: 0 | S25: 0 | T25: 0 | U25: 0
A26: ='ESCOLA MUNICIPAL LÚCIA DE ALMEI'!B5 | B26: =HYPERLINK("#'ESCOLA MUNICIPAL LÚCIA DE ALMEI'!A1",'ESCOLA MUNICIPAL LÚCIA DE ALMEI'!B2) | C26: 0 | D26: 0 | E26: 0 | F26: 0 | G26: 0 | H26: 0 | I26: 0 | J26: 0 | K26: 0 | L26: 0 | M26: 0 | N26: 0 | O26: 0 | P26: 0 | Q26: 0 | R26: 0 | S26: 0 | T26: 0 | U26: 0
A27: ='E M MAGDALENA TAGLIAFERRO'!B5 | B27: =HYPERLINK("#'E M MAGDALENA TAGLIAFERRO'!A1",'E M MAGDALENA TAGLIAFERRO'!B2) | C27: 0 | D27: 0 | E27: 0 | F27: 0 | G27: 0 | H27: 0 | I27: 0 | J27: 0 | K27: 0 | L27: 0 | M27: 0 | N27: 0 | O27: 0 | P27: 0 | Q27: 0 | R27: 0 | S27: 0 | T27: 0 | U27: 0
A28: ='ESCOLA MUNICIPAL MAJOR JÚLIO FR'!B5 | B28: =HYPERLINK("#'ESCOLA MUNICIPAL MAJOR JÚLIO FR'!A1",'ESCOLA MUNICIPAL MAJOR JÚLIO FR'!B2) | C28: 0 | D28: 0 | E28: 0 | F28: 0 | G28: 0 | H28: 0 | I28: 0 | J28: 0 | K28: 0 | L28: 0 | M28: 0 | N28: 0 | O28: 0 | P28: 0 | Q28: 0 | R28: 0 | S28: 0 | T28: 0 | U28: 0
A29: ='E M MARIETA GONÇALVES'!B5 | B29: =HYPERLINK("#'E M MARIETA GONÇALVES'!A1",'E M MARIETA GONÇALVES'!B2) | C29: 0 | D29: 0 | E29: 0 | F29: 0 | G29: 0 | H29: 0 | I29: 0 | J29: 0 | K29: 0 | L29: 0 | M29: 0 | N29: 0 | O29: 0 | P29: 0 | Q29: 0 | R29: 0 | S29: 0 | T29: 0 | U29: 0
A30: ='ESCOLA MUNICIPAL ODETTE YOUNG M'!B5 | B30: =HYPERLINK("#'ESCOLA MUNICIPAL ODETTE YOUNG M'!A1",'ESCOLA MUNICIPAL ODETTE YOUNG M'!B2) | C30: 0 | D30: 0 | E30: 0 | F30: 0 | G30: 0 | H30: 0 | I30: 0 | J30: 0 | K30: 0 | L30: 0 | M30: 0 | N30: 0 | O30: 0 | P30: 0 | Q30: 0 | R30: 0 | S30: 0 | T30: 0 | U30: 0
A31: ='E M FÁBRICA DO SABER'!B5 | B31: =HYPERLINK("#'E M FÁBRICA DO SABER'!A1",'E M FÁBRICA DO SABER'!B2) | C31: 0 | D31: 0 | E31: 0 | F31: 0 | G31: 0 | H31: 0 | I31: 0 | J31: 0 | K31: 0 | L31: 0 | M31: 0 | N31: 0 | O31: 0 | P31: 0 | Q31: 0 | R31: 0 | S31: 0 | T31: 0 | U31: 0
A32: ='ESCOLA MUNICIPAL PROFESSOR PAUL'!B5 | B32: =HYPERLINK("#'ESCOLA MUNICIPAL PROFESSOR PAUL'!A1",'ESCOLA MUNICIPAL PROFESSOR PAUL'!B2) | C32: 0 | D32: 0 | E32: 0 | F32: 0 | G32: 0 | H32: 0 | I32: 0 | J32: 0 | K32: 0 | L32: 0 | M32: 0 | N32: 0 | O32: 0 | P32: 0 | Q32: 0 | R32: 0 | S32: 0 | T32: 0 | U32: 0
A33: ='E M ROSEMIRA DE OLIVEIRA CAVALC'!B5 | B33: =HYPERLINK("#'E M ROSEMIRA DE OLIVEIRA CAVALC'!A1",'E M ROSEMIRA DE OLIVEIRA CAVALC'!B2) | C33: 0 | D33: 0 | E33: 0 | F33: 0 | G33: 0 | H33: 0 | I33: 0 | J33: 0 | K33: 0 | L33: 0 | M33: 0 | N33: 0 | O33: 0 | P33: 0 | Q33: 0 | R33: 0 | S33: 0 | T33: 0 | U33: 0
A34: ='E M AMÉLIA ANTUNES RABELLO'!B5 | B34: =HYPERLINK("#'E M AMÉLIA ANTUNES RABELLO'!A1",'E M AMÉLIA ANTUNES RABELLO'!B2) | C34: 0 | D34: 0 | E34: 0 | F34: 0 | G34: 0 | H34: 0 | I34: 0 | J34: 0 | K34: 0 | L34: 0 | M34: 0 | N34: 0 | O34: 0 | P34: 0 | Q34: 0 | R34: 0 | S34: 0 | T34: 0 | U34: 0
A35: ='ESCOLA MUNICIPAL AUGUSTO PUGNAL'!B5 | B35: =HYPERLINK("#'ESCOLA MUNICIPAL AUGUSTO PUGNAL'!A1",'ESCOLA MUNICIPAL AUGUSTO PUGNAL'!B2) | C35: 0 | D35: 0 | E35: 0 | F35: 0 | G35: 0 | H35: 0 | I35: 0 | J35: 0 | K35: 0 | L35: 0 | M35: 0 | N35: 0 | O35: 0 | P35: 0 | Q35: 0 | R35: 0 | S35: 0 | T35: 0 | U35: 0
A36: ='ESCOLA MUNICIPAL CELINA SCHECHN'!B5 | B36: =HYPERLINK("#'ESCOLA MUNICIPAL CELINA SCHECHN'!A1",'ESCOLA MUNICIPAL CELINA SCHECHN'!B2) | C36: 0 | D36: 0 | E36: 0 | F36: 0 | G36: 0 | H36: 0 | I36: 0 | J36: 0 | K36: 0 | L36: 0 | M36: 0 | N36: 0 | O36: 0 | P36: 0 | Q36: 0 | R36: 0 | S36: 0 | T36: 0 | U36: 0
A37: ='E M DARCY CORREA DA VEIGA'!B5 | B37: =HYPERLINK("#'E M DARCY CORREA DA VEIGA'!A1",'E M DARCY CORREA DA VEIGA'!B2) | C37: 0 | D37: 0 | E37: 0 | F37: 0 | G37: 0 | H37: 0 | I37: 0 | J37: 0 | K37: 0 | L37: 0 | M37: 0 | N37: 0 | O37: 0 | P37: 0 | Q37: 0 | R37: 0 | S37: 0 | T37: 0 | U37: 0
A38: ='E M DR PAULA BUARQUE'!B5 | B38: =HYPERLINK("#'E M DR PAULA BUARQUE'!A1",'E M DR PAULA BUARQUE'!B2) | C38: 0 | D38: 0 | E38: 0 | F38: 0 | G38: 0 | H38: 0 | I38: 0 | J38: 0 | K38: 0 | L38: 0 | M38: 0 | N38: 0 | O38: 0 | P38: 0 | Q38: 0 | R38: 0 | S38: 0 | T38: 0 | U38: 0
A39: ='E M DR THEODORO MACHADO'!B5 | B39: =HYPERLINK("#'E M DR THEODORO MACHADO'!A1",'E M DR THEODORO MACHADO'!B2) | C39: 0 | D39: 0 | E39: 0 | F39: 0 | G39: 0 | H39: 0 | I39: 0 | J39: 0 | K39: 0 | L39: 0 | M39: 0 | N39: 0 | O39: 0 | P39: 0 | Q39: 0 | R39: 0 | S39: 0 | T39: 0 | U39: 0
A40: ='E M ARNALDO DYCKERHOFF'!B5 | B40: =HYPERLINK("#'E M ARNALDO DYCKERHOFF'!A1",'E M ARNALDO DYCKERHOFF'!B2) | C40: 0 | D40: 0 | E40: 0 | F40: 0 | G40: 0 | H40: 0 | I40: 0 | J40: 0 | K40: 0 | L40: 0 | M40: 0 | N40: 0 | O40: 0 | P40: 0 | Q40: 0 | R40: 0 | S40: 0 | T40: 0 | U40: 0
A41: ='E M CARLOS CANEDO'!B5 | B41: =HYPERLINK("#'E M CARLOS CANEDO'!A1",'E M CARLOS CANEDO'!B2) | C41: 0 | D41: 0 | E41: 0 | F41: 0 | G41: 0 | H41: 0 | I41: 0 | J41: 0 | K41: 0 | L41: 0 | M41: 0 | N41: 0 | O41: 0 | P41: 0 | Q41: 0 | R41: 0 | S41: 0 | T41: 0 | U41: 0
A42: ='E M DR BARROS FRANCO'!B5 | B42: =HYPERLINK("#'E M DR BARROS FRANCO'!A1",'E M DR BARROS FRANCO'!B2) | C42: 0 | D42: 0 | E42: 0 | F42: 0 | G42: 0 | H42: 0 | I42: 0 | J42: 0 | K42: 0 | L42: 0 | M42: 0 | N42: 0 | O42: 0 | P42: 0 | Q42: 0 | R42: 0 | S42: 0 | T42: 0 | U42: 0
A43: ='E M MAJOR THEÓFILO DE CARVALHO'!B5 | B43: =HYPERLINK("#'E M MAJOR THEÓFILO DE CARVALHO'!A1",'E M MAJOR THEÓFILO DE CARVALHO'!B2) | C43: 0 | D43: 0 | E43: 0 | F43: 0 | G43: 0 | H43: 0 | I43: 0 | J43: 0 | K43: 0 | L43: 0 | M43: 0 | N43: 0 | O43: 0 | P43: 0 | Q43: 0 | R43: 0 | S43: 0 | T43: 0 | U43: 0
A44: ='E M TAQUARIL'!B5 | B44: =HYPERLINK("#'E M TAQUARIL'!A1",'E M TAQUARIL'!B2) | C44: 0 | D44: 0 | E44: 0 | F44: 0 | G44: 0 | H44: 0 | I44: 0 | J44: 0 | K44: 0 | L44: 0 | M44: 0 | N44: 0 | O44: 0 | P44: 0 | Q44: 0 | R44: 0 | S44: 0 | T44: 0 | U44: 0
A45: ='E M BEATRIZ ZALESKI'!B5 | B45: =HYPERLINK("#'E M BEATRIZ ZALESKI'!A1",'E M BEATRIZ ZALESKI'!B2) | C45: 0 | D45: 0 | E45: 0 | F45: 0 | G45: 0 | H45: 0 | I45: 0 | J45: 0 | K45: 0 | L45: 0 | M45: 0 | N45: 0 | O45: 0 | P45: 0 | Q45: 0 | R45: 0 | S45: 0 | T45: 0 | U45: 0
A46: ='E M ANTÔNIO JOSÉ DE LIMA'!B5 | B46: =HYPERLINK("#'E M ANTÔNIO JOSÉ DE LIMA'!A1",'E M ANTÔNIO JOSÉ DE LIMA'!B2) | C46: 0 | D46: 0 | E46: 0 | F46: 0 | G46: 0 | H46: 0 | I46: 0 | J46: 0 | K46: 0 | L46: 0 | M46: 0 | N46: 0 | O46: 0 | P46: 0 | Q46: 0 | R46: 0 | S46: 0 | T46: 0 | U46: 0
A47: ='E M FELIX WAN ERVEN DE BARROS'!B5 | B47: =HYPERLINK("#'E M FELIX WAN ERVEN DE BARROS'!A1",'E M FELIX WAN ERVEN DE BARROS'!B2) | C47: 0 | D47: 0 | E47: 0 | F47: 0 | G47: 0 | H47: 0 | I47: 0 | J47: 0 | K47: 0 | L47: 0 | M47: 0 | N47: 0 | O47: 0 | P47: 0 | Q47: 0 | R47: 0 | S47: 0 | T47: 0 | U47: 0
A48: ='ESCOLA MUNICIPAL HILDEBRANDO DE'!B5 | B48: =HYPERLINK("#'ESCOLA MUNICIPAL HILDEBRANDO DE'!A1",'ESCOLA MUNICIPAL HILDEBRANDO DE'!B2) | C48: 0 | D48: 0 | E48: 0 | F48: 0 | G48: 0 | H48: 0 | I48: 0 | J48: 0 | K48: 0 | L48: 0 | M48: 0 | N48: 0 | O48: 0 | P48: 0 | Q48: 0 | R48: 0 | S48: 0 | T48: 0 | U48: 0
A49: ='E M OSWALDO DA COSTA FRIAS'!B5 | B49: =HYPERLINK("#'E M OSWALDO DA COSTA FRIAS'!A1",'E M OSWALDO DA COSTA FRIAS'!B2) | C49: 0 | D49: 0 | E49: 0 | F49: 0 | G49: 0 | H49: 0 | I49: 0 | J49: 0 | K49: 0 | L49: 0 | M49: 0 | N49: 0 | O49: 0 | P49: 0 | Q49: 0 | R49: 0 | S49: 0 | T49: 0 | U49: 0
A50: ='E MZDA CARMEM NUNES MARTINS'!B5 | B50: =HYPERLINK("#'E MZDA CARMEM NUNES MARTINS'!A1",'E MZDA CARMEM NUNES MARTINS'!B2) | C50: 0 | D50: 0 | E50: 0 | F50: 0 | G50: 0 | H50: 0 | I50: 0 | J50: 0 | K50: 0 | L50: 0 | M50: 0 | N50: 0 | O50: 0 | P50: 0 | Q50: 0 | R50: 0 | S50: 0 | T50: 0 | U50: 0
A51: ='E MZDA AVELINO DE CARVALHO'!B5 | B51: =HYPERLINK("#'E MZDA AVELINO DE CARVALHO'!A1",'E MZDA AVELINO DE CARVALHO'!B2) | C51: 0 | D51: 0 | E51: 0 | F51: 0 | G51: 0 | H51: 0 | I51: 0 | J51: 0 | K51: 0 | L51: 0 | M51: 0 | N51: 0 | O51: 0 | P51: 0 | Q51: 0 | R51: 0 | S51: 0 | T51: 0 | U51: 0
A52: ='E M GERALDO VENTURA DIAS'!B5 | B52: =HYPERLINK("#'E M GERALDO VENTURA DIAS'!A1",'E M GERALDO VENTURA DIAS'!B2) | C52: 0 | D52: 0 | E52: 0 | F52: 0 | G52: 0 | H52: 0 | I52: 0 | J52: 0 | K52: 0 | L52: 0 | M52: 0 | N52: 0 | O52: 0 | P52: 0 | Q52: 0 | R52: 0 | S52: 0 | T52: 0 | U52: 0
A53: ='E M SALVADOR KLING'!B5 | B53: =HYPERLINK("#'E M SALVADOR KLING'!A1",'E M SALVADOR KLING'!B2) | C53: 0 | D53: 0 | E53: 0 | F53: 0 | G53: 0 | H53: 0 | I53: 0 | J53: 0 | K53: 0 | L53: 0 | M53: 0 | N53: 0 | O53: 0 | P53: 0 | Q53: 0 | R53: 0 | S53: 0 | T53: 0 | U53: 0
A54: ='E M PREFEITO JAMIL SABRÁ'!B5 | B54: =HYPERLINK("#'E M PREFEITO JAMIL SABRÁ'!A1",'E M PREFEITO JAMIL SABRÁ'!B2) | C54: 0 | D54: 0 | E54: 0 | F54: 0 | G54: 0 | H54: 0 | I54: 0 | J54: 0 | K54: 0 | L54: 0 | M54: 0 | N54: 0 | O54: 0 | P54: 0 | Q54: 0 | R54: 0 | S54: 0 | T54: 0 | U54: 0
A55: ='LICEU MUNICIPAL CARLOS CHAGAS F'!B5 | B55: =HYPERLINK("#'LICEU MUNICIPAL CARLOS CHAGAS F'!A1",'LICEU MUNICIPAL CARLOS CHAGAS F'!B2) | C55: 0 | D55: 0 | E55: 0 | F55: 0 | G55: 0 | H55: 0 | I55: 0 | J55: 0 | K55: 0 | L55: 0 | M55: 0 | N55: 0 | O55: 0 | P55: 0 | Q55: 0 | R55: 0 | S55: 0 | T55: 0 | U55: 0
A56: ='ESCOLA MUNICIPAL ANA MOHAMMAD'!B5 | B56: =HYPERLINK("#'ESCOLA MUNICIPAL ANA MOHAMMAD'!A1",'ESCOLA MUNICIPAL ANA MOHAMMAD'!B2) | C56: 0 | D56: 0 | E56: 0 | F56: 0 | G56: 0 | H56: 0 | I56: 0 | J56: 0 | K56: 0 | L56: 0 | M56: 0 | N56: 0 | O56: 0 | P56: 0 | Q56: 0 | R56: 0 | S56: 0 | T56: 0 | U56: 0
A57: ='ESCOLA MUNICIPAL ALTO INDEPENDÊ'!B5 | B57: =HYPERLINK("#'ESCOLA MUNICIPAL ALTO INDEPENDÊ'!A1",'ESCOLA MUNICIPAL ALTO INDEPENDÊ'!B2) | C57: 0 | D57: 0 | E57: 0 | F57: 0 | G57: 0 | H57: 0 | I57: 0 | J57: 0 | K57: 0 | L57: 0 | M57: 0 | N57: 0 | O57: 0 | P57: 0 | Q57: 0 | R57: 0 | S57: 0 | T57: 0 | U57: 0
A58: ='E M ALMIRANTE TAMANDARÉ'!B5 | B58: =HYPERLINK("#'E M ALMIRANTE TAMANDARÉ'!A1",'E M ALMIRANTE TAMANDARÉ'!B2) | C58: 0 | D58: 0 | E58: 0 | F58: 0 | G58: 0 | H58: 0 | I58: 0 | J58: 0 | K58: 0 | L58: 0 | M58: 0 | N58: 0 | O58: 0 | P58: 0 | Q58: 0 | R58: 0 | S58: 0 | T58: 0 | U58: 0
A59: ='ESCOLA MUNICIPALIZADA FREI ANIC'!B5 | B59: =HYPERLINK("#'ESCOLA MUNICIPALIZADA FREI ANIC'!A1",'ESCOLA MUNICIPALIZADA FREI ANIC'!B2) | C59: 0 | D59: 0 | E59: 0 | F59: 0 | G59: 0 | H59: 0 | I59: 0 | J59: 0 | K59: 0 | L59: 0 | M59: 0 | N59: 0 | O59: 0 | P59: 0 | Q59: 0 | R59: 0 | S59: 0 | T59: 0 | U59: 0
A60: ='E M PEDRO AMADO'!B5 | B60: =HYPERLINK("#'E M PEDRO AMADO'!A1",'E M PEDRO AMADO'!B2) | C60: 0 | D60: 0 | E60: 0 | F60: 0 | G60: 0 | H60: 0 | I60: 0 | J60: 0 | K60: 0 | L60: 0 | M60: 0 | N60: 0 | O60: 0 | P60: 0 | Q60: 0 | R60: 0 | S60: 0 | T60: 0 | U60: 0
A61: ='E M PROFª MARIA DA GLÓRIA QUEIR'!B5 | B61: =HYPERLINK("#'E M PROFª MARIA DA GLÓRIA QUEIR'!A1",'E M PROFª MARIA DA GLÓRIA QUEIR'!B2) | C61: 0 | D61: 0 | E61: 0 | F61: 0 | G61: 0 | H61: 0 | I61: 0 | J61: 0 | K61: 0 | L61: 0 | M61: 0 | N61: 0 | O61: 0 | P61: 0 | Q61: 0 | R61: 0 | S61: 0 | T61: 0 | U61: 0
A62: ='E M SEBASTIÃO LACERDA'!B5 | B62: =HYPERLINK("#'E M SEBASTIÃO LACERDA'!A1",'E M SEBASTIÃO LACERDA'!B2) | C62: 0 | D62: 0 | E62: 0 | F62: 0 | G62: 0 | H62: 0 | I62: 0 | J62: 0 | K62: 0 | L62: 0 | M62: 0 | N62: 0 | O62: 0 | P62: 0 | Q62: 0 | R62: 0 | S62: 0 | T62: 0 | U62: 0
A63: ='E M PROFESSOR FLÁVIO MACIEL'!B5 | B63: =HYPERLINK("#'E M PROFESSOR FLÁVIO MACIEL'!A1",'E M PROFESSOR FLÁVIO MACIEL'!B2) | C63: 0 | D63: 0 | E63: 0 | F63: 0 | G63: 0 | H63: 0 | I63: 0 | J63: 0 | K63: 0 | L63: 0 | M63: 0 | N63: 0 | O63: 0 | P63: 0 | Q63: 0 | R63: 0 | S63: 0 | T63: 0 | U63: 0
A64: ='ESCOLA MUNICIPAL PAULO SALDANHA'!B5 | B64: =HYPERLINK("#'ESCOLA MUNICIPAL PAULO SALDANHA'!A1",'ESCOLA MUNICIPAL PAULO SALDANHA'!B2) | C64: 0 | D64: 0 | E64: 0 | F64: 0 | G64: 0 | H64: 0 | I64: 0 | J64: 0 | K64: 0 | L64: 0 | M64: 0 | N64: 0 | O64: 0 | P64: 0 | Q64: 0 | R64: 0 | S64: 0 | T64: 0 | U64: 0
A65: ='ESCOLA MUNICIPAL PROFESSOR JOSE'!B5 | B65: =HYPERLINK("#'ESCOLA MUNICIPAL PROFESSOR JOSE'!A1",'ESCOLA MUNICIPAL PROFESSOR JOSE'!B2) | C65: 0 | D65: 0 | E65: 0 | F65: 0 | G65: 0 | H65: 0 | I65: 0 | J65: 0 | K65: 0 | L65: 0 | M65: 0 | N65: 0 | O65: 0 | P65: 0 | Q65: 0 | R65: 0 | S65: 0 | T65: 0 | U65: 0
A66: ='E M MONSENHOR CIRILLO CALAON'!B5 | B66: =HYPERLINK("#'E M MONSENHOR CIRILLO CALAON'!A1",'E M MONSENHOR CIRILLO CALAON'!B2) | C66: 0 | D66: 0 | E66: 0 | F66: 0 | G66: 0 | H66: 0 | I66: 0 | J66: 0 | K66: 0 | L66: 0 | M66: 0 | N66: 0 | O66: 0 | P66: 0 | Q66: 0 | R66: 0 | S66: 0 | T66: 0 | U66: 0
A67: ='E M AMÉRICO FERNANDES RIBEIRO'!B5 | B67: =HYPERLINK("#'E M AMÉRICO FERNANDES RIBEIRO'!A1",'E M AMÉRICO FERNANDES RIBEIRO'!B2) | C67: 0 | D67: 0 | E67: 0 | F67: 0 | G67: 0 | H67: 0 | I67: 0 | J67: 0 | K67: 0 | L67: 0 | M67: 0 | N67: 0 | O67: 0 | P67: 0 | Q67: 0 | R67: 0 | S67: 0 | T67: 0 | U67: 0
A68: ='E M PROFª JANDIRA PEIXOTO BORDI'!B5 | B68: =HYPERLINK("#'E M PROFª JANDIRA PEIXOTO BORDI'!A1",'E M PROFª JANDIRA PEIXOTO BORDI'!B2) | C68: 0 | D68: 0 | E68: 0 | F68: 0 | G68: 0 | H68: 0 | I68: 0 | J68: 0 | K68: 0 | L68: 0 | M68: 0 | N68: 0 | O68: 0 | P68: 0 | Q68: 0 | R68: 0 | S68: 0 | T68: 0 | U68: 0
A69: ='E M MONSENHOR JOÃO DE DEUS RODR'!B5 | B69: =HYPERLINK("#'E M MONSENHOR JOÃO DE DEUS RODR'!A1",'E M MONSENHOR JOÃO DE DEUS RODR'!B2) | C69: 0 | D69: 0 | E69: 0 | F69: 0 | G69: 0 | H69: 0 | I69: 0 | J69: 0 | K69: 0 | L69: 0 | M69: 0 | N69: 0 | O69: 0 | P69: 0 | Q69: 0 | R69: 0 | S69: 0 | T69: 0 | U69: 0
A70: ='E M DOM MANOEL PEDRO DA CUNHA C'!B5 | B70: =HYPERLINK("#'E M DOM MANOEL PEDRO DA CUNHA C'!A1",'E M DOM MANOEL PEDRO DA CUNHA C'!B2) | C70: 0 | D70: 0 | E70: 0 | F70: 0 | G70: 0 | H70: 0 | I70: 0 | J70: 0 | K70: 0 | L70: 0 | M70: 0 | N70: 0 | O70: 0 | P70: 0 | Q70: 0 | R70: 0 | S70: 0 | T70: 0 | U70: 0
A71: ='E M JOHANN NOEL'!B5 | B71: =HYPERLINK("#'E M JOHANN NOEL'!A1",'E M JOHANN NOEL'!B2) | C71: 0 | D71: 0 | E71: 0 | F71: 0 | G71: 0 | H71: 0 | I71: 0 | J71: 0 | K71: 0 | L71: 0 | M71: 0 | N71: 0 | O71: 0 | P71: 0 | Q71: 0 | R71: 0 | S71: 0 | T71: 0 | U71: 0
A72: ='E MZDA SANTA TEREZINHA'!B5 | B72: =HYPERLINK("#'E MZDA SANTA TEREZINHA'!A1",'E MZDA SANTA TEREZINHA'!B2) | C72: 0 | D72: 0 | E72: 0 | F72: 0 | G72: 0 | H72: 0 | I72: 0 | J72: 0 | K72: 0 | L72: 0 | M72: 0 | N72: 0 | O72: 0 | P72: 0 | Q72: 0 | R72: 0 | S72: 0 | T72: 0 | U72: 0
A73: ='E M PAPA JOÃO PAULO II'!B5 | B73: =HYPERLINK("#'E M PAPA JOÃO PAULO II'!A1",'E M PAPA JOÃO PAULO II'!B2) | C73: 0 | D73: 0 | E73: 0 | F73: 0 | G73: 0 | H73: 0 | I73: 0 | J73: 0 | K73: 0 | L73: 0 | M73: 0 | N73: 0 | O73: 0 | P73: 0 | Q73: 0 | R73: 0 | S73: 0 | T73: 0 | U73: 0
A74: ='E M STEFAN ZWEIG'!B5 | B74: =HYPERLINK("#'E M STEFAN ZWEIG'!A1",'E M STEFAN ZWEIG'!B2) | C74: 0 | D74: 0 | E74: 0 | F74: 0 | G74: 0 | H74: 0 | I74: 0 | J74: 0 | K74: 0 | L74: 0 | M74: 0 | N74: 0 | O74: 0 | P74: 0 | Q74: 0 | R74: 0 | S74: 0 | T74: 0 | U74: 0
A75: ='ESCOLA MUNICIPAL SENADOR MARIO '!B5 | B75: =HYPERLINK("#'ESCOLA MUNICIPAL SENADOR MARIO '!A1",'ESCOLA MUNICIPAL SENADOR MARIO '!B2) | C75: 0 | D75: 0 | E75: 0 | F75: 0 | G75: 0 | H75: 0 | I75: 0 | J75: 0 | K75: 0 | L75: 0 | M75: 0 | N75: 0 | O75: 0 | P75: 0 | Q75: 0 | R75: 0 | S75: 0 | T75: 0 | U75: 0
A76: ='E M DR RUBENS DE CASTRO BOMTEMP'!B5 | B76: =HYPERLINK("#'E M DR RUBENS DE CASTRO BOMTEMP'!A1",'E M DR RUBENS DE CASTRO BOMTEMP'!B2) | C76: 0 | D76: 0 | E76: 0 | F76: 0 | G76: 0 | H76: 0 | I76: 0 | J76: 0 | K76: 0 | L76: 0 | M76: 0 | N76: 0 | O76: 0 | P76: 0 | Q76: 0 | R76: 0 | S76: 0 | T76: 0 | U76: 0
A77: ='E M PAULO FREIRE'!B5 | B77: =HYPERLINK("#'E M PAULO FREIRE'!A1",'E M PAULO FREIRE'!B2) | C77: 0 | D77: 0 | E77: 0 | F77: 0 | G77: 0 | H77: 0 | I77: 0 | J77: 0 | K77: 0 | L77: 0 | M77: 0 | N77: 0 | O77: 0 | P77: 0 | Q77: 0 | R77: 0 | S77: 0 | T77: 0 | U77: 0
A78: ='E M PROFª MARIA CAMPOS DA SILVA'!B5 | B78: =HYPERLINK("#'E M PROFª MARIA CAMPOS DA SILVA'!A1",'E M PROFª MARIA CAMPOS DA SILVA'!B2) | C78: 0 | D78: 0 | E78: 0 | F78: 0 | G78: 0 | H78: 0 | I78: 0 | J78: 0 | K78: 0 | L78: 0 | M78: 0 | N78: 0 | O78: 0 | P78: 0 | Q78: 0 | R78: 0 | S78: 0 | T78: 0 | U78: 0
A79: ='E M HERCÍLIA HENRIQUES MORET'!B5 | B79: =HYPERLINK("#'E M HERCÍLIA HENRIQUES MORET'!A1",'E M HERCÍLIA HENRIQUES MORET'!B2) | C79: 0 | D79: 0 | E79: 0 | F79: 0 | G79: 0 | H79: 0 | I79: 0 | J79: 0 | K79: 0 | L79: 0 | M79: 0 | N79: 0 | O79: 0 | P79: 0 | Q79: 0 | R79: 0 | S79: 0 | T79: 0 | U79: 0
A80: ='ESCOLA MUNICIPALIZADA MOYSÉS FU'!B5 | B80: =HYPERLINK("#'ESCOLA MUNICIPALIZADA MOYSÉS FU'!A1",'ESCOLA MUNICIPALIZADA MOYSÉS FU'!B2) | C80: 0 | D80: 0 | E80: 0 | F80: 0 | G80: 0 | H80: 0 | I80: 0 | J80: 0 | K80: 0 | L80: 0 | M80: 0 | N80: 0 | O80: 0 | P80: 0 | Q80: 0 | R80: 0 | S80: 0 | T80: 0 | U80: 0
A81: ='CIEP BRIZOLÃO 474 MAESTRO GUERR'!B5 | B81: =HYPERLINK("#'CIEP BRIZOLÃO 474 MAESTRO GUERR'!A1",'CIEP BRIZOLÃO 474 MAESTRO GUERR'!B2) | C81: 0 | D81: 0 | E81: 0 | F81: 0 | G81: 0 | H81: 0 | I81: 0 | J81: 0 | K81: 0 | L81: 0 | M81: 0 | N81: 0 | O81: 0 | P81: 0 | Q81: 0 | R81: 0 | S81: 0 | T81: 0 | U81: 0
A82: ='CENTRO DE ENSINO PROF DARCY RIB'!B5 | B82: =HYPERLINK("#'CENTRO DE ENSINO PROF DARCY RIB'!A1",'CENTRO DE ENSINO PROF DARCY RIB'!B2) | C82: 0 | D82: 0 | E82: 0 | F82: 0 | G82: 0 | H82: 0 | I82: 0 | J82: 0 | K82: 0 | L82: 0 | M82: 0 | N82: 0 | O82: 0 | P82: 0 | Q82: 0 | R82: 0 | S82: 0 | T82: 0 | U82: 0
A83: ='CASA DA EDUCAÇÃO VISCONDE DE MA'!B5 | B83: =HYPERLINK("#'CASA DA EDUCAÇÃO VISCONDE DE MA'!A1",'CASA DA EDUCAÇÃO VISCONDE DE MA'!B2) | C83: 0 | D83: 0 | E83: 0 | F83: 0 | G83: 0 | H83: 0 | I83: 0 | J83: 0 | K83: 0 | L83: 0 | M83: 0 | N83: 0 | O83: 0 | P83: 0 | Q83: 0 | R83: 0 | S83: 0 | T83: 0 | U83: 0
A84: ='CENTRO DE REFERÊNCIA EM EDUCAÇÃ'!B5 | B84: =HYPERLINK("#'CENTRO DE REFERÊNCIA EM EDUCAÇÃ'!A1",'CENTRO DE REFERÊNCIA EM EDUCAÇÃ'!B2) | C84: 0 | D84: 0 | E84: 0 | F84: 0 | G84: 0 | H84: 0 | I84: 0 | J84: 0 | K84: 0 | L84: 0 | M84: 0 | N84: 0 | O84: 0 | P84: 0 | Q84: 0 | R84: 0 | S84: 0 | T84: 0 | U84: 0
A85: ='E M PROF NILTON COSTA PEREIRA D'!B5 | B85: =HYPERLINK("#'E M PROF NILTON COSTA PEREIRA D'!A1",'E M PROF NILTON COSTA PEREIRA D'!B2) | C85: 0 | D85: 0 | E85: 0 | F85: 0 | G85: 0 | H85: 0 | I85: 0 | J85: 0 | K85: 0 | L85: 0 | M85: 0 | N85: 0 | O85: 0 | P85: 0 | Q85: 0 | R85: 0 | S85: 0 | T85: 0 | U85: 0
A86: ='COLÉGIO GUNNAR VINGREN DE PETRÓ'!B5 | B86: =HYPERLINK("#'COLÉGIO GUNNAR VINGREN DE PETRÓ'!A1",'COLÉGIO GUNNAR VINGREN DE PETRÓ'!B2) | C86: 0 | D86: 0 | E86: 0 | F86: 0 | G86: 0 | H86: 0 | I86: 0 | J86: 0 | K86: 0 | L86: 0 | M86: 0 | N86: 0 | O86: 0 | P86: 0 | Q86: 0 | R86: 0 | S86: 0 | T86: 0 | U86: 0
A87: ='CENTRO DE REFERÊNCIA EM EDUC 2'!B5 | B87: =HYPERLINK("#'CENTRO DE REFERÊNCIA EM EDUC 2'!A1",'CENTRO DE REFERÊNCIA EM EDUC 2'!B2) | C87: 0 | D87: 0 | E87: 0 | F87: 0 | G87: 0 | H87: 0 | I87: 0 | J87: 0 | K87: 0 | L87: 0 | M87: 0 | N87: 0 | O87: 0 | P87: 0 | Q87: 0 | R87: 0 | S87: 0 | T87: 0 | U87: 0
A88: ='ESCOLA SANTA LUIZA DE MARILLAC'!B5 | B88: =HYPERLINK("#'ESCOLA SANTA LUIZA DE MARILLAC'!A1",'ESCOLA SANTA LUIZA DE MARILLAC'!B2) | C88: 0 | D88: 0 | E88: 0 | F88: 0 | G88: 0 | H88: 0 | I88: 0 | J88: 0 | K88: 0 | L88: 0 | M88: 0 | N88: 0 | O88: 0 | P88: 0 | Q88: 0 | R88: 0 | S88: 0 | T88: 0 | U88: 0
A89: ='CENTRO EDUCACIONAL COMUNIDADE S'!B5 | B89: =HYPERLINK("#'CENTRO EDUCACIONAL COMUNIDADE S'!A1",'CENTRO EDUCACIONAL COMUNIDADE S'!B2) | C89: 0 | D89: 0 | E89: 0 | F89: 0 | G89: 0 | H89: 0 | I89: 0 | J89: 0 | K89: 0 | L89: 0 | M89: 0 | N89: 0 | O89: 0 | P89: 0 | Q89: 0 | R89: 0 | S89: 0 | T89: 0 | U89: 0
A90: ='EDUCANDÁRIO TERRA SANTA'!B5 | B90: =HYPERLINK("#'EDUCANDÁRIO TERRA SANTA'!A1",'EDUCANDÁRIO TERRA SANTA'!B2) | C90: 0 | D90: 0 | E90: 0 | F90: 0 | G90: 0 | H90: 0 | I90: 0 | J90: 0 | K90: 0 | L90: 0 | M90: 0 | N90: 0 | O90: 0 | P90: 0 | Q90: 0 | R90: 0 | S90: 0 | T90: 0 | U90: 0
A91: ='ESCOLA GERMANO VALENTE'!B5 | B91: =HYPERLINK("#'ESCOLA GERMANO VALENTE'!A1",'ESCOLA GERMANO VALENTE'!B2) | C91: 0 | D91: 0 | E91: 0 | F91: 0 | G91: 0 | H91: 0 | I91: 0 | J91: 0 | K91: 0 | L91: 0 | M91: 0 | N91: 0 | O91: 0 | P91: 0 | Q91: 0 | R91: 0 | S91: 0 | T91: 0 | U91: 0
A92: ='ESCOLA DAS COMUNIDADES SANTO AN'!B5 | B92: =HYPERLINK("#'ESCOLA DAS COMUNIDADES SANTO AN'!A1",'ESCOLA DAS COMUNIDADES SANTO AN'!B2) | C92: 0 | D92: 0 | E92: 0 | F92: 0 | G92: 0 | H92: 0 | I92: 0 | J92: 0 | K92: 0 | L92: 0 | M92: 0 | N92: 0 | O92: 0 | P92: 0 | Q92: 0 | R92: 0 | S92: 0 | T92: 0 | U92: 0
A93: ='ESCOLA DOMÉSTICA NOSSA SENHORA '!B5 | B93: =HYPERLINK("#'ESCOLA DOMÉSTICA NOSSA SENHORA '!A1",'ESCOLA DOMÉSTICA NOSSA SENHORA '!B2) | C93: 0 | D93: 0 | E93: 0 | F93: 0 | G93: 0 | H93: 0 | I93: 0 | J93: 0 | K93: 0 | L93: 0 | M93: 0 | N93: 0 | O93: 0 | P93: 0 | Q93: 0 | R93: 0 | S93: 0 | T93: 0 | U93: 0
A94: ='ESCOLA PAROQUIAL NOSSA SENHO 3'!B5 | B94: =HYPERLINK("#'ESCOLA PAROQUIAL NOSSA SENHO 3'!A1",'ESCOLA PAROQUIAL NOSSA SENHO 3'!B2) | C94: 0 | D94: 0 | E94: 0 | F94: 0 | G94: 0 | H94: 0 | I94: 0 | J94: 0 | K94: 0 | L94: 0 | M94: 0 | N94: 0 | O94: 0 | P94: 0 | Q94: 0 | R94: 0 | S94: 0 | T94: 0 | U94: 0
A95: ='ESCOLA MONSENHOR GENTIL'!B5 | B95: =HYPERLINK("#'ESCOLA MONSENHOR GENTIL'!A1",'ESCOLA MONSENHOR GENTIL'!B2) | C95: 0 | D95: 0 | E95: 0 | F95: 0 | G95: 0 | H95: 0 | I95: 0 | J95: 0 | K95: 0 | L95: 0 | M95: 0 | N95: 0 | O95: 0 | P95: 0 | Q95: 0 | R95: 0 | S95: 0 | T95: 0 | U95: 0
A96: ='ESCOLA PAROQUIAL BOM JESUS'!B5 | B96: =HYPERLINK("#'ESCOLA PAROQUIAL BOM JESUS'!A1",'ESCOLA PAROQUIAL BOM JESUS'!B2) | C96: 0 | D96: 0 | E96: 0 | F96: 0 | G96: 0 | H96: 0 | I96: 0 | J96: 0 | K96: 0 | L96: 0 | M96: 0 | N96: 0 | O96: 0 | P96: 0 | Q96: 0 | R96: 0 | S96: 0 | T96: 0 | U96: 0
A97: ='ESCOLA PAROQUIAL CARLOS DEMIÁ'!B5 | B97: =HYPERLINK("#'ESCOLA PAROQUIAL CARLOS DEMIÁ'!A1",'ESCOLA PAROQUIAL CARLOS DEMIÁ'!B2) | C97: 0 | D97: 0 | E97: 0 | F97: 0 | G97: 0 | H97: 0 | I97: 0 | J97: 0 | K97: 0 | L97: 0 | M97: 0 | N97: 0 | O97: 0 | P97: 0 | Q97: 0 | R97: 0 | S97: 0 | T97: 0 | U97: 0
A98: ='ESCOLA PAROQUIAL NOSSA SENHO 2'!B5 | B98: =HYPERLINK("#'ESCOLA PAROQUIAL NOSSA SENHO 2'!A1",'ESCOLA PAROQUIAL NOSSA SENHO 2'!B2) | C98: 0 | D98: 0 | E98: 0 | F98: 0 | G98: 0 | H98: 0 | I98: 0 | J98: 0 | K98: 0 | L98: 0 | M98: 0 | N98: 0 | O98: 0 | P98: 0 | Q98: 0 | R98: 0 | S98: 0 | T98: 0 | U98: 0
A99: ='ESCOLA PAROQUIAL NOSSA SENHORA '!B5 | B99: =HYPERLINK("#'ESCOLA PAROQUIAL NOSSA SENHORA '!A1",'ESCOLA PAROQUIAL NOSSA SENHORA '!B2) | C99: 0 | D99: 0 | E99: 0 | F99: 0 | G99: 0 | H99: 0 | I99: 0 | J99: 0 | K99: 0 | L99: 0 | M99: 0 | N99: 0 | O99: 0 | P99: 0 | Q99: 0 | R99: 0 | S99: 0 | T99: 0 | U99: 0
A100: ='ESCOLA PAROQUIAL SÃO PEDRO DE A'!B5 | B100: =HYPERLINK("#'ESCOLA PAROQUIAL SÃO PEDRO DE A'!A1",'ESCOLA PAROQUIAL SÃO PEDRO DE A'!B2) | C100: 0 | D100: 0 | E100: 0 | F100: 0 | G100: 0 | H100: 0 | I100: 0 | J100: 0 | K100: 0 | L100: 0 | M100: 0 | N100: 0 | O100: 0 | P100: 0 | Q100: 0 | R100: 0 | S100: 0 | T100: 0 | U100: 0
A101: ='ESCOLA SANTA MARIA GORETTI'!B5 | B101: =HYPERLINK("#'ESCOLA SANTA MARIA GORETTI'!A1",'ESCOLA SANTA MARIA GORETTI'!B2) | C101: 0 | D101: 0 | E101: 0 | F101: 0 | G101: 0 | H101: 0 | I101: 0 | J101: 0 | K101: 0 | L101: 0 | M101: 0 | N101: 0 | O101: 0 | P101: 0 | Q101: 0 | R101: 0 | S101: 0 | T101: 0 | U101: 0
...

Sheet RESUMO
A1: RESUMO GERAL | H1: =HYPERLINK("#'ÍNDICE'!A1","◄ Voltar ao Índice")
A3: 🏫 ESCOLAS — PEDIDO × DEVOLUÇÃO × VALOR A COBRAR DA PREFEITURA
A4: PRODUTO | B4: PEDIDO (kg) | C4: DEVOLUÇÃO (kg) | D4: LÍQUIDO (kg) | E4: VALOR (R$/kg) | F4: VALOR A COBRAR (R$)
A5: ='Entrada de Dados'!C5 | B5: ='Entrada de Dados'!C197 | C5: ='E M ROTARY'!C9+'E M DE EDUCAÇÃO ESPECIAL SANTOS'!C9+'LICEU MUN PREFEITO CORDOLINO AM'!C9+'E M PREFEITO JAMIL SABRÁ'!C9+'LICEU MUNICIPAL CARLOS CHAGAS F'!C9+'E M PAULO FREIRE'!C9+'E M PROFª MARIA CAMPOS DA SILVA'!C9+'CASA DA EDUCAÇÃO VISCONDE DE MA'!C9+'CENTRO DE REFERÊNCIA EM EDUCAÇÃ'!C9+'ESCOLA SANTA LUIZA DE MARILLAC'!C9+'ESCOLA DOMÉSTICA NOSSA SENHORA '!C9+'ESCOLA MONSENHOR GENTIL'!C9+'ESCOLA PAROQUIAL NOSSA SENHORA '!C9+'ESCOLA PAROQUIAL SÃO PEDRO DE A'!C9+'CEI TERRA SANTA'!C9+'CEI PRIMEIRA INFÂNCIA'!C9+'CEI PROFª PATRÍCIA FERREIRA E S'!C9+'CEI DRA ZILDA ARNS NEUMANN'!C9+'CENTRO DE EDUCAÇÃO INFANTIL PRO'!C9+'CEI MONSENHOR PAULO ELIAS DAHER'!C9+'COLÉGIO GUNNAR VINGREN DE PETRÓ'!C9+'EDUCANDÁRIO TERRA SANTA'!C9+'CEI LIONS CLUBE DE PETRÓPOLIS'!C9+'ESCOLA PAROQUIAL NOSSA SENHO 2'!C9+'CENTRO DE EDUCAÇÃO INFANTIL IRM'!C9+'E M LUIZ CARLOS SOARES'!C9+'ESCOLA GERMANO VALENTE'!C9+'ESCOLA PAROQUIAL NOSSA SENHO 3'!C9+'CEI JORGE ROLANDO DA SILVA'!C9+'E M CLEMENTE FERNANDES'!C9+'E M GERALDO VENTURA DIAS'!C9+'ESCOLA DAS COMUNIDADES SANTO AN'!C9+'CEI PROFª ROSANGELA DA SILVA LE'!C9+'CEI DEISE ELOY GOMES'!C9+'CEI PROFª SONIA REGINA SCUDESE '!C9+'CEI TIA ALICE'!C9+'E M BATAILLARD'!C9+'E M SOROPTIMISTA'!C9+'E M SALVADOR KLING'!C9+'ESCOLA MUNICIPALIZADA FREI ANIC'!C9+'ESCOLA SÃO JUDAS TADEU'!C9+'CEI PEDRAS BRANCAS'!C9+'CEI MARIA THEREZA KLING DO VALL'!C9+'CEI DONA ESPERANZA DE BOURBON D'!C9+'CEI GIUSEPPE-NEVA VOLONTERIO'!C9+'CENTRO DE EDUCAÇÃO INFANTIL SÃO'!C9+'E M LEONARDO BOFF'!C9+'ESCOLA MUNICIPAL GENERAL HEITOR'!C9+'E M JOHANN NOEL'!C9+'ESCOLA SANTA MARIA GORETTI'!C9+'ESCOLA SANTA RITA DE CASSIA'!C9+'ESCOLA SÃO JOÃO BATISTA'!C9+'CEI CASA DA SOLIDARIEDADE DE NO'!C9+'CEI A SEMENTEIRA'!C9+'CEI VILA SAO JOSE'!C9+'E M DR RUBENS DE CASTRO BOMTEMP'!C9+'CEI FREI LEÃO'!C9+'CEI SÃO JOÃO BATISTA'!C9+'CEI JURACI PINTO DO AMARAL DE C'!C9+'E M PEDRO AMADO'!C9+'E M ABELARDO DE LAMARE'!C9+'ESCOLA MUNICIPAL SENADOR MARIO '!C9+'ESCOLA PAROQUIAL SÃO PIO X'!C9+'CEI SÃO CHARBEL'!C9+'E M ROSALINA NICOLAY'!C9+'CEI INÊS BELARMINO DE SOUZA'!C9+'E M PROFª MARIA DA GLÓRIA QUEIR'!C9+'CENTRO EDUCACIONAL COMUNIDADE S'!C9+'CEI ROMANO CANAVESE'!C9+'CEI CÉLIA LÔBO PAULO'!C9+'CEI PROFª DORA KILLER'!C9+'CEI ALTO INDEPENDÊNCIA'!C9+'ESCOLA MUNICIPAL ALTO INDEPENDÊ'!C9+'E M PAPA JOÃO PAULO II'!C9+'CEI ANDRÉ REBOUÇAS'!C9+'CEI PROFª HERMÍNIA MATHEUS'!C9+'ESCOLA MUNICIPAL MAJOR JÚLIO FR'!C9+'E M ALMIRANTE TAMANDARÉ'!C9+'ESCOLA PAROQUIAL CARLOS DEMIÁ'!C9+'CENTRO PAROQUIAL DE EDUCAÇÃO IN'!C9+'CEI IRMÃ SILVANA'!C9+'CEI OLÍVIA MACHADO DA COSTA NOG'!C9+'E M GOVERNADOR MARCELLO ALENCAR'!C9+'E M PROFESSOR FLÁVIO MACIEL'!C9+'E M PROFª JANDIRA PEIXOTO BORDI'!C9+'E M STEFAN ZWEIG'!C9+'ESCOLA PAROQUIAL BOM JESUS'!C9+'CEI MARLI SOARES FERREIRA NETTO'!C9+'CENTRO DE EDUCAÇÃO INFANTIL CHI'!C9+'CEI VILA IPANEMA'!C9+'E M ROBERT KENNEDY'!C9+'ESCOLA MUNICIPAL ANA MOHAMMAD'!C9+'ESCOLA SÃO CRISTÓVÃO'!C9+'CEI DÉA LÚCIA CORDEIRO'!C9+'CEI SAGRADA FAMÍLIA'!C9+'CEI SÃO JOSÉ DAS OBLATAS DE NAZ'!C9+'ESCOLA MUNICIPAL JORGE AMADO'!C9+'E M FÁBRICA DO SABER'!C9+'CIEP BRIZOLÃO 474 MAESTRO GUERR'!C9+'CENTRO DE ENSINO PROF DARCY RIB'!C9+'CEI ANDRÉ VANZAN'!C9+'CENTRO DE EDUCAÇÃO INFANTIL CAR'!C9+'CEI BOA VISTA'!C9+'ASSOCIAÇÃO DA CRECHE SÃO FRANCI'!C9+'ESCOLA MUNICIPAL PAULO SALDANHA'!C9+'ESCOLA MUNICIPAL LÚCIA DE ALMEI'!C9+'E M DOM MANOEL PEDRO DA CUNHA C'!C9+'ESCOLA SÃO GERALDO'!C9+'CEI LULU MONTEIRO DE CASTRO'!C9+'CEI CARANGOLA'!C9+'ASSOCIAÇÃO RECREAR'!C9+'CENTRO DE EDUCAÇÃO INFANTIL CAS'!C9+'E M ROSEMIRA DE OLIVEIRA CAVALC'!C9+'E MZDA CARMEM NUNES MARTINS'!C9+'CEI SÃO JOSÉ DO ITAMARATI'!C9+'E M DUQUE DE CAXIAS'!C9+'CENTRO DE EDUCAÇÃO INFANTIL 2'!C9+'E M ANTÔNIO LEITE GARCIA'!C9+'ESCOLA PAROQUIAL DA ALCOBAÇA'!C9+'CENTRO DE EDUCAÇÃO INFANTIL LOT'!C9+'ESCOLA PAROQUIAL DO LOTEAMENTO '!C9+'E M PROF JOAQUIM DEISTER'!C9+'E M MARIETA GONÇALVES'!C9+'ESCOLA MUNICIPAL ODETTE YOUNG M'!C9+'ESCOLA MUNICIPAL PROFESSOR JOSE'!C9+'E M HERCÍLIA HENRIQUES MORET'!C9+'COLEGIO VICENTINO PADRE CORRÊA'!C9+'CEI PROFª MARLUCE DE SOUZA PEST'!C9+'CEI IRINEU MARINHO'!C9+'CEI DAGMAR ROLANDO DE OLIVEIRA'!C9+'CEI NOSSA SENHORA DA GLÓRIA'!C9+'E M PROF NILTON COSTA PEREIRA D'!C9+'CENTRO DE EDUCAÇÃO INFANTIL SÉR'!C9+'CEI SANTO ANTÔNIO AGOSTINHO'!C9+'CEI OSWALDO CRUZ'!C9+'E M MAGDALENA TAGLIAFERRO'!C9+'ESCOLA SÃO JOSÉ DO CAETITU'!C9+'CRECHE-ESCOLA CASTELO SÃO MANOE'!C9+'CEI THEREZINHA DE JESUS LIMA'!C9+'ESCOLA MUNICIPAL PROFESSOR PAUL'!C9+'COLÉGIO ANGLICANO DE ARARAS'!C9+'ESCOLA PAROQUIAL SANTA BERNADET'!C9+'CEI VISTA ALEGRE'!C9+'CEI DENISE BESSA DE OLIVA MAYA'!C9+'CEI VIDEIRINHA'!C9+'E M AMÉRICO FERNANDES RIBEIRO'!C9+'ESCOLA MUNICIPAL AUGUSTO PUGNAL'!C9+'ESCOLA MUNICIPAL CELINA SCHECHN'!C9+'E M DARCY CORREA DA VEIGA'!C9+'E M DR PAULA BUARQUE'!C9+'LICEU SÃO JOSÉ DE ITAIPAVA'!C9+'CEI LUIZ MARCHIORI'!C9+'CENTRO DE EDUCAÇÃO INFANTIL AUG'!C9+'CEI PROFª ADRIANA CONSTÂNCIO TR'!C9+'E M AMÉLIA ANTUNES RABELLO'!C9+'CEI PREFEITO SÉRGIO FADEL'!C9+'E M DR THEODORO MACHADO'!C9+'ESCOLA SANTO ANTÔNIO'!C9+'E M TAQUARIL'!C9+'E M MONSENHOR JOÃO DE DEUS RODR'!C9+'CENTRO DE REFERÊNCIA EM EDUC 2'!C9+'CEI PROFª GRAÇA COSTA'!C9+'CEI VILA LEOPOLDINA'!C9+'CEI NILO PEÇANHA'!C9+'E MZDA SANTA TEREZINHA'!C9+'CEI CRIANÇA SANTA EDWIGES'!C9+'E M ARNALDO DYCKERHOFF'!C9+'E M CARLOS CANEDO'!C9+'E M BEATRIZ ZALESKI'!C9+'E M ANTÔNIO JOSÉ DE LIMA'!C9+'E M FELIX WAN ERVEN DE BARROS'!C9+'ESCOLA MUNICIPAL HILDEBRANDO DE'!C9+'E M OSWALDO DA COSTA FRIAS'!C9+'E MZDA AVELINO DE CARVALHO'!C9+'ESCOLA MUNICIPALIZADA MOYSÉS FU'!C9+'CEI ANGELA MARIA DA CONCEIÇÃO S'!C9+'CEI JOSÉ GONÇALVES DA MOTTA'!C9+'E M DR BARROS FRANCO'!C9+'E M MAJOR THEÓFILO DE CARVALHO'!C9+'E M JOÃO KOPKE'!C9+'CEI ASSOCIAÇÃO BENEFICENTE FAZE'!C9+'ESCOLA SAO FRANCISCO DE ASSIS'!C9+'CEI SÃO FRANCISCO ASSIS'!C9+'CEI ALDEIA DA CRIANCA'!C9+'ESCOLA MUNICIPAL ODETTE FONSECA'!C9+'CEI ANA CAROLINA TELLES'!C9+'E M SEBASTIÃO LACERDA'!C9+'E M DOM PEDRO DE ALCÂNTARA'!C9+'ESCOLA NOSSA SENHORA DE FÁTIMA'!C9+'ESCOLA PAROQUIAL SÃO FRANCISCO '!C9+'E M MONSENHOR CIRILLO CALAON'!C9 | D5: =B5-C5 | E5: ='Entrada de Dados'!C2 | F5: =D5*E5
A6: ='Entrada de Dados'!D5 | B6: ='Entrada de Dados'!D197 | C6: ='E M ROTARY'!C10+'E M DE EDUCAÇÃO ESPECIAL SANTOS'!C10+'LICEU MUN PREFEITO CORDOLINO AM'!C10+'E M PREFEITO JAMIL SABRÁ'!C10+'LICEU MUNICIPAL CARLOS CHAGAS F'!C10+'E M PAULO FREIRE'!C10+'E M PROFª MARIA CAMPOS DA SILVA'!C10+'CASA DA EDUCAÇÃO VISCONDE DE MA'!C10+'CENTRO DE REFERÊNCIA EM EDUCAÇÃ'!C10+'ESCOLA SANTA LUIZA DE MARILLAC'!C10+'ESCOLA DOMÉSTICA NOSSA SENHORA '!C10+'ESCOLA MONSENHOR GENTIL'!C10+'ESCOLA PAROQUIAL NOSSA SENHORA '!C10+'ESCOLA PAROQUIAL SÃO PEDRO DE A'!C10+'CEI TERRA SANTA'!C10+'CEI PRIMEIRA INFÂNCIA'!C10+'CEI PROFª PATRÍCIA FERREIRA E S'!C10+'CEI DRA ZILDA ARNS NEUMANN'!C10+'CENTRO DE EDUCAÇÃO INFANTIL PRO'!C10+'CEI MONSENHOR PAULO ELIAS DAHER'!C10+'COLÉGIO GUNNAR VINGREN DE PETRÓ'!C10+'EDUCANDÁRIO TERRA SANTA'!C10+'CEI LIONS CLUBE DE PETRÓPOLIS'!C10+'ESCOLA PAROQUIAL NOSSA SENHO 2'!C10+'CENTRO DE EDUCAÇÃO INFANTIL IRM'!C10+'E M LUIZ CARLOS SOARES'!C10+'ESCOLA GERMANO VALENTE'!C10+'ESCOLA PAROQUIAL NOSSA SENHO 3'!C10+'CEI JORGE ROLANDO DA SILVA'!C10+'E M CLEMENTE FERNANDES'!C10+'E M GERALDO VENTURA DIAS'!C10+'ESCOLA DAS COMUNIDADES SANTO AN'!C10+'CEI PROFª ROSANGELA DA SILVA LE'!C10+'CEI DEISE ELOY GOMES'!C10+'CEI PROFª SONIA REGINA SCUDESE '!C10+'CEI TIA ALICE'!C10+'E M BATAILLARD'!C10+'E M SOROPTIMISTA'!C10+'E M SALVADOR KLING'!C10+'ESCOLA MUNICIPALIZADA FREI ANIC'!C10+'ESCOLA SÃO JUDAS TADEU'!C10+'CEI PEDRAS BRANCAS'!C10+'CEI MARIA THEREZA KLING DO VALL'!C10+'CEI DONA ESPERANZA DE BOURBON D'!C10+'CEI GIUSEPPE-NEVA VOLONTERIO'!C10+'CENTRO DE EDUCAÇÃO INFANTIL SÃO'!C10+'E M LEONARDO BOFF'!C10+'ESCOLA MUNICIPAL GENERAL HEITOR'!C10+'E M JOHANN NOEL'!C10+'ESCOLA SANTA MARIA GORETTI'!C10+'ESCOLA SANTA RITA DE CASSIA'!C10+'ESCOLA SÃO JOÃO BATISTA'!C10+'CEI CASA DA SOLIDARIEDADE DE NO'!C10+'CEI A SEMENTEIRA'!C10+'CEI VILA SAO JOSE'!C10+'E M DR RUBENS DE CASTRO BOMTEMP'!C10+'CEI FREI LEÃO'!C10+'CEI SÃO JOÃO BATISTA'!C10+'CEI JURACI PINTO DO AMARAL DE C'!C10+'E M PEDRO AMADO'!C10+'E M ABELARDO DE LAMARE'!C10+'ESCOLA MUNICIPAL SENADOR MARIO '!C10+'ESCOLA PAROQUIAL SÃO PIO X'!C10+'CEI SÃO CHARBEL'!C10+'E M ROSALINA NICOLAY'!C10+'CEI INÊS BELARMINO DE SOUZA'!C10+'E M PROFª MARIA DA GLÓRIA QUEIR'!C10+'CENTRO EDUCACIONAL COMUNIDADE S'!C10+'CEI ROMANO CANAVESE'!C10+'CEI CÉLIA LÔBO PAULO'!C10+'CEI PROFª DORA KILLER'!C10+'CEI ALTO INDEPENDÊNCIA'!C10+'ESCOLA MUNICIPAL ALTO INDEPENDÊ'!C10+'E M PAPA JOÃO PAULO II'!C10+'CEI ANDRÉ REBOUÇAS'!C10+'CEI PROFª HERMÍNIA MATHEUS'!C10+'ESCOLA MUNICIPAL MAJOR JÚLIO FR'!C10+'E M ALMIRANTE TAMANDARÉ'!C10+'ESCOLA PAROQUIAL CARLOS DEMIÁ'!C10+'CENTRO PAROQUIAL DE EDUCAÇÃO IN'!C10+'CEI IRMÃ SILVANA'!C10+'CEI OLÍVIA MACHADO DA COSTA NOG'!C10+'E M GOVERNADOR MARCELLO ALENCAR'!C10+'E M PROFESSOR FLÁVIO MACIEL'!C10+'E M PROFª JANDIRA PEIXOTO BORDI'!C10+'E M STEFAN ZWEIG'!C10+'ESCOLA PAROQUIAL BOM JESUS'!C10+'CEI MARLI SOARES FERREIRA NETTO'!C10+'CENTRO DE EDUCAÇÃO INFANTIL CHI'!C10+'CEI VILA IPANEMA'!C10+'E M ROBERT KENNEDY'!C10+'ESCOLA MUNICIPAL ANA MOHAMMAD'!C10+'ESCOLA SÃO CRISTÓVÃO'!C10+'CEI DÉA LÚCIA CORDEIRO'!C10+'CEI SAGRADA FAMÍLIA'!C10+'CEI SÃO JOSÉ DAS OBLATAS DE NAZ'!C10+'ESCOLA MUNICIPAL JORGE AMADO'!C10+'E M FÁBRICA DO SABER'!C10+'CIEP BRIZOLÃO 474 MAESTRO GUERR'!C10+'CENTRO DE ENSINO PROF DARCY RIB'!C10+'CEI ANDRÉ VANZAN'!C10+'CENTRO DE EDUCAÇÃO INFANTIL CAR'!C10+'CEI BOA VISTA'!C10+'ASSOCIAÇÃO DA CRECHE SÃO FRANCI'!C10+'ESCOLA MUNICIPAL PAULO SALDANHA'!C10+'ESCOLA MUNICIPAL LÚCIA DE ALMEI'!C10+'E M DOM MANOEL PEDRO DA CUNHA C'!C10+'ESCOLA SÃO GERALDO'!C10+'CEI LULU MONTEIRO DE CASTRO'!C10+'CEI CARANGOLA'!C10+'ASSOCIAÇÃO RECREAR'!C10+'CENTRO DE EDUCAÇÃO INFANTIL CAS'!C10+'E M ROSEMIRA DE OLIVEIRA CAVALC'!C10+'E MZDA CARMEM NUNES MARTINS'!C10+'CEI SÃO JOSÉ DO ITAMARATI'!C10+'E M DUQUE DE CAXIAS'!C10+'CENTRO DE EDUCAÇÃO INFANTIL 2'!C10+'E M ANTÔNIO LEITE GARCIA'!C10+'ESCOLA PAROQUIAL DA ALCOBAÇA'!C10+'CENTRO DE EDUCAÇÃO INFANTIL LOT'!C10+'ESCOLA PAROQUIAL DO LOTEAMENTO '!C10+'E M PROF JOAQUIM DEISTER'!C10+'E M MARIETA GONÇALVES'!C10+'ESCOLA MUNICIPAL ODETTE YOUNG M'!C10+'ESCOLA MUNICIPAL PROFESSOR JOSE'!C10+'E M HERCÍLIA HENRIQUES MORET'!C10+'COLEGIO VICENTINO PADRE CORRÊA'!C10+'CEI PROFª MARLUCE DE SOUZA PEST'!C10+'CEI IRINEU MARINHO'!C10+'CEI DAGMAR ROLANDO DE OLIVEIRA'!C10+'CEI NOSSA SENHORA DA GLÓRIA'!C10+'E M PROF NILTON COSTA PEREIRA D'!C10+'CENTRO DE EDUCAÇÃO INFANTIL SÉR'!C10+'CEI SANTO ANTÔNIO AGOSTINHO'!C10+'CEI OSWALDO CRUZ'!C10+'E M MAGDALENA TAGLIAFERRO'!C10+'ESCOLA SÃO JOSÉ DO CAETITU'!C10+'CRECHE-ESCOLA CASTELO SÃO MANOE'!C10+'CEI THEREZINHA DE JESUS LIMA'!C10+'ESCOLA MUNICIPAL PROFESSOR PAUL'!C10+'COLÉGIO ANGLICANO DE ARARAS'!C10+'ESCOLA PAROQUIAL SANTA BERNADET'!C10+'CEI VISTA ALEGRE'!C10+'CEI DENISE BESSA DE OLIVA MAYA'!C10+'CEI VIDEIRINHA'!C10+'E M AMÉRICO FERNANDES RIBEIRO'!C10+'ESCOLA MUNICIPAL AUGUSTO PUGNAL'!C10+'ESCOLA MUNICIPAL CELINA SCHECHN'!C10+'E M DARCY CORREA DA VEIGA'!C10+'E M DR PAULA BUARQUE'!C10+'LICEU SÃO JOSÉ DE ITAIPAVA'!C10+'CEI LUIZ MARCHIORI'!C10+'CENTRO DE EDUCAÇÃO INFANTIL AUG'!C10+'CEI PROFª ADRIANA CONSTÂNCIO TR'!C10+'E M AMÉLIA ANTUNES RABELLO'!C10+'CEI PREFEITO SÉRGIO FADEL'!C10+'E M DR THEODORO MACHADO'!C10+'ESCOLA SANTO ANTÔNIO'!C10+'E M TAQUARIL'!C10+'E M MONSENHOR JOÃO DE DEUS RODR'!C10+'CENTRO DE REFERÊNCIA EM EDUC 2'!C10+'CEI PROFª GRAÇA COSTA'!C10+'CEI VILA LEOPOLDINA'!C10+'CEI NILO PEÇANHA'!C10+'E MZDA SANTA TEREZINHA'!C10+'CEI CRIANÇA SANTA EDWIGES'!C10+'E M ARNALDO DYCKERHOFF'!C10+'E M CARLOS CANEDO'!C10+'E M BEATRIZ ZALESKI'!C10+'E M ANTÔNIO JOSÉ DE LIMA'!C10+'E M FELIX WAN ERVEN DE BARROS'!C10+'ESCOLA MUNICIPAL HILDEBRANDO DE'!C10+'E M OSWALDO DA COSTA FRIAS'!C10+'E MZDA AVELINO DE CARVALHO'!C10+'ESCOLA MUNICIPALIZADA MOYSÉS FU'!C10+'CEI ANGELA MARIA DA CONCEIÇÃO S'!C10+'CEI JOSÉ GONÇALVES DA MOTTA'!C10+'E M DR BARROS FRANCO'!C10+'E M MAJOR THEÓFILO DE CARVALHO'!C10+'E M JOÃO KOPKE'!C10+'CEI ASSOCIAÇÃO BENEFICENTE FAZE'!C10+'ESCOLA SAO FRANCISCO DE ASSIS'!C10+'CEI SÃO FRANCISCO ASSIS'!C10+'CEI ALDEIA DA CRIANCA'!C10+'ESCOLA MUNICIPAL ODETTE FONSECA'!C10+'CEI ANA CAROLINA TELLES'!C10+'E M SEBASTIÃO LACERDA'!C10+'E M DOM PEDRO DE ALCÂNTARA'!C10+'ESCOLA NOSSA SENHORA DE FÁTIMA'!C10+'ESCOLA PAROQUIAL SÃO FRANCISCO '!C10+'E M MONSENHOR CIRILLO CALAON'!C10 | D6: =B6-C6 | E6: ='Entrada de Dados'!D2 | F6: =D6*E6
A7: ='Entrada de Dados'!E5 | B7: ='Entrada de Dados'!E197 | C7: ='E M ROTARY'!C11+'E M DE EDUCAÇÃO ESPECIAL SANTOS'!C11+'LICEU MUN PREFEITO CORDOLINO AM'!C11+'E M PREFEITO JAMIL SABRÁ'!C11+'LICEU MUNICIPAL CARLOS CHAGAS F'!C11+'E M PAULO FREIRE'!C11+'E M PROFª MARIA CAMPOS DA SILVA'!C11+'CASA DA EDUCAÇÃO VISCONDE DE MA'!C11+'CENTRO DE REFERÊNCIA EM EDUCAÇÃ'!C11+'ESCOLA SANTA LUIZA DE MARILLAC'!C11+'ESCOLA DOMÉSTICA NOSSA SENHORA '!C11+'ESCOLA MONSENHOR GENTIL'!C11+'ESCOLA PAROQUIAL NOSSA SENHORA '!C11+'ESCOLA PAROQUIAL SÃO PEDRO DE A'!C11+'CEI TERRA SANTA'!C11+'CEI PRIMEIRA INFÂNCIA'!C11+'CEI PROFª PATRÍCIA FERREIRA E S'!C11+'CEI DRA ZILDA ARNS NEUMANN'!C11+'CENTRO DE EDUCAÇÃO INFANTIL PRO'!C11+'CEI MONSENHOR PAULO ELIAS DAHER'!C11+'COLÉGIO GUNNAR VINGREN DE PETRÓ'!C11+'EDUCANDÁRIO TERRA SANTA'!C11+'CEI LIONS CLUBE DE PETRÓPOLIS'!C11+'ESCOLA PAROQUIAL NOSSA SENHO 2'!C11+'CENTRO DE EDUCAÇÃO INFANTIL IRM'!C11+'E M LUIZ CARLOS SOARES'!C11+'ESCOLA GERMANO VALENTE'!C11+'ESCOLA PAROQUIAL NOSSA SENHO 3'!C11+'CEI JORGE ROLANDO DA SILVA'!C11+'E M CLEMENTE FERNANDES'!C11+'E M GERALDO VENTURA DIAS'!C11+'ESCOLA DAS COMUNIDADES SANTO AN'!C11+'CEI PROFª ROSANGELA DA SILVA LE'!C11+'CEI DEISE ELOY GOMES'!C11+'CEI PROFª SONIA REGINA SCUDESE '!C11+'CEI TIA ALICE'!C11+'E M BATAILLARD'!C11+'E M SOROPTIMISTA'!C11+'E M SALVADOR KLING'!C11+'ESCOLA MUNICIPALIZADA FREI ANIC'!C11+'ESCOLA SÃO JUDAS TADEU'!C11+'CEI PEDRAS BRANCAS'!C11+'CEI MARIA THEREZA KLING DO VALL'!C11+'CEI DONA ESPERANZA DE BOURBON D'!C11+'CEI GIUSEPPE-NEVA VOLONTERIO'!C11+'CENTRO DE EDUCAÇÃO INFANTIL SÃO'!C11+'E M LEONARDO BOFF'!C11+'ESCOLA MUNICIPAL GENERAL HEITOR'!C11+'E M JOHANN NOEL'!C11+'ESCOLA SANTA MARIA GORETTI'!C11+'ESCOLA SANTA RITA DE CASSIA'!C11+'ESCOLA SÃO JOÃO BATISTA'!C11+'CEI CASA DA SOLIDARIEDADE DE NO'!C11+'CEI A SEMENTEIRA'!C11+'CEI VILA SAO JOSE'!C11+'E M DR RUBENS DE CASTRO BOMTEMP'!C11+'CEI FREI LEÃO'!C11+'CEI SÃO JOÃO BATISTA'!C11+'CEI JURACI PINTO DO AMARAL DE C'!C11+'E M PEDRO AMADO'!C11+'E M ABELARDO DE LAMARE'!C11+'ESCOLA MUNICIPAL SENADOR MARIO '!C11+'ESCOLA PAROQUIAL SÃO PIO X'!C11+'CEI SÃO CHARBEL'!C11+'E M ROSALINA NICOLAY'!C11+'CEI INÊS BELARMINO DE SOUZA'!C11+'E M PROFª MARIA DA GLÓRIA QUEIR'!C11+'CENTRO EDUCACIONAL COMUNIDADE S'!C11+'CEI ROMANO CANAVESE'!C11+'CEI CÉLIA LÔBO PAULO'!C11+'CEI PROFª DORA KILLER'!C11+'CEI ALTO INDEPENDÊNCIA'!C11+'ESCOLA MUNICIPAL ALTO INDEPENDÊ'!C11+'E M PAPA JOÃO PAULO II'!C11+'CEI ANDRÉ REBOUÇAS'!C11+'CEI PROFª HERMÍNIA MATHEUS'!C11+'ESCOLA MUNICIPAL MAJOR JÚLIO FR'!C11+'E M ALMIRANTE TAMANDARÉ'!C11+'ESCOLA PAROQUIAL CARLOS DEMIÁ'!C11+'CENTRO PAROQUIAL DE EDUCAÇÃO IN'!C11+'CEI IRMÃ SILVANA'!C11+'CEI OLÍVIA MACHADO DA COSTA NOG'!C11+'E M GOVERNADOR MARCELLO ALENCAR'!C11+'E M PROFESSOR FLÁVIO MACIEL'!C11+'E M PROFª JANDIRA PEIXOTO BORDI'!C11+'E M STEFAN ZWEIG'!C11+'ESCOLA PAROQUIAL BOM JESUS'!C11+'CEI MARLI SOARES FERREIRA NETTO'!C11+'CENTRO DE EDUCAÇÃO INFANTIL CHI'!C11+'CEI VILA IPANEMA'!C11+'E M ROBERT KENNEDY'!C11+'ESCOLA MUNICIPAL ANA MOHAMMAD'!C11+'ESCOLA SÃO CRISTÓVÃO'!C11+'CEI DÉA LÚCIA CORDEIRO'!C11+'CEI SAGRADA FAMÍLIA'!C11+'CEI SÃO JOSÉ DAS OBLATAS DE NAZ'!C11+'ESCOLA MUNICIPAL JORGE AMADO'!C11+'E M FÁBRICA DO SABER'!C11+'CIEP BRIZOLÃO 474 MAESTRO GUERR'!C11+'CENTRO DE ENSINO PROF DARCY RIB'!C11+'CEI ANDRÉ VANZAN'!C11+'CENTRO DE EDUCAÇÃO INFANTIL CAR'!C11+'CEI BOA VISTA'!C11+'ASSOCIAÇÃO DA CRECHE SÃO FRANCI'!C11+'ESCOLA MUNICIPAL PAULO SALDANHA'!C11+'ESCOLA MUNICIPAL LÚCIA DE ALMEI'!C11+'E M DOM MANOEL PEDRO DA CUNHA C'!C11+'ESCOLA SÃO GERALDO'!C11+'CEI LULU MONTEIRO DE CASTRO'!C11+'CEI CARANGOLA'!C11+'ASSOCIAÇÃO RECREAR'!C11+'CENTRO DE EDUCAÇÃO INFANTIL CAS'!C11+'E M ROSEMIRA DE OLIVEIRA CAVALC'!C11+'E MZDA CARMEM NUNES MARTINS'!C11+'CEI SÃO JOSÉ DO ITAMARATI'!C11+'E M DUQUE DE CAXIAS'!C11+'CENTRO DE EDUCAÇÃO INFANTIL 2'!C11+'E M ANTÔNIO LEITE GARCIA'!C11+'ESCOLA PAROQUIAL DA ALCOBAÇA'!C11+'CENTRO DE EDUCAÇÃO INFANTIL LOT'!C11+'ESCOLA PAROQUIAL DO LOTEAMENTO '!C11+'E M PROF JOAQUIM DEISTER'!C11+'E M MARIETA GONÇALVES'!C11+'ESCOLA MUNICIPAL ODETTE YOUNG M'!C11+'ESCOLA MUNICIPAL PROFESSOR JOSE'!C11+'E M HERCÍLIA HENRIQUES MORET'!C11+'COLEGIO VICENTINO PADRE CORRÊA'!C11+'CEI PROFª MARLUCE DE SOUZA PEST'!C11+'CEI IRINEU MARINHO'!C11+'CEI DAGMAR ROLANDO DE OLIVEIRA'!C11+'CEI NOSSA SENHORA DA GLÓRIA'!C11+'E M PROF NILTON COSTA PEREIRA D'!C11+'CENTRO DE EDUCAÇÃO INFANTIL SÉR'!C11+'CEI SANTO ANTÔNIO AGOSTINHO'!C11+'CEI OSWALDO CRUZ'!C11+'E M MAGDALENA TAGLIAFERRO'!C11+'ESCOLA SÃO JOSÉ DO CAETITU'!C11+'CRECHE-ESCOLA CASTELO SÃO MANOE'!C11+'CEI THEREZINHA DE JESUS LIMA'!C11+'ESCOLA MUNICIPAL PROFESSOR PAUL'!C11+'COLÉGIO ANGLICANO DE ARARAS'!C11+'ESCOLA PAROQUIAL SANTA BERNADET'!C11+'CEI VISTA ALEGRE'!C11+'CEI DENISE BESSA DE OLIVA MAYA'!C11+'CEI VIDEIRINHA'!C11+'E M AMÉRICO FERNANDES RIBEIRO'!C11+'ESCOLA MUNICIPAL AUGUSTO PUGNAL'!C11+'ESCOLA MUNICIPAL CELINA SCHECHN'!C11+'E M DARCY CORREA DA VEIGA'!C11+'E M DR PAULA BUARQUE'!C11+'LICEU SÃO JOSÉ DE ITAIPAVA'!C11+'CEI LUIZ MARCHIORI'!C11+'CENTRO DE EDUCAÇÃO INFANTIL AUG'!C11+'CEI PROFª ADRIANA CONSTÂNCIO TR'!C11+'E M AMÉLIA ANTUNES RABELLO'!C11+'CEI PREFEITO SÉRGIO FADEL'!C11+'E M DR THEODORO MACHADO'!C11+'ESCOLA SANTO ANTÔNIO'!C11+'E M TAQUARIL'!C11+'E M MONSENHOR JOÃO DE DEUS RODR'!C11+'CENTRO DE REFERÊNCIA EM EDUC 2'!C11+'CEI PROFª GRAÇA COSTA'!C11+'CEI VILA LEOPOLDINA'!C11+'CEI NILO PEÇANHA'!C11+'E MZDA SANTA TEREZINHA'!C11+'CEI CRIANÇA SANTA EDWIGES'!C11+'E M ARNALDO DYCKERHOFF'!C11+'E M CARLOS CANEDO'!C11+'E M BEATRIZ ZALESKI'!C11+'E M ANTÔNIO JOSÉ DE LIMA'!C11+'E M FELIX WAN ERVEN DE BARROS'!C11+'ESCOLA MUNICIPAL HILDEBRANDO DE'!C11+'E M OSWALDO DA COSTA FRIAS'!C11+'E MZDA AVELINO DE CARVALHO'!C11+'ESCOLA MUNICIPALIZADA MOYSÉS FU'!C11+'CEI ANGELA MARIA DA CONCEIÇÃO S'!C11+'CEI JOSÉ GONÇALVES DA MOTTA'!C11+'E M DR BARROS FRANCO'!C11+'E M MAJOR THEÓFILO DE CARVALHO'!C11+'E M JOÃO KOPKE'!C11+'CEI ASSOCIAÇÃO BENEFICENTE FAZE'!C11+'ESCOLA SAO FRANCISCO DE ASSIS'!C11+'CEI SÃO FRANCISCO ASSIS'!C11+'CEI ALDEIA DA CRIANCA'!C11+'ESCOLA MUNICIPAL ODETTE FONSECA'!C11+'CEI ANA CAROLINA TELLES'!C11+'E M SEBASTIÃO LACERDA'!C11+'E M DOM PEDRO DE ALCÂNTARA'!C11+'ESCOLA NOSSA SENHORA DE FÁTIMA'!C11+'ESCOLA PAROQUIAL SÃO FRANCISCO '!C11+'E M MONSENHOR CIRILLO CALAON'!C11 | D7: =B7-C7 | E7: ='Entrada de Dados'!E2 | F7: =D7*E7
A8: ='Entrada de Dados'!F5 | B8: ='Entrada de Dados'!F197 | C8: ='E M ROTARY'!C12+'E M DE EDUCAÇÃO ESPECIAL SANTOS'!C12+'LICEU MUN PREFEITO CORDOLINO AM'!C12+'E M PREFEITO JAMIL SABRÁ'!C12+'LICEU MUNICIPAL CARLOS CHAGAS F'!C12+'E M PAULO FREIRE'!C12+'E M PROFª MARIA CAMPOS DA SILVA'!C12+'CASA DA EDUCAÇÃO VISCONDE DE MA'!C12+'CENTRO DE REFERÊNCIA EM EDUCAÇÃ'!C12+'ESCOLA SANTA LUIZA DE MARILLAC'!C12+'ESCOLA DOMÉSTICA NOSSA SENHORA '!C12+'ESCOLA MONSENHOR GENTIL'!C12+'ESCOLA PAROQUIAL NOSSA SENHORA '!C12+'ESCOLA PAROQUIAL SÃO PEDRO DE A'!C12+'CEI TERRA SANTA'!C12+'CEI PRIMEIRA INFÂNCIA'!C12+'CEI PROFª PATRÍCIA FERREIRA E S'!C12+'CEI DRA ZILDA ARNS NEUMANN'!C12+'CENTRO DE EDUCAÇÃO INFANTIL PRO'!C12+'CEI MONSENHOR PAULO ELIAS DAHER'!C12+'COLÉGIO GUNNAR VINGREN DE PETRÓ'!C12+'EDUCANDÁRIO TERRA SANTA'!C12+'CEI LIONS CLUBE DE PETRÓPOLIS'!C12+'ESCOLA PAROQUIAL NOSSA SENHO 2'!C12+'CENTRO DE EDUCAÇÃO INFANTIL IRM'!C12+'E M LUIZ CARLOS SOARES'!C12+'ESCOLA GERMANO VALENTE'!C12+'ESCOLA PAROQUIAL NOSSA SENHO 3'!C12+'CEI JORGE ROLANDO DA SILVA'!C12+'E M CLEMENTE FERNANDES'!C12+'E M GERALDO VENTURA DIAS'!C12+'ESCOLA DAS COMUNIDADES SANTO AN'!C12+'CEI PROFª ROSANGELA DA SILVA LE'!C12+'CEI DEISE ELOY GOMES'!C12+'CEI PROFª SONIA REGINA SCUDESE '!C12+'CEI TIA ALICE'!C12+'E M BATAILLARD'!C12+'E M SOROPTIMISTA'!C12+'E M SALVADOR KLING'!C12+'ESCOLA MUNICIPALIZADA FREI ANIC'!C12+'ESCOLA SÃO JUDAS TADEU'!C12+'CEI PEDRAS BRANCAS'!C12+'CEI MARIA THEREZA KLING DO VALL'!C12+'CEI DONA ESPERANZA DE BOURBON D'!C12+'CEI GIUSEPPE-NEVA VOLONTERIO'!C12+'CENTRO DE EDUCAÇÃO INFANTIL SÃO'!C12+'E M LEONARDO BOFF'!C12+'ESCOLA MUNICIPAL GENERAL HEITOR'!C12+'E M JOHANN NOEL'!C12+'ESCOLA SANTA MARIA GORETTI'!C12+'ESCOLA SANTA RITA DE CASSIA'!C12+'ESCOLA SÃO JOÃO BATISTA'!C12+'CEI CASA DA SOLIDARIEDADE DE NO'!C12+'CEI A SEMENTEIRA'!C12+'CEI VILA SAO JOSE'!C12+'E M DR RUBENS DE CASTRO BOMTEMP'!C12+'CEI FREI LEÃO'!C12+'CEI SÃO JOÃO BATISTA'!C12+'CEI JURACI PINTO DO AMARAL DE C'!C12+'E M PEDRO AMADO'!C12+'E M ABELARDO DE LAMARE'!C12+'ESCOLA MUNICIPAL SENADOR MARIO '!C12+'ESCOLA PAROQUIAL SÃO PIO X'!C12+'CEI SÃO CHARBEL'!C12+'E M ROSALINA NICOLAY'!C12+'CEI INÊS BELARMINO DE SOUZA'!C12+'E M PROFª MARIA DA GLÓRIA QUEIR'!C12+'CENTRO EDUCACIONAL COMUNIDADE S'!C12+'CEI ROMANO CANAVESE'!C12+'CEI CÉLIA LÔBO PAULO'!C12+'CEI PROFª DORA KILLER'!C12+'CEI ALTO INDEPENDÊNCIA'!C12+'ESCOLA MUNICIPAL ALTO INDEPENDÊ'!C12+'E M PAPA JOÃO PAULO II'!C12+'CEI ANDRÉ REBOUÇAS'!C12+'CEI PROFª HERMÍNIA MATHEUS'!C12+'ESCOLA MUNICIPAL MAJOR JÚLIO FR'!C12+'E M ALMIRANTE TAMANDARÉ'!C12+'ESCOLA PAROQUIAL CARLOS DEMIÁ'!C12+'CENTRO PAROQUIAL DE EDUCAÇÃO IN'!C12+'CEI IRMÃ SILVANA'!C12+'CEI OLÍVIA MACHADO DA COSTA NOG'!C12+'E M GOVERNADOR MARCELLO ALENCAR'!C12+'E M PROFESSOR FLÁVIO MACIEL'!C12+'E M PROFª JANDIRA PEIXOTO BORDI'!C12+'E M STEFAN ZWEIG'!C12+'ESCOLA PAROQUIAL BOM JESUS'!C12+'CEI MARLI SOARES FERREIRA NETTO'!C12+'CENTRO DE EDUCAÇÃO INFANTIL CHI'!C12+'CEI VILA IPANEMA'!C12+'E M ROBERT KENNEDY'!C12+'ESCOLA MUNICIPAL ANA MOHAMMAD'!C12+'ESCOLA SÃO CRISTÓVÃO'!C12+'CEI DÉA LÚCIA CORDEIRO'!C12+'CEI SAGRADA FAMÍLIA'!C12+'CEI SÃO JOSÉ DAS OBLATAS DE NAZ'!C12+'ESCOLA MUNICIPAL JORGE AMADO'!C12+'E M FÁBRICA DO SABER'!C12+'CIEP BRIZOLÃO 474 MAESTRO GUERR'!C12+'CENTRO DE ENSINO PROF DARCY RIB'!C12+'CEI ANDRÉ VANZAN'!C12+'CENTRO DE EDUCAÇÃO INFANTIL CAR'!C12+'CEI BOA VISTA'!C12+'ASSOCIAÇÃO DA CRECHE SÃO FRANCI'!C12+'ESCOLA MUNICIPAL PAULO SALDANHA'!C12+'ESCOLA MUNICIPAL LÚCIA DE ALMEI'!C12+'E M DOM MANOEL PEDRO DA CUNHA C'!C12+'ESCOLA SÃO GERALDO'!C12+'CEI LULU MONTEIRO DE CASTRO'!C12+'CEI CARANGOLA'!C12+'ASSOCIAÇÃO RECREAR'!C12+'CENTRO DE EDUCAÇÃO INFANTIL CAS'!C12+'E M ROSEMIRA DE OLIVEIRA CAVALC'!C12+'E MZDA CARMEM NUNES MARTINS'!C12+'CEI SÃO JOSÉ DO ITAMARATI'!C12+'E M DUQUE DE CAXIAS'!C12+'CENTRO DE EDUCAÇÃO INFANTIL 2'!C12+'E M ANTÔNIO LEITE GARCIA'!C12+'ESCOLA PAROQUIAL DA ALCOBAÇA'!C12+'CENTRO DE EDUCAÇÃO INFANTIL LOT'!C12+'ESCOLA PAROQUIAL DO LOTEAMENTO '!C12+'E M PROF JOAQUIM DEISTER'!C12+'E M MARIETA GONÇALVES'!C12+'ESCOLA MUNICIPAL ODETTE YOUNG M'!C12+'ESCOLA MUNICIPAL PROFESSOR JOSE'!C12+'E M HERCÍLIA HENRIQUES MORET'!C12+'COLEGIO VICENTINO PADRE CORRÊA'!C12+'CEI PROFª MARLUCE DE SOUZA PEST'!C12+'CEI IRINEU MARINHO'!C12+'CEI DAGMAR ROLANDO DE OLIVEIRA'!C12+'CEI NOSSA SENHORA DA GLÓRIA'!C12+'E M PROF NILTON COSTA PEREIRA D'!C12+'CENTRO DE EDUCAÇÃO INFANTIL SÉR'!C12+'CEI SANTO ANTÔNIO AGOSTINHO'!C12+'CEI OSWALDO CRUZ'!C12+'E M MAGDALENA TAGLIAFERRO'!C12+'ESCOLA SÃO JOSÉ DO CAETITU'!C12+'CRECHE-ESCOLA CASTELO SÃO MANOE'!C12+'CEI THEREZINHA DE JESUS LIMA'!C12+'ESCOLA MUNICIPAL PROFESSOR PAUL'!C12+'COLÉGIO ANGLICANO DE ARARAS'!C12+'ESCOLA PAROQUIAL SANTA BERNADET'!C12+'CEI VISTA ALEGRE'!C12+'CEI DENISE BESSA DE OLIVA MAYA'!C12+'CEI VIDEIRINHA'!C12+'E M AMÉRICO FERNANDES RIBEIRO'!C12+'ESCOLA MUNICIPAL AUGUSTO PUGNAL'!C12+'ESCOLA MUNICIPAL CELINA SCHECHN'!C12+'E M DARCY CORREA DA VEIGA'!C12+'E M DR PAULA BUARQUE'!C12+'LICEU SÃO JOSÉ DE ITAIPAVA'!C12+'CEI LUIZ MARCHIORI'!C12+'CENTRO DE EDUCAÇÃO INFANTIL AUG'!C12+'CEI PROFª ADRIANA CONSTÂNCIO TR'!C12+'E M AMÉLIA ANTUNES RABELLO'!C12+'CEI PREFEITO SÉRGIO FADEL'!C12+'E M DR THEODORO MACHADO'!C12+'ESCOLA SANTO ANTÔNIO'!C12+'E M TAQUARIL'!C12+'E M MONSENHOR JOÃO DE DEUS RODR'!C12+'CENTRO DE REFERÊNCIA EM EDUC 2'!C12+'CEI PROFª GRAÇA COSTA'!C12+'CEI VILA LEOPOLDINA'!C12+'CEI NILO PEÇANHA'!C12+'E MZDA SANTA TEREZINHA'!C12+'CEI CRIANÇA SANTA EDWIGES'!C12+'E M ARNALDO DYCKERHOFF'!C12+'E M CARLOS CANEDO'!C12+'E M BEATRIZ ZALESKI'!C12+'E M ANTÔNIO JOSÉ DE LIMA'!C12+'E M FELIX WAN ERVEN DE BARROS'!C12+'ESCOLA MUNICIPAL HILDEBRANDO DE'!C12+'E M OSWALDO DA COSTA FRIAS'!C12+'E MZDA AVELINO DE CARVALHO'!C12+'ESCOLA MUNICIPALIZADA MOYSÉS FU'!C12+'CEI ANGELA MARIA DA CONCEIÇÃO S'!C12+'CEI JOSÉ GONÇALVES DA MOTTA'!C12+'E M DR BARROS FRANCO'!C12+'E M MAJOR THEÓFILO DE CARVALHO'!C12+'E M JOÃO KOPKE'!C12+'CEI ASSOCIAÇÃO BENEFICENTE FAZE'!C12+'ESCOLA SAO FRANCISCO DE ASSIS'!C12+'CEI SÃO FRANCISCO ASSIS'!C12+'CEI ALDEIA DA CRIANCA'!C12+'ESCOLA MUNICIPAL ODETTE FONSECA'!C12+'CEI ANA CAROLINA TELLES'!C12+'E M SEBASTIÃO LACERDA'!C12+'E M DOM PEDRO DE ALCÂNTARA'!C12+'ESCOLA NOSSA SENHORA DE FÁTIMA'!C12+'ESCOLA PAROQUIAL SÃO FRANCISCO '!C12+'E M MONSENHOR CIRILLO CALAON'!C12 | D8: =B8-C8 | E8: ='Entrada de Dados'!F2 | F8: =D8*E8
A9: ='Entrada de Dados'!G5 | B9: ='Entrada de Dados'!G197 | C9: ='E M ROTARY'!C13+'E M DE EDUCAÇÃO ESPECIAL SANTOS'!C13+'LICEU MUN PREFEITO CORDOLINO AM'!C13+'E M PREFEITO JAMIL SABRÁ'!C13+'LICEU MUNICIPAL CARLOS CHAGAS F'!C13+'E M PAULO FREIRE'!C13+'E M PROFª MARIA CAMPOS DA SILVA'!C13+'CASA DA EDUCAÇÃO VISCONDE DE MA'!C13+'CENTRO DE REFERÊNCIA EM EDUCAÇÃ'!C13+'ESCOLA SANTA LUIZA DE MARILLAC'!C13+'ESCOLA DOMÉSTICA NOSSA SENHORA '!C13+'ESCOLA MONSENHOR GENTIL'!C13+'ESCOLA PAROQUIAL NOSSA SENHORA '!C13+'ESCOLA PAROQUIAL SÃO PEDRO DE A'!C13+'CEI TERRA SANTA'!C13+'CEI PRIMEIRA INFÂNCIA'!C13+'CEI PROFª PATRÍCIA FERREIRA E S'!C13+'CEI DRA ZILDA ARNS NEUMANN'!C13+'CENTRO DE EDUCAÇÃO INFANTIL PRO'!C13+'CEI MONSENHOR PAULO ELIAS DAHER'!C13+'COLÉGIO GUNNAR VINGREN DE PETRÓ'!C13+'EDUCANDÁRIO TERRA SANTA'!C13+'CEI LIONS CLUBE DE PETRÓPOLIS'!C13+'ESCOLA PAROQUIAL NOSSA SENHO 2'!C13+'CENTRO DE EDUCAÇÃO INFANTIL IRM'!C13+'E M LUIZ CARLOS SOARES'!C13+'ESCOLA GERMANO VALENTE'!C13+'ESCOLA PAROQUIAL NOSSA SENHO 3'!C13+'CEI JORGE ROLANDO DA SILVA'!C13+'E M CLEMENTE FERNANDES'!C13+'E M GERALDO VENTURA DIAS'!C13+'ESCOLA DAS COMUNIDADES SANTO AN'!C13+'CEI PROFª ROSANGELA DA SILVA LE'!C13+'CEI DEISE ELOY GOMES'!C13+'CEI PROFª SONIA REGINA SCUDESE '!C13+'CEI TIA ALICE'!C13+'E M BATAILLARD'!C13+'E M SOROPTIMISTA'!C13+'E M SALVADOR KLING'!C13+'ESCOLA MUNICIPALIZADA FREI ANIC'!C13+'ESCOLA SÃO JUDAS TADEU'!C13+'CEI PEDRAS BRANCAS'!C13+'CEI MARIA THEREZA KLING DO VALL'!C13+'CEI DONA ESPERANZA DE BOURBON D'!C13+'CEI GIUSEPPE-NEVA VOLONTERIO'!C13+'CENTRO DE EDUCAÇÃO INFANTIL SÃO'!C13+'E M LEONARDO BOFF'!C13+'ESCOLA MUNICIPAL GENERAL HEITOR'!C13+'E M JOHANN NOEL'!C13+'ESCOLA SANTA MARIA GORETTI'!C13+'ESCOLA SANTA RITA DE CASSIA'!C13+'ESCOLA SÃO JOÃO BATISTA'!C13+'CEI CASA DA SOLIDARIEDADE DE NO'!C13+'CEI A SEMENTEIRA'!C13+'CEI VILA SAO JOSE'!C13+'E M DR RUBENS DE CASTRO BOMTEMP'!C13+'CEI FREI LEÃO'!C13+'CEI SÃO JOÃO BATISTA'!C13+'CEI JURACI PINTO DO AMARAL DE C'!C13+'E M PEDRO AMADO'!C13+'E M ABELARDO DE LAMARE'!C13+'ESCOLA MUNICIPAL SENADOR MARIO '!C13+'ESCOLA PAROQUIAL SÃO PIO X'!C13+'CEI SÃO CHARBEL'!C13+'E M ROSALINA NICOLAY'!C13+'CEI INÊS BELARMINO DE SOUZA'!C13+'E M PROFª MARIA DA GLÓRIA QUEIR'!C13+'CENTRO EDUCACIONAL COMUNIDADE S'!C13+'CEI ROMANO CANAVESE'!C13+'CEI CÉLIA LÔBO PAULO'!C13+'CEI PROFª DORA KILLER'!C13+'CEI ALTO INDEPENDÊNCIA'!C13+'ESCOLA MUNICIPAL ALTO INDEPENDÊ'!C13+'E M PAPA JOÃO PAULO II'!C13+'CEI ANDRÉ REBOUÇAS'!C13+'CEI PROFª HERMÍNIA MATHEUS'!C13+'ESCOLA MUNICIPAL MAJOR JÚLIO FR'!C13+'E M ALMIRANTE TAMANDARÉ'!C13+'ESCOLA PAROQUIAL CARLOS DEMIÁ'!C13+'CENTRO PAROQUIAL DE EDUCAÇÃO IN'!C13+'CEI IRMÃ SILVANA'!C13+'CEI OLÍVIA MACHADO DA COSTA NOG'!C13+'E M GOVERNADOR MARCELLO ALENCAR'!C13+'E M PROFESSOR FLÁVIO MACIEL'!C13+'E M PROFª JANDIRA PEIXOTO BORDI'!C13+'E M STEFAN ZWEIG'!C13+'ESCOLA PAROQUIAL BOM JESUS'!C13+'CEI MARLI SOARES FERREIRA NETTO'!C13+'CENTRO DE EDUCAÇÃO INFANTIL CHI'!C13+'CEI VILA IPANEMA'!C13+'E M ROBERT KENNEDY'!C13+'ESCOLA MUNICIPAL ANA MOHAMMAD'!C13+'ESCOLA SÃO CRISTÓVÃO'!C13+'CEI DÉA LÚCIA CORDEIRO'!C13+'CEI SAGRADA FAMÍLIA'!C13+'CEI SÃO JOSÉ DAS OBLATAS DE NAZ'!C13+'ESCOLA MUNICIPAL JORGE AMADO'!C13+'E M FÁBRICA DO SABER'!C13+'CIEP BRIZOLÃO 474 MAESTRO GUERR'!C13+'CENTRO DE ENSINO PROF DARCY RIB'!C13+'CEI ANDRÉ VANZAN'!C13+'CENTRO DE EDUCAÇÃO INFANTIL CAR'!C13+'CEI BOA VISTA'!C13+'ASSOCIAÇÃO DA CRECHE SÃO FRANCI'!C13+'ESCOLA MUNICIPAL PAULO SALDANHA'!C13+'ESCOLA MUNICIPAL LÚCIA DE ALMEI'!C13+'E M DOM MANOEL PEDRO DA CUNHA C'!C13+'ESCOLA SÃO GERALDO'!C13+'CEI LULU MONTEIRO DE CASTRO'!C13+'CEI CARANGOLA'!C13+'ASSOCIAÇÃO RECREAR'!C13+'CENTRO DE EDUCAÇÃO INFANTIL CAS'!C13+'E M ROSEMIRA DE OLIVEIRA CAVALC'!C13+'E MZDA CARMEM NUNES MARTINS'!C13+'CEI SÃO JOSÉ DO ITAMARATI'!C13+'E M DUQUE DE CAXIAS'!C13+'CENTRO DE EDUCAÇÃO INFANTIL 2'!C13+'E M ANTÔNIO LEITE GARCIA'!C13+'ESCOLA PAROQUIAL DA ALCOBAÇA'!C13+'CENTRO DE EDUCAÇÃO INFANTIL LOT'!C13+'ESCOLA PAROQUIAL DO LOTEAMENTO '!C13+'E M PROF JOAQUIM DEISTER'!C13+'E M MARIETA GONÇALVES'!C13+'ESCOLA MUNICIPAL ODETTE YOUNG M'!C13+'ESCOLA MUNICIPAL PROFESSOR JOSE'!C13+'E M HERCÍLIA HENRIQUES MORET'!C13+'COLEGIO VICENTINO PADRE CORRÊA'!C13+'CEI PROFª MARLUCE DE SOUZA PEST'!C13+'CEI IRINEU MARINHO'!C13+'CEI DAGMAR ROLANDO DE OLIVEIRA'!C13+'CEI NOSSA SENHORA DA GLÓRIA'!C13+'E M PROF NILTON COSTA PEREIRA D'!C13+'CENTRO DE EDUCAÇÃO INFANTIL SÉR'!C13+'CEI SANTO ANTÔNIO AGOSTINHO'!C13+'CEI OSWALDO CRUZ'!C13+'E M MAGDALENA TAGLIAFERRO'!C13+'ESCOLA SÃO JOSÉ DO CAETITU'!C13+'CRECHE-ESCOLA CASTELO SÃO MANOE'!C13+'CEI THEREZINHA DE JESUS LIMA'!C13+'ESCOLA MUNICIPAL PROFESSOR PAUL'!C13+'COLÉGIO ANGLICANO DE ARARAS'!C13+'ESCOLA PAROQUIAL SANTA BERNADET'!C13+'CEI VISTA ALEGRE'!C13+'CEI DENISE BESSA DE OLIVA MAYA'!C13+'CEI VIDEIRINHA'!C13+'E M AMÉRICO FERNANDES RIBEIRO'!C13+'ESCOLA MUNICIPAL AUGUSTO PUGNAL'!C13+'ESCOLA MUNICIPAL CELINA SCHECHN'!C13+'E M DARCY CORREA DA VEIGA'!C13+'E M DR PAULA BUARQUE'!C13+'LICEU SÃO JOSÉ DE ITAIPAVA'!C13+'CEI LUIZ MARCHIORI'!C13+'CENTRO DE EDUCAÇÃO INFANTIL AUG'!C13+'CEI PROFª ADRIANA CONSTÂNCIO TR'!C13+'E M AMÉLIA ANTUNES RABELLO'!C13+'CEI PREFEITO SÉRGIO FADEL'!C13+'E M DR THEODORO MACHADO'!C13+'ESCOLA SANTO ANTÔNIO'!C13+'E M TAQUARIL'!C13+'E M MONSENHOR JOÃO DE DEUS RODR'!C13+'CENTRO DE REFERÊNCIA EM EDUC 2'!C13+'CEI PROFª GRAÇA COSTA'!C13+'CEI VILA LEOPOLDINA'!C13+'CEI NILO PEÇANHA'!C13+'E MZDA SANTA TEREZINHA'!C13+'CEI CRIANÇA SANTA EDWIGES'!C13+'E M ARNALDO DYCKERHOFF'!C13+'E M CARLOS CANEDO'!C13+'E M BEATRIZ ZALESKI'!C13+'E M ANTÔNIO JOSÉ DE LIMA'!C13+'E M FELIX WAN ERVEN DE BARROS'!C13+'ESCOLA MUNICIPAL HILDEBRANDO DE'!C13+'E M OSWALDO DA COSTA FRIAS'!C13+'E MZDA AVELINO DE CARVALHO'!C13+'ESCOLA MUNICIPALIZADA MOYSÉS FU'!C13+'CEI ANGELA MARIA DA CONCEIÇÃO S'!C13+'CEI JOSÉ GONÇALVES DA MOTTA'!C13+'E M DR BARROS FRANCO'!C13+'E M MAJOR THEÓFILO DE CARVALHO'!C13+'E M JOÃO KOPKE'!C13+'CEI ASSOCIAÇÃO BENEFICENTE FAZE'!C13+'ESCOLA SAO FRANCISCO DE ASSIS'!C13+'CEI SÃO FRANCISCO ASSIS'!C13+'CEI ALDEIA DA CRIANCA'!C13+'ESCOLA MUNICIPAL ODETTE FONSECA'!C13+'CEI ANA CAROLINA TELLES'!C13+'E M SEBASTIÃO LACERDA'!C13+'E M DOM PEDRO DE ALCÂNTARA'!C13+'ESCOLA NOSSA SENHORA DE FÁTIMA'!C13+'ESCOLA PAROQUIAL SÃO FRANCISCO '!C13+'E M MONSENHOR CIRILLO CALAON'!C13 | D9: =B9-C9 | E9: ='Entrada de Dados'!G2 | F9: =D9*E9
A10: ='Entrada de Dados'!H5 | B10: ='Entrada de Dados'!H197 | C10: ='E M ROTARY'!C14+'E M DE EDUCAÇÃO ESPECIAL SANTOS'!C14+'LICEU MUN PREFEITO CORDOLINO AM'!C14+'E M PREFEITO JAMIL SABRÁ'!C14+'LICEU MUNICIPAL CARLOS CHAGAS F'!C14+'E M PAULO FREIRE'!C14+'E M PROFª MARIA CAMPOS DA SILVA'!C14+'CASA DA EDUCAÇÃO VISCONDE DE MA'!C14+'CENTRO DE REFERÊNCIA EM EDUCAÇÃ'!C14+'ESCOLA SANTA LUIZA DE MARILLAC'!C14+'ESCOLA DOMÉSTICA NOSSA SENHORA '!C14+'ESCOLA MONSENHOR GENTIL'!C14+'ESCOLA PAROQUIAL NOSSA SENHORA '!C14+'ESCOLA PAROQUIAL SÃO PEDRO DE A'!C14+'CEI TERRA SANTA'!C14+'CEI PRIMEIRA INFÂNCIA'!C14+'CEI PROFª PATRÍCIA FERREIRA E S'!C14+'CEI DRA ZILDA ARNS NEUMANN'!C14+'CENTRO DE EDUCAÇÃO INFANTIL PRO'!C14+'CEI MONSENHOR PAULO ELIAS DAHER'!C14+'COLÉGIO GUNNAR VINGREN DE PETRÓ'!C14+'EDUCANDÁRIO TERRA SANTA'!C14+'CEI LIONS CLUBE DE PETRÓPOLIS'!C14+'ESCOLA PAROQUIAL NOSSA SENHO 2'!C14+'CENTRO DE EDUCAÇÃO INFANTIL IRM'!C14+'E M LUIZ CARLOS SOARES'!C14+'ESCOLA GERMANO VALENTE'!C14+'ESCOLA PAROQUIAL NOSSA SENHO 3'!C14+'CEI JORGE ROLANDO DA SILVA'!C14+'E M CLEMENTE FERNANDES'!C14+'E M GERALDO VENTURA DIAS'!C14+'ESCOLA DAS COMUNIDADES SANTO AN'!C14+'CEI PROFª ROSANGELA DA SILVA LE'!C14+'CEI DEISE ELOY GOMES'!C14+'CEI PROFª SONIA REGINA SCUDESE '!C14+'CEI TIA ALICE'!C14+'E M BATAILLARD'!C14+'E M SOROPTIMISTA'!C14+'E M SALVADOR KLING'!C14+'ESCOLA MUNICIPALIZADA FREI ANIC'!C14+'ESCOLA SÃO JUDAS TADEU'!C14+'CEI PEDRAS BRANCAS'!C14+'CEI MARIA THEREZA KLING DO VALL'!C14+'CEI DONA ESPERANZA DE BOURBON D'!C14+'CEI GIUSEPPE-NEVA VOLONTERIO'!C14+'CENTRO DE EDUCAÇÃO INFANTIL SÃO'!C14+'E M LEONARDO BOFF'!C14+'ESCOLA MUNICIPAL GENERAL HEITOR'!C14+'E M JOHANN NOEL'!C14+'ESCOLA SANTA MARIA GORETTI'!C14+'ESCOLA SANTA RITA DE CASSIA'!C14+'ESCOLA SÃO JOÃO BATISTA'!C14+'CEI CASA DA SOLIDARIEDADE DE NO'!C14+'CEI A SEMENTEIRA'!C14+'CEI VILA SAO JOSE'!C14+'E M DR RUBENS DE CASTRO BOMTEMP'!C14+'CEI FREI LEÃO'!C14+'CEI SÃO JOÃO BATISTA'!C14+'CEI JURACI PINTO DO AMARAL DE C'!C14+'E M PEDRO AMADO'!C14+'E M ABELARDO DE LAMARE'!C14+'ESCOLA MUNICIPAL SENADOR MARIO '!C14+'ESCOLA PAROQUIAL SÃO PIO X'!C14+'CEI SÃO CHARBEL'!C14+'E M ROSALINA NICOLAY'!C14+'CEI INÊS BELARMINO DE SOUZA'!C14+'E M PROFª MARIA DA GLÓRIA QUEIR'!C14+'CENTRO EDUCACIONAL COMUNIDADE S'!C14+'CEI ROMANO CANAVESE'!C14+'CEI CÉLIA LÔBO PAULO'!C14+'CEI PROFª DORA KILLER'!C14+'CEI ALTO INDEPENDÊNCIA'!C14+'ESCOLA MUNICIPAL ALTO INDEPENDÊ'!C14+'E M PAPA JOÃO PAULO II'!C14+'CEI ANDRÉ REBOUÇAS'!C14+'CEI PROFª HERMÍNIA MATHEUS'!C14+'ESCOLA MUNICIPAL MAJOR JÚLIO FR'!C14+'E M ALMIRANTE TAMANDARÉ'!C14+'ESCOLA PAROQUIAL CARLOS DEMIÁ'!C14+'CENTRO PAROQUIAL DE EDUCAÇÃO IN'!C14+'CEI IRMÃ SILVANA'!C14+'CEI OLÍVIA MACHADO DA COSTA NOG'!C14+'E M GOVERNADOR MARCELLO ALENCAR'!C14+'E M PROFESSOR FLÁVIO MACIEL'!C14+'E M PROFª JANDIRA PEIXOTO BORDI'!C14+'E M STEFAN ZWEIG'!C14+'ESCOLA PAROQUIAL BOM JESUS'!C14+'CEI MARLI SOARES FERREIRA NETTO'!C14+'CENTRO DE EDUCAÇÃO INFANTIL CHI'!C14+'CEI VILA IPANEMA'!C14+'E M ROBERT KENNEDY'!C14+'ESCOLA MUNICIPAL ANA MOHAMMAD'!C14+'ESCOLA SÃO CRISTÓVÃO'!C14+'CEI DÉA LÚCIA CORDEIRO'!C14+'CEI SAGRADA FAMÍLIA'!C14+'CEI SÃO JOSÉ DAS OBLATAS DE NAZ'!C14+'ESCOLA MUNICIPAL JORGE AMADO'!C14+'E M FÁBRICA DO SABER'!C14+'CIEP BRIZOLÃO 474 MAESTRO GUERR'!C14+'CENTRO DE ENSINO PROF DARCY RIB'!C14+'CEI ANDRÉ VANZAN'!C14+'CENTRO DE EDUCAÇÃO INFANTIL CAR'!C14+'CEI BOA VISTA'!C14+'ASSOCIAÇÃO DA CRECHE SÃO FRANCI'!C14+'ESCOLA MUNICIPAL PAULO SALDANHA'!C14+'ESCOLA MUNICIPAL LÚCIA DE ALMEI'!C14+'E M DOM MANOEL PEDRO DA CUNHA C'!C14+'ESCOLA SÃO GERALDO'!C14+'CEI LULU MONTEIRO DE CASTRO'!C14+'CEI CARANGOLA'!C14+'ASSOCIAÇÃO RECREAR'!C14+'CENTRO DE EDUCAÇÃO INFANTIL CAS'!C14+'E M ROSEMIRA DE OLIVEIRA CAVALC'!C14+'E MZDA CARMEM NUNES MARTINS'!C14+'CEI SÃO JOSÉ DO ITAMARATI'!C14+'E M DUQUE DE CAXIAS'!C14+'CENTRO DE EDUCAÇÃO INFANTIL 2'!C14+'E M ANTÔNIO LEITE GARCIA'!C14+'ESCOLA PAROQUIAL DA ALCOBAÇA'!C14+'CENTRO DE EDUCAÇÃO INFANTIL LOT'!C14+'ESCOLA PAROQUIAL DO LOTEAMENTO '!C14+'E M PROF JOAQUIM DEISTER'!C14+'E M MARIETA GONÇALVES'!C14+'ESCOLA MUNICIPAL ODETTE YOUNG M'!C14+'ESCOLA MUNICIPAL PROFESSOR JOSE'!C14+'E M HERCÍLIA HENRIQUES MORET'!C14+'COLEGIO VICENTINO PADRE CORRÊA'!C14+'CEI PROFª MARLUCE DE SOUZA PEST'!C14+'CEI IRINEU MARINHO'!C14+'CEI DAGMAR ROLANDO DE OLIVEIRA'!C14+'CEI NOSSA SENHORA DA GLÓRIA'!C14+'E M PROF NILTON COSTA PEREIRA D'!C14+'CENTRO DE EDUCAÇÃO INFANTIL SÉR'!C14+'CEI SANTO ANTÔNIO AGOSTINHO'!C14+'CEI OSWALDO CRUZ'!C14+'E M MAGDALENA TAGLIAFERRO'!C14+'ESCOLA SÃO JOSÉ DO CAETITU'!C14+'CRECHE-ESCOLA CASTELO SÃO MANOE'!C14+'CEI THEREZINHA DE JESUS LIMA'!C14+'ESCOLA MUNICIPAL PROFESSOR PAUL'!C14+'COLÉGIO ANGLICANO DE ARARAS'!C14+'ESCOLA PAROQUIAL SANTA BERNADET'!C14+'CEI VISTA ALEGRE'!C14+'CEI DENISE BESSA DE OLIVA MAYA'!C14+'CEI VIDEIRINHA'!C14+'E M AMÉRICO FERNANDES RIBEIRO'!C14+'ESCOLA MUNICIPAL AUGUSTO PUGNAL'!C14+'ESCOLA MUNICIPAL CELINA SCHECHN'!C14+'E M DARCY CORREA DA VEIGA'!C14+'E M DR PAULA BUARQUE'!C14+'LICEU SÃO JOSÉ DE ITAIPAVA'!C14+'CEI LUIZ MARCHIORI'!C14+'CENTRO DE EDUCAÇÃO INFANTIL AUG'!C14+'CEI PROFª ADRIANA CONSTÂNCIO TR'!C14+'E M AMÉLIA ANTUNES RABELLO'!C14+'CEI PREFEITO SÉRGIO FADEL'!C14+'E M DR THEODORO MACHADO'!C14+'ESCOLA SANTO ANTÔNIO'!C14+'E M TAQUARIL'!C14+'E M MONSENHOR JOÃO DE DEUS RODR'!C14+'CENTRO DE REFERÊNCIA EM EDUC 2'!C14+'CEI PROFª GRAÇA COSTA'!C14+'CEI VILA LEOPOLDINA'!C14+'CEI NILO PEÇANHA'!C14+'E MZDA SANTA TEREZINHA'!C14+'CEI CRIANÇA SANTA EDWIGES'!C14+'E M ARNALDO DYCKERHOFF'!C14+'E M CARLOS CANEDO'!C14+'E M BEATRIZ ZALESKI'!C14+'E M ANTÔNIO JOSÉ DE LIMA'!C14+'E M FELIX WAN ERVEN DE BARROS'!C14+'ESCOLA MUNICIPAL HILDEBRANDO DE'!C14+'E M OSWALDO DA COSTA FRIAS'!C14+'E MZDA AVELINO DE CARVALHO'!C14+'ESCOLA MUNICIPALIZADA MOYSÉS FU'!C14+'CEI ANGELA MARIA DA CONCEIÇÃO S'!C14+'CEI JOSÉ GONÇALVES DA MOTTA'!C14+'E M DR BARROS FRANCO'!C14+'E M MAJOR THEÓFILO DE CARVALHO'!C14+'E M JOÃO KOPKE'!C14+'CEI ASSOCIAÇÃO BENEFICENTE FAZE'!C14+'ESCOLA SAO FRANCISCO DE ASSIS'!C14+'CEI SÃO FRANCISCO ASSIS'!C14+'CEI ALDEIA DA CRIANCA'!C14+'ESCOLA MUNICIPAL ODETTE FONSECA'!C14+'CEI ANA CAROLINA TELLES'!C14+'E M SEBASTIÃO LACERDA'!C14+'E M DOM PEDRO DE ALCÂNTARA'!C14+'ESCOLA NOSSA SENHORA DE FÁTIMA'!C14+'ESCOLA PAROQUIAL SÃO FRANCISCO '!C14+'E M MONSENHOR CIRILLO CALAON'!C14 | D10: =B10-C10 | E10: ='Entrada de Dados'!H2 | F10: =D10*E10
A11: ='Entrada de Dados'!I5 | B11: ='Entrada de Dados'!I197 | C11: ='E M ROTARY'!C15+'E M DE EDUCAÇÃO ESPECIAL SANTOS'!C15+'LICEU MUN PREFEITO CORDOLINO AM'!C15+'E M PREFEITO JAMIL SABRÁ'!C15+'LICEU MUNICIPAL CARLOS CHAGAS F'!C15+'E M PAULO FREIRE'!C15+'E M PROFª MARIA CAMPOS DA SILVA'!C15+'CASA DA EDUCAÇÃO VISCONDE DE MA'!C15+'CENTRO DE REFERÊNCIA EM EDUCAÇÃ'!C15+'ESCOLA SANTA LUIZA DE MARILLAC'!C15+'ESCOLA DOMÉSTICA NOSSA SENHORA '!C15+'ESCOLA MONSENHOR GENTIL'!C15+'ESCOLA PAROQUIAL NOSSA SENHORA '!C15+'ESCOLA PAROQUIAL SÃO PEDRO DE A'!C15+'CEI TERRA SANTA'!C15+'CEI PRIMEIRA INFÂNCIA'!C15+'CEI PROFª PATRÍCIA FERREIRA E S'!C15+'CEI DRA ZILDA ARNS NEUMANN'!C15+'CENTRO DE EDUCAÇÃO INFANTIL PRO'!C15+'CEI MONSENHOR PAULO ELIAS DAHER'!C15+'COLÉGIO GUNNAR VINGREN DE PETRÓ'!C15+'EDUCANDÁRIO TERRA SANTA'!C15+'CEI LIONS CLUBE DE PETRÓPOLIS'!C15+'ESCOLA PAROQUIAL NOSSA SENHO 2'!C15+'CENTRO DE EDUCAÇÃO INFANTIL IRM'!C15+'E M LUIZ CARLOS SOARES'!C15+'ESCOLA GERMANO VALENTE'!C15+'ESCOLA PAROQUIAL NOSSA SENHO 3'!C15+'CEI JORGE ROLANDO DA SILVA'!C15+'E M CLEMENTE FERNANDES'!C15+'E M GERALDO VENTURA DIAS'!C15+'ESCOLA DAS COMUNIDADES SANTO AN'!C15+'CEI PROFª ROSANGELA DA SILVA LE'!C15+'CEI DEISE ELOY GOMES'!C15+'CEI PROFª SONIA REGINA SCUDESE '!C15+'CEI TIA ALICE'!C15+'E M BATAILLARD'!C15+'E M SOROPTIMISTA'!C15+'E M SALVADOR KLING'!C15+'ESCOLA MUNICIPALIZADA FREI ANIC'!C15+'ESCOLA SÃO JUDAS TADEU'!C15+'CEI PEDRAS BRANCAS'!C15+'CEI MARIA THEREZA KLING DO VALL'!C15+'CEI DONA ESPERANZA DE BOURBON D'!C15+'CEI GIUSEPPE-NEVA VOLONTERIO'!C15+'CENTRO DE EDUCAÇÃO INFANTIL SÃO'!C15+'E M LEONARDO BOFF'!C15+'ESCOLA MUNICIPAL GENERAL HEITOR'!C15+'E M JOHANN NOEL'!C15+'ESCOLA SANTA MARIA GORETTI'!C15+'ESCOLA SANTA RITA DE CASSIA'!C15+'ESCOLA SÃO JOÃO BATISTA'!C15+'CEI CASA DA SOLIDARIEDADE DE NO'!C15+'CEI A SEMENTEIRA'!C15+'CEI VILA SAO JOSE'!C15+'E M DR RUBENS DE CASTRO BOMTEMP'!C15+'CEI FREI LEÃO'!C15+'CEI SÃO JOÃO BATISTA'!C15+'CEI JURACI PINTO DO AMARAL DE C'!C15+'E M PEDRO AMADO'!C15+'E M ABELARDO DE LAMARE'!C15+'ESCOLA MUNICIPAL SENADOR MARIO '!C15+'ESCOLA PAROQUIAL SÃO PIO X'!C15+'CEI SÃO CHARBEL'!C15+'E M ROSALINA NICOLAY'!C15+'CEI INÊS BELARMINO DE SOUZA'!C15+'E M PROFª MARIA DA GLÓRIA QUEIR'!C15+'CENTRO EDUCACIONAL COMUNIDADE S'!C15+'CEI ROMANO CANAVESE'!C15+'CEI CÉLIA LÔBO PAULO'!C15+'CEI PROFª DORA KILLER'!C15+'CEI ALTO INDEPENDÊNCIA'!C15+'ESCOLA MUNICIPAL ALTO INDEPENDÊ'!C15+'E M PAPA JOÃO PAULO II'!C15+'CEI ANDRÉ REBOUÇAS'!C15+'CEI PROFª HERMÍNIA MATHEUS'!C15+'ESCOLA MUNICIPAL MAJOR JÚLIO FR'!C15+'E M ALMIRANTE TAMANDARÉ'!C15+'ESCOLA PAROQUIAL CARLOS DEMIÁ'!C15+'CENTRO PAROQUIAL DE EDUCAÇÃO IN'!C15+'CEI IRMÃ SILVANA'!C15+'CEI OLÍVIA MACHADO DA COSTA NOG'!C15+'E M GOVERNADOR MARCELLO ALENCAR'!C15+'E M PROFESSOR FLÁVIO MACIEL'!C15+'E M PROFª JANDIRA PEIXOTO BORDI'!C15+'E M STEFAN ZWEIG'!C15+'ESCOLA PAROQUIAL BOM JESUS'!C15+'CEI MARLI SOARES FERREIRA NETTO'!C15+'CENTRO DE EDUCAÇÃO INFANTIL CHI'!C15+'CEI VILA IPANEMA'!C15+'E M ROBERT KENNEDY'!C15+'ESCOLA MUNICIPAL ANA MOHAMMAD'!C15+'ESCOLA SÃO CRISTÓVÃO'!C15+'CEI DÉA LÚCIA CORDEIRO'!C15+'CEI SAGRADA FAMÍLIA'!C15+'CEI SÃO JOSÉ DAS OBLATAS DE NAZ'!C15+'ESCOLA MUNICIPAL JORGE AMADO'!C15+'E M FÁBRICA DO SABER'!C15+'CIEP BRIZOLÃO 474 MAESTRO GUERR'!C15+'CENTRO DE ENSINO PROF DARCY RIB'!C15+'CEI ANDRÉ VANZAN'!C15+'CENTRO DE EDUCAÇÃO INFANTIL CAR'!C15+'CEI BOA VISTA'!C15+'ASSOCIAÇÃO DA CRECHE SÃO FRANCI'!C15+'ESCOLA MUNICIPAL PAULO SALDANHA'!C15+'ESCOLA MUNICIPAL LÚCIA DE ALMEI'!C15+'E M DOM MANOEL PEDRO DA CUNHA C'!C15+'ESCOLA SÃO GERALDO'!C15+'CEI LULU MONTEIRO DE CASTRO'!C15+'CEI CARANGOLA'!C15+'ASSOCIAÇÃO RECREAR'!C15+'CENTRO DE EDUCAÇÃO INFANTIL CAS'!C15+'E M ROSEMIRA DE OLIVEIRA CAVALC'!C15+'E MZDA CARMEM NUNES MARTINS'!C15+'CEI SÃO JOSÉ DO ITAMARATI'!C15+'E M DUQUE DE CAXIAS'!C15+'CENTRO DE EDUCAÇÃO INFANTIL 2'!C15+'E M ANTÔNIO LEITE GARCIA'!C15+'ESCOLA PAROQUIAL DA ALCOBAÇA'!C15+'CENTRO DE EDUCAÇÃO INFANTIL LOT'!C15+'ESCOLA PAROQUIAL DO LOTEAMENTO '!C15+'E M PROF JOAQUIM DEISTER'!C15+'E M MARIETA GONÇALVES'!C15+'ESCOLA MUNICIPAL ODETTE YOUNG M'!C15+'ESCOLA MUNICIPAL PROFESSOR JOSE'!C15+'E M HERCÍLIA HENRIQUES MORET'!C15+'COLEGIO VICENTINO PADRE CORRÊA'!C15+'CEI PROFª MARLUCE DE SOUZA PEST'!C15+'CEI IRINEU MARINHO'!C15+'CEI DAGMAR ROLANDO DE OLIVEIRA'!C15+'CEI NOSSA SENHORA DA GLÓRIA'!C15+'E M PROF NILTON COSTA PEREIRA D'!C15+'CENTRO DE EDUCAÇÃO INFANTIL SÉR'!C15+'CEI SANTO ANTÔNIO AGOSTINHO'!C15+'CEI OSWALDO CRUZ'!C15+'E M MAGDALENA TAGLIAFERRO'!C15+'ESCOLA SÃO JOSÉ DO CAETITU'!C15+'CRECHE-ESCOLA CASTELO SÃO MANOE'!C15+'CEI THEREZINHA DE JESUS LIMA'!C15+'ESCOLA MUNICIPAL PROFESSOR PAUL'!C15+'COLÉGIO ANGLICANO DE ARARAS'!C15+'ESCOLA PAROQUIAL SANTA BERNADET'!C15+'CEI VISTA ALEGRE'!C15+'CEI DENISE BESSA DE OLIVA MAYA'!C15+'CEI VIDEIRINHA'!C15+'E M AMÉRICO FERNANDES RIBEIRO'!C15+'ESCOLA MUNICIPAL AUGUSTO PUGNAL'!C15+'ESCOLA MUNICIPAL CELINA SCHECHN'!C15+'E M DARCY CORREA DA VEIGA'!C15+'E M DR PAULA BUARQUE'!C15+'LICEU SÃO JOSÉ DE ITAIPAVA'!C15+'CEI LUIZ MARCHIORI'!C15+'CENTRO DE EDUCAÇÃO INFANTIL AUG'!C15+'CEI PROFª ADRIANA CONSTÂNCIO TR'!C15+'E M AMÉLIA ANTUNES RABELLO'!C15+'CEI PREFEITO SÉRGIO FADEL'!C15+'E M DR THEODORO MACHADO'!C15+'ESCOLA SANTO ANTÔNIO'!C15+'E M TAQUARIL'!C15+'E M MONSENHOR JOÃO DE DEUS RODR'!C15+'CENTRO DE REFERÊNCIA EM EDUC 2'!C15+'CEI PROFª GRAÇA COSTA'!C15+'CEI VILA LEOPOLDINA'!C15+'CEI NILO PEÇANHA'!C15+'E MZDA SANTA TEREZINHA'!C15+'CEI CRIANÇA SANTA EDWIGES'!C15+'E M ARNALDO DYCKERHOFF'!C15+'E M CARLOS CANEDO'!C15+'E M BEATRIZ ZALESKI'!C15+'E M ANTÔNIO JOSÉ DE LIMA'!C15+'E M FELIX WAN ERVEN DE BARROS'!C15+'ESCOLA MUNICIPAL HILDEBRANDO DE'!C15+'E M OSWALDO DA COSTA FRIAS'!C15+'E MZDA AVELINO DE CARVALHO'!C15+'ESCOLA MUNICIPALIZADA MOYSÉS FU'!C15+'CEI ANGELA MARIA DA CONCEIÇÃO S'!C15+'CEI JOSÉ GONÇALVES DA MOTTA'!C15+'E M DR BARROS FRANCO'!C15+'E M MAJOR THEÓFILO DE CARVALHO'!C15+'E M JOÃO KOPKE'!C15+'CEI ASSOCIAÇÃO BENEFICENTE FAZE'!C15+'ESCOLA SAO FRANCISCO DE ASSIS'!C15+'CEI SÃO FRANCISCO ASSIS'!C15+'CEI ALDEIA DA CRIANCA'!C15+'ESCOLA MUNICIPAL ODETTE FONSECA'!C15+'CEI ANA CAROLINA TELLES'!C15+'E M SEBASTIÃO LACERDA'!C15+'E M DOM PEDRO DE ALCÂNTARA'!C15+'ESCOLA NOSSA SENHORA DE FÁTIMA'!C15+'ESCOLA PAROQUIAL SÃO FRANCISCO '!C15+'E M MONSENHOR CIRILLO CALAON'!C15 | D11: =B11-C11 | E11: ='Entrada de Dados'!I2 | F11: =D11*E11
A12: ='Entrada de Dados'!J5 | B12: ='Entrada de Dados'!J197 | C12: ='E M ROTARY'!C16+'E M DE EDUCAÇÃO ESPECIAL SANTOS'!C16+'LICEU MUN PREFEITO CORDOLINO AM'!C16+'E M PREFEITO JAMIL SABRÁ'!C16+'LICEU MUNICIPAL CARLOS CHAGAS F'!C16+'E M PAULO FREIRE'!C16+'E M PROFª MARIA CAMPOS DA SILVA'!C16+'CASA DA EDUCAÇÃO VISCONDE DE MA'!C16+'CENTRO DE REFERÊNCIA EM EDUCAÇÃ'!C16+'ESCOLA SANTA LUIZA DE MARILLAC'!C16+'ESCOLA DOMÉSTICA NOSSA SENHORA '!C16+'ESCOLA MONSENHOR GENTIL'!C16+'ESCOLA PAROQUIAL NOSSA SENHORA '!C16+'ESCOLA PAROQUIAL SÃO PEDRO DE A'!C16+'CEI TERRA SANTA'!C16+'CEI PRIMEIRA INFÂNCIA'!C16+'CEI PROFª PATRÍCIA FERREIRA E S'!C16+'CEI DRA ZILDA ARNS NEUMANN'!C16+'CENTRO DE EDUCAÇÃO INFANTIL PRO'!C16+'CEI MONSENHOR PAULO ELIAS DAHER'!C16+'COLÉGIO GUNNAR VINGREN DE PETRÓ'!C16+'EDUCANDÁRIO TERRA SANTA'!C16+'CEI LIONS CLUBE DE PETRÓPOLIS'!C16+'ESCOLA PAROQUIAL NOSSA SENHO 2'!C16+'CENTRO DE EDUCAÇÃO INFANTIL IRM'!C16+'E M LUIZ CARLOS SOARES'!C16+'ESCOLA GERMANO VALENTE'!C16+'ESCOLA PAROQUIAL NOSSA SENHO 3'!C16+'CEI JORGE ROLANDO DA SILVA'!C16+'E M CLEMENTE FERNANDES'!C16+'E M GERALDO VENTURA DIAS'!C16+'ESCOLA DAS COMUNIDADES SANTO AN'!C16+'CEI PROFª ROSANGELA DA SILVA LE'!C16+'CEI DEISE ELOY GOMES'!C16+'CEI PROFª SONIA REGINA SCUDESE '!C16+'CEI TIA ALICE'!C16+'E M BATAILLARD'!C16+'E M SOROPTIMISTA'!C16+'E M SALVADOR KLING'!C16+'ESCOLA MUNICIPALIZADA FREI ANIC'!C16+'ESCOLA SÃO JUDAS TADEU'!C16+'CEI PEDRAS BRANCAS'!C16+'CEI MARIA THEREZA KLING DO VALL'!C16+'CEI DONA ESPERANZA DE BOURBON D'!C16+'CEI GIUSEPPE-NEVA VOLONTERIO'!C16+'CENTRO DE EDUCAÇÃO INFANTIL SÃO'!C16+'E M LEONARDO BOFF'!C16+'ESCOLA MUNICIPAL GENERAL HEITOR'!C16+'E M JOHANN NOEL'!C16+'ESCOLA SANTA MARIA GORETTI'!C16+'ESCOLA SANTA RITA DE CASSIA'!C16+'ESCOLA SÃO JOÃO BATISTA'!C16+'CEI CASA DA SOLIDARIEDADE DE NO'!C16+'CEI A SEMENTEIRA'!C16+'CEI VILA SAO JOSE'!C16+'E M DR RUBENS DE CASTRO BOMTEMP'!C16+'CEI FREI LEÃO'!C16+'CEI SÃO JOÃO BATISTA'!C16+'CEI JURACI PINTO DO AMARAL DE C'!C16+'E M PEDRO AMADO'!C16+'E M ABELARDO DE LAMARE'!C16+'ESCOLA MUNICIPAL SENADOR MARIO '!C16+'ESCOLA PAROQUIAL SÃO PIO X'!C16+'CEI SÃO CHARBEL'!C16+'E M ROSALINA NICOLAY'!C16+'CEI INÊS BELARMINO DE SOUZA'!C16+'E M PROFª MARIA DA GLÓRIA QUEIR'!C16+'CENTRO EDUCACIONAL COMUNIDADE S'!C16+'CEI ROMANO CANAVESE'!C16+'CEI CÉLIA LÔBO PAULO'!C16+'CEI PROFª DORA KILLER'!C16+'CEI ALTO INDEPENDÊNCIA'!C16+'ESCOLA MUNICIPAL ALTO INDEPENDÊ'!C16+'E M PAPA JOÃO PAULO II'!C16+'CEI ANDRÉ REBOUÇAS'!C16+'CEI PROFª HERMÍNIA MATHEUS'!C16+'ESCOLA MUNICIPAL MAJOR JÚLIO FR'!C16+'E M ALMIRANTE TAMANDARÉ'!C16+'ESCOLA PAROQUIAL CARLOS DEMIÁ'!C16+'CENTRO PAROQUIAL DE EDUCAÇÃO IN'!C16+'CEI IRMÃ SILVANA'!C16+'CEI OLÍVIA MACHADO DA COSTA NOG'!C16+'E M GOVERNADOR MARCELLO ALENCAR'!C16+'E M PROFESSOR FLÁVIO MACIEL'!C16+'E M PROFª JANDIRA PEIXOTO BORDI'!C16+'E M STEFAN ZWEIG'!C16+'ESCOLA PAROQUIAL BOM JESUS'!C16+'CEI MARLI SOARES FERREIRA NETTO'!C16+'CENTRO DE EDUCAÇÃO INFANTIL CHI'!C16+'CEI VILA IPANEMA'!C16+'E M ROBERT KENNEDY'!C16+'ESCOLA MUNICIPAL ANA MOHAMMAD'!C16+'ESCOLA SÃO CRISTÓVÃO'!C16+'CEI DÉA LÚCIA CORDEIRO'!C16+'CEI SAGRADA FAMÍLIA'!C16+'CEI SÃO JOSÉ DAS OBLATAS DE NAZ'!C16+'ESCOLA MUNICIPAL JORGE AMADO'!C16+'E M FÁBRICA DO SABER'!C16+'CIEP BRIZOLÃO 474 MAESTRO GUERR'!C16+'CENTRO DE ENSINO PROF DARCY RIB'!C16+'CEI ANDRÉ VANZAN'!C16+'CENTRO DE EDUCAÇÃO INFANTIL CAR'!C16+'CEI BOA VISTA'!C16+'ASSOCIAÇÃO DA CRECHE SÃO FRANCI'!C16+'ESCOLA MUNICIPAL PAULO SALDANHA'!C16+'ESCOLA MUNICIPAL LÚCIA DE ALMEI'!C16+'E M DOM MANOEL PEDRO DA CUNHA C'!C16+'ESCOLA SÃO GERALDO'!C16+'CEI LULU MONTEIRO DE CASTRO'!C16+'CEI CARANGOLA'!C16+'ASSOCIAÇÃO RECREAR'!C16+'CENTRO DE EDUCAÇÃO INFANTIL CAS'!C16+'E M ROSEMIRA DE OLIVEIRA CAVALC'!C16+'E MZDA CARMEM NUNES MARTINS'!C16+'CEI SÃO JOSÉ DO ITAMARATI'!C16+'E M DUQUE DE CAXIAS'!C16+'CENTRO DE EDUCAÇÃO INFANTIL 2'!C16+'E M ANTÔNIO LEITE GARCIA'!C16+'ESCOLA PAROQUIAL DA ALCOBAÇA'!C16+'CENTRO DE EDUCAÇÃO INFANTIL LOT'!C16+'ESCOLA PAROQUIAL DO LOTEAMENTO '!C16+'E M PROF JOAQUIM DEISTER'!C16+'E M MARIETA GONÇALVES'!C16+'ESCOLA MUNICIPAL ODETTE YOUNG M'!C16+'ESCOLA MUNICIPAL PROFESSOR JOSE'!C16+'E M HERCÍLIA HENRIQUES MORET'!C16+'COLEGIO VICENTINO PADRE CORRÊA'!C16+'CEI PROFª MARLUCE DE SOUZA PEST'!C16+'CEI IRINEU MARINHO'!C16+'CEI DAGMAR ROLANDO DE OLIVEIRA'!C16+'CEI NOSSA SENHORA DA GLÓRIA'!C16+'E M PROF NILTON COSTA PEREIRA D'!C16+'CENTRO DE EDUCAÇÃO INFANTIL SÉR'!C16+'CEI SANTO ANTÔNIO AGOSTINHO'!C16+'CEI OSWALDO CRUZ'!C16+'E M MAGDALENA TAGLIAFERRO'!C16+'ESCOLA SÃO JOSÉ DO CAETITU'!C16+'CRECHE-ESCOLA CASTELO SÃO MANOE'!C16+'CEI THEREZINHA DE JESUS LIMA'!C16+'ESCOLA MUNICIPAL PROFESSOR PAUL'!C16+'COLÉGIO ANGLICANO DE ARARAS'!C16+'ESCOLA PAROQUIAL SANTA BERNADET'!C16+'CEI VISTA ALEGRE'!C16+'CEI DENISE BESSA DE OLIVA MAYA'!C16+'CEI VIDEIRINHA'!C16+'E M AMÉRICO FERNANDES RIBEIRO'!C16+'ESCOLA MUNICIPAL AUGUSTO PUGNAL'!C16+'ESCOLA MUNICIPAL CELINA SCHECHN'!C16+'E M DARCY CORREA DA VEIGA'!C16+'E M DR PAULA BUARQUE'!C16+'LICEU SÃO JOSÉ DE ITAIPAVA'!C16+'CEI LUIZ MARCHIORI'!C16+'CENTRO DE EDUCAÇÃO INFANTIL AUG'!C16+'CEI PROFª ADRIANA CONSTÂNCIO TR'!C16+'E M AMÉLIA ANTUNES RABELLO'!C16+'CEI PREFEITO SÉRGIO FADEL'!C16+'E M DR THEODORO MACHADO'!C16+'ESCOLA SANTO ANTÔNIO'!C16+'E M TAQUARIL'!C16+'E M MONSENHOR JOÃO DE DEUS RODR'!C16+'CENTRO DE REFERÊNCIA EM EDUC 2'!C16+'CEI PROFª GRAÇA COSTA'!C16+'CEI VILA LEOPOLDINA'!C16+'CEI NILO PEÇANHA'!C16+'E MZDA SANTA TEREZINHA'!C16+'CEI CRIANÇA SANTA EDWIGES'!C16+'E M ARNALDO DYCKERHOFF'!C16+'E M CARLOS CANEDO'!C16+'E M BEATRIZ ZALESKI'!C16+'E M ANTÔNIO JOSÉ DE LIMA'!C16+'E M FELIX WAN ERVEN DE BARROS'!C16+'ESCOLA MUNICIPAL HILDEBRANDO DE'!C16+'E M OSWALDO DA COSTA FRIAS'!C16+'E MZDA AVELINO DE CARVALHO'!C16+'ESCOLA MUNICIPALIZADA MOYSÉS FU'!C16+'CEI ANGELA MARIA DA CONCEIÇÃO S'!C16+'CEI JOSÉ GONÇALVES DA MOTTA'!C16+'E M DR BARROS FRANCO'!C16+'E M MAJOR THEÓFILO DE CARVALHO'!C16+'E M JOÃO KOPKE'!C16+'CEI ASSOCIAÇÃO BENEFICENTE FAZE'!C16+'ESCOLA SAO FRANCISCO DE ASSIS'!C16+'CEI SÃO FRANCISCO ASSIS'!C16+'CEI ALDEIA DA CRIANCA'!C16+'ESCOLA MUNICIPAL ODETTE FONSECA'!C16+'CEI ANA CAROLINA TELLES'!C16+'E M SEBASTIÃO LACERDA'!C16+'E M DOM PEDRO DE ALCÂNTARA'!C16+'ESCOLA NOSSA SENHORA DE FÁTIMA'!C16+'ESCOLA PAROQUIAL SÃO FRANCISCO '!C16+'E M MONSENHOR CIRILLO CALAON'!C16 | D12: =B12-C12 | E12: ='Entrada de Dados'!J2 | F12: =D12*E12
A13: ='Entrada de Dados'!K5 | B13: ='Entrada de Dados'!K197 | C13: ='E M ROTARY'!C17+'E M DE EDUCAÇÃO ESPECIAL SANTOS'!C17+'LICEU MUN PREFEITO CORDOLINO AM'!C17+'E M PREFEITO JAMIL SABRÁ'!C17+'LICEU MUNICIPAL CARLOS CHAGAS F'!C17+'E M PAULO FREIRE'!C17+'E M PROFª MARIA CAMPOS DA SILVA'!C17+'CASA DA EDUCAÇÃO VISCONDE DE MA'!C17+'CENTRO DE REFERÊNCIA EM EDUCAÇÃ'!C17+'ESCOLA SANTA LUIZA DE MARILLAC'!C17+'ESCOLA DOMÉSTICA NOSSA SENHORA '!C17+'ESCOLA MONSENHOR GENTIL'!C17+'ESCOLA PAROQUIAL NOSSA SENHORA '!C17+'ESCOLA PAROQUIAL SÃO PEDRO DE A'!C17+'CEI TERRA SANTA'!C17+'CEI PRIMEIRA INFÂNCIA'!C17+'CEI PROFª PATRÍCIA FERREIRA E S'!C17+'CEI DRA ZILDA ARNS NEUMANN'!C17+'CENTRO DE EDUCAÇÃO INFANTIL PRO'!C17+'CEI MONSENHOR PAULO ELIAS DAHER'!C17+'COLÉGIO GUNNAR VINGREN DE PETRÓ'!C17+'EDUCANDÁRIO TERRA SANTA'!C17+'CEI LIONS CLUBE DE PETRÓPOLIS'!C17+'ESCOLA PAROQUIAL NOSSA SENHO 2'!C17+'CENTRO DE EDUCAÇÃO INFANTIL IRM'!C17+'E M LUIZ CARLOS SOARES'!C17+'ESCOLA GERMANO VALENTE'!C17+'ESCOLA PAROQUIAL NOSSA SENHO 3'!C17+'CEI JORGE ROLANDO DA SILVA'!C17+'E M CLEMENTE FERNANDES'!C17+'E M GERALDO VENTURA DIAS'!C17+'ESCOLA DAS COMUNIDADES SANTO AN'!C17+'CEI PROFª ROSANGELA DA SILVA LE'!C17+'CEI DEISE ELOY GOMES'!C17+'CEI PROFª SONIA REGINA SCUDESE '!C17+'CEI TIA ALICE'!C17+'E M BATAILLARD'!C17+'E M SOROPTIMISTA'!C17+'E M SALVADOR KLING'!C17+'ESCOLA MUNICIPALIZADA FREI ANIC'!C17+'ESCOLA SÃO JUDAS TADEU'!C17+'CEI PEDRAS BRANCAS'!C17+'CEI MARIA THEREZA KLING DO VALL'!C17+'CEI DONA ESPERANZA DE BOURBON D'!C17+'CEI GIUSEPPE-NEVA VOLONTERIO'!C17+'CENTRO DE EDUCAÇÃO INFANTIL SÃO'!C17+'E M LEONARDO BOFF'!C17+'ESCOLA MUNICIPAL GENERAL HEITOR'!C17+'E M JOHANN NOEL'!C17+'ESCOLA SANTA MARIA GORETTI'!C17+'ESCOLA SANTA RITA DE CASSIA'!C17+'ESCOLA SÃO JOÃO BATISTA'!C17+'CEI CASA DA SOLIDARIEDADE DE NO'!C17+'CEI A SEMENTEIRA'!C17+'CEI VILA SAO JOSE'!C17+'E M DR RUBENS DE CASTRO BOMTEMP'!C17+'CEI FREI LEÃO'!C17+'CEI SÃO JOÃO BATISTA'!C17+'CEI JURACI PINTO DO AMARAL DE C'!C17+'E M PEDRO AMADO'!C17+'E M ABELARDO DE LAMARE'!C17+'ESCOLA MUNICIPAL SENADOR MARIO '!C17+'ESCOLA PAROQUIAL SÃO PIO X'!C17+'CEI SÃO CHARBEL'!C17+'E M ROSALINA NICOLAY'!C17+'CEI INÊS BELARMINO DE SOUZA'!C17+'E M PROFª MARIA DA GLÓRIA QUEIR'!C17+'CENTRO EDUCACIONAL COMUNIDADE S'!C17+'CEI ROMANO CANAVESE'!C17+'CEI CÉLIA LÔBO PAULO'!C17+'CEI PROFª DORA KILLER'!C17+'CEI ALTO INDEPENDÊNCIA'!C17+'ESCOLA MUNICIPAL ALTO INDEPENDÊ'!C17+'E M PAPA JOÃO PAULO II'!C17+'CEI ANDRÉ REBOUÇAS'!C17+'CEI PROFª HERMÍNIA MATHEUS'!C17+'ESCOLA MUNICIPAL MAJOR JÚLIO FR'!C17+'E M ALMIRANTE TAMANDARÉ'!C17+'ESCOLA PAROQUIAL CARLOS DEMIÁ'!C17+'CENTRO PAROQUIAL DE EDUCAÇÃO IN'!C17+'CEI IRMÃ SILVANA'!C17+'CEI OLÍVIA MACHADO DA COSTA NOG'!C17+'E M GOVERNADOR MARCELLO ALENCAR'!C17+'E M PROFESSOR FLÁVIO MACIEL'!C17+'E M PROFª JANDIRA PEIXOTO BORDI'!C17+'E M STEFAN ZWEIG'!C17+'ESCOLA PAROQUIAL BOM JESUS'!C17+'CEI MARLI SOARES FERREIRA NETTO'!C17+'CENTRO DE EDUCAÇÃO INFANTIL CHI'!C17+'CEI VILA IPANEMA'!C17+'E M ROBERT KENNEDY'!C17+'ESCOLA MUNICIPAL ANA MOHAMMAD'!C17+'ESCOLA SÃO CRISTÓVÃO'!C17+'CEI DÉA LÚCIA CORDEIRO'!C17+'CEI SAGRADA FAMÍLIA'!C17+'CEI SÃO JOSÉ DAS OBLATAS DE NAZ'!C17+'ESCOLA MUNICIPAL JORGE AMADO'!C17+'E M FÁBRICA DO SABER'!C17+'CIEP BRIZOLÃO 474 MAESTRO GUERR'!C17+'CENTRO DE ENSINO PROF DARCY RIB'!C17+'CEI ANDRÉ VANZAN'!C17+'CENTRO DE EDUCAÇÃO INFANTIL CAR'!C17+'CEI BOA VISTA'!C17+'ASSOCIAÇÃO DA CRECHE SÃO FRANCI'!C17+'ESCOLA MUNICIPAL PAULO SALDANHA'!C17+'ESCOLA MUNICIPAL LÚCIA DE ALMEI'!C17+'E M DOM MANOEL PEDRO DA CUNHA C'!C17+'ESCOLA SÃO GERALDO'!C17+'CEI LULU MONTEIRO DE CASTRO'!C17+'CEI CARANGOLA'!C17+'ASSOCIAÇÃO RECREAR'!C17+'CENTRO DE EDUCAÇÃO INFANTIL CAS'!C17+'E M ROSEMIRA DE OLIVEIRA CAVALC'!C17+'E MZDA CARMEM NUNES MARTINS'!C17+'CEI SÃO JOSÉ DO ITAMARATI'!C17+'E M DUQUE DE CAXIAS'!C17+'CENTRO DE EDUCAÇÃO INFANTIL 2'!C17+'E M ANTÔNIO LEITE GARCIA'!C17+'ESCOLA PAROQUIAL DA ALCOBAÇA'!C17+'CENTRO DE EDUCAÇÃO INFANTIL LOT'!C17+'ESCOLA PAROQUIAL DO LOTEAMENTO '!C17+'E M PROF JOAQUIM DEISTER'!C17+'E M MARIETA GONÇALVES'!C17+'ESCOLA MUNICIPAL ODETTE YOUNG M'!C17+'ESCOLA MUNICIPAL PROFESSOR JOSE'!C17+'E M HERCÍLIA HENRIQUES MORET'!C17+'COLEGIO VICENTINO PADRE CORRÊA'!C17+'CEI PROFª MARLUCE DE SOUZA PEST'!C17+'CEI IRINEU MARINHO'!C17+'CEI DAGMAR ROLANDO DE OLIVEIRA'!C17+'CEI NOSSA SENHORA DA GLÓRIA'!C17+'E M PROF NILTON COSTA PEREIRA D'!C17+'CENTRO DE EDUCAÇÃO INFANTIL SÉR'!C17+'CEI SANTO ANTÔNIO AGOSTINHO'!C17+'CEI OSWALDO CRUZ'!C17+'E M MAGDALENA TAGLIAFERRO'!C17+'ESCOLA SÃO JOSÉ DO CAETITU'!C17+'CRECHE-ESCOLA CASTELO SÃO MANOE'!C17+'CEI THEREZINHA DE JESUS LIMA'!C17+'ESCOLA MUNICIPAL PROFESSOR PAUL'!C17+'COLÉGIO ANGLICANO DE ARARAS'!C17+'ESCOLA PAROQUIAL SANTA BERNADET'!C17+'CEI VISTA ALEGRE'!C17+'CEI DENISE BESSA DE OLIVA MAYA'!C17+'CEI VIDEIRINHA'!C17+'E M AMÉRICO FERNANDES RIBEIRO'!C17+'ESCOLA MUNICIPAL AUGUSTO PUGNAL'!C17+'ESCOLA MUNICIPAL CELINA SCHECHN'!C17+'E M DARCY CORREA DA VEIGA'!C17+'E M DR PAULA BUARQUE'!C17+'LICEU SÃO JOSÉ DE ITAIPAVA'!C17+'CEI LUIZ MARCHIORI'!C17+'CENTRO DE EDUCAÇÃO INFANTIL AUG'!C17+'CEI PROFª ADRIANA CONSTÂNCIO TR'!C17+'E M AMÉLIA ANTUNES RABELLO'!C17+'CEI PREFEITO SÉRGIO FADEL'!C17+'E M DR THEODORO MACHADO'!C17+'ESCOLA SANTO ANTÔNIO'!C17+'E M TAQUARIL'!C17+'E M MONSENHOR JOÃO DE DEUS RODR'!C17+'CENTRO DE REFERÊNCIA EM EDUC 2'!C17+'CEI PROFª GRAÇA COSTA'!C17+'CEI VILA LEOPOLDINA'!C17+'CEI NILO PEÇANHA'!C17+'E MZDA SANTA TEREZINHA'!C17+'CEI CRIANÇA SANTA EDWIGES'!C17+'E M ARNALDO DYCKERHOFF'!C17+'E M CARLOS CANEDO'!C17+'E M BEATRIZ ZALESKI'!C17+'E M ANTÔNIO JOSÉ DE LIMA'!C17+'E M FELIX WAN ERVEN DE BARROS'!C17+'ESCOLA MUNICIPAL HILDEBRANDO DE'!C17+'E M OSWALDO DA COSTA FRIAS'!C17+'E MZDA AVELINO DE CARVALHO'!C17+'ESCOLA MUNICIPALIZADA MOYSÉS FU'!C17+'CEI ANGELA MARIA DA CONCEIÇÃO S'!C17+'CEI JOSÉ GONÇALVES DA MOTTA'!C17+'E M DR BARROS FRANCO'!C17+'E M MAJOR THEÓFILO DE CARVALHO'!C17+'E M JOÃO KOPKE'!C17+'CEI ASSOCIAÇÃO BENEFICENTE FAZE'!C17+'ESCOLA SAO FRANCISCO DE ASSIS'!C17+'CEI SÃO FRANCISCO ASSIS'!C17+'CEI ALDEIA DA CRIANCA'!C17+'ESCOLA MUNICIPAL ODETTE FONSECA'!C17+'CEI ANA CAROLINA TELLES'!C17+'E M SEBASTIÃO LACERDA'!C17+'E M DOM PEDRO DE ALCÂNTARA'!C17+'ESCOLA NOSSA SENHORA DE FÁTIMA'!C17+'ESCOLA PAROQUIAL SÃO FRANCISCO '!C17+'E M MONSENHOR CIRILLO CALAON'!C17 | D13: =B13-C13 | E13: ='Entrada de Dados'!K2 | F13: =D13*E13
A14: ='Entrada de Dados'!L5 | B14: ='Entrada de Dados'!L197 | C14: ='E M ROTARY'!C18+'E M DE EDUCAÇÃO ESPECIAL SANTOS'!C18+'LICEU MUN PREFEITO CORDOLINO AM'!C18+'E M PREFEITO JAMIL SABRÁ'!C18+'LICEU MUNICIPAL CARLOS CHAGAS F'!C18+'E M PAULO FREIRE'!C18+'E M PROFª MARIA CAMPOS DA SILVA'!C18+'CASA DA EDUCAÇÃO VISCONDE DE MA'!C18+'CENTRO DE REFERÊNCIA EM EDUCAÇÃ'!C18+'ESCOLA SANTA LUIZA DE MARILLAC'!C18+'ESCOLA DOMÉSTICA NOSSA SENHORA '!C18+'ESCOLA MONSENHOR GENTIL'!C18+'ESCOLA PAROQUIAL NOSSA SENHORA '!C18+'ESCOLA PAROQUIAL SÃO PEDRO DE A'!C18+'CEI TERRA SANTA'!C18+'CEI PRIMEIRA INFÂNCIA'!C18+'CEI PROFª PATRÍCIA FERREIRA E S'!C18+'CEI DRA ZILDA ARNS NEUMANN'!C18+'CENTRO DE EDUCAÇÃO INFANTIL PRO'!C18+'CEI MONSENHOR PAULO ELIAS DAHER'!C18+'COLÉGIO GUNNAR VINGREN DE PETRÓ'!C18+'EDUCANDÁRIO TERRA SANTA'!C18+'CEI LIONS CLUBE DE PETRÓPOLIS'!C18+'ESCOLA PAROQUIAL NOSSA SENHO 2'!C18+'CENTRO DE EDUCAÇÃO INFANTIL IRM'!C18+'E M LUIZ CARLOS SOARES'!C18+'ESCOLA GERMANO VALENTE'!C18+'ESCOLA PAROQUIAL NOSSA SENHO 3'!C18+'CEI JORGE ROLANDO DA SILVA'!C18+'E M CLEMENTE FERNANDES'!C18+'E M GERALDO VENTURA DIAS'!C18+'ESCOLA DAS COMUNIDADES SANTO AN'!C18+'CEI PROFª ROSANGELA DA SILVA LE'!C18+'CEI DEISE ELOY GOMES'!C18+'CEI PROFª SONIA REGINA SCUDESE '!C18+'CEI TIA ALICE'!C18+'E M BATAILLARD'!C18+'E M SOROPTIMISTA'!C18+'E M SALVADOR KLING'!C18+'ESCOLA MUNICIPALIZADA FREI ANIC'!C18+'ESCOLA SÃO JUDAS TADEU'!C18+'CEI PEDRAS BRANCAS'!C18+'CEI MARIA THEREZA KLING DO VALL'!C18+'CEI DONA ESPERANZA DE BOURBON D'!C18+'CEI GIUSEPPE-NEVA VOLONTERIO'!C18+'CENTRO DE EDUCAÇÃO INFANTIL SÃO'!C18+'E M LEONARDO BOFF'!C18+'ESCOLA MUNICIPAL GENERAL HEITOR'!C18+'E M JOHANN NOEL'!C18+'ESCOLA SANTA MARIA GORETTI'!C18+'ESCOLA SANTA RITA DE CASSIA'!C18+'ESCOLA SÃO JOÃO BATISTA'!C18+'CEI CASA DA SOLIDARIEDADE DE NO'!C18+'CEI A SEMENTEIRA'!C18+'CEI VILA SAO JOSE'!C18+'E M DR RUBENS DE CASTRO BOMTEMP'!C18+'CEI FREI LEÃO'!C18+'CEI SÃO JOÃO BATISTA'!C18+'CEI JURACI PINTO DO AMARAL DE C'!C18+'E M PEDRO AMADO'!C18+'E M ABELARDO DE LAMARE'!C18+'ESCOLA MUNICIPAL SENADOR MARIO '!C18+'ESCOLA PAROQUIAL SÃO PIO X'!C18+'CEI SÃO CHARBEL'!C18+'E M ROSALINA NICOLAY'!C18+'CEI INÊS BELARMINO DE SOUZA'!C18+'E M PROFª MARIA DA GLÓRIA QUEIR'!C18+'CENTRO EDUCACIONAL COMUNIDADE S'!C18+'CEI ROMANO CANAVESE'!C18+'CEI CÉLIA LÔBO PAULO'!C18+'CEI PROFª DORA KILLER'!C18+'CEI ALTO INDEPENDÊNCIA'!C18+'ESCOLA MUNICIPAL ALTO INDEPENDÊ'!C18+'E M PAPA JOÃO PAULO II'!C18+'CEI ANDRÉ REBOUÇAS'!C18+'CEI PROFª HERMÍNIA MATHEUS'!C18+'ESCOLA MUNICIPAL MAJOR JÚLIO FR'!C18+'E M ALMIRANTE TAMANDARÉ'!C18+'ESCOLA PAROQUIAL CARLOS DEMIÁ'!C18+'CENTRO PAROQUIAL DE EDUCAÇÃO IN'!C18+'CEI IRMÃ SILVANA'!C18+'CEI OLÍVIA MACHADO DA COSTA NOG'!C18+'E M GOVERNADOR MARCELLO ALENCAR'!C18+'E M PROFESSOR FLÁVIO MACIEL'!C18+'E M PROFª JANDIRA PEIXOTO BORDI'!C18+'E M STEFAN ZWEIG'!C18+'ESCOLA PAROQUIAL BOM JESUS'!C18+'CEI MARLI SOARES FERREIRA NETTO'!C18+'CENTRO DE EDUCAÇÃO INFANTIL CHI'!C18+'CEI VILA IPANEMA'!C18+'E M ROBERT KENNEDY'!C18+'ESCOLA MUNICIPAL ANA MOHAMMAD'!C18+'ESCOLA SÃO CRISTÓVÃO'!C18+'CEI DÉA LÚCIA CORDEIRO'!C18+'CEI SAGRADA FAMÍLIA'!C18+'CEI SÃO JOSÉ DAS OBLATAS DE NAZ'!C18+'ESCOLA MUNICIPAL JORGE AMADO'!C18+'E M FÁBRICA DO SABER'!C18+'CIEP BRIZOLÃO 474 MAESTRO GUERR'!C18+'CENTRO DE ENSINO PROF DARCY RIB'!C18+'CEI ANDRÉ VANZAN'!C18+'CENTRO DE EDUCAÇÃO INFANTIL CAR'!C18+'CEI BOA VISTA'!C18+'ASSOCIAÇÃO DA CRECHE SÃO FRANCI'!C18+'ESCOLA MUNICIPAL PAULO SALDANHA'!C18+'ESCOLA MUNICIPAL LÚCIA DE ALMEI'!C18+'E M DOM MANOEL PEDRO DA CUNHA C'!C18+'ESCOLA SÃO GERALDO'!C18+'CEI LULU MONTEIRO DE CASTRO'!C18+'CEI CARANGOLA'!C18+'ASSOCIAÇÃO RECREAR'!C18+'CENTRO DE EDUCAÇÃO INFANTIL CAS'!C18+'E M ROSEMIRA DE OLIVEIRA CAVALC'!C18+'E MZDA CARMEM NUNES MARTINS'!C18+'CEI SÃO JOSÉ DO ITAMARATI'!C18+'E M DUQUE DE CAXIAS'!C18+'CENTRO DE EDUCAÇÃO INFANTIL 2'!C18+'E M ANTÔNIO LEITE GARCIA'!C18+'ESCOLA PAROQUIAL DA ALCOBAÇA'!C18+'CENTRO DE EDUCAÇÃO INFANTIL LOT'!C18+'ESCOLA PAROQUIAL DO LOTEAMENTO '!C18+'E M PROF JOAQUIM DEISTER'!C18+'E M MARIETA GONÇALVES'!C18+'ESCOLA MUNICIPAL ODETTE YOUNG M'!C18+'ESCOLA MUNICIPAL PROFESSOR JOSE'!C18+'E M HERCÍLIA HENRIQUES MORET'!C18+'COLEGIO VICENTINO PADRE CORRÊA'!C18+'CEI PROFª MARLUCE DE SOUZA PEST'!C18+'CEI IRINEU MARINHO'!C18+'CEI DAGMAR ROLANDO DE OLIVEIRA'!C18+'CEI NOSSA SENHORA DA GLÓRIA'!C18+'E M PROF NILTON COSTA PEREIRA D'!C18+'CENTRO DE EDUCAÇÃO INFANTIL SÉR'!C18+'CEI SANTO ANTÔNIO AGOSTINHO'!C18+'CEI OSWALDO CRUZ'!C18+'E M MAGDALENA TAGLIAFERRO'!C18+'ESCOLA SÃO JOSÉ DO CAETITU'!C18+'CRECHE-ESCOLA CASTELO SÃO MANOE'!C18+'CEI THEREZINHA DE JESUS LIMA'!C18+'ESCOLA MUNICIPAL PROFESSOR PAUL'!C18+'COLÉGIO ANGLICANO DE ARARAS'!C18+'ESCOLA PAROQUIAL SANTA BERNADET'!C18+'CEI VISTA ALEGRE'!C18+'CEI DENISE BESSA DE OLIVA MAYA'!C18+'CEI VIDEIRINHA'!C18+'E M AMÉRICO FERNANDES RIBEIRO'!C18+'ESCOLA MUNICIPAL AUGUSTO PUGNAL'!C18+'ESCOLA MUNICIPAL CELINA SCHECHN'!C18+'E M DARCY CORREA DA VEIGA'!C18+'E M DR PAULA BUARQUE'!C18+'LICEU SÃO JOSÉ DE ITAIPAVA'!C18+'CEI LUIZ MARCHIORI'!C18+'CENTRO DE EDUCAÇÃO INFANTIL AUG'!C18+'CEI PROFª ADRIANA CONSTÂNCIO TR'!C18+'E M AMÉLIA ANTUNES RABELLO'!C18+'CEI PREFEITO SÉRGIO FADEL'!C18+'E M DR THEODORO MACHADO'!C18+'ESCOLA SANTO ANTÔNIO'!C18+'E M TAQUARIL'!C18+'E M MONSENHOR JOÃO DE DEUS RODR'!C18+'CENTRO DE REFERÊNCIA EM EDUC 2'!C18+'CEI PROFª GRAÇA COSTA'!C18+'CEI VILA LEOPOLDINA'!C18+'CEI NILO PEÇANHA'!C18+'E MZDA SANTA TEREZINHA'!C18+'CEI CRIANÇA SANTA EDWIGES'!C18+'E M ARNALDO DYCKERHOFF'!C18+'E M CARLOS CANEDO'!C18+'E M BEATRIZ ZALESKI'!C18+'E M ANTÔNIO JOSÉ DE LIMA'!C18+'E M FELIX WAN ERVEN DE BARROS'!C18+'ESCOLA MUNICIPAL HILDEBRANDO DE'!C18+'E M OSWALDO DA COSTA FRIAS'!C18+'E MZDA AVELINO DE CARVALHO'!C18+'ESCOLA MUNICIPALIZADA MOYSÉS FU'!C18+'CEI ANGELA MARIA DA CONCEIÇÃO S'!C18+'CEI JOSÉ GONÇALVES DA MOTTA'!C18+'E M DR BARROS FRANCO'!C18+'E M MAJOR THEÓFILO DE CARVALHO'!C18+'E M JOÃO KOPKE'!C18+'CEI ASSOCIAÇÃO BENEFICENTE FAZE'!C18+'ESCOLA SAO FRANCISCO DE ASSIS'!C18+'CEI SÃO FRANCISCO ASSIS'!C18+'CEI ALDEIA DA CRIANCA'!C18+'ESCOLA MUNICIPAL ODETTE FONSECA'!C18+'CEI ANA CAROLINA TELLES'!C18+'E M SEBASTIÃO LACERDA'!C18+'E M DOM PEDRO DE ALCÂNTARA'!C18+'ESCOLA NOSSA SENHORA DE FÁTIMA'!C18+'ESCOLA PAROQUIAL SÃO FRANCISCO '!C18+'E M MONSENHOR CIRILLO CALAON'!C18 | D14: =B14-C14 | E14: ='Entrada de Dados'!L2 | F14: =D14*E14
A15: ='Entrada de Dados'!M5 | B15: ='Entrada de Dados'!M197 | C15: ='E M ROTARY'!C19+'E M DE EDUCAÇÃO ESPECIAL SANTOS'!C19+'LICEU MUN PREFEITO CORDOLINO AM'!C19+'E M PREFEITO JAMIL SABRÁ'!C19+'LICEU MUNICIPAL CARLOS CHAGAS F'!C19+'E M PAULO FREIRE'!C19+'E M PROFª MARIA CAMPOS DA SILVA'!C19+'CASA DA EDUCAÇÃO VISCONDE DE MA'!C19+'CENTRO DE REFERÊNCIA EM EDUCAÇÃ'!C19+'ESCOLA SANTA LUIZA DE MARILLAC'!C19+'ESCOLA DOMÉSTICA NOSSA SENHORA '!C19+'ESCOLA MONSENHOR GENTIL'!C19+'ESCOLA PAROQUIAL NOSSA SENHORA '!C19+'ESCOLA PAROQUIAL SÃO PEDRO DE A'!C19+'CEI TERRA SANTA'!C19+'CEI PRIMEIRA INFÂNCIA'!C19+'CEI PROFª PATRÍCIA FERREIRA E S'!C19+'CEI DRA ZILDA ARNS NEUMANN'!C19+'CENTRO DE EDUCAÇÃO INFANTIL PRO'!C19+'CEI MONSENHOR PAULO ELIAS DAHER'!C19+'COLÉGIO GUNNAR VINGREN DE PETRÓ'!C19+'EDUCANDÁRIO TERRA SANTA'!C19+'CEI LIONS CLUBE DE PETRÓPOLIS'!C19+'ESCOLA PAROQUIAL NOSSA SENHO 2'!C19+'CENTRO DE EDUCAÇÃO INFANTIL IRM'!C19+'E M LUIZ CARLOS SOARES'!C19+'ESCOLA GERMANO VALENTE'!C19+'ESCOLA PAROQUIAL NOSSA SENHO 3'!C19+'CEI JORGE ROLANDO DA SILVA'!C19+'E M CLEMENTE FERNANDES'!C19+'E M GERALDO VENTURA DIAS'!C19+'ESCOLA DAS COMUNIDADES SANTO AN'!C19+'CEI PROFª ROSANGELA DA SILVA LE'!C19+'CEI DEISE ELOY GOMES'!C19+'CEI PROFª SONIA REGINA SCUDESE '!C19+'CEI TIA ALICE'!C19+'E M BATAILLARD'!C19+'E M SOROPTIMISTA'!C19+'E M SALVADOR KLING'!C19+'ESCOLA MUNICIPALIZADA FREI ANIC'!C19+'ESCOLA SÃO JUDAS TADEU'!C19+'CEI PEDRAS BRANCAS'!C19+'CEI MARIA THEREZA KLING DO VALL'!C19+'CEI DONA ESPERANZA DE BOURBON D'!C19+'CEI GIUSEPPE-NEVA VOLONTERIO'!C19+'CENTRO DE EDUCAÇÃO INFANTIL SÃO'!C19+'E M LEONARDO BOFF'!C19+'ESCOLA MUNICIPAL GENERAL HEITOR'!C19+'E M JOHANN NOEL'!C19+'ESCOLA SANTA MARIA GORETTI'!C19+'ESCOLA SANTA RITA DE CASSIA'!C19+'ESCOLA SÃO JOÃO BATISTA'!C19+'CEI CASA DA SOLIDARIEDADE DE NO'!C19+'CEI A SEMENTEIRA'!C19+'CEI VILA SAO JOSE'!C19+'E M DR RUBENS DE CASTRO BOMTEMP'!C19+'CEI FREI LEÃO'!C19+'CEI SÃO JOÃO BATISTA'!C19+'CEI JURACI PINTO DO AMARAL DE C'!C19+'E M PEDRO AMADO'!C19+'E M ABELARDO DE LAMARE'!C19+'ESCOLA MUNICIPAL SENADOR MARIO '!C19+'ESCOLA PAROQUIAL SÃO PIO X'!C19+'CEI SÃO CHARBEL'!C19+'E M ROSALINA NICOLAY'!C19+'CEI INÊS BELARMINO DE SOUZA'!C19+'E M PROFª MARIA DA GLÓRIA QUEIR'!C19+'CENTRO EDUCACIONAL COMUNIDADE S'!C19+'CEI ROMANO CANAVESE'!C19+'CEI CÉLIA LÔBO PAULO'!C19+'CEI PROFª DORA KILLER'!C19+'CEI ALTO INDEPENDÊNCIA'!C19+'ESCOLA MUNICIPAL ALTO INDEPENDÊ'!C19+'E M PAPA JOÃO PAULO II'!C19+'CEI ANDRÉ REBOUÇAS'!C19+'CEI PROFª HERMÍNIA MATHEUS'!C19+'ESCOLA MUNICIPAL MAJOR JÚLIO FR'!C19+'E M ALMIRANTE TAMANDARÉ'!C19+'ESCOLA PAROQUIAL CARLOS DEMIÁ'!C19+'CENTRO PAROQUIAL DE EDUCAÇÃO IN'!C19+'CEI IRMÃ SILVANA'!C19+'CEI OLÍVIA MACHADO DA COSTA NOG'!C19+'E M GOVERNADOR MARCELLO ALENCAR'!C19+'E M PROFESSOR FLÁVIO MACIEL'!C19+'E M PROFª JANDIRA PEIXOTO BORDI'!C19+'E M STEFAN ZWEIG'!C19+'ESCOLA PAROQUIAL BOM JESUS'!C19+'CEI MARLI SOARES FERREIRA NETTO'!C19+'CENTRO DE EDUCAÇÃO INFANTIL CHI'!C19+'CEI VILA IPANEMA'!C19+'E M ROBERT KENNEDY'!C19+'ESCOLA MUNICIPAL ANA MOHAMMAD'!C19+'ESCOLA SÃO CRISTÓVÃO'!C19+'CEI DÉA LÚCIA CORDEIRO'!C19+'CEI SAGRADA FAMÍLIA'!C19+'CEI SÃO JOSÉ DAS OBLATAS DE NAZ'!C19+'ESCOLA MUNICIPAL JORGE AMADO'!C19+'E M FÁBRICA DO SABER'!C19+'CIEP BRIZOLÃO 474 MAESTRO GUERR'!C19+'CENTRO DE ENSINO PROF DARCY RIB'!C19+'CEI ANDRÉ VANZAN'!C19+'CENTRO DE EDUCAÇÃO INFANTIL CAR'!C19+'CEI BOA VISTA'!C19+'ASSOCIAÇÃO DA CRECHE SÃO FRANCI'!C19+'ESCOLA MUNICIPAL PAULO SALDANHA'!C19+'ESCOLA MUNICIPAL LÚCIA DE ALMEI'!C19+'E M DOM MANOEL PEDRO DA CUNHA C'!C19+'ESCOLA SÃO GERALDO'!C19+'CEI LULU MONTEIRO DE CASTRO'!C19+'CEI CARANGOLA'!C19+'ASSOCIAÇÃO RECREAR'!C19+'CENTRO DE EDUCAÇÃO INFANTIL CAS'!C19+'E M ROSEMIRA DE OLIVEIRA CAVALC'!C19+'E MZDA CARMEM NUNES MARTINS'!C19+'CEI SÃO JOSÉ DO ITAMARATI'!C19+'E M DUQUE DE CAXIAS'!C19+'CENTRO DE EDUCAÇÃO INFANTIL 2'!C19+'E M ANTÔNIO LEITE GARCIA'!C19+'ESCOLA PAROQUIAL DA ALCOBAÇA'!C19+'CENTRO DE EDUCAÇÃO INFANTIL LOT'!C19+'ESCOLA PAROQUIAL DO LOTEAMENTO '!C19+'E M PROF JOAQUIM DEISTER'!C19+'E M MARIETA GONÇALVES'!C19+'ESCOLA MUNICIPAL ODETTE YOUNG M'!C19+'ESCOLA MUNICIPAL PROFESSOR JOSE'!C19+'E M HERCÍLIA HENRIQUES MORET'!C19+'COLEGIO VICENTINO PADRE CORRÊA'!C19+'CEI PROFª MARLUCE DE SOUZA PEST'!C19+'CEI IRINEU MARINHO'!C19+'CEI DAGMAR ROLANDO DE OLIVEIRA'!C19+'CEI NOSSA SENHORA DA GLÓRIA'!C19+'E M PROF NILTON COSTA PEREIRA D'!C19+'CENTRO DE EDUCAÇÃO INFANTIL SÉR'!C19+'CEI SANTO ANTÔNIO AGOSTINHO'!C19+'CEI OSWALDO CRUZ'!C19+'E M MAGDALENA TAGLIAFERRO'!C19+'ESCOLA SÃO JOSÉ DO CAETITU'!C19+'CRECHE-ESCOLA CASTELO SÃO MANOE'!C19+'CEI THEREZINHA DE JESUS LIMA'!C19+'ESCOLA MUNICIPAL PROFESSOR PAUL'!C19+'COLÉGIO ANGLICANO DE ARARAS'!C19+'ESCOLA PAROQUIAL SANTA BERNADET'!C19+'CEI VISTA ALEGRE'!C19+'CEI DENISE BESSA DE OLIVA MAYA'!C19+'CEI VIDEIRINHA'!C19+'E M AMÉRICO FERNANDES RIBEIRO'!C19+'ESCOLA MUNICIPAL AUGUSTO PUGNAL'!C19+'ESCOLA MUNICIPAL CELINA SCHECHN'!C19+'E M DARCY CORREA DA VEIGA'!C19+'E M DR PAULA BUARQUE'!C19+'LICEU SÃO JOSÉ DE ITAIPAVA'!C19+'CEI LUIZ MARCHIORI'!C19+'CENTRO DE EDUCAÇÃO INFANTIL AUG'!C19+'CEI PROFª ADRIANA CONSTÂNCIO TR'!C19+'E M AMÉLIA ANTUNES RABELLO'!C19+'CEI PREFEITO SÉRGIO FADEL'!C19+'E M DR THEODORO MACHADO'!C19+'ESCOLA SANTO ANTÔNIO'!C19+'E M TAQUARIL'!C19+'E M MONSENHOR JOÃO DE DEUS RODR'!C19+'CENTRO DE REFERÊNCIA EM EDUC 2'!C19+'CEI PROFª GRAÇA COSTA'!C19+'CEI VILA LEOPOLDINA'!C19+'CEI NILO PEÇANHA'!C19+'E MZDA SANTA TEREZINHA'!C19+'CEI CRIANÇA SANTA EDWIGES'!C19+'E M ARNALDO DYCKERHOFF'!C19+'E M CARLOS CANEDO'!C19+'E M BEATRIZ ZALESKI'!C19+'E M ANTÔNIO JOSÉ DE LIMA'!C19+'E M FELIX WAN ERVEN DE BARROS'!C19+'ESCOLA MUNICIPAL HILDEBRANDO DE'!C19+'E M OSWALDO DA COSTA FRIAS'!C19+'E MZDA AVELINO DE CARVALHO'!C19+'ESCOLA MUNICIPALIZADA MOYSÉS FU'!C19+'CEI ANGELA MARIA DA CONCEIÇÃO S'!C19+'CEI JOSÉ GONÇALVES DA MOTTA'!C19+'E M DR BARROS FRANCO'!C19+'E M MAJOR THEÓFILO DE CARVALHO'!C19+'E M JOÃO KOPKE'!C19+'CEI ASSOCIAÇÃO BENEFICENTE FAZE'!C19+'ESCOLA SAO FRANCISCO DE ASSIS'!C19+'CEI SÃO FRANCISCO ASSIS'!C19+'CEI ALDEIA DA CRIANCA'!C19+'ESCOLA MUNICIPAL ODETTE FONSECA'!C19+'CEI ANA CAROLINA TELLES'!C19+'E M SEBASTIÃO LACERDA'!C19+'E M DOM PEDRO DE ALCÂNTARA'!C19+'ESCOLA NOSSA SENHORA DE FÁTIMA'!C19+'ESCOLA PAROQUIAL SÃO FRANCISCO '!C19+'E M MONSENHOR CIRILLO CALAON'!C19 | D15: =B15-C15 | E15: ='Entrada de Dados'!M2 | F15: =D15*E15
A16: ='Entrada de Dados'!N5 | B16: ='Entrada de Dados'!N197 | C16: ='E M ROTARY'!C20+'E M DE EDUCAÇÃO ESPECIAL SANTOS'!C20+'LICEU MUN PREFEITO CORDOLINO AM'!C20+'E M PREFEITO JAMIL SABRÁ'!C20+'LICEU MUNICIPAL CARLOS CHAGAS F'!C20+'E M PAULO FREIRE'!C20+'E M PROFª MARIA CAMPOS DA SILVA'!C20+'CASA DA EDUCAÇÃO VISCONDE DE MA'!C20+'CENTRO DE REFERÊNCIA EM EDUCAÇÃ'!C20+'ESCOLA SANTA LUIZA DE MARILLAC'!C20+'ESCOLA DOMÉSTICA NOSSA SENHORA '!C20+'ESCOLA MONSENHOR GENTIL'!C20+'ESCOLA PAROQUIAL NOSSA SENHORA '!C20+'ESCOLA PAROQUIAL SÃO PEDRO DE A'!C20+'CEI TERRA SANTA'!C20+'CEI PRIMEIRA INFÂNCIA'!C20+'CEI PROFª PATRÍCIA FERREIRA E S'!C20+'CEI DRA ZILDA ARNS NEUMANN'!C20+'CENTRO DE EDUCAÇÃO INFANTIL PRO'!C20+'CEI MONSENHOR PAULO ELIAS DAHER'!C20+'COLÉGIO GUNNAR VINGREN DE PETRÓ'!C20+'EDUCANDÁRIO TERRA SANTA'!C20+'CEI LIONS CLUBE DE PETRÓPOLIS'!C20+'ESCOLA PAROQUIAL NOSSA SENHO 2'!C20+'CENTRO DE EDUCAÇÃO INFANTIL IRM'!C20+'E M LUIZ CARLOS SOARES'!C20+'ESCOLA GERMANO VALENTE'!C20+'ESCOLA PAROQUIAL NOSSA SENHO 3'!C20+'CEI JORGE ROLANDO DA SILVA'!C20+'E M CLEMENTE FERNANDES'!C20+'E M GERALDO VENTURA DIAS'!C20+'ESCOLA DAS COMUNIDADES SANTO AN'!C20+'CEI PROFª ROSANGELA DA SILVA LE'!C20+'CEI DEISE ELOY GOMES'!C20+'CEI PROFª SONIA REGINA SCUDESE '!C20+'CEI TIA ALICE'!C20+'E M BATAILLARD'!C20+'E M SOROPTIMISTA'!C20+'E M SALVADOR KLING'!C20+'ESCOLA MUNICIPALIZADA FREI ANIC'!C20+'ESCOLA SÃO JUDAS TADEU'!C20+'CEI PEDRAS BRANCAS'!C20+'CEI MARIA THEREZA KLING DO VALL'!C20+'CEI DONA ESPERANZA DE BOURBON D'!C20+'CEI GIUSEPPE-NEVA VOLONTERIO'!C20+'CENTRO DE EDUCAÇÃO INFANTIL SÃO'!C20+'E M LEONARDO BOFF'!C20+'ESCOLA MUNICIPAL GENERAL HEITOR'!C20+'E M JOHANN NOEL'!C20+'ESCOLA SANTA MARIA GORETTI'!C20+'ESCOLA SANTA RITA DE CASSIA'!C20+'ESCOLA SÃO JOÃO BATISTA'!C20+'CEI CASA DA SOLIDARIEDADE DE NO'!C20+'CEI A SEMENTEIRA'!C20+'CEI VILA SAO JOSE'!C20+'E M DR RUBENS DE CASTRO BOMTEMP'!C20+'CEI FREI LEÃO'!C20+'CEI SÃO JOÃO BATISTA'!C20+'CEI JURACI PINTO DO AMARAL DE C'!C20+'E M PEDRO AMADO'!C20+'E M ABELARDO DE LAMARE'!C20+'ESCOLA MUNICIPAL SENADOR MARIO '!C20+'ESCOLA PAROQUIAL SÃO PIO X'!C20+'CEI SÃO CHARBEL'!C20+'E M ROSALINA NICOLAY'!C20+'CEI INÊS BELARMINO DE SOUZA'!C20+'E M PROFª MARIA DA GLÓRIA QUEIR'!C20+'CENTRO EDUCACIONAL COMUNIDADE S'!C20+'CEI ROMANO CANAVESE'!C20+'CEI CÉLIA LÔBO PAULO'!C20+'CEI PROFª DORA KILLER'!C20+'CEI ALTO INDEPENDÊNCIA'!C20+'ESCOLA MUNICIPAL ALTO INDEPENDÊ'!C20+'E M PAPA JOÃO PAULO II'!C20+'CEI ANDRÉ REBOUÇAS'!C20+'CEI PROFª HERMÍNIA MATHEUS'!C20+'ESCOLA MUNICIPAL MAJOR JÚLIO FR'!C20+'E M ALMIRANTE TAMANDARÉ'!C20+'ESCOLA PAROQUIAL CARLOS DEMIÁ'!C20+'CENTRO PAROQUIAL DE EDUCAÇÃO IN'!C20+'CEI IRMÃ SILVANA'!C20+'CEI OLÍVIA MACHADO DA COSTA NOG'!C20+'E M GOVERNADOR MARCELLO ALENCAR'!C20+'E M PROFESSOR FLÁVIO MACIEL'!C20+'E M PROFª JANDIRA PEIXOTO BORDI'!C20+'E M STEFAN ZWEIG'!C20+'ESCOLA PAROQUIAL BOM JESUS'!C20+'CEI MARLI SOARES FERREIRA NETTO'!C20+'CENTRO DE EDUCAÇÃO INFANTIL CHI'!C20+'CEI VILA IPANEMA'!C20+'E M ROBERT KENNEDY'!C20+'ESCOLA MUNICIPAL ANA MOHAMMAD'!C20+'ESCOLA SÃO CRISTÓVÃO'!C20+'CEI DÉA LÚCIA CORDEIRO'!C20+'CEI SAGRADA FAMÍLIA'!C20+'CEI SÃO JOSÉ DAS OBLATAS DE NAZ'!C20+'ESCOLA MUNICIPAL JORGE AMADO'!C20+'E M FÁBRICA DO SABER'!C20+'CIEP BRIZOLÃO 474 MAESTRO GUERR'!C20+'CENTRO DE ENSINO PROF DARCY RIB'!C20+'CEI ANDRÉ VANZAN'!C20+'CENTRO DE EDUCAÇÃO INFANTIL CAR'!C20+'CEI BOA VISTA'!C20+'ASSOCIAÇÃO DA CRECHE SÃO FRANCI'!C20+'ESCOLA MUNICIPAL PAULO SALDANHA'!C20+'ESCOLA MUNICIPAL LÚCIA DE ALMEI'!C20+'E M DOM MANOEL PEDRO DA CUNHA C'!C20+'ESCOLA SÃO GERALDO'!C20+'CEI LULU MONTEIRO DE CASTRO'!C20+'CEI CARANGOLA'!C20+'ASSOCIAÇÃO RECREAR'!C20+'CENTRO DE EDUCAÇÃO INFANTIL CAS'!C20+'E M ROSEMIRA DE OLIVEIRA CAVALC'!C20+'E MZDA CARMEM NUNES MARTINS'!C20+'CEI SÃO JOSÉ DO ITAMARATI'!C20+'E M DUQUE DE CAXIAS'!C20+'CENTRO DE EDUCAÇÃO INFANTIL 2'!C20+'E M ANTÔNIO LEITE GARCIA'!C20+'ESCOLA PAROQUIAL DA ALCOBAÇA'!C20+'CENTRO DE EDUCAÇÃO INFANTIL LOT'!C20+'ESCOLA PAROQUIAL DO LOTEAMENTO '!C20+'E M PROF JOAQUIM DEISTER'!C20+'E M MARIETA GONÇALVES'!C20+'ESCOLA MUNICIPAL ODETTE YOUNG M'!C20+'ESCOLA MUNICIPAL PROFESSOR JOSE'!C20+'E M HERCÍLIA HENRIQUES MORET'!C20+'COLEGIO VICENTINO PADRE CORRÊA'!C20+'CEI PROFª MARLUCE DE SOUZA PEST'!C20+'CEI IRINEU MARINHO'!C20+'CEI DAGMAR ROLANDO DE OLIVEIRA'!C20+'CEI NOSSA SENHORA DA GLÓRIA'!C20+'E M PROF NILTON COSTA PEREIRA D'!C20+'CENTRO DE EDUCAÇÃO INFANTIL SÉR'!C20+'CEI SANTO ANTÔNIO AGOSTINHO'!C20+'CEI OSWALDO CRUZ'!C20+'E M MAGDALENA TAGLIAFERRO'!C20+'ESCOLA SÃO JOSÉ DO CAETITU'!C20+'CRECHE-ESCOLA CASTELO SÃO MANOE'!C20+'CEI THEREZINHA DE JESUS LIMA'!C20+'ESCOLA MUNICIPAL PROFESSOR PAUL'!C20+'COLÉGIO ANGLICANO DE ARARAS'!C20+'ESCOLA PAROQUIAL SANTA BERNADET'!C20+'CEI VISTA ALEGRE'!C20+'CEI DENISE BESSA DE OLIVA MAYA'!C20+'CEI VIDEIRINHA'!C20+'E M AMÉRICO FERNANDES RIBEIRO'!C20+'ESCOLA MUNICIPAL AUGUSTO PUGNAL'!C20+'ESCOLA MUNICIPAL CELINA SCHECHN'!C20+'E M DARCY CORREA DA VEIGA'!C20+'E M DR PAULA BUARQUE'!C20+'LICEU SÃO JOSÉ DE ITAIPAVA'!C20+'CEI LUIZ MARCHIORI'!C20+'CENTRO DE EDUCAÇÃO INFANTIL AUG'!C20+'CEI PROFª ADRIANA CONSTÂNCIO TR'!C20+'E M AMÉLIA ANTUNES RABELLO'!C20+'CEI PREFEITO SÉRGIO FADEL'!C20+'E M DR THEODORO MACHADO'!C20+'ESCOLA SANTO ANTÔNIO'!C20+'E M TAQUARIL'!C20+'E M MONSENHOR JOÃO DE DEUS RODR'!C20+'CENTRO DE REFERÊNCIA EM EDUC 2'!C20+'CEI PROFª GRAÇA COSTA'!C20+'CEI VILA LEOPOLDINA'!C20+'CEI NILO PEÇANHA'!C20+'E MZDA SANTA TEREZINHA'!C20+'CEI CRIANÇA SANTA EDWIGES'!C20+'E M ARNALDO DYCKERHOFF'!C20+'E M CARLOS CANEDO'!C20+'E M BEATRIZ ZALESKI'!C20+'E M ANTÔNIO JOSÉ DE LIMA'!C20+'E M FELIX WAN ERVEN DE BARROS'!C20+'ESCOLA MUNICIPAL HILDEBRANDO DE'!C20+'E M OSWALDO DA COSTA FRIAS'!C20+'E MZDA AVELINO DE CARVALHO'!C20+'ESCOLA MUNICIPALIZADA MOYSÉS FU'!C20+'CEI ANGELA MARIA DA CONCEIÇÃO S'!C20+'CEI JOSÉ GONÇALVES DA MOTTA'!C20+'E M DR BARROS FRANCO'!C20+'E M MAJOR THEÓFILO DE CARVALHO'!C20+'E M JOÃO KOPKE'!C20+'CEI ASSOCIAÇÃO BENEFICENTE FAZE'!C20+'ESCOLA SAO FRANCISCO DE ASSIS'!C20+'CEI SÃO FRANCISCO ASSIS'!C20+'CEI ALDEIA DA CRIANCA'!C20+'ESCOLA MUNICIPAL ODETTE FONSECA'!C20+'CEI ANA CAROLINA TELLES'!C20+'E M SEBASTIÃO LACERDA'!C20+'E M DOM PEDRO DE ALCÂNTARA'!C20+'ESCOLA NOSSA SENHORA DE FÁTIMA'!C20+'ESCOLA PAROQUIAL SÃO FRANCISCO '!C20+'E M MONSENHOR CIRILLO CALAON'!C20 | D16: =B16-C16 | E16: ='Entrada de Dados'!N2 | F16: =D16*E16
A17: ='Entrada de Dados'!O5 | B17: ='Entrada de Dados'!O197 | C17: ='E M ROTARY'!C21+'E M DE EDUCAÇÃO ESPECIAL SANTOS'!C21+'LICEU MUN PREFEITO CORDOLINO AM'!C21+'E M PREFEITO JAMIL SABRÁ'!C21+'LICEU MUNICIPAL CARLOS CHAGAS F'!C21+'E M PAULO FREIRE'!C21+'E M PROFª MARIA CAMPOS DA SILVA'!C21+'CASA DA EDUCAÇÃO VISCONDE DE MA'!C21+'CENTRO DE REFERÊNCIA EM EDUCAÇÃ'!C21+'ESCOLA SANTA LUIZA DE MARILLAC'!C21+'ESCOLA DOMÉSTICA NOSSA SENHORA '!C21+'ESCOLA MONSENHOR GENTIL'!C21+'ESCOLA PAROQUIAL NOSSA SENHORA '!C21+'ESCOLA PAROQUIAL SÃO PEDRO DE A'!C21+'CEI TERRA SANTA'!C21+'CEI PRIMEIRA INFÂNCIA'!C21+'CEI PROFª PATRÍCIA FERREIRA E S'!C21+'CEI DRA ZILDA ARNS NEUMANN'!C21+'CENTRO DE EDUCAÇÃO INFANTIL PRO'!C21+'CEI MONSENHOR PAULO ELIAS DAHER'!C21+'COLÉGIO GUNNAR VINGREN DE PETRÓ'!C21+'EDUCANDÁRIO TERRA SANTA'!C21+'CEI LIONS CLUBE DE PETRÓPOLIS'!C21+'ESCOLA PAROQUIAL NOSSA SENHO 2'!C21+'CENTRO DE EDUCAÇÃO INFANTIL IRM'!C21+'E M LUIZ CARLOS SOARES'!C21+'ESCOLA GERMANO VALENTE'!C21+'ESCOLA PAROQUIAL NOSSA SENHO 3'!C21+'CEI JORGE ROLANDO DA SILVA'!C21+'E M CLEMENTE FERNANDES'!C21+'E M GERALDO VENTURA DIAS'!C21+'ESCOLA DAS COMUNIDADES SANTO AN'!C21+'CEI PROFª ROSANGELA DA SILVA LE'!C21+'CEI DEISE ELOY GOMES'!C21+'CEI PROFª SONIA REGINA SCUDESE '!C21+'CEI TIA ALICE'!C21+'E M BATAILLARD'!C21+'E M SOROPTIMISTA'!C21+'E M SALVADOR KLING'!C21+'ESCOLA MUNICIPALIZADA FREI ANIC'!C21+'ESCOLA SÃO JUDAS TADEU'!C21+'CEI PEDRAS BRANCAS'!C21+'CEI MARIA THEREZA KLING DO VALL'!C21+'CEI DONA ESPERANZA DE BOURBON D'!C21+'CEI GIUSEPPE-NEVA VOLONTERIO'!C21+'CENTRO DE EDUCAÇÃO INFANTIL SÃO'!C21+'E M LEONARDO BOFF'!C21+'ESCOLA MUNICIPAL GENERAL HEITOR'!C21+'E M JOHANN NOEL'!C21+'ESCOLA SANTA MARIA GORETTI'!C21+'ESCOLA SANTA RITA DE CASSIA'!C21+'ESCOLA SÃO JOÃO BATISTA'!C21+'CEI CASA DA SOLIDARIEDADE DE NO'!C21+'CEI A SEMENTEIRA'!C21+'CEI VILA SAO JOSE'!C21+'E M DR RUBENS DE CASTRO BOMTEMP'!C21+'CEI FREI LEÃO'!C21+'CEI SÃO JOÃO BATISTA'!C21+'CEI JURACI PINTO DO AMARAL DE C'!C21+'E M PEDRO AMADO'!C21+'E M ABELARDO DE LAMARE'!C21+'ESCOLA MUNICIPAL SENADOR MARIO '!C21+'ESCOLA PAROQUIAL SÃO PIO X'!C21+'CEI SÃO CHARBEL'!C21+'E M ROSALINA NICOLAY'!C21+'CEI INÊS BELARMINO DE SOUZA'!C21+'E M PROFª MARIA DA GLÓRIA QUEIR'!C21+'CENTRO EDUCACIONAL COMUNIDADE S'!C21+'CEI ROMANO CANAVESE'!C21+'CEI CÉLIA LÔBO PAULO'!C21+'CEI PROFª DORA KILLER'!C21+'CEI ALTO INDEPENDÊNCIA'!C21+'ESCOLA MUNICIPAL ALTO INDEPENDÊ'!C21+'E M PAPA JOÃO PAULO II'!C21+'CEI ANDRÉ REBOUÇAS'!C21+'CEI PROFª HERMÍNIA MATHEUS'!C21+'ESCOLA MUNICIPAL MAJOR JÚLIO FR'!C21+'E M ALMIRANTE TAMANDARÉ'!C21+'ESCOLA PAROQUIAL CARLOS DEMIÁ'!C21+'CENTRO PAROQUIAL DE EDUCAÇÃO IN'!C21+'CEI IRMÃ SILVANA'!C21+'CEI OLÍVIA MACHADO DA COSTA NOG'!C21+'E M GOVERNADOR MARCELLO ALENCAR'!C21+'E M PROFESSOR FLÁVIO MACIEL'!C21+'E M PROFª JANDIRA PEIXOTO BORDI'!C21+'E M STEFAN ZWEIG'!C21+'ESCOLA PAROQUIAL BOM JESUS'!C21+'CEI MARLI SOARES FERREIRA NETTO'!C21+'CENTRO DE EDUCAÇÃO INFANTIL CHI'!C21+'CEI VILA IPANEMA'!C21+'E M ROBERT KENNEDY'!C21+'ESCOLA MUNICIPAL ANA MOHAMMAD'!C21+'ESCOLA SÃO CRISTÓVÃO'!C21+'CEI DÉA LÚCIA CORDEIRO'!C21+'CEI SAGRADA FAMÍLIA'!C21+'CEI SÃO JOSÉ DAS OBLATAS DE NAZ'!C21+'ESCOLA MUNICIPAL JORGE AMADO'!C21+'E M FÁBRICA DO SABER'!C21+'CIEP BRIZOLÃO 474 MAESTRO GUERR'!C21+'CENTRO DE ENSINO PROF DARCY RIB'!C21+'CEI ANDRÉ VANZAN'!C21+'CENTRO DE EDUCAÇÃO INFANTIL CAR'!C21+'CEI BOA VISTA'!C21+'ASSOCIAÇÃO DA CRECHE SÃO FRANCI'!C21+'ESCOLA MUNICIPAL PAULO SALDANHA'!C21+'ESCOLA MUNICIPAL LÚCIA DE ALMEI'!C21+'E M DOM MANOEL PEDRO DA CUNHA C'!C21+'ESCOLA SÃO GERALDO'!C21+'CEI LULU MONTEIRO DE CASTRO'!C21+'CEI CARANGOLA'!C21+'ASSOCIAÇÃO RECREAR'!C21+'CENTRO DE EDUCAÇÃO INFANTIL CAS'!C21+'E M ROSEMIRA DE OLIVEIRA CAVALC'!C21+'E MZDA CARMEM NUNES MARTINS'!C21+'CEI SÃO JOSÉ DO ITAMARATI'!C21+'E M DUQUE DE CAXIAS'!C21+'CENTRO DE EDUCAÇÃO INFANTIL 2'!C21+'E M ANTÔNIO LEITE GARCIA'!C21+'ESCOLA PAROQUIAL DA ALCOBAÇA'!C21+'CENTRO DE EDUCAÇÃO INFANTIL LOT'!C21+'ESCOLA PAROQUIAL DO LOTEAMENTO '!C21+'E M PROF JOAQUIM DEISTER'!C21+'E M MARIETA GONÇALVES'!C21+'ESCOLA MUNICIPAL ODETTE YOUNG M'!C21+'ESCOLA MUNICIPAL PROFESSOR JOSE'!C21+'E M HERCÍLIA HENRIQUES MORET'!C21+'COLEGIO VICENTINO PADRE CORRÊA'!C21+'CEI PROFª MARLUCE DE SOUZA PEST'!C21+'CEI IRINEU MARINHO'!C21+'CEI DAGMAR ROLANDO DE OLIVEIRA'!C21+'CEI NOSSA SENHORA DA GLÓRIA'!C21+'E M PROF NILTON COSTA PEREIRA D'!C21+'CENTRO DE EDUCAÇÃO INFANTIL SÉR'!C21+'CEI SANTO ANTÔNIO AGOSTINHO'!C21+'CEI OSWALDO CRUZ'!C21+'E M MAGDALENA TAGLIAFERRO'!C21+'ESCOLA SÃO JOSÉ DO CAETITU'!C21+'CRECHE-ESCOLA CASTELO SÃO MANOE'!C21+'CEI THEREZINHA DE JESUS LIMA'!C21+'ESCOLA MUNICIPAL PROFESSOR PAUL'!C21+'COLÉGIO ANGLICANO DE ARARAS'!C21+'ESCOLA PAROQUIAL SANTA BERNADET'!C21+'CEI VISTA ALEGRE'!C21+'CEI DENISE BESSA DE OLIVA MAYA'!C21+'CEI VIDEIRINHA'!C21+'E M AMÉRICO FERNANDES RIBEIRO'!C21+'ESCOLA MUNICIPAL AUGUSTO PUGNAL'!C21+'ESCOLA MUNICIPAL CELINA SCHECHN'!C21+'E M DARCY CORREA DA VEIGA'!C21+'E M DR PAULA BUARQUE'!C21+'LICEU SÃO JOSÉ DE ITAIPAVA'!C21+'CEI LUIZ MARCHIORI'!C21+'CENTRO DE EDUCAÇÃO INFANTIL AUG'!C21+'CEI PROFª ADRIANA CONSTÂNCIO TR'!C21+'E M AMÉLIA ANTUNES RABELLO'!C21+'CEI PREFEITO SÉRGIO FADEL'!C21+'E M DR THEODORO MACHADO'!C21+'ESCOLA SANTO ANTÔNIO'!C21+'E M TAQUARIL'!C21+'E M MONSENHOR JOÃO DE DEUS RODR'!C21+'CENTRO DE REFERÊNCIA EM EDUC 2'!C21+'CEI PROFª GRAÇA COSTA'!C21+'CEI VILA LEOPOLDINA'!C21+'CEI NILO PEÇANHA'!C21+'E MZDA SANTA TEREZINHA'!C21+'CEI CRIANÇA SANTA EDWIGES'!C21+'E M ARNALDO DYCKERHOFF'!C21+'E M CARLOS CANEDO'!C21+'E M BEATRIZ ZALESKI'!C21+'E M ANTÔNIO JOSÉ DE LIMA'!C21+'E M FELIX WAN ERVEN DE BARROS'!C21+'ESCOLA MUNICIPAL HILDEBRANDO DE'!C21+'E M OSWALDO DA COSTA FRIAS'!C21+'E MZDA AVELINO DE CARVALHO'!C21+'ESCOLA MUNICIPALIZADA MOYSÉS FU'!C21+'CEI ANGELA MARIA DA CONCEIÇÃO S'!C21+'CEI JOSÉ GONÇALVES DA MOTTA'!C21+'E M DR BARROS FRANCO'!C21+'E M MAJOR THEÓFILO DE CARVALHO'!C21+'E M JOÃO KOPKE'!C21+'CEI ASSOCIAÇÃO BENEFICENTE FAZE'!C21+'ESCOLA SAO FRANCISCO DE ASSIS'!C21+'CEI SÃO FRANCISCO ASSIS'!C21+'CEI ALDEIA DA CRIANCA'!C21+'ESCOLA MUNICIPAL ODETTE FONSECA'!C21+'CEI ANA CAROLINA TELLES'!C21+'E M SEBASTIÃO LACERDA'!C21+'E M DOM PEDRO DE ALCÂNTARA'!C21+'ESCOLA NOSSA SENHORA DE FÁTIMA'!C21+'ESCOLA PAROQUIAL SÃO FRANCISCO '!C21+'E M MONSENHOR CIRILLO CALAON'!C21 | D17: =B17-C17 | E17: ='Entrada de Dados'!O2 | F17: =D17*E17
A18: ='Entrada de Dados'!P5 | B18: ='Entrada de Dados'!P197 | C18: ='E M ROTARY'!C22+'E M DE EDUCAÇÃO ESPECIAL SANTOS'!C22+'LICEU MUN PREFEITO CORDOLINO AM'!C22+'E M PREFEITO JAMIL SABRÁ'!C22+'LICEU MUNICIPAL CARLOS CHAGAS F'!C22+'E M PAULO FREIRE'!C22+'E M PROFª MARIA CAMPOS DA SILVA'!C22+'CASA DA EDUCAÇÃO VISCONDE DE MA'!C22+'CENTRO DE REFERÊNCIA EM EDUCAÇÃ'!C22+'ESCOLA SANTA LUIZA DE MARILLAC'!C22+'ESCOLA DOMÉSTICA NOSSA SENHORA '!C22+'ESCOLA MONSENHOR GENTIL'!C22+'ESCOLA PAROQUIAL NOSSA SENHORA '!C22+'ESCOLA PAROQUIAL SÃO PEDRO DE A'!C22+'CEI TERRA SANTA'!C22+'CEI PRIMEIRA INFÂNCIA'!C22+'CEI PROFª PATRÍCIA FERREIRA E S'!C22+'CEI DRA ZILDA ARNS NEUMANN'!C22+'CENTRO DE EDUCAÇÃO INFANTIL PRO'!C22+'CEI MONSENHOR PAULO ELIAS DAHER'!C22+'COLÉGIO GUNNAR VINGREN DE PETRÓ'!C22+'EDUCANDÁRIO TERRA SANTA'!C22+'CEI LIONS CLUBE DE PETRÓPOLIS'!C22+'ESCOLA PAROQUIAL NOSSA SENHO 2'!C22+'CENTRO DE EDUCAÇÃO INFANTIL IRM'!C22+'E M LUIZ CARLOS SOARES'!C22+'ESCOLA GERMANO VALENTE'!C22+'ESCOLA PAROQUIAL NOSSA SENHO 3'!C22+'CEI JORGE ROLANDO DA SILVA'!C22+'E M CLEMENTE FERNANDES'!C22+'E M GERALDO VENTURA DIAS'!C22+'ESCOLA DAS COMUNIDADES SANTO AN'!C22+'CEI PROFª ROSANGELA DA SILVA LE'!C22+'CEI DEISE ELOY GOMES'!C22+'CEI PROFª SONIA REGINA SCUDESE '!C22+'CEI TIA ALICE'!C22+'E M BATAILLARD'!C22+'E M SOROPTIMISTA'!C22+'E M SALVADOR KLING'!C22+'ESCOLA MUNICIPALIZADA FREI ANIC'!C22+'ESCOLA SÃO JUDAS TADEU'!C22+'CEI PEDRAS BRANCAS'!C22+'CEI MARIA THEREZA KLING DO VALL'!C22+'CEI DONA ESPERANZA DE BOURBON D'!C22+'CEI GIUSEPPE-NEVA VOLONTERIO'!C22+'CENTRO DE EDUCAÇÃO INFANTIL SÃO'!C22+'E M LEONARDO BOFF'!C22+'ESCOLA MUNICIPAL GENERAL HEITOR'!C22+'E M JOHANN NOEL'!C22+'ESCOLA SANTA MARIA GORETTI'!C22+'ESCOLA SANTA RITA DE CASSIA'!C22+'ESCOLA SÃO JOÃO BATISTA'!C22+'CEI CASA DA SOLIDARIEDADE DE NO'!C22+'CEI A SEMENTEIRA'!C22+'CEI VILA SAO JOSE'!C22+'E M DR RUBENS DE CASTRO BOMTEMP'!C22+'CEI FREI LEÃO'!C22+'CEI SÃO JOÃO BATISTA'!C22+'CEI JURACI PINTO DO AMARAL DE C'!C22+'E M PEDRO AMADO'!C22+'E M ABELARDO DE LAMARE'!C22+'ESCOLA MUNICIPAL SENADOR MARIO '!C22+'ESCOLA PAROQUIAL SÃO PIO X'!C22+'CEI SÃO CHARBEL'!C22+'E M ROSALINA NICOLAY'!C22+'CEI INÊS BELARMINO DE SOUZA'!C22+'E M PROFª MARIA DA GLÓRIA QUEIR'!C22+'CENTRO EDUCACIONAL COMUNIDADE S'!C22+'CEI ROMANO CANAVESE'!C22+'CEI CÉLIA LÔBO PAULO'!C22+'CEI PROFª DORA KILLER'!C22+'CEI ALTO INDEPENDÊNCIA'!C22+'ESCOLA MUNICIPAL ALTO INDEPENDÊ'!C22+'E M PAPA JOÃO PAULO II'!C22+'CEI ANDRÉ REBOUÇAS'!C22+'CEI PROFª HERMÍNIA MATHEUS'!C22+'ESCOLA MUNICIPAL MAJOR JÚLIO FR'!C22+'E M ALMIRANTE TAMANDARÉ'!C22+'ESCOLA PAROQUIAL CARLOS DEMIÁ'!C22+'CENTRO PAROQUIAL DE EDUCAÇÃO IN'!C22+'CEI IRMÃ SILVANA'!C22+'CEI OLÍVIA MACHADO DA COSTA NOG'!C22+'E M GOVERNADOR MARCELLO ALENCAR'!C22+'E M PROFESSOR FLÁVIO MACIEL'!C22+'E M PROFª JANDIRA PEIXOTO BORDI'!C22+'E M STEFAN ZWEIG'!C22+'ESCOLA PAROQUIAL BOM JESUS'!C22+'CEI MARLI SOARES FERREIRA NETTO'!C22+'CENTRO DE EDUCAÇÃO INFANTIL CHI'!C22+'CEI VILA IPANEMA'!C22+'E M ROBERT KENNEDY'!C22+'ESCOLA MUNICIPAL ANA MOHAMMAD'!C22+'ESCOLA SÃO CRISTÓVÃO'!C22+'CEI DÉA LÚCIA CORDEIRO'!C22+'CEI SAGRADA FAMÍLIA'!C22+'CEI SÃO JOSÉ DAS OBLATAS DE NAZ'!C22+'ESCOLA MUNICIPAL JORGE AMADO'!C22+'E M FÁBRICA DO SABER'!C22+'CIEP BRIZOLÃO 474 MAESTRO GUERR'!C22+'CENTRO DE ENSINO PROF DARCY RIB'!C22+'CEI ANDRÉ VANZAN'!C22+'CENTRO DE EDUCAÇÃO INFANTIL CAR'!C22+'CEI BOA VISTA'!C22+'ASSOCIAÇÃO DA CRECHE SÃO FRANCI'!C22+'ESCOLA MUNICIPAL PAULO SALDANHA'!C22+'ESCOLA MUNICIPAL LÚCIA DE ALMEI'!C22+'E M DOM MANOEL PEDRO DA CUNHA C'!C22+'ESCOLA SÃO GERALDO'!C22+'CEI LULU MONTEIRO DE CASTRO'!C22+'CEI CARANGOLA'!C22+'ASSOCIAÇÃO RECREAR'!C22+'CENTRO DE EDUCAÇÃO INFANTIL CAS'!C22+'E M ROSEMIRA DE OLIVEIRA CAVALC'!C22+'E MZDA CARMEM NUNES MARTINS'!C22+'CEI SÃO JOSÉ DO ITAMARATI'!C22+'E M DUQUE DE CAXIAS'!C22+'CENTRO DE EDUCAÇÃO INFANTIL 2'!C22+'E M ANTÔNIO LEITE GARCIA'!C22+'ESCOLA PAROQUIAL DA ALCOBAÇA'!C22+'CENTRO DE EDUCAÇÃO INFANTIL LOT'!C22+'ESCOLA PAROQUIAL DO LOTEAMENTO '!C22+'E M PROF JOAQUIM DEISTER'!C22+'E M MARIETA GONÇALVES'!C22+'ESCOLA MUNICIPAL ODETTE YOUNG M'!C22+'ESCOLA MUNICIPAL PROFESSOR JOSE'!C22+'E M HERCÍLIA HENRIQUES MORET'!C22+'COLEGIO VICENTINO PADRE CORRÊA'!C22+'CEI PROFª MARLUCE DE SOUZA PEST'!C22+'CEI IRINEU MARINHO'!C22+'CEI DAGMAR ROLANDO DE OLIVEIRA'!C22+'CEI NOSSA SENHORA DA GLÓRIA'!C22+'E M PROF NILTON COSTA PEREIRA D'!C22+'CENTRO DE EDUCAÇÃO INFANTIL SÉR'!C22+'CEI SANTO ANTÔNIO AGOSTINHO'!C22+'CEI OSWALDO CRUZ'!C22+'E M MAGDALENA TAGLIAFERRO'!C22+'ESCOLA SÃO JOSÉ DO CAETITU'!C22+'CRECHE-ESCOLA CASTELO SÃO MANOE'!C22+'CEI THEREZINHA DE JESUS LIMA'!C22+'ESCOLA MUNICIPAL PROFESSOR PAUL'!C22+'COLÉGIO ANGLICANO DE ARARAS'!C22+'ESCOLA PAROQUIAL SANTA BERNADET'!C22+'CEI VISTA ALEGRE'!C22+'CEI DENISE BESSA DE OLIVA MAYA'!C22+'CEI VIDEIRINHA'!C22+'E M AMÉRICO FERNANDES RIBEIRO'!C22+'ESCOLA MUNICIPAL AUGUSTO PUGNAL'!C22+'ESCOLA MUNICIPAL CELINA SCHECHN'!C22+'E M DARCY CORREA DA VEIGA'!C22+'E M DR PAULA BUARQUE'!C22+'LICEU SÃO JOSÉ DE ITAIPAVA'!C22+'CEI LUIZ MARCHIORI'!C22+'CENTRO DE EDUCAÇÃO INFANTIL AUG'!C22+'CEI PROFª ADRIANA CONSTÂNCIO TR'!C22+'E M AMÉLIA ANTUNES RABELLO'!C22+'CEI PREFEITO SÉRGIO FADEL'!C22+'E M DR THEODORO MACHADO'!C22+'ESCOLA SANTO ANTÔNIO'!C22+'E M TAQUARIL'!C22+'E M MONSENHOR JOÃO DE DEUS RODR'!C22+'CENTRO DE REFERÊNCIA EM EDUC 2'!C22+'CEI PROFª GRAÇA COSTA'!C22+'CEI VILA LEOPOLDINA'!C22+'CEI NILO PEÇANHA'!C22+'E MZDA SANTA TEREZINHA'!C22+'CEI CRIANÇA SANTA EDWIGES'!C22+'E M ARNALDO DYCKERHOFF'!C22+'E M CARLOS CANEDO'!C22+'E M BEATRIZ ZALESKI'!C22+'E M ANTÔNIO JOSÉ DE LIMA'!C22+'E M FELIX WAN ERVEN DE BARROS'!C22+'ESCOLA MUNICIPAL HILDEBRANDO DE'!C22+'E M OSWALDO DA COSTA FRIAS'!C22+'E MZDA AVELINO DE CARVALHO'!C22+'ESCOLA MUNICIPALIZADA MOYSÉS FU'!C22+'CEI ANGELA MARIA DA CONCEIÇÃO S'!C22+'CEI JOSÉ GONÇALVES DA MOTTA'!C22+'E M DR BARROS FRANCO'!C22+'E M MAJOR THEÓFILO DE CARVALHO'!C22+'E M JOÃO KOPKE'!C22+'CEI ASSOCIAÇÃO BENEFICENTE FAZE'!C22+'ESCOLA SAO FRANCISCO DE ASSIS'!C22+'CEI SÃO FRANCISCO ASSIS'!C22+'CEI ALDEIA DA CRIANCA'!C22+'ESCOLA MUNICIPAL ODETTE FONSECA'!C22+'CEI ANA CAROLINA TELLES'!C22+'E M SEBASTIÃO LACERDA'!C22+'E M DOM PEDRO DE ALCÂNTARA'!C22+'ESCOLA NOSSA SENHORA DE FÁTIMA'!C22+'ESCOLA PAROQUIAL SÃO FRANCISCO '!C22+'E M MONSENHOR CIRILLO CALAON'!C22 | D18: =B18-C18 | E18: ='Entrada de Dados'!P2 | F18: =D18*E18
A19: ='Entrada de Dados'!Q5 | B19: ='Entrada de Dados'!Q197 | C19: ='E M ROTARY'!C23+'E M DE EDUCAÇÃO ESPECIAL SANTOS'!C23+'LICEU MUN PREFEITO CORDOLINO AM'!C23+'E M PREFEITO JAMIL SABRÁ'!C23+'LICEU MUNICIPAL CARLOS CHAGAS F'!C23+'E M PAULO FREIRE'!C23+'E M PROFª MARIA CAMPOS DA SILVA'!C23+'CASA DA EDUCAÇÃO VISCONDE DE MA'!C23+'CENTRO DE REFERÊNCIA EM EDUCAÇÃ'!C23+'ESCOLA SANTA LUIZA DE MARILLAC'!C23+'ESCOLA DOMÉSTICA NOSSA SENHORA '!C23+'ESCOLA MONSENHOR GENTIL'!C23+'ESCOLA PAROQUIAL NOSSA SENHORA '!C23+'ESCOLA PAROQUIAL SÃO PEDRO DE A'!C23+'CEI TERRA SANTA'!C23+'CEI PRIMEIRA INFÂNCIA'!C23+'CEI PROFª PATRÍCIA FERREIRA E S'!C23+'CEI DRA ZILDA ARNS NEUMANN'!C23+'CENTRO DE EDUCAÇÃO INFANTIL PRO'!C23+'CEI MONSENHOR PAULO ELIAS DAHER'!C23+'COLÉGIO GUNNAR VINGREN DE PETRÓ'!C23+'EDUCANDÁRIO TERRA SANTA'!C23+'CEI LIONS CLUBE DE PETRÓPOLIS'!C23+'ESCOLA PAROQUIAL NOSSA SENHO 2'!C23+'CENTRO DE EDUCAÇÃO INFANTIL IRM'!C23+'E M LUIZ CARLOS SOARES'!C23+'ESCOLA GERMANO VALENTE'!C23+'ESCOLA PAROQUIAL NOSSA SENHO 3'!C23+'CEI JORGE ROLANDO DA SILVA'!C23+'E M CLEMENTE FERNANDES'!C23+'E M GERALDO VENTURA DIAS'!C23+'ESCOLA DAS COMUNIDADES SANTO AN'!C23+'CEI PROFª ROSANGELA DA SILVA LE'!C23+'CEI DEISE ELOY GOMES'!C23+'CEI PROFª SONIA REGINA SCUDESE '!C23+'CEI TIA ALICE'!C23+'E M BATAILLARD'!C23+'E M SOROPTIMISTA'!C23+'E M SALVADOR KLING'!C23+'ESCOLA MUNICIPALIZADA FREI ANIC'!C23+'ESCOLA SÃO JUDAS TADEU'!C23+'CEI PEDRAS BRANCAS'!C23+'CEI MARIA THEREZA KLING DO VALL'!C23+'CEI DONA ESPERANZA DE BOURBON D'!C23+'CEI GIUSEPPE-NEVA VOLONTERIO'!C23+'CENTRO DE EDUCAÇÃO INFANTIL SÃO'!C23+'E M LEONARDO BOFF'!C23+'ESCOLA MUNICIPAL GENERAL HEITOR'!C23+'E M JOHANN NOEL'!C23+'ESCOLA SANTA MARIA GORETTI'!C23+'ESCOLA SANTA RITA DE CASSIA'!C23+'ESCOLA SÃO JOÃO BATISTA'!C23+'CEI CASA DA SOLIDARIEDADE DE NO'!C23+'CEI A SEMENTEIRA'!C23+'CEI VILA SAO JOSE'!C23+'E M DR RUBENS DE CASTRO BOMTEMP'!C23+'CEI FREI LEÃO'!C23+'CEI SÃO JOÃO BATISTA'!C23+'CEI JURACI PINTO DO AMARAL DE C'!C23+'E M PEDRO AMADO'!C23+'E M ABELARDO DE LAMARE'!C23+'ESCOLA MUNICIPAL SENADOR MARIO '!C23+'ESCOLA PAROQUIAL SÃO PIO X'!C23+'CEI SÃO CHARBEL'!C23+'E M ROSALINA NICOLAY'!C23+'CEI INÊS BELARMINO DE SOUZA'!C23+'E M PROFª MARIA DA GLÓRIA QUEIR'!C23+'CENTRO EDUCACIONAL COMUNIDADE S'!C23+'CEI ROMANO CANAVESE'!C23+'CEI CÉLIA LÔBO PAULO'!C23+'CEI PROFª DORA KILLER'!C23+'CEI ALTO INDEPENDÊNCIA'!C23+'ESCOLA MUNICIPAL ALTO INDEPENDÊ'!C23+'E M PAPA JOÃO PAULO II'!C23+'CEI ANDRÉ REBOUÇAS'!C23+'CEI PROFª HERMÍNIA MATHEUS'!C23+'ESCOLA MUNICIPAL MAJOR JÚLIO FR'!C23+'E M ALMIRANTE TAMANDARÉ'!C23+'ESCOLA PAROQUIAL CARLOS DEMIÁ'!C23+'CENTRO PAROQUIAL DE EDUCAÇÃO IN'!C23+'CEI IRMÃ SILVANA'!C23+'CEI OLÍVIA MACHADO DA COSTA NOG'!C23+'E M GOVERNADOR MARCELLO ALENCAR'!C23+'E M PROFESSOR FLÁVIO MACIEL'!C23+'E M PROFª JANDIRA PEIXOTO BORDI'!C23+'E M STEFAN ZWEIG'!C23+'ESCOLA PAROQUIAL BOM JESUS'!C23+'CEI MARLI SOARES FERREIRA NETTO'!C23+'CENTRO DE EDUCAÇÃO INFANTIL CHI'!C23+'CEI VILA IPANEMA'!C23+'E M ROBERT KENNEDY'!C23+'ESCOLA MUNICIPAL ANA MOHAMMAD'!C23+'ESCOLA SÃO CRISTÓVÃO'!C23+'CEI DÉA LÚCIA CORDEIRO'!C23+'CEI SAGRADA FAMÍLIA'!C23+'CEI SÃO JOSÉ DAS OBLATAS DE NAZ'!C23+'ESCOLA MUNICIPAL JORGE AMADO'!C23+'E M FÁBRICA DO SABER'!C23+'CIEP BRIZOLÃO 474 MAESTRO GUERR'!C23+'CENTRO DE ENSINO PROF DARCY RIB'!C23+'CEI ANDRÉ VANZAN'!C23+'CENTRO DE EDUCAÇÃO INFANTIL CAR'!C23+'CEI BOA VISTA'!C23+'ASSOCIAÇÃO DA CRECHE SÃO FRANCI'!C23+'ESCOLA MUNICIPAL PAULO SALDANHA'!C23+'ESCOLA MUNICIPAL LÚCIA DE ALMEI'!C23+'E M DOM MANOEL PEDRO DA CUNHA C'!C23+'ESCOLA SÃO GERALDO'!C23+'CEI LULU MONTEIRO DE CASTRO'!C23+'CEI CARANGOLA'!C23+'ASSOCIAÇÃO RECREAR'!C23+'CENTRO DE EDUCAÇÃO INFANTIL CAS'!C23+'E M ROSEMIRA DE OLIVEIRA CAVALC'!C23+'E MZDA CARMEM NUNES MARTINS'!C23+'CEI SÃO JOSÉ DO ITAMARATI'!C23+'E M DUQUE DE CAXIAS'!C23+'CENTRO DE EDUCAÇÃO INFANTIL 2'!C23+'E M ANTÔNIO LEITE GARCIA'!C23+'ESCOLA PAROQUIAL DA ALCOBAÇA'!C23+'CENTRO DE EDUCAÇÃO INFANTIL LOT'!C23+'ESCOLA PAROQUIAL DO LOTEAMENTO '!C23+'E M PROF JOAQUIM DEISTER'!C23+'E M MARIETA GONÇALVES'!C23+'ESCOLA MUNICIPAL ODETTE YOUNG M'!C23+'ESCOLA MUNICIPAL PROFESSOR JOSE'!C23+'E M HERCÍLIA HENRIQUES MORET'!C23+'COLEGIO VICENTINO PADRE CORRÊA'!C23+'CEI PROFª MARLUCE DE SOUZA PEST'!C23+'CEI IRINEU MARINHO'!C23+'CEI DAGMAR ROLANDO DE OLIVEIRA'!C23+'CEI NOSSA SENHORA DA GLÓRIA'!C23+'E M PROF NILTON COSTA PEREIRA D'!C23+'CENTRO DE EDUCAÇÃO INFANTIL SÉR'!C23+'CEI SANTO ANTÔNIO AGOSTINHO'!C23+'CEI OSWALDO CRUZ'!C23+'E M MAGDALENA TAGLIAFERRO'!C23+'ESCOLA SÃO JOSÉ DO CAETITU'!C23+'CRECHE-ESCOLA CASTELO SÃO MANOE'!C23+'CEI THEREZINHA DE JESUS LIMA'!C23+'ESCOLA MUNICIPAL PROFESSOR PAUL'!C23+'COLÉGIO ANGLICANO DE ARARAS'!C23+'ESCOLA PAROQUIAL SANTA BERNADET'!C23+'CEI VISTA ALEGRE'!C23+'CEI DENISE BESSA DE OLIVA MAYA'!C23+'CEI VIDEIRINHA'!C23+'E M AMÉRICO FERNANDES RIBEIRO'!C23+'ESCOLA MUNICIPAL AUGUSTO PUGNAL'!C23+'ESCOLA MUNICIPAL CELINA SCHECHN'!C23+'E M DARCY CORREA DA VEIGA'!C23+'E M DR PAULA BUARQUE'!C23+'LICEU SÃO JOSÉ DE ITAIPAVA'!C23+'CEI LUIZ MARCHIORI'!C23+'CENTRO DE EDUCAÇÃO INFANTIL AUG'!C23+'CEI PROFª ADRIANA CONSTÂNCIO TR'!C23+'E M AMÉLIA ANTUNES RABELLO'!C23+'CEI PREFEITO SÉRGIO FADEL'!C23+'E M DR THEODORO MACHADO'!C23+'ESCOLA SANTO ANTÔNIO'!C23+'E M TAQUARIL'!C23+'E M MONSENHOR JOÃO DE DEUS RODR'!C23+'CENTRO DE REFERÊNCIA EM EDUC 2'!C23+'CEI PROFª GRAÇA COSTA'!C23+'CEI VILA LEOPOLDINA'!C23+'CEI NILO PEÇANHA'!C23+'E MZDA SANTA TEREZINHA'!C23+'CEI CRIANÇA SANTA EDWIGES'!C23+'E M ARNALDO DYCKERHOFF'!C23+'E M CARLOS CANEDO'!C23+'E M BEATRIZ ZALESKI'!C23+'E M ANTÔNIO JOSÉ DE LIMA'!C23+'E M FELIX WAN ERVEN DE BARROS'!C23+'ESCOLA MUNICIPAL HILDEBRANDO DE'!C23+'E M OSWALDO DA COSTA FRIAS'!C23+'E MZDA AVELINO DE CARVALHO'!C23+'ESCOLA MUNICIPALIZADA MOYSÉS FU'!C23+'CEI ANGELA MARIA DA CONCEIÇÃO S'!C23+'CEI JOSÉ GONÇALVES DA MOTTA'!C23+'E M DR BARROS FRANCO'!C23+'E M MAJOR THEÓFILO DE CARVALHO'!C23+'E M JOÃO KOPKE'!C23+'CEI ASSOCIAÇÃO BENEFICENTE FAZE'!C23+'ESCOLA SAO FRANCISCO DE ASSIS'!C23+'CEI SÃO FRANCISCO ASSIS'!C23+'CEI ALDEIA DA CRIANCA'!C23+'ESCOLA MUNICIPAL ODETTE FONSECA'!C23+'CEI ANA CAROLINA TELLES'!C23+'E M SEBASTIÃO LACERDA'!C23+'E M DOM PEDRO DE ALCÂNTARA'!C23+'ESCOLA NOSSA SENHORA DE FÁTIMA'!C23+'ESCOLA PAROQUIAL SÃO FRANCISCO '!C23+'E M MONSENHOR CIRILLO CALAON'!C23 | D19: =B19-C19 | E19: ='Entrada de Dados'!Q2 | F19: =D19*E19
A20: ='Entrada de Dados'!R5 | B20: ='Entrada de Dados'!R197 | C20: ='E M ROTARY'!C24+'E M DE EDUCAÇÃO ESPECIAL SANTOS'!C24+'LICEU MUN PREFEITO CORDOLINO AM'!C24+'E M PREFEITO JAMIL SABRÁ'!C24+'LICEU MUNICIPAL CARLOS CHAGAS F'!C24+'E M PAULO FREIRE'!C24+'E M PROFª MARIA CAMPOS DA SILVA'!C24+'CASA DA EDUCAÇÃO VISCONDE DE MA'!C24+'CENTRO DE REFERÊNCIA EM EDUCAÇÃ'!C24+'ESCOLA SANTA LUIZA DE MARILLAC'!C24+'ESCOLA DOMÉSTICA NOSSA SENHORA '!C24+'ESCOLA MONSENHOR GENTIL'!C24+'ESCOLA PAROQUIAL NOSSA SENHORA '!C24+'ESCOLA PAROQUIAL SÃO PEDRO DE A'!C24+'CEI TERRA SANTA'!C24+'CEI PRIMEIRA INFÂNCIA'!C24+'CEI PROFª PATRÍCIA FERREIRA E S'!C24+'CEI DRA ZILDA ARNS NEUMANN'!C24+'CENTRO DE EDUCAÇÃO INFANTIL PRO'!C24+'CEI MONSENHOR PAULO ELIAS DAHER'!C24+'COLÉGIO GUNNAR VINGREN DE PETRÓ'!C24+'EDUCANDÁRIO TERRA SANTA'!C24+'CEI LIONS CLUBE DE PETRÓPOLIS'!C24+'ESCOLA PAROQUIAL NOSSA SENHO 2'!C24+'CENTRO DE EDUCAÇÃO INFANTIL IRM'!C24+'E M LUIZ CARLOS SOARES'!C24+'ESCOLA GERMANO VALENTE'!C24+'ESCOLA PAROQUIAL NOSSA SENHO 3'!C24+'CEI JORGE ROLANDO DA SILVA'!C24+'E M CLEMENTE FERNANDES'!C24+'E M GERALDO VENTURA DIAS'!C24+'ESCOLA DAS COMUNIDADES SANTO AN'!C24+'CEI PROFª ROSANGELA DA SILVA LE'!C24+'CEI DEISE ELOY GOMES'!C24+'CEI PROFª SONIA REGINA SCUDESE '!C24+'CEI TIA ALICE'!C24+'E M BATAILLARD'!C24+'E M SOROPTIMISTA'!C24+'E M SALVADOR KLING'!C24+'ESCOLA MUNICIPALIZADA FREI ANIC'!C24+'ESCOLA SÃO JUDAS TADEU'!C24+'CEI PEDRAS BRANCAS'!C24+'CEI MARIA THEREZA KLING DO VALL'!C24+'CEI DONA ESPERANZA DE BOURBON D'!C24+'CEI GIUSEPPE-NEVA VOLONTERIO'!C24+'CENTRO DE EDUCAÇÃO INFANTIL SÃO'!C24+'E M LEONARDO BOFF'!C24+'ESCOLA MUNICIPAL GENERAL HEITOR'!C24+'E M JOHANN NOEL'!C24+'ESCOLA SANTA MARIA GORETTI'!C24+'ESCOLA SANTA RITA DE CASSIA'!C24+'ESCOLA SÃO JOÃO BATISTA'!C24+'CEI CASA DA SOLIDARIEDADE DE NO'!C24+'CEI A SEMENTEIRA'!C24+'CEI VILA SAO JOSE'!C24+'E M DR RUBENS DE CASTRO BOMTEMP'!C24+'CEI FREI LEÃO'!C24+'CEI SÃO JOÃO BATISTA'!C24+'CEI JURACI PINTO DO AMARAL DE C'!C24+'E M PEDRO AMADO'!C24+'E M ABELARDO DE LAMARE'!C24+'ESCOLA MUNICIPAL SENADOR MARIO '!C24+'ESCOLA PAROQUIAL SÃO PIO X'!C24+'CEI SÃO CHARBEL'!C24+'E M ROSALINA NICOLAY'!C24+'CEI INÊS BELARMINO DE SOUZA'!C24+'E M PROFª MARIA DA GLÓRIA QUEIR'!C24+'CENTRO EDUCACIONAL COMUNIDADE S'!C24+'CEI ROMANO CANAVESE'!C24+'CEI CÉLIA LÔBO PAULO'!C24+'CEI PROFª DORA KILLER'!C24+'CEI ALTO INDEPENDÊNCIA'!C24+'ESCOLA MUNICIPAL ALTO INDEPENDÊ'!C24+'E M PAPA JOÃO PAULO II'!C24+'CEI ANDRÉ REBOUÇAS'!C24+'CEI PROFª HERMÍNIA MATHEUS'!C24+'ESCOLA MUNICIPAL MAJOR JÚLIO FR'!C24+'E M ALMIRANTE TAMANDARÉ'!C24+'ESCOLA PAROQUIAL CARLOS DEMIÁ'!C24+'CENTRO PAROQUIAL DE EDUCAÇÃO IN'!C24+'CEI IRMÃ SILVANA'!C24+'CEI OLÍVIA MACHADO DA COSTA NOG'!C24+'E M GOVERNADOR MARCELLO ALENCAR'!C24+'E M PROFESSOR FLÁVIO MACIEL'!C24+'E M PROFª JANDIRA PEIXOTO BORDI'!C24+'E M STEFAN ZWEIG'!C24+'ESCOLA PAROQUIAL BOM JESUS'!C24+'CEI MARLI SOARES FERREIRA NETTO'!C24+'CENTRO DE EDUCAÇÃO INFANTIL CHI'!C24+'CEI VILA IPANEMA'!C24+'E M ROBERT KENNEDY'!C24+'ESCOLA MUNICIPAL ANA MOHAMMAD'!C24+'ESCOLA SÃO CRISTÓVÃO'!C24+'CEI DÉA LÚCIA CORDEIRO'!C24+'CEI SAGRADA FAMÍLIA'!C24+'CEI SÃO JOSÉ DAS OBLATAS DE NAZ'!C24+'ESCOLA MUNICIPAL JORGE AMADO'!C24+'E M FÁBRICA DO SABER'!C24+'CIEP BRIZOLÃO 474 MAESTRO GUERR'!C24+'CENTRO DE ENSINO PROF DARCY RIB'!C24+'CEI ANDRÉ VANZAN'!C24+'CENTRO DE EDUCAÇÃO INFANTIL CAR'!C24+'CEI BOA VISTA'!C24+'ASSOCIAÇÃO DA CRECHE SÃO FRANCI'!C24+'ESCOLA MUNICIPAL PAULO SALDANHA'!C24+'ESCOLA MUNICIPAL LÚCIA DE ALMEI'!C24+'E M DOM MANOEL PEDRO DA CUNHA C'!C24+'ESCOLA SÃO GERALDO'!C24+'CEI LULU MONTEIRO DE CASTRO'!C24+'CEI CARANGOLA'!C24+'ASSOCIAÇÃO RECREAR'!C24+'CENTRO DE EDUCAÇÃO INFANTIL CAS'!C24+'E M ROSEMIRA DE OLIVEIRA CAVALC'!C24+'E MZDA CARMEM NUNES MARTINS'!C24+'CEI SÃO JOSÉ DO ITAMARATI'!C24+'E M DUQUE DE CAXIAS'!C24+'CENTRO DE EDUCAÇÃO INFANTIL 2'!C24+'E M ANTÔNIO LEITE GARCIA'!C24+'ESCOLA PAROQUIAL DA ALCOBAÇA'!C24+'CENTRO DE EDUCAÇÃO INFANTIL LOT'!C24+'ESCOLA PAROQUIAL DO LOTEAMENTO '!C24+'E M PROF JOAQUIM DEISTER'!C24+'E M MARIETA GONÇALVES'!C24+'ESCOLA MUNICIPAL ODETTE YOUNG M'!C24+'ESCOLA MUNICIPAL PROFESSOR JOSE'!C24+'E M HERCÍLIA HENRIQUES MORET'!C24+'COLEGIO VICENTINO PADRE CORRÊA'!C24+'CEI PROFª MARLUCE DE SOUZA PEST'!C24+'CEI IRINEU MARINHO'!C24+'CEI DAGMAR ROLANDO DE OLIVEIRA'!C24+'CEI NOSSA SENHORA DA GLÓRIA'!C24+'E M PROF NILTON COSTA PEREIRA D'!C24+'CENTRO DE EDUCAÇÃO INFANTIL SÉR'!C24+'CEI SANTO ANTÔNIO AGOSTINHO'!C24+'CEI OSWALDO CRUZ'!C24+'E M MAGDALENA TAGLIAFERRO'!C24+'ESCOLA SÃO JOSÉ DO CAETITU'!C24+'CRECHE-ESCOLA CASTELO SÃO MANOE'!C24+'CEI THEREZINHA DE JESUS LIMA'!C24+'ESCOLA MUNICIPAL PROFESSOR PAUL'!C24+'COLÉGIO ANGLICANO DE ARARAS'!C24+'ESCOLA PAROQUIAL SANTA BERNADET'!C24+'CEI VISTA ALEGRE'!C24+'CEI DENISE BESSA DE OLIVA MAYA'!C24+'CEI VIDEIRINHA'!C24+'E M AMÉRICO FERNANDES RIBEIRO'!C24+'ESCOLA MUNICIPAL AUGUSTO PUGNAL'!C24+'ESCOLA MUNICIPAL CELINA SCHECHN'!C24+'E M DARCY CORREA DA VEIGA'!C24+'E M DR PAULA BUARQUE'!C24+'LICEU SÃO JOSÉ DE ITAIPAVA'!C24+'CEI LUIZ MARCHIORI'!C24+'CENTRO DE EDUCAÇÃO INFANTIL AUG'!C24+'CEI PROFª ADRIANA CONSTÂNCIO TR'!C24+'E M AMÉLIA ANTUNES RABELLO'!C24+'CEI PREFEITO SÉRGIO FADEL'!C24+'E M DR THEODORO MACHADO'!C24+'ESCOLA SANTO ANTÔNIO'!C24+'E M TAQUARIL'!C24+'E M MONSENHOR JOÃO DE DEUS RODR'!C24+'CENTRO DE REFERÊNCIA EM EDUC 2'!C24+'CEI PROFª GRAÇA COSTA'!C24+'CEI VILA LEOPOLDINA'!C24+'CEI NILO PEÇANHA'!C24+'E MZDA SANTA TEREZINHA'!C24+'CEI CRIANÇA SANTA EDWIGES'!C24+'E M ARNALDO DYCKERHOFF'!C24+'E M CARLOS CANEDO'!C24+'E M BEATRIZ ZALESKI'!C24+'E M ANTÔNIO JOSÉ DE LIMA'!C24+'E M FELIX WAN ERVEN DE BARROS'!C24+'ESCOLA MUNICIPAL HILDEBRANDO DE'!C24+'E M OSWALDO DA COSTA FRIAS'!C24+'E MZDA AVELINO DE CARVALHO'!C24+'ESCOLA MUNICIPALIZADA MOYSÉS FU'!C24+'CEI ANGELA MARIA DA CONCEIÇÃO S'!C24+'CEI JOSÉ GONÇALVES DA MOTTA'!C24+'E M DR BARROS FRANCO'!C24+'E M MAJOR THEÓFILO DE CARVALHO'!C24+'E M JOÃO KOPKE'!C24+'CEI ASSOCIAÇÃO BENEFICENTE FAZE'!C24+'ESCOLA SAO FRANCISCO DE ASSIS'!C24+'CEI SÃO FRANCISCO ASSIS'!C24+'CEI ALDEIA DA CRIANCA'!C24+'ESCOLA MUNICIPAL ODETTE FONSECA'!C24+'CEI ANA CAROLINA TELLES'!C24+'E M SEBASTIÃO LACERDA'!C24+'E M DOM PEDRO DE ALCÂNTARA'!C24+'ESCOLA NOSSA SENHORA DE FÁTIMA'!C24+'ESCOLA PAROQUIAL SÃO FRANCISCO '!C24+'E M MONSENHOR CIRILLO CALAON'!C24 | D20: =B20-C20 | E20: ='Entrada de Dados'!R2 | F20: =D20*E20
A21: ='Entrada de Dados'!S5 | B21: ='Entrada de Dados'!S197 | C21: ='E M ROTARY'!C25+'E M DE EDUCAÇÃO ESPECIAL SANTOS'!C25+'LICEU MUN PREFEITO CORDOLINO AM'!C25+'E M PREFEITO JAMIL SABRÁ'!C25+'LICEU MUNICIPAL CARLOS CHAGAS F'!C25+'E M PAULO FREIRE'!C25+'E M PROFª MARIA CAMPOS DA SILVA'!C25+'CASA DA EDUCAÇÃO VISCONDE DE MA'!C25+'CENTRO DE REFERÊNCIA EM EDUCAÇÃ'!C25+'ESCOLA SANTA LUIZA DE MARILLAC'!C25+'ESCOLA DOMÉSTICA NOSSA SENHORA '!C25+'ESCOLA MONSENHOR GENTIL'!C25+'ESCOLA PAROQUIAL NOSSA SENHORA '!C25+'ESCOLA PAROQUIAL SÃO PEDRO DE A'!C25+'CEI TERRA SANTA'!C25+'CEI PRIMEIRA INFÂNCIA'!C25+'CEI PROFª PATRÍCIA FERREIRA E S'!C25+'CEI DRA ZILDA ARNS NEUMANN'!C25+'CENTRO DE EDUCAÇÃO INFANTIL PRO'!C25+'CEI MONSENHOR PAULO ELIAS DAHER'!C25+'COLÉGIO GUNNAR VINGREN DE PETRÓ'!C25+'EDUCANDÁRIO TERRA SANTA'!C25+'CEI LIONS CLUBE DE PETRÓPOLIS'!C25+'ESCOLA PAROQUIAL NOSSA SENHO 2'!C25+'CENTRO DE EDUCAÇÃO INFANTIL IRM'!C25+'E M LUIZ CARLOS SOARES'!C25+'ESCOLA GERMANO VALENTE'!C25+'ESCOLA PAROQUIAL NOSSA SENHO 3'!C25+'CEI JORGE ROLANDO DA SILVA'!C25+'E M CLEMENTE FERNANDES'!C25+'E M GERALDO VENTURA DIAS'!C25+'ESCOLA DAS COMUNIDADES SANTO AN'!C25+'CEI PROFª ROSANGELA DA SILVA LE'!C25+'CEI DEISE ELOY GOMES'!C25+'CEI PROFª SONIA REGINA SCUDESE '!C25+'CEI TIA ALICE'!C25+'E M BATAILLARD'!C25+'E M SOROPTIMISTA'!C25+'E M SALVADOR KLING'!C25+'ESCOLA MUNICIPALIZADA FREI ANIC'!C25+'ESCOLA SÃO JUDAS TADEU'!C25+'CEI PEDRAS BRANCAS'!C25+'CEI MARIA THEREZA KLING DO VALL'!C25+'CEI DONA ESPERANZA DE BOURBON D'!C25+'CEI GIUSEPPE-NEVA VOLONTERIO'!C25+'CENTRO DE EDUCAÇÃO INFANTIL SÃO'!C25+'E M LEONARDO BOFF'!C25+'ESCOLA MUNICIPAL GENERAL HEITOR'!C25+'E M JOHANN NOEL'!C25+'ESCOLA SANTA MARIA GORETTI'!C25+'ESCOLA SANTA RITA DE CASSIA'!C25+'ESCOLA SÃO JOÃO BATISTA'!C25+'CEI CASA DA SOLIDARIEDADE DE NO'!C25+'CEI A SEMENTEIRA'!C25+'CEI VILA SAO JOSE'!C25+'E M DR RUBENS DE CASTRO BOMTEMP'!C25+'CEI FREI LEÃO'!C25+'CEI SÃO JOÃO BATISTA'!C25+'CEI JURACI PINTO DO AMARAL DE C'!C25+'E M PEDRO AMADO'!C25+'E M ABELARDO DE LAMARE'!C25+'ESCOLA MUNICIPAL SENADOR MARIO '!C25+'ESCOLA PAROQUIAL SÃO PIO X'!C25+'CEI SÃO CHARBEL'!C25+'E M ROSALINA NICOLAY'!C25+'CEI INÊS BELARMINO DE SOUZA'!C25+'E M PROFª MARIA DA GLÓRIA QUEIR'!C25+'CENTRO EDUCACIONAL COMUNIDADE S'!C25+'CEI ROMANO CANAVESE'!C25+'CEI CÉLIA LÔBO PAULO'!C25+'CEI PROFª DORA KILLER'!C25+'CEI ALTO INDEPENDÊNCIA'!C25+'ESCOLA MUNICIPAL ALTO INDEPENDÊ'!C25+'E M PAPA JOÃO PAULO II'!C25+'CEI ANDRÉ REBOUÇAS'!C25+'CEI PROFª HERMÍNIA MATHEUS'!C25+'ESCOLA MUNICIPAL MAJOR JÚLIO FR'!C25+'E M ALMIRANTE TAMANDARÉ'!C25+'ESCOLA PAROQUIAL CARLOS DEMIÁ'!C25+'CENTRO PAROQUIAL DE EDUCAÇÃO IN'!C25+'CEI IRMÃ SILVANA'!C25+'CEI OLÍVIA MACHADO DA COSTA NOG'!C25+'E M GOVERNADOR MARCELLO ALENCAR'!C25+'E M PROFESSOR FLÁVIO MACIEL'!C25+'E M PROFª JANDIRA PEIXOTO BORDI'!C25+'E M STEFAN ZWEIG'!C25+'ESCOLA PAROQUIAL BOM JESUS'!C25+'CEI MARLI SOARES FERREIRA NETTO'!C25+'CENTRO DE EDUCAÇÃO INFANTIL CHI'!C25+'CEI VILA IPANEMA'!C25+'E M ROBERT KENNEDY'!C25+'ESCOLA MUNICIPAL ANA MOHAMMAD'!C25+'ESCOLA SÃO CRISTÓVÃO'!C25+'CEI DÉA LÚCIA CORDEIRO'!C25+'CEI SAGRADA FAMÍLIA'!C25+'CEI SÃO JOSÉ DAS OBLATAS DE NAZ'!C25+'ESCOLA MUNICIPAL JORGE AMADO'!C25+'E M FÁBRICA DO SABER'!C25+'CIEP BRIZOLÃO 474 MAESTRO GUERR'!C25+'CENTRO DE ENSINO PROF DARCY RIB'!C25+'CEI ANDRÉ VANZAN'!C25+'CENTRO DE EDUCAÇÃO INFANTIL CAR'!C25+'CEI BOA VISTA'!C25+'ASSOCIAÇÃO DA CRECHE SÃO FRANCI'!C25+'ESCOLA MUNICIPAL PAULO SALDANHA'!C25+'ESCOLA MUNICIPAL LÚCIA DE ALMEI'!C25+'E M DOM MANOEL PEDRO DA CUNHA C'!C25+'ESCOLA SÃO GERALDO'!C25+'CEI LULU MONTEIRO DE CASTRO'!C25+'CEI CARANGOLA'!C25+'ASSOCIAÇÃO RECREAR'!C25+'CENTRO DE EDUCAÇÃO INFANTIL CAS'!C25+'E M ROSEMIRA DE OLIVEIRA CAVALC'!C25+'E MZDA CARMEM NUNES MARTINS'!C25+'CEI SÃO JOSÉ DO ITAMARATI'!C25+'E M DUQUE DE CAXIAS'!C25+'CENTRO DE EDUCAÇÃO INFANTIL 2'!C25+'E M ANTÔNIO LEITE GARCIA'!C25+'ESCOLA PAROQUIAL DA ALCOBAÇA'!C25+'CENTRO DE EDUCAÇÃO INFANTIL LOT'!C25+'ESCOLA PAROQUIAL DO LOTEAMENTO '!C25+'E M PROF JOAQUIM DEISTER'!C25+'E M MARIETA GONÇALVES'!C25+'ESCOLA MUNICIPAL ODETTE YOUNG M'!C25+'ESCOLA MUNICIPAL PROFESSOR JOSE'!C25+'E M HERCÍLIA HENRIQUES MORET'!C25+'COLEGIO VICENTINO PADRE CORRÊA'!C25+'CEI PROFª MARLUCE DE SOUZA PEST'!C25+'CEI IRINEU MARINHO'!C25+'CEI DAGMAR ROLANDO DE OLIVEIRA'!C25+'CEI NOSSA SENHORA DA GLÓRIA'!C25+'E M PROF NILTON COSTA PEREIRA D'!C25+'CENTRO DE EDUCAÇÃO INFANTIL SÉR'!C25+'CEI SANTO ANTÔNIO AGOSTINHO'!C25+'CEI OSWALDO CRUZ'!C25+'E M MAGDALENA TAGLIAFERRO'!C25+'ESCOLA SÃO JOSÉ DO CAETITU'!C25+'CRECHE-ESCOLA CASTELO SÃO MANOE'!C25+'CEI THEREZINHA DE JESUS LIMA'!C25+'ESCOLA MUNICIPAL PROFESSOR PAUL'!C25+'COLÉGIO ANGLICANO DE ARARAS'!C25+'ESCOLA PAROQUIAL SANTA BERNADET'!C25+'CEI VISTA ALEGRE'!C25+'CEI DENISE BESSA DE OLIVA MAYA'!C25+'CEI VIDEIRINHA'!C25+'E M AMÉRICO FERNANDES RIBEIRO'!C25+'ESCOLA MUNICIPAL AUGUSTO PUGNAL'!C25+'ESCOLA MUNICIPAL CELINA SCHECHN'!C25+'E M DARCY CORREA DA VEIGA'!C25+'E M DR PAULA BUARQUE'!C25+'LICEU SÃO JOSÉ DE ITAIPAVA'!C25+'CEI LUIZ MARCHIORI'!C25+'CENTRO DE EDUCAÇÃO INFANTIL AUG'!C25+'CEI PROFª ADRIANA CONSTÂNCIO TR'!C25+'E M AMÉLIA ANTUNES RABELLO'!C25+'CEI PREFEITO SÉRGIO FADEL'!C25+'E M DR THEODORO MACHADO'!C25+'ESCOLA SANTO ANTÔNIO'!C25+'E M TAQUARIL'!C25+'E M MONSENHOR JOÃO DE DEUS RODR'!C25+'CENTRO DE REFERÊNCIA EM EDUC 2'!C25+'CEI PROFª GRAÇA COSTA'!C25+'CEI VILA LEOPOLDINA'!C25+'CEI NILO PEÇANHA'!C25+'E MZDA SANTA TEREZINHA'!C25+'CEI CRIANÇA SANTA EDWIGES'!C25+'E M ARNALDO DYCKERHOFF'!C25+'E M CARLOS CANEDO'!C25+'E M BEATRIZ ZALESKI'!C25+'E M ANTÔNIO JOSÉ DE LIMA'!C25+'E M FELIX WAN ERVEN DE BARROS'!C25+'ESCOLA MUNICIPAL HILDEBRANDO DE'!C25+'E M OSWALDO DA COSTA FRIAS'!C25+'E MZDA AVELINO DE CARVALHO'!C25+'ESCOLA MUNICIPALIZADA MOYSÉS FU'!C25+'CEI ANGELA MARIA DA CONCEIÇÃO S'!C25+'CEI JOSÉ GONÇALVES DA MOTTA'!C25+'E M DR BARROS FRANCO'!C25+'E M MAJOR THEÓFILO DE CARVALHO'!C25+'E M JOÃO KOPKE'!C25+'CEI ASSOCIAÇÃO BENEFICENTE FAZE'!C25+'ESCOLA SAO FRANCISCO DE ASSIS'!C25+'CEI SÃO FRANCISCO ASSIS'!C25+'CEI ALDEIA DA CRIANCA'!C25+'ESCOLA MUNICIPAL ODETTE FONSECA'!C25+'CEI ANA CAROLINA TELLES'!C25+'E M SEBASTIÃO LACERDA'!C25+'E M DOM PEDRO DE ALCÂNTARA'!C25+'ESCOLA NOSSA SENHORA DE FÁTIMA'!C25+'ESCOLA PAROQUIAL SÃO FRANCISCO '!C25+'E M MONSENHOR CIRILLO CALAON'!C25 | D21: =B21-C21 | E21: ='Entrada de Dados'!S2 | F21: =D21*E21
A22: ='Entrada de Dados'!T5 | B22: ='Entrada de Dados'!T197 | C22: ='E M ROTARY'!C26+'E M DE EDUCAÇÃO ESPECIAL SANTOS'!C26+'LICEU MUN PREFEITO CORDOLINO AM'!C26+'E M PREFEITO JAMIL SABRÁ'!C26+'LICEU MUNICIPAL CARLOS CHAGAS F'!C26+'E M PAULO FREIRE'!C26+'E M PROFª MARIA CAMPOS DA SILVA'!C26+'CASA DA EDUCAÇÃO VISCONDE DE MA'!C26+'CENTRO DE REFERÊNCIA EM EDUCAÇÃ'!C26+'ESCOLA SANTA LUIZA DE MARILLAC'!C26+'ESCOLA DOMÉSTICA NOSSA SENHORA '!C26+'ESCOLA MONSENHOR GENTIL'!C26+'ESCOLA PAROQUIAL NOSSA SENHORA '!C26+'ESCOLA PAROQUIAL SÃO PEDRO DE A'!C26+'CEI TERRA SANTA'!C26+'CEI PRIMEIRA INFÂNCIA'!C26+'CEI PROFª PATRÍCIA FERREIRA E S'!C26+'CEI DRA ZILDA ARNS NEUMANN'!C26+'CENTRO DE EDUCAÇÃO INFANTIL PRO'!C26+'CEI MONSENHOR PAULO ELIAS DAHER'!C26+'COLÉGIO GUNNAR VINGREN DE PETRÓ'!C26+'EDUCANDÁRIO TERRA SANTA'!C26+'CEI LIONS CLUBE DE PETRÓPOLIS'!C26+'ESCOLA PAROQUIAL NOSSA SENHO 2'!C26+'CENTRO DE EDUCAÇÃO INFANTIL IRM'!C26+'E M LUIZ CARLOS SOARES'!C26+'ESCOLA GERMANO VALENTE'!C26+'ESCOLA PAROQUIAL NOSSA SENHO 3'!C26+'CEI JORGE ROLANDO DA SILVA'!C26+'E M CLEMENTE FERNANDES'!C26+'E M GERALDO VENTURA DIAS'!C26+'ESCOLA DAS COMUNIDADES SANTO AN'!C26+'CEI PROFª ROSANGELA DA SILVA LE'!C26+'CEI DEISE ELOY GOMES'!C26+'CEI PROFª SONIA REGINA SCUDESE '!C26+'CEI TIA ALICE'!C26+'E M BATAILLARD'!C26+'E M SOROPTIMISTA'!C26+'E M SALVADOR KLING'!C26+'ESCOLA MUNICIPALIZADA FREI ANIC'!C26+'ESCOLA SÃO JUDAS TADEU'!C26+'CEI PEDRAS BRANCAS'!C26+'CEI MARIA THEREZA KLING DO VALL'!C26+'CEI DONA ESPERANZA DE BOURBON D'!C26+'CEI GIUSEPPE-NEVA VOLONTERIO'!C26+'CENTRO DE EDUCAÇÃO INFANTIL SÃO'!C26+'E M LEONARDO BOFF'!C26+'ESCOLA MUNICIPAL GENERAL HEITOR'!C26+'E M JOHANN NOEL'!C26+'ESCOLA SANTA MARIA GORETTI'!C26+'ESCOLA SANTA RITA DE CASSIA'!C26+'ESCOLA SÃO JOÃO BATISTA'!C26+'CEI CASA DA SOLIDARIEDADE DE NO'!C26+'CEI A SEMENTEIRA'!C26+'CEI VILA SAO JOSE'!C26+'E M DR RUBENS DE CASTRO BOMTEMP'!C26+'CEI FREI LEÃO'!C26+'CEI SÃO JOÃO BATISTA'!C26+'CEI JURACI PINTO DO AMARAL DE C'!C26+'E M PEDRO AMADO'!C26+'E M ABELARDO DE LAMARE'!C26+'ESCOLA MUNICIPAL SENADOR MARIO '!C26+'ESCOLA PAROQUIAL SÃO PIO X'!C26+'CEI SÃO CHARBEL'!C26+'E M ROSALINA NICOLAY'!C26+'CEI INÊS BELARMINO DE SOUZA'!C26+'E M PROFª MARIA DA GLÓRIA QUEIR'!C26+'CENTRO EDUCACIONAL COMUNIDADE S'!C26+'CEI ROMANO CANAVESE'!C26+'CEI CÉLIA LÔBO PAULO'!C26+'CEI PROFª DORA KILLER'!C26+'CEI ALTO INDEPENDÊNCIA'!C26+'ESCOLA MUNICIPAL ALTO INDEPENDÊ'!C26+'E M PAPA JOÃO PAULO II'!C26+'CEI ANDRÉ REBOUÇAS'!C26+'CEI PROFª HERMÍNIA MATHEUS'!C26+'ESCOLA MUNICIPAL MAJOR JÚLIO FR'!C26+'E M ALMIRANTE TAMANDARÉ'!C26+'ESCOLA PAROQUIAL CARLOS DEMIÁ'!C26+'CENTRO PAROQUIAL DE EDUCAÇÃO IN'!C26+'CEI IRMÃ SILVANA'!C26+'CEI OLÍVIA MACHADO DA COSTA NOG'!C26+'E M GOVERNADOR MARCELLO ALENCAR'!C26+'E M PROFESSOR FLÁVIO MACIEL'!C26+'E M PROFª JANDIRA PEIXOTO BORDI'!C26+'E M STEFAN ZWEIG'!C26+'ESCOLA PAROQUIAL BOM JESUS'!C26+'CEI MARLI SOARES FERREIRA NETTO'!C26+'CENTRO DE EDUCAÇÃO INFANTIL CHI'!C26+'CEI VILA IPANEMA'!C26+'E M ROBERT KENNEDY'!C26+'ESCOLA MUNICIPAL ANA MOHAMMAD'!C26+'ESCOLA SÃO CRISTÓVÃO'!C26+'CEI DÉA LÚCIA CORDEIRO'!C26+'CEI SAGRADA FAMÍLIA'!C26+'CEI SÃO JOSÉ DAS OBLATAS DE NAZ'!C26+'ESCOLA MUNICIPAL JORGE AMADO'!C26+'E M FÁBRICA DO SABER'!C26+'CIEP BRIZOLÃO 474 MAESTRO GUERR'!C26+'CENTRO DE ENSINO PROF DARCY RIB'!C26+'CEI ANDRÉ VANZAN'!C26+'CENTRO DE EDUCAÇÃO INFANTIL CAR'!C26+'CEI BOA VISTA'!C26+'ASSOCIAÇÃO DA CRECHE SÃO FRANCI'!C26+'ESCOLA MUNICIPAL PAULO SALDANHA'!C26+'ESCOLA MUNICIPAL LÚCIA DE ALMEI'!C26+'E M DOM MANOEL PEDRO DA CUNHA C'!C26+'ESCOLA SÃO GERALDO'!C26+'CEI LULU MONTEIRO DE CASTRO'!C26+'CEI CARANGOLA'!C26+'ASSOCIAÇÃO RECREAR'!C26+'CENTRO DE EDUCAÇÃO INFANTIL CAS'!C26+'E M ROSEMIRA DE OLIVEIRA CAVALC'!C26+'E MZDA CARMEM NUNES MARTINS'!C26+'CEI SÃO JOSÉ DO ITAMARATI'!C26+'E M DUQUE DE CAXIAS'!C26+'CENTRO DE EDUCAÇÃO INFANTIL 2'!C26+'E M ANTÔNIO LEITE GARCIA'!C26+'ESCOLA PAROQUIAL DA ALCOBAÇA'!C26+'CENTRO DE EDUCAÇÃO INFANTIL LOT'!C26+'ESCOLA PAROQUIAL DO LOTEAMENTO '!C26+'E M PROF JOAQUIM DEISTER'!C26+'E M MARIETA GONÇALVES'!C26+'ESCOLA MUNICIPAL ODETTE YOUNG M'!C26+'ESCOLA MUNICIPAL PROFESSOR JOSE'!C26+'E M HERCÍLIA HENRIQUES MORET'!C26+'COLEGIO VICENTINO PADRE CORRÊA'!C26+'CEI PROFª MARLUCE DE SOUZA PEST'!C26+'CEI IRINEU MARINHO'!C26+'CEI DAGMAR ROLANDO DE OLIVEIRA'!C26+'CEI NOSSA SENHORA DA GLÓRIA'!C26+'E M PROF NILTON COSTA PEREIRA D'!C26+'CENTRO DE EDUCAÇÃO INFANTIL SÉR'!C26+'CEI SANTO ANTÔNIO AGOSTINHO'!C26+'CEI OSWALDO CRUZ'!C26+'E M MAGDALENA TAGLIAFERRO'!C26+'ESCOLA SÃO JOSÉ DO CAETITU'!C26+'CRECHE-ESCOLA CASTELO SÃO MANOE'!C26+'CEI THEREZINHA DE JESUS LIMA'!C26+'ESCOLA MUNICIPAL PROFESSOR PAUL'!C26+'COLÉGIO ANGLICANO DE ARARAS'!C26+'ESCOLA PAROQUIAL SANTA BERNADET'!C26+'CEI VISTA ALEGRE'!C26+'CEI DENISE BESSA DE OLIVA MAYA'!C26+'CEI VIDEIRINHA'!C26+'E M AMÉRICO FERNANDES RIBEIRO'!C26+'ESCOLA MUNICIPAL AUGUSTO PUGNAL'!C26+'ESCOLA MUNICIPAL CELINA SCHECHN'!C26+'E M DARCY CORREA DA VEIGA'!C26+'E M DR PAULA BUARQUE'!C26+'LICEU SÃO JOSÉ DE ITAIPAVA'!C26+'CEI LUIZ MARCHIORI'!C26+'CENTRO DE EDUCAÇÃO INFANTIL AUG'!C26+'CEI PROFª ADRIANA CONSTÂNCIO TR'!C26+'E M AMÉLIA ANTUNES RABELLO'!C26+'CEI PREFEITO SÉRGIO FADEL'!C26+'E M DR THEODORO MACHADO'!C26+'ESCOLA SANTO ANTÔNIO'!C26+'E M TAQUARIL'!C26+'E M MONSENHOR JOÃO DE DEUS RODR'!C26+'CENTRO DE REFERÊNCIA EM EDUC 2'!C26+'CEI PROFª GRAÇA COSTA'!C26+'CEI VILA LEOPOLDINA'!C26+'CEI NILO PEÇANHA'!C26+'E MZDA SANTA TEREZINHA'!C26+'CEI CRIANÇA SANTA EDWIGES'!C26+'E M ARNALDO DYCKERHOFF'!C26+'E M CARLOS CANEDO'!C26+'E M BEATRIZ ZALESKI'!C26+'E M ANTÔNIO JOSÉ DE LIMA'!C26+'E M FELIX WAN ERVEN DE BARROS'!C26+'ESCOLA MUNICIPAL HILDEBRANDO DE'!C26+'E M OSWALDO DA COSTA FRIAS'!C26+'E MZDA AVELINO DE CARVALHO'!C26+'ESCOLA MUNICIPALIZADA MOYSÉS FU'!C26+'CEI ANGELA MARIA DA CONCEIÇÃO S'!C26+'CEI JOSÉ GONÇALVES DA MOTTA'!C26+'E M DR BARROS FRANCO'!C26+'E M MAJOR THEÓFILO DE CARVALHO'!C26+'E M JOÃO KOPKE'!C26+'CEI ASSOCIAÇÃO BENEFICENTE FAZE'!C26+'ESCOLA SAO FRANCISCO DE ASSIS'!C26+'CEI SÃO FRANCISCO ASSIS'!C26+'CEI ALDEIA DA CRIANCA'!C26+'ESCOLA MUNICIPAL ODETTE FONSECA'!C26+'CEI ANA CAROLINA TELLES'!C26+'E M SEBASTIÃO LACERDA'!C26+'E M DOM PEDRO DE ALCÂNTARA'!C26+'ESCOLA NOSSA SENHORA DE FÁTIMA'!C26+'ESCOLA PAROQUIAL SÃO FRANCISCO '!C26+'E M MONSENHOR CIRILLO CALAON'!C26 | D22: =B22-C22 | E22: ='Entrada de Dados'!T2 | F22: =D22*E22
A23: ='Entrada de Dados'!U5 | B23: ='Entrada de Dados'!U197 | C23: ='E M ROTARY'!C27+'E M DE EDUCAÇÃO ESPECIAL SANTOS'!C27+'LICEU MUN PREFEITO CORDOLINO AM'!C27+'E M PREFEITO JAMIL SABRÁ'!C27+'LICEU MUNICIPAL CARLOS CHAGAS F'!C27+'E M PAULO FREIRE'!C27+'E M PROFª MARIA CAMPOS DA SILVA'!C27+'CASA DA EDUCAÇÃO VISCONDE DE MA'!C27+'CENTRO DE REFERÊNCIA EM EDUCAÇÃ'!C27+'ESCOLA SANTA LUIZA DE MARILLAC'!C27+'ESCOLA DOMÉSTICA NOSSA SENHORA '!C27+'ESCOLA MONSENHOR GENTIL'!C27+'ESCOLA PAROQUIAL NOSSA SENHORA '!C27+'ESCOLA PAROQUIAL SÃO PEDRO DE A'!C27+'CEI TERRA SANTA'!C27+'CEI PRIMEIRA INFÂNCIA'!C27+'CEI PROFª PATRÍCIA FERREIRA E S'!C27+'CEI DRA ZILDA ARNS NEUMANN'!C27+'CENTRO DE EDUCAÇÃO INFANTIL PRO'!C27+'CEI MONSENHOR PAULO ELIAS DAHER'!C27+'COLÉGIO GUNNAR VINGREN DE PETRÓ'!C27+'EDUCANDÁRIO TERRA SANTA'!C27+'CEI LIONS CLUBE DE PETRÓPOLIS'!C27+'ESCOLA PAROQUIAL NOSSA SENHO 2'!C27+'CENTRO DE EDUCAÇÃO INFANTIL IRM'!C27+'E M LUIZ CARLOS SOARES'!C27+'ESCOLA GERMANO VALENTE'!C27+'ESCOLA PAROQUIAL NOSSA SENHO 3'!C27+'CEI JORGE ROLANDO DA SILVA'!C27+'E M CLEMENTE FERNANDES'!C27+'E M GERALDO VENTURA DIAS'!C27+'ESCOLA DAS COMUNIDADES SANTO AN'!C27+'CEI PROFª ROSANGELA DA SILVA LE'!C27+'CEI DEISE ELOY GOMES'!C27+'CEI PROFª SONIA REGINA SCUDESE '!C27+'CEI TIA ALICE'!C27+'E M BATAILLARD'!C27+'E M SOROPTIMISTA'!C27+'E M SALVADOR KLING'!C27+'ESCOLA MUNICIPALIZADA FREI ANIC'!C27+'ESCOLA SÃO JUDAS TADEU'!C27+'CEI PEDRAS BRANCAS'!C27+'CEI MARIA THEREZA KLING DO VALL'!C27+'CEI DONA ESPERANZA DE BOURBON D'!C27+'CEI GIUSEPPE-NEVA VOLONTERIO'!C27+'CENTRO DE EDUCAÇÃO INFANTIL SÃO'!C27+'E M LEONARDO BOFF'!C27+'ESCOLA MUNICIPAL GENERAL HEITOR'!C27+'E M JOHANN NOEL'!C27+'ESCOLA SANTA MARIA GORETTI'!C27+'ESCOLA SANTA RITA DE CASSIA'!C27+'ESCOLA SÃO JOÃO BATISTA'!C27+'CEI CASA DA SOLIDARIEDADE DE NO'!C27+'CEI A SEMENTEIRA'!C27+'CEI VILA SAO JOSE'!C27+'E M DR RUBENS DE CASTRO BOMTEMP'!C27+'CEI FREI LEÃO'!C27+'CEI SÃO JOÃO BATISTA'!C27+'CEI JURACI PINTO DO AMARAL DE C'!C27+'E M PEDRO AMADO'!C27+'E M ABELARDO DE LAMARE'!C27+'ESCOLA MUNICIPAL SENADOR MARIO '!C27+'ESCOLA PAROQUIAL SÃO PIO X'!C27+'CEI SÃO CHARBEL'!C27+'E M ROSALINA NICOLAY'!C27+'CEI INÊS BELARMINO DE SOUZA'!C27+'E M PROFª MARIA DA GLÓRIA QUEIR'!C27+'CENTRO EDUCACIONAL COMUNIDADE S'!C27+'CEI ROMANO CANAVESE'!C27+'CEI CÉLIA LÔBO PAULO'!C27+'CEI PROFª DORA KILLER'!C27+'CEI ALTO INDEPENDÊNCIA'!C27+'ESCOLA MUNICIPAL ALTO INDEPENDÊ'!C27+'E M PAPA JOÃO PAULO II'!C27+'CEI ANDRÉ REBOUÇAS'!C27+'CEI PROFª HERMÍNIA MATHEUS'!C27+'ESCOLA MUNICIPAL MAJOR JÚLIO FR'!C27+'E M ALMIRANTE TAMANDARÉ'!C27+'ESCOLA PAROQUIAL CARLOS DEMIÁ'!C27+'CENTRO PAROQUIAL DE EDUCAÇÃO IN'!C27+'CEI IRMÃ SILVANA'!C27+'CEI OLÍVIA MACHADO DA COSTA NOG'!C27+'E M GOVERNADOR MARCELLO ALENCAR'!C27+'E M PROFESSOR FLÁVIO MACIEL'!C27+'E M PROFª JANDIRA PEIXOTO BORDI'!C27+'E M STEFAN ZWEIG'!C27+'ESCOLA PAROQUIAL BOM JESUS'!C27+'CEI MARLI SOARES FERREIRA NETTO'!C27+'CENTRO DE EDUCAÇÃO INFANTIL CHI'!C27+'CEI VILA IPANEMA'!C27+'E M ROBERT KENNEDY'!C27+'ESCOLA MUNICIPAL ANA MOHAMMAD'!C27+'ESCOLA SÃO CRISTÓVÃO'!C27+'CEI DÉA LÚCIA CORDEIRO'!C27+'CEI SAGRADA FAMÍLIA'!C27+'CEI SÃO JOSÉ DAS OBLATAS DE NAZ'!C27+'ESCOLA MUNICIPAL JORGE AMADO'!C27+'E M FÁBRICA DO SABER'!C27+'CIEP BRIZOLÃO 474 MAESTRO GUERR'!C27+'CENTRO DE ENSINO PROF DARCY RIB'!C27+'CEI ANDRÉ VANZAN'!C27+'CENTRO DE EDUCAÇÃO INFANTIL CAR'!C27+'CEI BOA VISTA'!C27+'ASSOCIAÇÃO DA CRECHE SÃO FRANCI'!C27+'ESCOLA MUNICIPAL PAULO SALDANHA'!C27+'ESCOLA MUNICIPAL LÚCIA DE ALMEI'!C27+'E M DOM MANOEL PEDRO DA CUNHA C'!C27+'ESCOLA SÃO GERALDO'!C27+'CEI LULU MONTEIRO DE CASTRO'!C27+'CEI CARANGOLA'!C27+'ASSOCIAÇÃO RECREAR'!C27+'CENTRO DE EDUCAÇÃO INFANTIL CAS'!C27+'E M ROSEMIRA DE OLIVEIRA CAVALC'!C27+'E MZDA CARMEM NUNES MARTINS'!C27+'CEI SÃO JOSÉ DO ITAMARATI'!C27+'E M DUQUE DE CAXIAS'!C27+'CENTRO DE EDUCAÇÃO INFANTIL 2'!C27+'E M ANTÔNIO LEITE GARCIA'!C27+'ESCOLA PAROQUIAL DA ALCOBAÇA'!C27+'CENTRO DE EDUCAÇÃO INFANTIL LOT'!C27+'ESCOLA PAROQUIAL DO LOTEAMENTO '!C27+'E M PROF JOAQUIM DEISTER'!C27+'E M MARIETA GONÇALVES'!C27+'ESCOLA MUNICIPAL ODETTE YOUNG M'!C27+'ESCOLA MUNICIPAL PROFESSOR JOSE'!C27+'E M HERCÍLIA HENRIQUES MORET'!C27+'COLEGIO VICENTINO PADRE CORRÊA'!C27+'CEI PROFª MARLUCE DE SOUZA PEST'!C27+'CEI IRINEU MARINHO'!C27+'CEI DAGMAR ROLANDO DE OLIVEIRA'!C27+'CEI NOSSA SENHORA DA GLÓRIA'!C27+'E M PROF NILTON COSTA PEREIRA D'!C27+'CENTRO DE EDUCAÇÃO INFANTIL SÉR'!C27+'CEI SANTO ANTÔNIO AGOSTINHO'!C27+'CEI OSWALDO CRUZ'!C27+'E M MAGDALENA TAGLIAFERRO'!C27+'ESCOLA SÃO JOSÉ DO CAETITU'!C27+'CRECHE-ESCOLA CASTELO SÃO MANOE'!C27+'CEI THEREZINHA DE JESUS LIMA'!C27+'ESCOLA MUNICIPAL PROFESSOR PAUL'!C27+'COLÉGIO ANGLICANO DE ARARAS'!C27+'ESCOLA PAROQUIAL SANTA BERNADET'!C27+'CEI VISTA ALEGRE'!C27+'CEI DENISE BESSA DE OLIVA MAYA'!C27+'CEI VIDEIRINHA'!C27+'E M AMÉRICO FERNANDES RIBEIRO'!C27+'ESCOLA MUNICIPAL AUGUSTO PUGNAL'!C27+'ESCOLA MUNICIPAL CELINA SCHECHN'!C27+'E M DARCY CORREA DA VEIGA'!C27+'E M DR PAULA BUARQUE'!C27+'LICEU SÃO JOSÉ DE ITAIPAVA'!C27+'CEI LUIZ MARCHIORI'!C27+'CENTRO DE EDUCAÇÃO INFANTIL AUG'!C27+'CEI PROFª ADRIANA CONSTÂNCIO TR'!C27+'E M AMÉLIA ANTUNES RABELLO'!C27+'CEI PREFEITO SÉRGIO FADEL'!C27+'E M DR THEODORO MACHADO'!C27+'ESCOLA SANTO ANTÔNIO'!C27+'E M TAQUARIL'!C27+'E M MONSENHOR JOÃO DE DEUS RODR'!C27+'CENTRO DE REFERÊNCIA EM EDUC 2'!C27+'CEI PROFª GRAÇA COSTA'!C27+'CEI VILA LEOPOLDINA'!C27+'CEI NILO PEÇANHA'!C27+'E MZDA SANTA TEREZINHA'!C27+'CEI CRIANÇA SANTA EDWIGES'!C27+'E M ARNALDO DYCKERHOFF'!C27+'E M CARLOS CANEDO'!C27+'E M BEATRIZ ZALESKI'!C27+'E M ANTÔNIO JOSÉ DE LIMA'!C27+'E M FELIX WAN ERVEN DE BARROS'!C27+'ESCOLA MUNICIPAL HILDEBRANDO DE'!C27+'E M OSWALDO DA COSTA FRIAS'!C27+'E MZDA AVELINO DE CARVALHO'!C27+'ESCOLA MUNICIPALIZADA MOYSÉS FU'!C27+'CEI ANGELA MARIA DA CONCEIÇÃO S'!C27+'CEI JOSÉ GONÇALVES DA MOTTA'!C27+'E M DR BARROS FRANCO'!C27+'E M MAJOR THEÓFILO DE CARVALHO'!C27+'E M JOÃO KOPKE'!C27+'CEI ASSOCIAÇÃO BENEFICENTE FAZE'!C27+'ESCOLA SAO FRANCISCO DE ASSIS'!C27+'CEI SÃO FRANCISCO ASSIS'!C27+'CEI ALDEIA DA CRIANCA'!C27+'ESCOLA MUNICIPAL ODETTE FONSECA'!C27+'CEI ANA CAROLINA TELLES'!C27+'E M SEBASTIÃO LACERDA'!C27+'E M DOM PEDRO DE ALCÂNTARA'!C27+'ESCOLA NOSSA SENHORA DE FÁTIMA'!C27+'ESCOLA PAROQUIAL SÃO FRANCISCO '!C27+'E M MONSENHOR CIRILLO CALAON'!C27 | D23: =B23-C23 | E23: ='Entrada de Dados'!U2 | F23: =D23*E23
A24: TOTAL | B24: =SUM(B5:B23) | C24: =SUM(C5:C23) | D24: =SUM(D5:D23) | F24: =SUM(F5:F23)
A26: 🚚 PRODUTORES / GALPÃO — ENTREGA × DEVOLUÇÃO × VALOR A PAGAR (frete R$ 3,67/kg já descontado)
A27: PRODUTO | B27: ENTREGA BRUTA (kg) | C27: DEVOLUÇÃO (kg) | D27: LÍQUIDO (kg) | E27: PREÇO LÍQUIDO (R$/kg) | F27: VALOR A PAGAR (R$)
A28: ='Entrada de Dados'!C5 | B28: ='Entrada de Dados'!C250 | C28: =B28-D28 | D28: ='Entrada de Dados'!C252 | E28: ='Entrada de Dados'!C2-3.67 | F28: =D28*E28
A29: ='Entrada de Dados'!D5 | B29: ='Entrada de Dados'!D250 | C29: =B29-D29 | D29: ='Entrada de Dados'!D252 | E29: ='Entrada de Dados'!D2-3.67 | F29: =D29*E29
A30: ='Entrada de Dados'!E5 | B30: ='Entrada de Dados'!E250 | C30: =B30-D30 | D30: ='Entrada de Dados'!E252 | E30: ='Entrada de Dados'!E2-3.67 | F30: =D30*E30
A31: ='Entrada de Dados'!F5 | B31: ='Entrada de Dados'!F250 | C31: =B31-D31 | D31: ='Entrada de Dados'!F252 | E31: ='Entrada de Dados'!F2-3.67 | F31: =D31*E31
A32: ='Entrada de Dados'!G5 | B32: ='Entrada de Dados'!G250 | C32: =B32-D32 | D32: ='Entrada de Dados'!G252 | E32: ='Entrada de Dados'!G2-3.67 | F32: =D32*E32
A33: ='Entrada de Dados'!H5 | B33: ='Entrada de Dados'!H250 | C33: =B33-D33 | D33: ='Entrada de Dados'!H252 | E33: ='Entrada de Dados'!H2-3.67 | F33: =D33*E33
A34: ='Entrada de Dados'!I5 | B34: ='Entrada de Dados'!I250 | C34: =B34-D34 | D34: ='Entrada de Dados'!I252 | E34: ='Entrada de Dados'!I2-3.67 | F34: =D34*E34
A35: ='Entrada de Dados'!J5 | B35: ='Entrada de Dados'!J250 | C35: =B35-D35 | D35: ='Entrada de Dados'!J252 | E35: ='Entrada de Dados'!J2-3.67 | F35: =D35*E35
A36: ='Entrada de Dados'!K5 | B36: ='Entrada de Dados'!K250 | C36: =B36-D36 | D36: ='Entrada de Dados'!K252 | E36: ='Entrada de Dados'!K2-3.67 | F36: =D36*E36
A37: ='Entrada de Dados'!L5 | B37: ='Entrada de Dados'!L250 | C37: =B37-D37 | D37: ='Entrada de Dados'!L252 | E37: ='Entrada de Dados'!L2-3.67 | F37: =D37*E37
A38: ='Entrada de Dados'!M5 | B38: ='Entrada de Dados'!M250 | C38: =B38-D38 | D38: ='Entrada de Dados'!M252 | E38: ='Entrada de Dados'!M2-3.67 | F38: =D38*E38
A39: ='Entrada de Dados'!N5 | B39: ='Entrada de Dados'!N250 | C39: =B39-D39 | D39: ='Entrada de Dados'!N252 | E39: ='Entrada de Dados'!N2-3.67 | F39: =D39*E39
A40: ='Entrada de Dados'!O5 | B40: ='Entrada de Dados'!O250 | C40: =B40-D40 | D40: ='Entrada de Dados'!O252 | E40: ='Entrada de Dados'!O2-3.67 | F40: =D40*E40
A41: ='Entrada de Dados'!P5 | B41: ='Entrada de Dados'!P250 | C41: =B41-D41 | D41: ='Entrada de Dados'!P252 | E41: ='Entrada de Dados'!P2-3.67 | F41: =D41*E41
A42: ='Entrada de Dados'!Q5 | B42: ='Entrada de Dados'!Q250 | C42: =B42-D42 | D42: ='Entrada de Dados'!Q252 | E42: ='Entrada de Dados'!Q2-3.67 | F42: =D42*E42
A43: ='Entrada de Dados'!R5 | B43: ='Entrada de Dados'!R250 | C43: =B43-D43 | D43: ='Entrada de Dados'!R252 | E43: ='Entrada de Dados'!R2-3.67 | F43: =D43*E43
A44: ='Entrada de Dados'!S5 | B44: ='Entrada de Dados'!S250 | C44: =B44-D44 | D44: ='Entrada de Dados'!S252 | E44: ='Entrada de Dados'!S2-3.67 | F44: =D44*E44
A45: ='Entrada de Dados'!T5 | B45: ='Entrada de Dados'!T250 | C45: =B45-D45 | D45: ='Entrada de Dados'!T252 | E45: ='Entrada de Dados'!T2-3.67 | F45: =D45*E45
A46: ='Entrada de Dados'!U5 | B46: ='Entrada de Dados'!U250 | C46: =B46-D46 | D46: ='Entrada de Dados'!U252 | E46: ='Entrada de Dados'!U2-3.67 | F46: =D46*E46
A47: TOTAL | B47: =SUM(B28:B46) | C47: =SUM(C28:C46) | D47: =SUM(D28:D46) | F47: =SUM(F28:F46)
A49: 📋 DEVOLUÇÃO POR MOTIVO — ESCOLAS
A50: CÓDIGO | B50: MOTIVO | C50: TOTAL (kg)
A51: =MOTIVO!A4 | B51: =IF(MOTIVO!B4="","",MOTIVO!B4) | C51: =SUMIF(_AUX_MOTIVO_ESCOLAS!$A$2:$A$3630,A51,_AUX_MOTIVO_ESCOLAS!$B$2:$B$3630)
A52: =MOTIVO!A5 | B52: =IF(MOTIVO!B5="","",MOTIVO!B5) | C52: =SUMIF(_AUX_MOTIVO_ESCOLAS!$A$2:$A$3630,A52,_AUX_MOTIVO_ESCOLAS!$B$2:$B$3630)
A53: =MOTIVO!A6 | B53: =IF(MOTIVO!B6="","",MOTIVO!B6) | C53: =SUMIF(_AUX_MOTIVO_ESCOLAS!$A$2:$A$3630,A53,_AUX_MOTIVO_ESCOLAS!$B$2:$B$3630)
A54: =MOTIVO!A7 | B54: =IF(MOTIVO!B7="","",MOTIVO!B7) | C54: =SUMIF(_AUX_MOTIVO_ESCOLAS!$A$2:$A$3630,A54,_AUX_MOTIVO_ESCOLAS!$B$2:$B$3630)
A55: =MOTIVO!A8 | B55: =IF(MOTIVO!B8="","",MOTIVO!B8) | C55: =SUMIF(_AUX_MOTIVO_ESCOLAS!$A$2:$A$3630,A55,_AUX_MOTIVO_ESCOLAS!$B$2:$B$3630)
A56: =MOTIVO!A9 | B56: =IF(MOTIVO!B9="","",MOTIVO!B9) | C56: =SUMIF(_AUX_MOTIVO_ESCOLAS!$A$2:$A$3630,A56,_AUX_MOTIVO_ESCOLAS!$B$2:$B$3630)
A57: =MOTIVO!A10 | B57: =IF(MOTIVO!B10="","",MOTIVO!B10) | C57: =SUMIF(_AUX_MOTIVO_ESCOLAS!$A$2:$A$3630,A57,_AUX_MOTIVO_ESCOLAS!$B$2:$B$3630)
A58: =MOTIVO!A11 | B58: =IF(MOTIVO!B11="","",MOTIVO!B11) | C58: =SUMIF(_AUX_MOTIVO_ESCOLAS!$A$2:$A$3630,A58,_AUX_MOTIVO_ESCOLAS!$B$2:$B$3630)
A59: =MOTIVO!A12 | B59: =IF(MOTIVO!B12="","",MOTIVO!B12) | C59: =SUMIF(_AUX_MOTIVO_ESCOLAS!$A$2:$A$3630,A59,_AUX_MOTIVO_ESCOLAS!$B$2:$B$3630)
A60: =MOTIVO!A13 | B60: =IF(MOTIVO!B13="","",MOTIVO!B13) | C60: =SUMIF(_AUX_MOTIVO_ESCOLAS!$A$2:$A$3630,A60,_AUX_MOTIVO_ESCOLAS!$B$2:$B$3630)
A61: =MOTIVO!A14 | B61: =IF(MOTIVO!B14="","",MOTIVO!B14) | C61: =SUMIF(_AUX_MOTIVO_ESCOLAS!$A$2:$A$3630,A61,_AUX_MOTIVO_ESCOLAS!$B$2:$B$3630)
A62: =MOTIVO!A15 | B62: =IF(MOTIVO!B15="","",MOTIVO!B15) | C62: =SUMIF(_AUX_MOTIVO_ESCOLAS!$A$2:$A$3630,A62,_AUX_MOTIVO_ESCOLAS!$B$2:$B$3630)
... A70: =MOTIVO!A23 | B70: =IF(MOTIVO!B23="","",MOTIVO!B23) | C70: =SUMIF(_AUX_MOTIVO_ESCOLAS!$A$2:$A$3630,A70,_AUX_MOTIVO_ESCOLAS!$B$2:$B$3630)
A71: TOTAL | C71: =SUM(C51:C70)
A73: 📋 DEVOLUÇÃO POR MOTIVO — PRODUTORES (GALPÃO)
A74: CÓDIGO | B74: MOTIVO | C74: TOTAL (kg)
A75: =MOTIVO!A4 | B75: =IF(MOTIVO!B4="","",MOTIVO!B4) | C75: =SUMIF('PROD - Ana C. C. R. Souza'!G6:G24,A75,'PROD - Ana C. C. R. Souza'!D6:D24)+SUMIF('PROD - Anderson Mello Quimas'!G6:G24,A75,'PROD - Anderson Mello Quimas'!D6:D24)+SUMIF('PROD - Armando Jose Silva'!G6:G24,A75,'PROD - Armando Jose Silva'!D6:D24)+SUMIF('PROD - Arnaldo Silva'!G6:G24,A75,'PROD - Arnaldo Silva'!D6:D24)+SUMIF('PROD - Claudeni R. Xavier'!G6:G24,A75,'PROD - Claudeni R. Xavier'!D6:D24)+SUMIF('PROD - Edson Jose Silva'!G6:G24,A75,'PROD - Edson Jose Silva'!D6:D24)+SUMIF('PROD - Gabriel Adriano Souza'!G6:G24,A75,'PROD - Gabriel Adriano Souza'!D6:D24)+SUMIF('PROD - Gustavo Mello Rodrigues'!G6:G24,A75,'PROD - Gustavo Mello Rodrigues'!D6:D24)+SUMIF('PROD - Joaquim Sergio Lage'!G6:G24,A75,'PROD - Joaquim Sergio Lage'!D6:D24)+SUMIF('PROD - Jorge G. P. Diniz'!G6:G24,A75,'PROD - Jorge G. P. Diniz'!D6:D24)+SUMIF('PROD - Jose G. S. Mello'!G6:G24,A75,'PROD - Jose G. S. Mello'!D6:D24)+SUMIF('PROD - Jose Rodrigues Melo'!G6:G24,A75,'PROD - Jose Rodrigues Melo'!D6:D24)+SUMIF('PROD - Lucio Mauro Felix Silva'!G6:G24,A75,'PROD - Lucio Mauro Felix Silva'!D6:D24)+SUMIF('PROD - Luiz A. O. Pinto'!G6:G24,A75,'PROD - Luiz A. O. Pinto'!D6:D24)+SUMIF('PROD - Marcelo Marcos Delgado'!G6:G24,A75,'PROD - Marcelo Marcos Delgado'!D6:D24)+SUMIF('PROD - Marcio Azevedo Souza'!G6:G24,A75,'PROD - Marcio Azevedo Souza'!D6:D24)+SUMIF('PROD - Marco Antonio Coelho'!G6:G24,A75,'PROD - Marco Antonio Coelho'!D6:D24)+SUMIF('PROD - Marcos Marcelo Delgado'!G6:G24,A75,'PROD - Marcos Marcelo Delgado'!D6:D24)+SUMIF('PROD - Miguel Fernando Almeida'!G6:G24,A75,'PROD - Miguel Fernando Almeida'!D6:D24)+SUMIF('PROD - Nilson Ferreira Silva'!G6:G24,A75,'PROD - Nilson Ferreira Silva'!D6:D24)+SUMIF('PROD - Renato Jose Silva'!G6:G24,A75,'PROD - Renato Jose Silva'!D6:D24)+SUMIF('PROD - Rodolfo Azevedo Andrade'!G6:G24,A75,'PROD - Rodolfo Azevedo Andrade'!D6:D24)
A76: =MOTIVO!A5 | B76: =IF(MOTIVO!B5="","",MOTIVO!B5) | C76: =SUMIF('PROD - Ana C. C. R. Souza'!G6:G24,A76,'PROD - Ana C. C. R. Souza'!D6:D24)+SUMIF('PROD - Anderson Mello Quimas'!G6:G24,A76,'PROD - Anderson Mello Quimas'!D6:D24)+SUMIF('PROD - Armando Jose Silva'!G6:G24,A76,'PROD - Armando Jose Silva'!D6:D24)+SUMIF('PROD - Arnaldo Silva'!G6:G24,A76,'PROD - Arnaldo Silva'!D6:D24)+SUMIF('PROD - Claudeni R. Xavier'!G6:G24,A76,'PROD - Claudeni R. Xavier'!D6:D24)+SUMIF('PROD - Edson Jose Silva'!G6:G24,A76,'PROD - Edson Jose Silva'!D6:D24)+SUMIF('PROD - Gabriel Adriano Souza'!G6:G24,A76,'PROD - Gabriel Adriano Souza'!D6:D24)+SUMIF('PROD - Gustavo Mello Rodrigues'!G6:G24,A76,'PROD - Gustavo Mello Rodrigues'!D6:D24)+SUMIF('PROD - Joaquim Sergio Lage'!G6:G24,A76,'PROD - Joaquim Sergio Lage'!D6:D24)+SUMIF('PROD - Jorge G. P. Diniz'!G6:G24,A76,'PROD - Jorge G. P. Diniz'!D6:D24)+SUMIF('PROD - Jose G. S. Mello'!G6:G24,A76,'PROD - Jose G. S. Mello'!D6:D24)+SUMIF('PROD - Jose Rodrigues Melo'!G6:G24,A76,'PROD - Jose Rodrigues Melo'!D6:D24)+SUMIF('PROD - Lucio Mauro Felix Silva'!G6:G24,A76,'PROD - Lucio Mauro Felix Silva'!D6:D24)+SUMIF('PROD - Luiz A. O. Pinto'!G6:G24,A76,'PROD - Luiz A. O. Pinto'!D6:D24)+SUMIF('PROD - Marcelo Marcos Delgado'!G6:G24,A76,'PROD - Marcelo Marcos Delgado'!D6:D24)+SUMIF('PROD - Marcio Azevedo Souza'!G6:G24,A76,'PROD - Marcio Azevedo Souza'!D6:D24)+SUMIF('PROD - Marco Antonio Coelho'!G6:G24,A76,'PROD - Marco Antonio Coelho'!D6:D24)+SUMIF('PROD - Marcos Marcelo Delgado'!G6:G24,A76,'PROD - Marcos Marcelo Delgado'!D6:D24)+SUMIF('PROD - Miguel Fernando Almeida'!G6:G24,A76,'PROD - Miguel Fernando Almeida'!D6:D24)+SUMIF('PROD - Nilson Ferreira Silva'!G6:G24,A76,'PROD - Nilson Ferreira Silva'!D6:D24)+SUMIF('PROD - Renato Jose Silva'!G6:G24,A76,'PROD - Renato Jose Silva'!D6:D24)+SUMIF('PROD - Rodolfo Azevedo Andrade'!G6:G24,A76,'PROD - Rodolfo Azevedo Andrade'!D6:D24)
A77: =MOTIVO!A6 | B77: =IF(MOTIVO!B6="","",MOTIVO!B6) | C77: =SUMIF('PROD - Ana C. C. R. Souza'!G6:G24,A77,'PROD - Ana C. C. R. Souza'!D6:D24)+SUMIF('PROD - Anderson Mello Quimas'!G6:G24,A77,'PROD - Anderson Mello Quimas'!D6:D24)+SUMIF('PROD - Armando Jose Silva'!G6:G24,A77,'PROD - Armando Jose Silva'!D6:D24)+SUMIF('PROD - Arnaldo Silva'!G6:G24,A77,'PROD - Arnaldo Silva'!D6:D24)+SUMIF('PROD - Claudeni R. Xavier'!G6:G24,A77,'PROD - Claudeni R. Xavier'!D6:D24)+SUMIF('PROD - Edson Jose Silva'!G6:G24,A77,'PROD - Edson Jose Silva'!D6:D24)+SUMIF('PROD - Gabriel Adriano Souza'!G6:G24,A77,'PROD - Gabriel Adriano Souza'!D6:D24)+SUMIF('PROD - Gustavo Mello Rodrigues'!G6:G24,A77,'PROD - Gustavo Mello Rodrigues'!D6:D24)+SUMIF('PROD - Joaquim Sergio Lage'!G6:G24,A77,'PROD - Joaquim Sergio Lage'!D6:D24)+SUMIF('PROD - Jorge G. P. Diniz'!G6:G24,A77,'PROD - Jorge G. P. Diniz'!D6:D24)+SUMIF('PROD - Jose G. S. Mello'!G6:G24,A77,'PROD - Jose G. S. Mello'!D6:D24)+SUMIF('PROD - Jose Rodrigues Melo'!G6:G24,A77,'PROD - Jose Rodrigues Melo'!D6:D24)+SUMIF('PROD - Lucio Mauro Felix Silva'!G6:G24,A77,'PROD - Lucio Mauro Felix Silva'!D6:D24)+SUMIF('PROD - Luiz A. O. Pinto'!G6:G24,A77,'PROD - Luiz A. O. Pinto'!D6:D24)+SUMIF('PROD - Marcelo Marcos Delgado'!G6:G24,A77,'PROD - Marcelo Marcos Delgado'!D6:D24)+SUMIF('PROD - Marcio Azevedo Souza'!G6:G24,A77,'PROD - Marcio Azevedo Souza'!D6:D24)+SUMIF('PROD - Marco Antonio Coelho'!G6:G24,A77,'PROD - Marco Antonio Coelho'!D6:D24)+SUMIF('PROD - Marcos Marcelo Delgado'!G6:G24,A77,'PROD - Marcos Marcelo Delgado'!D6:D24)+SUMIF('PROD - Miguel Fernando Almeida'!G6:G24,A77,'PROD - Miguel Fernando Almeida'!D6:D24)+SUMIF('PROD - Nilson Ferreira Silva'!G6:G24,A77,'PROD - Nilson Ferreira Silva'!D6:D24)+SUMIF('PROD - Renato Jose Silva'!G6:G24,A77,'PROD - Renato Jose Silva'!D6:D24)+SUMIF('PROD - Rodolfo Azevedo Andrade'!G6:G24,A77,'PROD - Rodolfo Azevedo Andrade'!D6:D24)
A78: =MOTIVO!A7 | B78: =IF(MOTIVO!B7="","",MOTIVO!B7) | C78: =SUMIF('PROD - Ana C. C. R. Souza'!G6:G24,A78,'PROD - Ana C. C. R. Souza'!D6:D24)+SUMIF('PROD - Anderson Mello Quimas'!G6:G24,A78,'PROD - Anderson Mello Quimas'!D6:D24)+SUMIF('PROD - Armando Jose Silva'!G6:G24,A78,'PROD - Armando Jose Silva'!D6:D24)+SUMIF('PROD - Arnaldo Silva'!G6:G24,A78,'PROD - Arnaldo Silva'!D6:D24)+SUMIF('PROD - Claudeni R. Xavier'!G6:G24,A78,'PROD - Claudeni R. Xavier'!D6:D24)+SUMIF('PROD - Edson Jose Silva'!G6:G24,A78,'PROD - Edson Jose Silva'!D6:D24)+SUMIF('PROD - Gabriel Adriano Souza'!G6:G24,A78,'PROD - Gabriel Adriano Souza'!D6:D24)+SUMIF('PROD - Gustavo Mello Rodrigues'!G6:G24,A78,'PROD - Gustavo Mello Rodrigues'!D6:D24)+SUMIF('PROD - Joaquim Sergio Lage'!G6:G24,A78,'PROD - Joaquim Sergio Lage'!D6:D24)+SUMIF('PROD - Jorge G. P. Diniz'!G6:G24,A78,'PROD - Jorge G. P. Diniz'!D6:D24)+SUMIF('PROD - Jose G. S. Mello'!G6:G24,A78,'PROD - Jose G. S. Mello'!D6:D24)+SUMIF('PROD - Jose Rodrigues Melo'!G6:G24,A78,'PROD - Jose Rodrigues Melo'!D6:D24)+SUMIF('PROD - Lucio Mauro Felix Silva'!G6:G24,A78,'PROD - Lucio Mauro Felix Silva'!D6:D24)+SUMIF('PROD - Luiz A. O. Pinto'!G6:G24,A78,'PROD - Luiz A. O. Pinto'!D6:D24)+SUMIF('PROD - Marcelo Marcos Delgado'!G6:G24,A78,'PROD - Marcelo Marcos Delgado'!D6:D24)+SUMIF('PROD - Marcio Azevedo Souza'!G6:G24,A78,'PROD - Marcio Azevedo Souza'!D6:D24)+SUMIF('PROD - Marco Antonio Coelho'!G6:G24,A78,'PROD - Marco Antonio Coelho'!D6:D24)+SUMIF('PROD - Marcos Marcelo Delgado'!G6:G24,A78,'PROD - Marcos Marcelo Delgado'!D6:D24)+SUMIF('PROD - Miguel Fernando Almeida'!G6:G24,A78,'PROD - Miguel Fernando Almeida'!D6:D24)+SUMIF('PROD - Nilson Ferreira Silva'!G6:G24,A78,'PROD - Nilson Ferreira Silva'!D6:D24)+SUMIF('PROD - Renato Jose Silva'!G6:G24,A78,'PROD - Renato Jose Silva'!D6:D24)+SUMIF('PROD - Rodolfo Azevedo Andrade'!G6:G24,A78,'PROD - Rodolfo Azevedo Andrade'!D6:D24)
A79: =MOTIVO!A8 | B79: =IF(MOTIVO!B8="","",MOTIVO!B8) | C79: =SUMIF('PROD - Ana C. C. R. Souza'!G6:G24,A79,'PROD - Ana C. C. R. Souza'!D6:D24)+SUMIF('PROD - Anderson Mello Quimas'!G6:G24,A79,'PROD - Anderson Mello Quimas'!D6:D24)+SUMIF('PROD - Armando Jose Silva'!G6:G24,A79,'PROD - Armando Jose Silva'!D6:D24)+SUMIF('PROD - Arnaldo Silva'!G6:G24,A79,'PROD - Arnaldo Silva'!D6:D24)+SUMIF('PROD - Claudeni R. Xavier'!G6:G24,A79,'PROD - Claudeni R. Xavier'!D6:D24)+SUMIF('PROD - Edson Jose Silva'!G6:G24,A79,'PROD - Edson Jose Silva'!D6:D24)+SUMIF('PROD - Gabriel Adriano Souza'!G6:G24,A79,'PROD - Gabriel Adriano Souza'!D6:D24)+SUMIF('PROD - Gustavo Mello Rodrigues'!G6:G24,A79,'PROD - Gustavo Mello Rodrigues'!D6:D24)+SUMIF('PROD - Joaquim Sergio Lage'!G6:G24,A79,'PROD - Joaquim Sergio Lage'!D6:D24)+SUMIF('PROD - Jorge G. P. Diniz'!G6:G24,A79,'PROD - Jorge G. P. Diniz'!D6:D24)+SUMIF('PROD - Jose G. S. Mello'!G6:G24,A79,'PROD - Jose G. S. Mello'!D6:D24)+SUMIF('PROD - Jose Rodrigues Melo'!G6:G24,A79,'PROD - Jose Rodrigues Melo'!D6:D24)+SUMIF('PROD - Lucio Mauro Felix Silva'!G6:G24,A79,'PROD - Lucio Mauro Felix Silva'!D6:D24)+SUMIF('PROD - Luiz A. O. Pinto'!G6:G24,A79,'PROD - Luiz A. O. Pinto'!D6:D24)+SUMIF('PROD - Marcelo Marcos Delgado'!G6:G24,A79,'PROD - Marcelo Marcos Delgado'!D6:D24)+SUMIF('PROD - Marcio Azevedo Souza'!G6:G24,A79,'PROD - Marcio Azevedo Souza'!D6:D24)+SUMIF('PROD - Marco Antonio Coelho'!G6:G24,A79,'PROD - Marco Antonio Coelho'!D6:D24)+SUMIF('PROD - Marcos Marcelo Delgado'!G6:G24,A79,'PROD - Marcos Marcelo Delgado'!D6:D24)+SUMIF('PROD - Miguel Fernando Almeida'!G6:G24,A79,'PROD - Miguel Fernando Almeida'!D6:D24)+SUMIF('PROD - Nilson Ferreira Silva'!G6:G24,A79,'PROD - Nilson Ferreira Silva'!D6:D24)+SUMIF('PROD - Renato Jose Silva'!G6:G24,A79,'PROD - Renato Jose Silva'!D6:D24)+SUMIF('PROD - Rodolfo Azevedo Andrade'!G6:G24,A79,'PROD - Rodolfo Azevedo Andrade'!D6:D24)
A80: =MOTIVO!A9 | B80: =IF(MOTIVO!B9="","",MOTIVO!B9) | C80: =SUMIF('PROD - Ana C. C. R. Souza'!G6:G24,A80,'PROD - Ana C. C. R. Souza'!D6:D24)+SUMIF('PROD - Anderson Mello Quimas'!G6:G24,A80,'PROD - Anderson Mello Quimas'!D6:D24)+SUMIF('PROD - Armando Jose Silva'!G6:G24,A80,'PROD - Armando Jose Silva'!D6:D24)+SUMIF('PROD - Arnaldo Silva'!G6:G24,A80,'PROD - Arnaldo Silva'!D6:D24)+SUMIF('PROD - Claudeni R. Xavier'!G6:G24,A80,'PROD - Claudeni R. Xavier'!D6:D24)+SUMIF('PROD - Edson Jose Silva'!G6:G24,A80,'PROD - Edson Jose Silva'!D6:D24)+SUMIF('PROD - Gabriel Adriano Souza'!G6:G24,A80,'PROD - Gabriel Adriano Souza'!D6:D24)+SUMIF('PROD - Gustavo Mello Rodrigues'!G6:G24,A80,'PROD - Gustavo Mello Rodrigues'!D6:D24)+SUMIF('PROD - Joaquim Sergio Lage'!G6:G24,A80,'PROD - Joaquim Sergio Lage'!D6:D24)+SUMIF('PROD - Jorge G. P. Diniz'!G6:G24,A80,'PROD - Jorge G. P. Diniz'!D6:D24)+SUMIF('PROD - Jose G. S. Mello'!G6:G24,A80,'PROD - Jose G. S. Mello'!D6:D24)+SUMIF('PROD - Jose Rodrigues Melo'!G6:G24,A80,'PROD - Jose Rodrigues Melo'!D6:D24)+SUMIF('PROD - Lucio Mauro Felix Silva'!G6:G24,A80,'PROD - Lucio Mauro Felix Silva'!D6:D24)+SUMIF('PROD - Luiz A. O. Pinto'!G6:G24,A80,'PROD - Luiz A. O. Pinto'!D6:D24)+SUMIF('PROD - Marcelo Marcos Delgado'!G6:G24,A80,'PROD - Marcelo Marcos Delgado'!D6:D24)+SUMIF('PROD - Marcio Azevedo Souza'!G6:G24,A80,'PROD - Marcio Azevedo Souza'!D6:D24)+SUMIF('PROD - Marco Antonio Coelho'!G6:G24,A80,'PROD - Marco Antonio Coelho'!D6:D24)+SUMIF('PROD - Marcos Marcelo Delgado'!G6:G24,A80,'PROD - Marcos Marcelo Delgado'!D6:D24)+SUMIF('PROD - Miguel Fernando Almeida'!G6:G24,A80,'PROD - Miguel Fernando Almeida'!D6:D24)+SUMIF('PROD - Nilson Ferreira Silva'!G6:G24,A80,'PROD - Nilson Ferreira Silva'!D6:D24)+SUMIF('PROD - Renato Jose Silva'!G6:G24,A80,'PROD - Renato Jose Silva'!D6:D24)+SUMIF('PROD - Rodolfo Azevedo Andrade'!G6:G24,A80,'PROD - Rodolfo Azevedo Andrade'!D6:D24)
A81: =MOTIVO!A10 | B81: =IF(MOTIVO!B10="","",MOTIVO!B10) | C81: =SUMIF('PROD - Ana C. C. R. Souza'!G6:G24,A81,'PROD - Ana C. C. R. Souza'!D6:D24)+SUMIF('PROD - Anderson Mello Quimas'!G6:G24,A81,'PROD - Anderson Mello Quimas'!D6:D24)+SUMIF('PROD - Armando Jose Silva'!G6:G24,A81,'PROD - Armando Jose Silva'!D6:D24)+SUMIF('PROD - Arnaldo Silva'!G6:G24,A81,'PROD - Arnaldo Silva'!D6:D24)+SUMIF('PROD - Claudeni R. Xavier'!G6:G24,A81,'PROD - Claudeni R. Xavier'!D6:D24)+SUMIF('PROD - Edson Jose Silva'!G6:G24,A81,'PROD - Edson Jose Silva'!D6:D24)+SUMIF('PROD - Gabriel Adriano Souza'!G6:G24,A81,'PROD - Gabriel Adriano Souza'!D6:D24)+SUMIF('PROD - Gustavo Mello Rodrigues'!G6:G24,A81,'PROD - Gustavo Mello Rodrigues'!D6:D24)+SUMIF('PROD - Joaquim Sergio Lage'!G6:G24,A81,'PROD - Joaquim Sergio Lage'!D6:D24)+SUMIF('PROD - Jorge G. P. Diniz'!G6:G24,A81,'PROD - Jorge G. P. Diniz'!D6:D24)+SUMIF('PROD - Jose G. S. Mello'!G6:G24,A81,'PROD - Jose G. S. Mello'!D6:D24)+SUMIF('PROD - Jose Rodrigues Melo'!G6:G24,A81,'PROD - Jose Rodrigues Melo'!D6:D24)+SUMIF('PROD - Lucio Mauro Felix Silva'!G6:G24,A81,'PROD - Lucio Mauro Felix Silva'!D6:D24)+SUMIF('PROD - Luiz A. O. Pinto'!G6:G24,A81,'PROD - Luiz A. O. Pinto'!D6:D24)+SUMIF('PROD - Marcelo Marcos Delgado'!G6:G24,A81,'PROD - Marcelo Marcos Delgado'!D6:D24)+SUMIF('PROD - Marcio Azevedo Souza'!G6:G24,A81,'PROD - Marcio Azevedo Souza'!D6:D24)+SUMIF('PROD - Marco Antonio Coelho'!G6:G24,A81,'PROD - Marco Antonio Coelho'!D6:D24)+SUMIF('PROD - Marcos Marcelo Delgado'!G6:G24,A81,'PROD - Marcos Marcelo Delgado'!D6:D24)+SUMIF('PROD - Miguel Fernando Almeida'!G6:G24,A81,'PROD - Miguel Fernando Almeida'!D6:D24)+SUMIF('PROD - Nilson Ferreira Silva'!G6:G24,A81,'PROD - Nilson Ferreira Silva'!D6:D24)+SUMIF('PROD - Renato Jose Silva'!G6:G24,A81,'PROD - Renato Jose Silva'!D6:D24)+SUMIF('PROD - Rodolfo Azevedo Andrade'!G6:G24,A81,'PROD - Rodolfo Azevedo Andrade'!D6:D24)
A82: =MOTIVO!A11 | B82: =IF(MOTIVO!B11="","",MOTIVO!B11) | C82: =SUMIF('PROD - Ana C. C. R. Souza'!G6:G24,A82,'PROD - Ana C. C. R. Souza'!D6:D24)+SUMIF('PROD - Anderson Mello Quimas'!G6:G24,A82,'PROD - Anderson Mello Quimas'!D6:D24)+SUMIF('PROD - Armando Jose Silva'!G6:G24,A82,'PROD - Armando Jose Silva'!D6:D24)+SUMIF('PROD - Arnaldo Silva'!G6:G24,A82,'PROD - Arnaldo Silva'!D6:D24)+SUMIF('PROD - Claudeni R. Xavier'!G6:G24,A82,'PROD - Claudeni R. Xavier'!D6:D24)+SUMIF('PROD - Edson Jose Silva'!G6:G24,A82,'PROD - Edson Jose Silva'!D6:D24)+SUMIF('PROD - Gabriel Adriano Souza'!G6:G24,A82,'PROD - Gabriel Adriano Souza'!D6:D24)+SUMIF('PROD - Gustavo Mello Rodrigues'!G6:G24,A82,'PROD - Gustavo Mello Rodrigues'!D6:D24)+SUMIF('PROD - Joaquim Sergio Lage'!G6:G24,A82,'PROD - Joaquim Sergio Lage'!D6:D24)+SUMIF('PROD - Jorge G. P. Diniz'!G6:G24,A82,'PROD - Jorge G. P. Diniz'!D6:D24)+SUMIF('PROD - Jose G. S. Mello'!G6:G24,A82,'PROD - Jose G. S. Mello'!D6:D24)+SUMIF('PROD - Jose Rodrigues Melo'!G6:G24,A82,'PROD - Jose Rodrigues Melo'!D6:D24)+SUMIF('PROD - Lucio Mauro Felix Silva'!G6:G24,A82,'PROD - Lucio Mauro Felix Silva'!D6:D24)+SUMIF('PROD - Luiz A. O. Pinto'!G6:G24,A82,'PROD - Luiz A. O. Pinto'!D6:D24)+SUMIF('PROD - Marcelo Marcos Delgado'!G6:G24,A82,'PROD - Marcelo Marcos Delgado'!D6:D24)+SUMIF('PROD - Marcio Azevedo Souza'!G6:G24,A82,'PROD - Marcio Azevedo Souza'!D6:D24)+SUMIF('PROD - Marco Antonio Coelho'!G6:G24,A82,'PROD - Marco Antonio Coelho'!D6:D24)+SUMIF('PROD - Marcos Marcelo Delgado'!G6:G24,A82,'PROD - Marcos Marcelo Delgado'!D6:D24)+SUMIF('PROD - Miguel Fernando Almeida'!G6:G24,A82,'PROD - Miguel Fernando Almeida'!D6:D24)+SUMIF('PROD - Nilson Ferreira Silva'!G6:G24,A82,'PROD - Nilson Ferreira Silva'!D6:D24)+SUMIF('PROD - Renato Jose Silva'!G6:G24,A82,'PROD - Renato Jose Silva'!D6:D24)+SUMIF('PROD - Rodolfo Azevedo Andrade'!G6:G24,A82,'PROD - Rodolfo Azevedo Andrade'!D6:D24)
A83: =MOTIVO!A12 | B83: =IF(MOTIVO!B12="","",MOTIVO!B12) | C83: =SUMIF('PROD - Ana C. C. R. Souza'!G6:G24,A83,'PROD - Ana C. C. R. Souza'!D6:D24)+SUMIF('PROD - Anderson Mello Quimas'!G6:G24,A83,'PROD - Anderson Mello Quimas'!D6:D24)+SUMIF('PROD - Armando Jose Silva'!G6:G24,A83,'PROD - Armando Jose Silva'!D6:D24)+SUMIF('PROD - Arnaldo Silva'!G6:G24,A83,'PROD - Arnaldo Silva'!D6:D24)+SUMIF('PROD - Claudeni R. Xavier'!G6:G24,A83,'PROD - Claudeni R. Xavier'!D6:D24)+SUMIF('PROD - Edson Jose Silva'!G6:G24,A83,'PROD - Edson Jose Silva'!D6:D24)+SUMIF('PROD - Gabriel Adriano Souza'!G6:G24,A83,'PROD - Gabriel Adriano Souza'!D6:D24)+SUMIF('PROD - Gustavo Mello Rodrigues'!G6:G24,A83,'PROD - Gustavo Mello Rodrigues'!D6:D24)+SUMIF('PROD - Joaquim Sergio Lage'!G6:G24,A83,'PROD - Joaquim Sergio Lage'!D6:D24)+SUMIF('PROD - Jorge G. P. Diniz'!G6:G24,A83,'PROD - Jorge G. P. Diniz'!D6:D24)+SUMIF('PROD - Jose G. S. Mello'!G6:G24,A83,'PROD - Jose G. S. Mello'!D6:D24)+SUMIF('PROD - Jose Rodrigues Melo'!G6:G24,A83,'PROD - Jose Rodrigues Melo'!D6:D24)+SUMIF('PROD - Lucio Mauro Felix Silva'!G6:G24,A83,'PROD - Lucio Mauro Felix Silva'!D6:D24)+SUMIF('PROD - Luiz A. O. Pinto'!G6:G24,A83,'PROD - Luiz A. O. Pinto'!D6:D24)+SUMIF('PROD - Marcelo Marcos Delgado'!G6:G24,A83,'PROD - Marcelo Marcos Delgado'!D6:D24)+SUMIF('PROD - Marcio Azevedo Souza'!G6:G24,A83,'PROD - Marcio Azevedo Souza'!D6:D24)+SUMIF('PROD - Marco Antonio Coelho'!G6:G24,A83,'PROD - Marco Antonio Coelho'!D6:D24)+SUMIF('PROD - Marcos Marcelo Delgado'!G6:G24,A83,'PROD - Marcos Marcelo Delgado'!D6:D24)+SUMIF('PROD - Miguel Fernando Almeida'!G6:G24,A83,'PROD - Miguel Fernando Almeida'!D6:D24)+SUMIF('PROD - Nilson Ferreira Silva'!G6:G24,A83,'PROD - Nilson Ferreira Silva'!D6:D24)+SUMIF('PROD - Renato Jose Silva'!G6:G24,A83,'PROD - Renato Jose Silva'!D6:D24)+SUMIF('PROD - Rodolfo Azevedo Andrade'!G6:G24,A83,'PROD - Rodolfo Azevedo Andrade'!D6:D24)
A84: =MOTIVO!A13 | B84: =IF(MOTIVO!B13="","",MOTIVO!B13) | C84: =SUMIF('PROD - Ana C. C. R. Souza'!G6:G24,A84,'PROD - Ana C. C. R. Souza'!D6:D24)+SUMIF('PROD - Anderson Mello Quimas'!G6:G24,A84,'PROD - Anderson Mello Quimas'!D6:D24)+SUMIF('PROD - Armando Jose Silva'!G6:G24,A84,'PROD - Armando Jose Silva'!D6:D24)+SUMIF('PROD - Arnaldo Silva'!G6:G24,A84,'PROD - Arnaldo Silva'!D6:D24)+SUMIF('PROD - Claudeni R. Xavier'!G6:G24,A84,'PROD - Claudeni R. Xavier'!D6:D24)+SUMIF('PROD - Edson Jose Silva'!G6:G24,A84,'PROD - Edson Jose Silva'!D6:D24)+SUMIF('PROD - Gabriel Adriano Souza'!G6:G24,A84,'PROD - Gabriel Adriano Souza'!D6:D24)+SUMIF('PROD - Gustavo Mello Rodrigues'!G6:G24,A84,'PROD - Gustavo Mello Rodrigues'!D6:D24)+SUMIF('PROD - Joaquim Sergio Lage'!G6:G24,A84,'PROD - Joaquim Sergio Lage'!D6:D24)+SUMIF('PROD - Jorge G. P. Diniz'!G6:G24,A84,'PROD - Jorge G. P. Diniz'!D6:D24)+SUMIF('PROD - Jose G. S. Mello'!G6:G24,A84,'PROD - Jose G. S. Mello'!D6:D24)+SUMIF('PROD - Jose Rodrigues Melo'!G6:G24,A84,'PROD - Jose Rodrigues Melo'!D6:D24)+SUMIF('PROD - Lucio Mauro Felix Silva'!G6:G24,A84,'PROD - Lucio Mauro Felix Silva'!D6:D24)+SUMIF('PROD - Luiz A. O. Pinto'!G6:G24,A84,'PROD - Luiz A. O. Pinto'!D6:D24)+SUMIF('PROD - Marcelo Marcos Delgado'!G6:G24,A84,'PROD - Marcelo Marcos Delgado'!D6:D24)+SUMIF('PROD - Marcio Azevedo Souza'!G6:G24,A84,'PROD - Marcio Azevedo Souza'!D6:D24)+SUMIF('PROD - Marco Antonio Coelho'!G6:G24,A84,'PROD - Marco Antonio Coelho'!D6:D24)+SUMIF('PROD - Marcos Marcelo Delgado'!G6:G24,A84,'PROD - Marcos Marcelo Delgado'!D6:D24)+SUMIF('PROD - Miguel Fernando Almeida'!G6:G24,A84,'PROD - Miguel Fernando Almeida'!D6:D24)+SUMIF('PROD - Nilson Ferreira Silva'!G6:G24,A84,'PROD - Nilson Ferreira Silva'!D6:D24)+SUMIF('PROD - Renato Jose Silva'!G6:G24,A84,'PROD - Renato Jose Silva'!D6:D24)+SUMIF('PROD - Rodolfo Azevedo Andrade'!G6:G24,A84,'PROD - Rodolfo Azevedo Andrade'!D6:D24)
A85: =MOTIVO!A14 | B85: =IF(MOTIVO!B14="","",MOTIVO!B14) | C85: =SUMIF('PROD - Ana C. C. R. Souza'!G6:G24,A85,'PROD - Ana C. C. R. Souza'!D6:D24)+SUMIF('PROD - Anderson Mello Quimas'!G6:G24,A85,'PROD - Anderson Mello Quimas'!D6:D24)+SUMIF('PROD - Armando Jose Silva'!G6:G24,A85,'PROD - Armando Jose Silva'!D6:D24)+SUMIF('PROD - Arnaldo Silva'!G6:G24,A85,'PROD - Arnaldo Silva'!D6:D24)+SUMIF('PROD - Claudeni R. Xavier'!G6:G24,A85,'PROD - Claudeni R. Xavier'!D6:D24)+SUMIF('PROD - Edson Jose Silva'!G6:G24,A85,'PROD - Edson Jose Silva'!D6:D24)+SUMIF('PROD - Gabriel Adriano Souza'!G6:G24,A85,'PROD - Gabriel Adriano Souza'!D6:D24)+SUMIF('PROD - Gustavo Mello Rodrigues'!G6:G24,A85,'PROD - Gustavo Mello Rodrigues'!D6:D24)+SUMIF('PROD - Joaquim Sergio Lage'!G6:G24,A85,'PROD - Joaquim Sergio Lage'!D6:D24)+SUMIF('PROD - Jorge G. P. Diniz'!G6:G24,A85,'PROD - Jorge G. P. Diniz'!D6:D24)+SUMIF('PROD - Jose G. S. Mello'!G6:G24,A85,'PROD - Jose G. S. Mello'!D6:D24)+SUMIF('PROD - Jose Rodrigues Melo'!G6:G24,A85,'PROD - Jose Rodrigues Melo'!D6:D24)+SUMIF('PROD - Lucio Mauro Felix Silva'!G6:G24,A85,'PROD - Lucio Mauro Felix Silva'!D6:D24)+SUMIF('PROD - Luiz A. O. Pinto'!G6:G24,A85,'PROD - Luiz A. O. Pinto'!D6:D24)+SUMIF('PROD - Marcelo Marcos Delgado'!G6:G24,A85,'PROD - Marcelo Marcos Delgado'!D6:D24)+SUMIF('PROD - Marcio Azevedo Souza'!G6:G24,A85,'PROD - Marcio Azevedo Souza'!D6:D24)+SUMIF('PROD - Marco Antonio Coelho'!G6:G24,A85,'PROD - Marco Antonio Coelho'!D6:D24)+SUMIF('PROD - Marcos Marcelo Delgado'!G6:G24,A85,'PROD - Marcos Marcelo Delgado'!D6:D24)+SUMIF('PROD - Miguel Fernando Almeida'!G6:G24,A85,'PROD - Miguel Fernando Almeida'!D6:D24)+SUMIF('PROD - Nilson Ferreira Silva'!G6:G24,A85,'PROD - Nilson Ferreira Silva'!D6:D24)+SUMIF('PROD - Renato Jose Silva'!G6:G24,A85,'PROD - Renato Jose Silva'!D6:D24)+SUMIF('PROD - Rodolfo Azevedo Andrade'!G6:G24,A85,'PROD - Rodolfo Azevedo Andrade'!D6:D24)
A86: =MOTIVO!A15 | B86: =IF(MOTIVO!B15="","",MOTIVO!B15) | C86: =SUMIF('PROD - Ana C. C. R. Souza'!G6:G24,A86,'PROD - Ana C. C. R. Souza'!D6:D24)+SUMIF('PROD - Anderson Mello Quimas'!G6:G24,A86,'PROD - Anderson Mello Quimas'!D6:D24)+SUMIF('PROD - Armando Jose Silva'!G6:G24,A86,'PROD - Armando Jose Silva'!D6:D24)+SUMIF('PROD - Arnaldo Silva'!G6:G24,A86,'PROD - Arnaldo Silva'!D6:D24)+SUMIF('PROD - Claudeni R. Xavier'!G6:G24,A86,'PROD - Claudeni R. Xavier'!D6:D24)+SUMIF('PROD - Edson Jose Silva'!G6:G24,A86,'PROD - Edson Jose Silva'!D6:D24)+SUMIF('PROD - Gabriel Adriano Souza'!G6:G24,A86,'PROD - Gabriel Adriano Souza'!D6:D24)+SUMIF('PROD - Gustavo Mello Rodrigues'!G6:G24,A86,'PROD - Gustavo Mello Rodrigues'!D6:D24)+SUMIF('PROD - Joaquim Sergio Lage'!G6:G24,A86,'PROD - Joaquim Sergio Lage'!D6:D24)+SUMIF('PROD - Jorge G. P. Diniz'!G6:G24,A86,'PROD - Jorge G. P. Diniz'!D6:D24)+SUMIF('PROD - Jose G. S. Mello'!G6:G24,A86,'PROD - Jose G. S. Mello'!D6:D24)+SUMIF('PROD - Jose Rodrigues Melo'!G6:G24,A86,'PROD - Jose Rodrigues Melo'!D6:D24)+SUMIF('PROD - Lucio Mauro Felix Silva'!G6:G24,A86,'PROD - Lucio Mauro Felix Silva'!D6:D24)+SUMIF('PROD - Luiz A. O. Pinto'!G6:G24,A86,'PROD - Luiz A. O. Pinto'!D6:D24)+SUMIF('PROD - Marcelo Marcos Delgado'!G6:G24,A86,'PROD - Marcelo Marcos Delgado'!D6:D24)+SUMIF('PROD - Marcio Azevedo Souza'!G6:G24,A86,'PROD - Marcio Azevedo Souza'!D6:D24)+SUMIF('PROD - Marco Antonio Coelho'!G6:G24,A86,'PROD - Marco Antonio Coelho'!D6:D24)+SUMIF('PROD - Marcos Marcelo Delgado'!G6:G24,A86,'PROD - Marcos Marcelo Delgado'!D6:D24)+SUMIF('PROD - Miguel Fernando Almeida'!G6:G24,A86,'PROD - Miguel Fernando Almeida'!D6:D24)+SUMIF('PROD - Nilson Ferreira Silva'!G6:G24,A86,'PROD - Nilson Ferreira Silva'!D6:D24)+SUMIF('PROD - Renato Jose Silva'!G6:G24,A86,'PROD - Renato Jose Silva'!D6:D24)+SUMIF('PROD - Rodolfo Azevedo Andrade'!G6:G24,A86,'PROD - Rodolfo Azevedo Andrade'!D6:D24)
A87: =MOTIVO!A16 | B87: =IF(MOTIVO!B16="","",MOTIVO!B16) | C87: =SUMIF('PROD - Ana C. C. R. Souza'!G6:G24,A87,'PROD - Ana C. C. R. Souza'!D6:D24)+SUMIF('PROD - Anderson Mello Quimas'!G6:G24,A87,'PROD - Anderson Mello Quimas'!D6:D24)+SUMIF('PROD - Armando Jose Silva'!G6:G24,A87,'PROD - Armando Jose Silva'!D6:D24)+SUMIF('PROD - Arnaldo Silva'!G6:G24,A87,'PROD - Arnaldo Silva'!D6:D24)+SUMIF('PROD - Claudeni R. Xavier'!G6:G24,A87,'PROD - Claudeni R. Xavier'!D6:D24)+SUMIF('PROD - Edson Jose Silva'!G6:G24,A87,'PROD - Edson Jose Silva'!D6:D24)+SUMIF('PROD - Gabriel Adriano Souza'!G6:G24,A87,'PROD - Gabriel Adriano Souza'!D6:D24)+SUMIF('PROD - Gustavo Mello Rodrigues'!G6:G24,A87,'PROD - Gustavo Mello Rodrigues'!D6:D24)+SUMIF('PROD - Joaquim Sergio Lage'!G6:G24,A87,'PROD - Joaquim Sergio Lage'!D6:D24)+SUMIF('PROD - Jorge G. P. Diniz'!G6:G24,A87,'PROD - Jorge G. P. Diniz'!D6:D24)+SUMIF('PROD - Jose G. S. Mello'!G6:G24,A87,'PROD - Jose G. S. Mello'!D6:D24)+SUMIF('PROD - Jose Rodrigues Melo'!G6:G24,A87,'PROD - Jose Rodrigues Melo'!D6:D24)+SUMIF('PROD - Lucio Mauro Felix Silva'!G6:G24,A87,'PROD - Lucio Mauro Felix Silva'!D6:D24)+SUMIF('PROD - Luiz A. O. Pinto'!G6:G24,A87,'PROD - Luiz A. O. Pinto'!D6:D24)+SUMIF('PROD - Marcelo Marcos Delgado'!G6:G24,A87,'PROD - Marcelo Marcos Delgado'!D6:D24)+SUMIF('PROD - Marcio Azevedo Souza'!G6:G24,A87,'PROD - Marcio Azevedo Souza'!D6:D24)+SUMIF('PROD - Marco Antonio Coelho'!G6:G24,A87,'PROD - Marco Antonio Coelho'!D6:D24)+SUMIF('PROD - Marcos Marcelo Delgado'!G6:G24,A87,'PROD - Marcos Marcelo Delgado'!D6:D24)+SUMIF('PROD - Miguel Fernando Almeida'!G6:G24,A87,'PROD - Miguel Fernando Almeida'!D6:D24)+SUMIF('PROD - Nilson Ferreira Silva'!G6:G24,A87,'PROD - Nilson Ferreira Silva'!D6:D24)+SUMIF('PROD - Renato Jose Silva'!G6:G24,A87,'PROD - Renato Jose Silva'!D6:D24)+SUMIF('PROD - Rodolfo Azevedo Andrade'!G6:G24,A87,'PROD - Rodolfo Azevedo Andrade'!D6:D24)
A88: =MOTIVO!A17 | B88: =IF(MOTIVO!B17="","",MOTIVO!B17) | C88: =SUMIF('PROD - Ana C. C. R. Souza'!G6:G24,A88,'PROD - Ana C. C. R. Souza'!D6:D24)+SUMIF('PROD - Anderson Mello Quimas'!G6:G24,A88,'PROD - Anderson Mello Quimas'!D6:D24)+SUMIF('PROD - Armando Jose Silva'!G6:G24,A88,'PROD - Armando Jose Silva'!D6:D24)+SUMIF('PROD - Arnaldo Silva'!G6:G24,A88,'PROD - Arnaldo Silva'!D6:D24)+SUMIF('PROD - Claudeni R. Xavier'!G6:G24,A88,'PROD - Claudeni R. Xavier'!D6:D24)+SUMIF('PROD - Edson Jose Silva'!G6:G24,A88,'PROD - Edson Jose Silva'!D6:D24)+SUMIF('PROD - Gabriel Adriano Souza'!G6:G24,A88,'PROD - Gabriel Adriano Souza'!D6:D24)+SUMIF('PROD - Gustavo Mello Rodrigues'!G6:G24,A88,'PROD - Gustavo Mello Rodrigues'!D6:D24)+SUMIF('PROD - Joaquim Sergio Lage'!G6:G24,A88,'PROD - Joaquim Sergio Lage'!D6:D24)+SUMIF('PROD - Jorge G. P. Diniz'!G6:G24,A88,'PROD - Jorge G. P. Diniz'!D6:D24)+SUMIF('PROD - Jose G. S. Mello'!G6:G24,A88,'PROD - Jose G. S. Mello'!D6:D24)+SUMIF('PROD - Jose Rodrigues Melo'!G6:G24,A88,'PROD - Jose Rodrigues Melo'!D6:D24)+SUMIF('PROD - Lucio Mauro Felix Silva'!G6:G24,A88,'PROD - Lucio Mauro Felix Silva'!D6:D24)+SUMIF('PROD - Luiz A. O. Pinto'!G6:G24,A88,'PROD - Luiz A. O. Pinto'!D6:D24)+SUMIF('PROD - Marcelo Marcos Delgado'!G6:G24,A88,'PROD - Marcelo Marcos Delgado'!D6:D24)+SUMIF('PROD - Marcio Azevedo Souza'!G6:G24,A88,'PROD - Marcio Azevedo Souza'!D6:D24)+SUMIF('PROD - Marco Antonio Coelho'!G6:G24,A88,'PROD - Marco Antonio Coelho'!D6:D24)+SUMIF('PROD - Marcos Marcelo Delgado'!G6:G24,A88,'PROD - Marcos Marcelo Delgado'!D6:D24)+SUMIF('PROD - Miguel Fernando Almeida'!G6:G24,A88,'PROD - Miguel Fernando Almeida'!D6:D24)+SUMIF('PROD - Nilson Ferreira Silva'!G6:G24,A88,'PROD - Nilson Ferreira Silva'!D6:D24)+SUMIF('PROD - Renato Jose Silva'!G6:G24,A88,'PROD - Renato Jose Silva'!D6:D24)+SUMIF('PROD - Rodolfo Azevedo Andrade'!G6:G24,A88,'PROD - Rodolfo Azevedo Andrade'!D6:D24)
A89: =MOTIVO!A18 | B89: =IF(MOTIVO!B18="","",MOTIVO!B18) | C89: =SUMIF('PROD - Ana C. C. R. Souza'!G6:G24,A89,'PROD - Ana C. C. R. Souza'!D6:D24)+SUMIF('PROD - Anderson Mello Quimas'!G6:G24,A89,'PROD - Anderson Mello Quimas'!D6:D24)+SUMIF('PROD - Armando Jose Silva'!G6:G24,A89,'PROD - Armando Jose Silva'!D6:D24)+SUMIF('PROD - Arnaldo Silva'!G6:G24,A89,'PROD - Arnaldo Silva'!D6:D24)+SUMIF('PROD - Claudeni R. Xavier'!G6:G24,A89,'PROD - Claudeni R. Xavier'!D6:D24)+SUMIF('PROD - Edson Jose Silva'!G6:G24,A89,'PROD - Edson Jose Silva'!D6:D24)+SUMIF('PROD - Gabriel Adriano Souza'!G6:G24,A89,'PROD - Gabriel Adriano Souza'!D6:D24)+SUMIF('PROD - Gustavo Mello Rodrigues'!G6:G24,A89,'PROD - Gustavo Mello Rodrigues'!D6:D24)+SUMIF('PROD - Joaquim Sergio Lage'!G6:G24,A89,'PROD - Joaquim Sergio Lage'!D6:D24)+SUMIF('PROD - Jorge G. P. Diniz'!G6:G24,A89,'PROD - Jorge G. P. Diniz'!D6:D24)+SUMIF('PROD - Jose G. S. Mello'!G6:G24,A89,'PROD - Jose G. S. Mello'!D6:D24)+SUMIF('PROD - Jose Rodrigues Melo'!G6:G24,A89,'PROD - Jose Rodrigues Melo'!D6:D24)+SUMIF('PROD - Lucio Mauro Felix Silva'!G6:G24,A89,'PROD - Lucio Mauro Felix Silva'!D6:D24)+SUMIF('PROD - Luiz A. O. Pinto'!G6:G24,A89,'PROD - Luiz A. O. Pinto'!D6:D24)+SUMIF('PROD - Marcelo Marcos Delgado'!G6:G24,A89,'PROD - Marcelo Marcos Delgado'!D6:D24)+SUMIF('PROD - Marcio Azevedo Souza'!G6:G24,A89,'PROD - Marcio Azevedo Souza'!D6:D24)+SUMIF('PROD - Marco Antonio Coelho'!G6:G24,A89,'PROD - Marco Antonio Coelho'!D6:D24)+SUMIF('PROD - Marcos Marcelo Delgado'!G6:G24,A89,'PROD - Marcos Marcelo Delgado'!D6:D24)+SUMIF('PROD - Miguel Fernando Almeida'!G6:G24,A89,'PROD - Miguel Fernando Almeida'!D6:D24)+SUMIF('PROD - Nilson Ferreira Silva'!G6:G24,A89,'PROD - Nilson Ferreira Silva'!D6:D24)+SUMIF('PROD - Renato Jose Silva'!G6:G24,A89,'PROD - Renato Jose Silva'!D6:D24)+SUMIF('PROD - Rodolfo Azevedo Andrade'!G6:G24,A89,'PROD - Rodolfo Azevedo Andrade'!D6:D24)
A90: =MOTIVO!A19 | B90: =IF(MOTIVO!B19="","",MOTIVO!B19) | C90: =SUMIF('PROD - Ana C. C. R. Souza'!G6:G24,A90,'PROD - Ana C. C. R. Souza'!D6:D24)+SUMIF('PROD - Anderson Mello Quimas'!G6:G24,A90,'PROD - Anderson Mello Quimas'!D6:D24)+SUMIF('PROD - Armando Jose Silva'!G6:G24,A90,'PROD - Armando Jose Silva'!D6:D24)+SUMIF('PROD - Arnaldo Silva'!G6:G24,A90,'PROD - Arnaldo Silva'!D6:D24)+SUMIF('PROD - Claudeni R. Xavier'!G6:G24,A90,'PROD - Claudeni R. Xavier'!D6:D24)+SUMIF('PROD - Edson Jose Silva'!G6:G24,A90,'PROD - Edson Jose Silva'!D6:D24)+SUMIF('PROD - Gabriel Adriano Souza'!G6:G24,A90,'PROD - Gabriel Adriano Souza'!D6:D24)+SUMIF('PROD - Gustavo Mello Rodrigues'!G6:G24,A90,'PROD - Gustavo Mello Rodrigues'!D6:D24)+SUMIF('PROD - Joaquim Sergio Lage'!G6:G24,A90,'PROD - Joaquim Sergio Lage'!D6:D24)+SUMIF('PROD - Jorge G. P. Diniz'!G6:G24,A90,'PROD - Jorge G. P. Diniz'!D6:D24)+SUMIF('PROD - Jose G. S. Mello'!G6:G24,A90,'PROD - Jose G. S. Mello'!D6:D24)+SUMIF('PROD - Jose Rodrigues Melo'!G6:G24,A90,'PROD - Jose Rodrigues Melo'!D6:D24)+SUMIF('PROD - Lucio Mauro Felix Silva'!G6:G24,A90,'PROD - Lucio Mauro Felix Silva'!D6:D24)+SUMIF('PROD - Luiz A. O. Pinto'!G6:G24,A90,'PROD - Luiz A. O. Pinto'!D6:D24)+SUMIF('PROD - Marcelo Marcos Delgado'!G6:G24,A90,'PROD - Marcelo Marcos Delgado'!D6:D24)+SUMIF('PROD - Marcio Azevedo Souza'!G6:G24,A90,'PROD - Marcio Azevedo Souza'!D6:D24)+SUMIF('PROD - Marco Antonio Coelho'!G6:G24,A90,'PROD - Marco Antonio Coelho'!D6:D24)+SUMIF('PROD - Marcos Marcelo Delgado'!G6:G24,A90,'PROD - Marcos Marcelo Delgado'!D6:D24)+SUMIF('PROD - Miguel Fernando Almeida'!G6:G24,A90,'PROD - Miguel Fernando Almeida'!D6:D24)+SUMIF('PROD - Nilson Ferreira Silva'!G6:G24,A90,'PROD - Nilson Ferreira Silva'!D6:D24)+SUMIF('PROD - Renato Jose Silva'!G6:G24,A90,'PROD - Renato Jose Silva'!D6:D24)+SUMIF('PROD - Rodolfo Azevedo Andrade'!G6:G24,A90,'PROD - Rodolfo Azevedo Andrade'!D6:D24)
